Workbook

Sheet hse1
B2: OLE SAMEDHA APARTMENTS-Kitengela | N2: VAR | O2: TAX DUE
B3: P.O BOX 9473-00200 NAIROBI | N3: =O3-Q3 -> 10270 | O3: 10270
B4: WATER BILL | G4: BILL NO. | H4: 20242001 | N4: =O4-Q4 -> 10304 | O4: 10304
N5: =O5-Q5 -> 10988 | O5: 10988
B6: TENANT NAME | C6: MAUREEN | N6: =O6-Q6 -> 11070 | O6: 11070
B7: PHONE NO | C7: O731078405 | N7: =O7-Q7 -> 1197 | O7: 1197
B8: HOUSE NUMBER | C8: 1A | N8: =O8-Q8 -> 9250 | O8: 9250
N9: =O9-Q9 -> 8770 | O9: 8770
B10: ISSUE DATE | C10: 27/1/2026 | N10: =O10-Q10 -> 23190 | O10: 23190
N11: =O11-Q11 -> 10910 | O11: 10910
B12: LAST PAY DATE | C12: 46144 | N12: =O12-Q12 -> 10910 | O12: 10910
N13: =O13-Q13 -> 12190 | O13: 12190
N14: =O14-Q14 -> 11070 | O14: 11070
B15: PREVIOUS READING | C15: CURRENT READING | E15: CONSUMPTION (Units) | N15: =O15-Q15 -> 9090 | O15: 9090
B16: =meter!D3 -> 32 | C16: =meter!E3 -> 33 | D16: Units | E16: =C16-B16 -> 1 | N16: =O16-Q16 -> 9420 | O16: 9420
E17: AMOUNT KSHS | N17: =O17-Q17 -> 11154 | O17: 11154
C18: LAST ACCOUNT B/F | D18: Kshs. | N18: =O18-Q18 -> 10430 | O18: 10430
N19: =O19-Q19 -> 11831 | O19: 11831
C20: MONTH Water BILL | D20: Kshs. | E20: =meter!H3 -> 220 | N20: =O20-Q20 -> 10590 | O20: 10590
N21: =O21-Q21 -> 22423 | O21: 22423
C22: PUMP/POWER CHARGES | D22: Kshs. | E22: 110 | N22: =O22-Q22 -> 9250 | O22: 9250
N23: =O23-Q23 -> 10162 | O23: 10162
C24: MONTH HOUSE RENT | D24: Kshs. | E24: 10000 | N24: =O24-Q24 -> 10270 | O24: 10270
N25: =O25-Q25 -> 11070 | O25: 11070
C26: security | D26: Kshs. | E26: 500 | N26: =O26-Q26 -> 11550 | O26: 11550
C27: GARBAGE FEE | D27: Kshs. | E27: 150 | N27: =O27-Q27 -> 11393 | O27: 11393
C28: LATE PAY INTEREST | D28: Kshs. | N28: =O28-Q28 -> 10802 | O28: 10802
N29: =O29-Q29 -> 8930 | O29: 8930
C30: TOTAL PAYABLE | D30: Kshs. | E30: =E18+E20+E22+E24+E26+E27+E28 -> 10980 | N30: =O30-Q30 -> 9570 | O30: 9570
N31: =O31-Q31 -> 11390 | O31: 11390
C32: PAID | E32: =meter!R3 -> 0 | N32: =O32-Q32 -> 10750 | O32: 10750
N33: =O33-Q33 -> 11732 | O33: 11732
C34: AMOUNT DUE | E34: =E30-E32 -> 10980 | N34: =O34-Q34 -> 10934 | O34: 10934 | R34: 700
B35: NOTE | N35: =O35-Q35 -> 10270 | O35: 10270
A36: a) | B36: Rent is due on or before 5th of the month. By 7th day, any rent not paid will attract interest at 2% per day. | N36: =O36-Q36 -> 10598 | O36: 10598
A37: b) | B37: Any default in Rent payment by 10th of the following month the house shall be locked without notice and belongings removed for re-letting. | N37: =O37-Q37 -> 8770 | O37: 8770
N38: =O38-Q38 -> 8770 | O38: 8770
A39: c) | B39: Amounts not cleared by last pay date will render to water disconnection. | O39: =SUM(O3:O38) -> 391268 | Q39: =SUM(Q3:Q38) -> 0
A41: d) | B41: A reconnection fee of Kshs. 1,000 will be charged and paid before supply is reconnected.
A42: e) | B42: ANY MINOR REPAIRS OCCURING AFTER 3 MONTHS OF OCCUPANCY ARE TENANT'S RESPONSIBILITY AS PER TENANCY AGREEMENT.
A43: f) | B43: The water bills are payable through the same account for monthly rent strictly through:
B44: Frebazeth Company Limited
B45: Consolidated Bank Account
B46: Kitengela Branch
B47: PAY BILL 4139271
B48: (Kindly indicate your Name & House number on the deposit slip & inform the Bank teller to capture it.)
B49: A receipt will be issued upon bank confirmation of the transaction. | O49: ……………
B51: ACC NO KT 1A
B52: E & O E
B53: NB: Kindly give the management atleast two (2) months prior notice incase you intend to terminate the tenancy for ease of logisitics.

Sheet hse2
B2: OLE SAMEDHA APARTMENTS-Kitengela | N2: VAR | O2: TAX DUE
B3: ='hse1'!B3 -> P.O BOX 9473-00200 NAIROBI | N3: =O3-Q3 -> 10270 | O3: 10270
B4: WATER BILL | F4: BILL NO. | G4: ='hse1'!H4+2-1 -> 20242002 | N4: =O4-Q4 -> 10304 | O4: 10304
N5: =O5-Q5 -> 10988 | O5: 10988
B6: TENANT NAME | D6: =meter!A4 -> GODFREY IRONGO | N6: =O6-Q6 -> 11070 | O6: 11070
N7: =O7-Q7 -> 1197 | O7: 1197
B8: HOUSE NUMBER | D8: 2A | N8: =O8-Q8 -> 9250 | O8: 9250
N9: =O9-Q9 -> 8770 | O9: 8770
B10: ISSUE DATE | D10: ='hse1'!C10 -> 27/1/2026 | N10: =O10-Q10 -> 23190 | O10: 23190
N11: =O11-Q11 -> 10910 | O11: 10910
B12: LAST PAY DATE | D12: ='hse1'!C12 -> 46144 | N12: =O12-Q12 -> 10910 | O12: 10910
N13: =O13-Q13 -> 12190 | O13: 12190
N14: =O14-Q14 -> 11070 | O14: 11070
B15: PREVIOUS READING | D15: CURRENT READING | F15: CONSUMPTION (Units) | N15: =O15-Q15 -> 9090 | O15: 9090
B16: =meter!D4 -> 229 | D16: =meter!E4 -> 232 | E16: Units | F16: =D16-B16 -> 3 | N16: =O16-Q16 -> 9420 | O16: 9420
F17: Amount (Kshs.) | N17: =O17-Q17 -> 11154 | O17: 11154
D18: LAST ACCOUNT B/F | E18: Kshs. | F18: =meter!O4 -> 0 | N18: =O18-Q18 -> 10430 | O18: 10430
N19: =O19-Q19 -> 11831 | O19: 11831
D20: MONTH BILL | E20: Kshs. | F20: =meter!H4 -> 660 | N20: =O20-Q20 -> 10590 | O20: 10590
N21: =O21-Q21 -> 22423 | O21: 22423
D22: PUMP/POWER CHARGES | E22: Kshs. | F22: ='hse1'!E22 -> 110 | N22: =O22-Q22 -> 9250 | O22: 9250
N23: =O23-Q23 -> 10162 | O23: 10162
D24: MONTH HOUSE RENT | E24: Kshs. | F24: 10000 | N24: =O24-Q24 -> 10270 | O24: 10270
N25: =O25-Q25 -> 11070 | O25: 11070
D26: ='hse1'!C26 -> security | E26: Kshs. | F26: 500 | N26: =O26-Q26 -> 11550 | O26: 11550
D27: GARBAGE FEE | F27: 150 | N27: =O27-Q27 -> 11393 | O27: 11393
D28: INTEREST ON ARREARS | E28: Kshs. | F28: =IF(F18*6%*3<0,0,F18*6%*3) -> 0 | N28: =O28-Q28 -> 10802 | O28: 10802
F29: 0 | N29: =O29-Q29 -> 8930 | O29: 8930
D30: TOTAL PAYABLE | E30: Kshs. | F30: =SUM(F17:F29) -> 11420 | N30: =O30-Q30 -> 9570 | O30: 9570
N31: =O31-Q31 -> 11390 | O31: 11390
D32: PAID | F32: =meter!R4 -> 0 | N32: =O32-Q32 -> 10750 | O32: 10750
N33: =O33-Q33 -> 11732 | O33: 11732
D34: AMOUNT DUE | F34: =F30-F32 -> 11420 | N34: =O34-Q34 -> 10934 | O34: 10934 | R34: 700
C35: NOTE | N35: =O35-Q35 -> 10270 | O35: 10270
B36: a) | C36: Rent is due on or before 5th of the month. By 7th day, any rent not paid will attract interest at 2% per day. | N36: =O36-Q36 -> 10598 | O36: 10598
B37: b) | C37: Any default in Rent payment by 10th of the following month the house shall be locked without notice and belongings removed for re-letting. | N37: =O37-Q37 -> 8770 | O37: 8770
N38: =O38-Q38 -> 8770 | O38: 8770
B39: c) | C39: Amounts not cleared by last pay date will render to water disconnection. | O39: =SUM(O3:O38) -> 391268 | Q39: =SUM(Q3:Q38) -> 0
B41: d) | C41: A reconnection fee of Kshs. 1,000 will be charged and paid before supply is reconnected.
B42: e) | C42: ANY MINOR REPAIRS OCCURING AFTER 3 MONTHS OF OCCUPANCY ARE TENANT'S RESPONSIBILITY AS PER TENANCY AGREEMENT.
B43: f) | C43: The water bills are payable through the same account for monthly rent strictly through:
C44: Frebazeth Company Limited
C45: Consolidated Bank Account
C46: Kitengela Branch
C47: PAY BILL 4139271
C48: (Kindly indicate your Name & House number on the deposit slip & inform the Bank teller to capture it.)
C49: A receipt will be issued upon bank confirmation of the transaction. | O49: ……………
C51: ACC NO KT 2A
C52: E & O E
C53: NB: Kindly give the management atleast two (2) months prior notice incase you intend to terminate the tenancy for ease of logisitics.

Sheet hse3
B2: OLE SAMEDHA APARTMENTS-Kitengela | N2: VAR | O2: TAX DUE
B3: ='hse1'!B3 -> P.O BOX 9473-00200 NAIROBI | N3: =O3-Q3 -> 10270 | O3: 10270
B4: WATER BILL | G4: BILL NO. | H4: ='hse1'!H4+3-1 -> 20242003 | N4: =O4-Q4 -> 10304 | O4: 10304
N5: =O5-Q5 -> 10988 | O5: 10988
B6: TENANT NAME | C6: =meter!A5 -> STACY | N6: =O6-Q6 -> 11070 | O6: 11070
N7: =O7-Q7 -> 1197 | O7: 1197
B8: HOUSE NUMBER: | C8: 3A | N8: =O8-Q8 -> 9250 | O8: 9250
N9: =O9-Q9 -> 8770 | O9: 8770
B10: ISSUE DATE | C10: ='hse1'!C10 -> 27/1/2026 | N10: =O10-Q10 -> 23190 | O10: 23190
N11: =O11-Q11 -> 10910 | O11: 10910
B12: LAST PAY DATE | C12: ='hse1'!C12 -> 46144 | N12: =O12-Q12 -> 10910 | O12: 10910
N13: =O13-Q13 -> 12190 | O13: 12190
N14: =O14-Q14 -> 11070 | O14: 11070
B15: PREVIOUS READING | C15: CURRENT READING | E15: CONSUMPTION (Units) | N15: =O15-Q15 -> 9090 | O15: 9090
B16: =meter!D5 -> 845 | C16: =meter!E5 -> 847 | D16: Units | E16: =C16-B16 -> 2 | N16: =O16-Q16 -> 9420 | O16: 9420
E17: Amount (Kshs.) | N17: =O17-Q17 -> 11154 | O17: 11154
C18: LAST ACCOUNT B/F | D18: Kshs. | E18: =meter!O5 -> 2450 | N18: =O18-Q18 -> 10430 | O18: 10430
N19: =O19-Q19 -> 11831 | O19: 11831
C20: MONTH BILL | D20: Kshs. | E20: =meter!H5 -> 440 | N20: =O20-Q20 -> 10590 | O20: 10590
N21: =O21-Q21 -> 22423 | O21: 22423
C22: PUMP/POWER CHARGES | D22: Kshs. | E22: =meter!J5 -> 110 | N22: =O22-Q22 -> 9250 | O22: 9250
N23: =O23-Q23 -> 10162 | O23: 10162
C24: MONTH HOUSE RENT | D24: Kshs. | E24: =meter!N5 -> 10500 | N24: =O24-Q24 -> 10270 | O24: 10270
N25: =O25-Q25 -> 11070 | O25: 11070
C26: SECURITY | D26: Kshs. | E26: 500 | N26: =O26-Q26 -> 11550 | O26: 11550
C27: GARBAGE FEE | D27: Kshs. | E27: 150 | N27: =O27-Q27 -> 11393 | O27: 11393
C28: ADJUSTMENT | D28: Kshs. | E28: =IF(E18*6%*3<0,0,E18*6%*3) -> 441 | N28: =O28-Q28 -> 10802 | O28: 10802
N29: =O29-Q29 -> 8930 | O29: 8930
C30: TOTAL PAYABLE | D30: Kshs. | E30: =SUM(E17:E29) -> 14591 | N30: =O30-Q30 -> 9570 | O30: 9570
N31: =O31-Q31 -> 11390 | O31: 11390
C32: PAID | E32: =meter!R5 -> 0 | N32: =O32-Q32 -> 10750 | O32: 10750
N33: =O33-Q33 -> 11732 | O33: 11732
C34: AMOUNT DUE | E34: =E30-E32 -> 14591 | N34: =O34-Q34 -> 10934 | O34: 10934 | R34: 700
B35: NOTE | N35: =O35-Q35 -> 10270 | O35: 10270
A36: a) | B36: Rent is due on or before 5th of the month. By 7th day, any rent not paid will attract interest at 2% per day. | N36: =O36-Q36 -> 10598 | O36: 10598
A37: b) | B37: Any default in Rent payment by 10th of the following month the house shall be locked without notice and belongings removed for re-letting. | N37: =O37-Q37 -> 8770 | O37: 8770
N38: =O38-Q38 -> 8770 | O38: 8770
A39: c) | B39: Amounts not cleared by last pay date will render to water disconnection. | O39: =SUM(O3:O38) -> 391268 | Q39: =SUM(Q3:Q38) -> 0
A41: d) | B41: A reconnection fee of Kshs. 1,000 will be charged and paid before supply is reconnected.
A42: e) | B42: ANY MINOR REPAIRS OCCURING AFTER 3 MONTHS OF OCCUPANCY ARE TENANT'S RESPONSIBILITY AS PER TENANCY AGREEMENT.
A43: f) | B43: The water bills are payable through the same account for monthly rent strictly through:
B44: Frebazeth Company Limited
B45: Consolidated Bank Account
B46: Kitengela Branch
B47: PAY BILL 4139271
B48: (Kindly indicate your Name & House number on the deposit slip & inform the Bank teller to capture it.)
B49: A receipt will be issued upon bank confirmation of the transaction. | O49: ……………
A51: E & O E | B51: ACC NO KT 3A
A52: NB: Kindly give the management atleast two (2) months prior notice incase you intend to terminate the tenancy for ease of logisitics. | B52: E & O E
B53: NB: Kindly give the management atleast two (2) months prior notice incase you intend to terminate the tenancy for ease of logisitics.

Sheet hse4
B2: OLE SAMEDHA APARTMENTS-Kitengela | N2: VAR | O2: TAX DUE
B3: ='hse1'!B3 -> P.O BOX 9473-00200 NAIROBI | N3: =O3-Q3 -> 10270 | O3: 10270
B4: WATER BILL | G4: BILL NO. | H4: ='hse1'!H4+4-1 -> 20242004 | N4: =O4-Q4 -> 10304 | O4: 10304
N5: =O5-Q5 -> 10988 | O5: 10988
B6: TENANT NAME | C6: =meter!A6 -> MARY | N6: =O6-Q6 -> 11070 | O6: 11070
N7: =O7-Q7 -> 1197 | O7: 1197
B8: HOUSE NUMBER: | C8: 4A | N8: =O8-Q8 -> 9250 | O8: 9250
N9: =O9-Q9 -> 8770 | O9: 8770
B10: ISSUE DATE | C10: ='hse1'!C10 -> 27/1/2026 | N10: =O10-Q10 -> 23190 | O10: 23190
N11: =O11-Q11 -> 10910 | O11: 10910
B12: LAST PAY DATE | C12: ='hse1'!C12 -> 46144 | N12: =O12-Q12 -> 10910 | O12: 10910
N13: =O13-Q13 -> 12190 | O13: 12190
N14: =O14-Q14 -> 11070 | O14: 11070
B15: PREVIOUS READING | C15: CURRENT READING | E15: CONSUMPTION | N15: =O15-Q15 -> 9090 | O15: 9090
B16: =meter!D6 -> 721 | C16: =meter!E6 -> 724 | D16: Units | E16: =C16-B16 -> 3 | N16: =O16-Q16 -> 9420 | O16: 9420
E17: Amount (Kshs) | N17: =O17-Q17 -> 11154 | O17: 11154
C18: LAST ACCOUNT B/F | D18: Kshs. | E18: =meter!O6 -> 5250 | N18: =O18-Q18 -> 10430 | O18: 10430
N19: =O19-Q19 -> 11831 | O19: 11831
C20: MONTH BILL | D20: Kshs. | E20: =meter!H6 -> 660 | N20: =O20-Q20 -> 10590 | O20: 10590
N21: =O21-Q21 -> 22423 | O21: 22423
C22: PUMP/POWER CHARGES | D22: Kshs. | E22: =meter!J6 -> 110 | N22: =O22-Q22 -> 9250 | O22: 9250
N23: =O23-Q23 -> 10162 | O23: 10162
C24: MONTH HOUSE RENT | D24: Kshs. | E24: =meter!N6 -> 10000 | N24: =O24-Q24 -> 10270 | O24: 10270
N25: =O25-Q25 -> 11070 | O25: 11070
C26: SECURITY | D26: Kshs. | E26: 500 | N26: =O26-Q26 -> 11550 | O26: 11550
C27: GARBAGE FEE | D27: Kshs. | E27: 150 | N27: =O27-Q27 -> 11393 | O27: 11393
C28: INTEREST ON ARREARS | D28: Kshs. | E28: =IF(E18*6%*3<0,0,E18*6%*3) -> 945 | N28: =O28-Q28 -> 10802 | O28: 10802
N29: =O29-Q29 -> 8930 | O29: 8930
C30: TOTAL PAYABLE | D30: Kshs. | E30: =SUM(E17:E29) -> 17615 | N30: =O30-Q30 -> 9570 | O30: 9570
N31: =O31-Q31 -> 11390 | O31: 11390
C32: PAID | E32: =meter!R6 -> 0 | N32: =O32-Q32 -> 10750 | O32: 10750
N33: =O33-Q33 -> 11732 | O33: 11732
C34: AMOUNT DUE | E34: =E30-E32 -> 17615 | N34: =O34-Q34 -> 10934 | O34: 10934 | R34: 700
B35: NOTE | N35: =O35-Q35 -> 10270 | O35: 10270
A36: a) | B36: Rent is due on or before 5th of the month. By 7th day, any rent not paid will attract interest at 2% per day. | N36: =O36-Q36 -> 10598 | O36: 10598
A37: b) | B37: Any default in Rent payment by 10th of the following month the house shall be locked without notice and belongings removed for re-letting. | N37: =O37-Q37 -> 8770 | O37: 8770
N38: =O38-Q38 -> 8770 | O38: 8770
A39: c) | B39: Amounts not cleared by last pay date will render to water disconnection. | O39: =SUM(O3:O38) -> 391268 | Q39: =SUM(Q3:Q38) -> 0
A41: d) | B41: A reconnection fee of Kshs. 1,000 will be charged and paid before supply is reconnected.
A42: e) | B42: ANY MINOR REPAIRS OCCURING AFTER 3 MONTHS OF OCCUPANCY ARE TENANT'S RESPONSIBILITY AS PER TENANCY AGREEMENT.
A43: f) | B43: The water bills are payable through the same account for monthly rent strictly through:
B44: Frebazeth Company Limited
B45: Consolidated Bank Account
B46: Kitengela Branch
B47: PAY BILL 4139271
B48: (Kindly indicate your Name & House number on the deposit slip & inform the Bank teller to capture it.)
B49: A receipt will be issued upon bank confirmation of the transaction. | O49: ……………
A51: E & O E | B51: ACC NO KT 4A
A52: NB: Kindly give the management atleast two (2) months prior notice incase you intend to terminate the tenancy for ease of logisitics. | B52: E & O E
B53: NB: Kindly give the management atleast two (2) months prior notice incase you intend to terminate the tenancy for ease of logisitics.

Sheet hse5
B2: OLE SAMEDHA APARTMENTS-Kitengela | N2: VAR | O2: TAX DUE
B3: ='hse1'!B3 -> P.O BOX 9473-00200 NAIROBI | N3: =O3-Q3 -> 10270 | O3: 10270
B4: WATER BILL | G4: BILL NO. | H4: ='hse1'!H4+5-1 -> 20242005 | N4: =O4-Q4 -> 10304 | O4: 10304
N5: =O5-Q5 -> 10988 | O5: 10988
B6: TENANT NAME | C6: =meter!A7 -> GEOFFREY | N6: =O6-Q6 -> 11070 | O6: 11070
N7: =O7-Q7 -> 1197 | O7: 1197
B8: HOUSE NUMBER; | C8: 5A | N8: =O8-Q8 -> 9250 | O8: 9250
N9: =O9-Q9 -> 8770 | O9: 8770
B10: ISSUE DATE | C10: ='hse1'!C10 -> 27/1/2026 | N10: =O10-Q10 -> 23190 | O10: 23190
N11: =O11-Q11 -> 10910 | O11: 10910
B12: LAST PAY DATE | C12: ='hse1'!C12 -> 46144 | N12: =O12-Q12 -> 10910 | O12: 10910
N13: =O13-Q13 -> 12190 | O13: 12190
N14: =O14-Q14 -> 11070 | O14: 11070
B15: PREVIOUS READING | C15: CURRENT READING | E15: CONSUMPTION (Units) | N15: =O15-Q15 -> 9090 | O15: 9090
B16: =meter!D7 -> 125 | C16: =meter!E7 -> 126 | D16: Units | E16: =C16-B16 -> 1 | N16: =O16-Q16 -> 9420 | O16: 9420
E17: Amount(Kshs) | N17: =O17-Q17 -> 11154 | O17: 11154
C18: LAST ACCOUNT B/F | D18: Kshs. | E18: =meter!O7 -> 0 | N18: =O18-Q18 -> 10430 | O18: 10430
N19: =O19-Q19 -> 11831 | O19: 11831
C20: MONTH BILL | D20: Kshs. | E20: =meter!H7 -> 0 | N20: =O20-Q20 -> 10590 | O20: 10590
N21: =O21-Q21 -> 22423 | O21: 22423
C22: PUMP/POWER CHARGES | D22: Kshs. | E22: ='hse1'!E22 -> 110 | N22: =O22-Q22 -> 9250 | O22: 9250
N23: =O23-Q23 -> 10162 | O23: 10162
C24: MONTH HOUSE RENT | D24: Kshs. | N24: =O24-Q24 -> 10270 | O24: 10270
N25: =O25-Q25 -> 11070 | O25: 11070
C26: security | D26: ='hse1'!D26 -> Kshs. | E26: 500 | N26: =O26-Q26 -> 11550 | O26: 11550
C27: GARBAGE FEE | D27: Kshs. | E27: 150 | N27: =O27-Q27 -> 11393 | O27: 11393
C28: INTEREST ON ARREARS | D28: Kshs. | E28: =IF(E18*6%*3<0,0,E18*6%*3) -> 0 | N28: =O28-Q28 -> 10802 | O28: 10802
N29: =O29-Q29 -> 8930 | O29: 8930
C30: TOTAL PAYABLE | D30: Kshs. | E30: =SUM(E17:E29) -> 760 | N30: =O30-Q30 -> 9570 | O30: 9570
N31: =O31-Q31 -> 11390 | O31: 11390
C32: PAID | E32: =meter!R7 -> 0 | N32: =O32-Q32 -> 10750 | O32: 10750
N33: =O33-Q33 -> 11732 | O33: 11732
C34: AMOUNT DUE | E34: =E30-E32 -> 760 | N34: =O34-Q34 -> 10934 | O34: 10934 | R34: 700
B35: NOTE | N35: =O35-Q35 -> 10270 | O35: 10270
A36: a) | B36: Rent is due on or before 5th of the month. By 7th day, any rent not paid will attract interest at 2% per day. | N36: =O36-Q36 -> 10598 | O36: 10598
A37: b) | B37: Any default in Rent payment by 10th of the following month the house shall be locked without notice and belongings removed for re-letting. | N37: =O37-Q37 -> 8770 | O37: 8770
N38: =O38-Q38 -> 8770 | O38: 8770
A39: c) | B39: Amounts not cleared by last pay date will render to water disconnection. | O39: =SUM(O3:O38) -> 391268 | Q39: =SUM(Q3:Q38) -> 0
A41: d) | B41: A reconnection fee of Kshs. 1,000 will be charged and paid before supply is reconnected.
A42: e) | B42: ANY MINOR REPAIRS OCCURING AFTER 3 MONTHS OF OCCUPANCY ARE TENANT'S RESPONSIBILITY AS PER TENANCY AGREEMENT.
A43: f) | B43: The water bills are payable through the same account for monthly rent strictly through:
B44: Frebazeth Company Limited
B45: Consolidated Bank Account
B46: Kitengela Branch
B47: PAY BILL 4139271
B48: (Kindly indicate your Name & House number on the deposit slip & inform the Bank teller to capture it.)
B49: A receipt will be issued upon bank confirmation of the transaction. | O49: ……………
A51: E & O E | B51: ACC NO KT 5A
A52: NB: Kindly give the management atleast two (2) months prior notice incase you intend to terminate the tenancy for ease of logisitics. | B52: E & O E
B53: NB: Kindly give the management atleast two (2) months prior notice incase you intend to terminate the tenancy for ease of logisitics.

Sheet hse6B
B2: OLE SAMEDHA APARTMENTS-Kitengela | N2: VAR | O2: TAX DUE
B3: ='hse1'!B3 -> P.O BOX 9473-00200 NAIROBI | N3: =O3-Q3 -> 10270 | O3: 10270
B4: WATER BILL | F4: BILL NO. | G4: BILL NO. | H4: ='hse1'!H4+6-1 -> 20242006 | N4: =O4-Q4 -> 10304 | O4: 10304
N5: =O5-Q5 -> 10988 | O5: 10988
B6: TENANT NAME | C6: EVERLINE | N6: =O6-Q6 -> 11070 | O6: 11070
N7: =O7-Q7 -> 1197 | O7: 1197
B8: HOUSE NUMBER: | C8: 6B | N8: =O8-Q8 -> 9250 | O8: 9250
N9: =O9-Q9 -> 8770 | O9: 8770
B10: ISSUE DATE | C10: ='hse1'!C10 -> 27/1/2026 | N10: =O10-Q10 -> 23190 | O10: 23190
N11: =O11-Q11 -> 10910 | O11: 10910
B12: LAST PAY DATE | C12: ='hse1'!C12 -> 46144 | N12: =O12-Q12 -> 10910 | O12: 10910
N13: =O13-Q13 -> 12190 | O13: 12190
N14: =O14-Q14 -> 11070 | O14: 11070
B15: PREVIOUS READING | C15: CURRENT READING | E15: CONSUMPTION | N15: =O15-Q15 -> 9090 | O15: 9090
B16: =meter!D8 -> 450 | C16: =meter!E8 -> 450 | D16: Units | E16: =C16-B16 -> 0 | N16: =O16-Q16 -> 9420 | O16: 9420
E17: Amount(Kshs) | N17: =O17-Q17 -> 11154 | O17: 11154
C18: LAST ACCOUNT | D18: kshs. | E18: =meter!O8 -> 0 | N18: =O18-Q18 -> 10430 | O18: 10430
N19: =O19-Q19 -> 11831 | O19: 11831
C20: MONTH BILL | D20: KSHS. | E20: =meter!H8 -> 0 | N20: =O20-Q20 -> 10590 | O20: 10590
N21: =O21-Q21 -> 22423 | O21: 22423
C22: PUMP/POWER CHARGES | D22: KSHS. | E22: ='hse1'!E22 -> 110 | N22: =O22-Q22 -> 9250 | O22: 9250
N23: =O23-Q23 -> 10162 | O23: 10162
C24: MONTH HOUSE RENT | D24: KSHS. | E24: =meter!N8 -> 8500 | N24: =O24-Q24 -> 10270 | O24: 10270
N25: =O25-Q25 -> 11070 | O25: 11070
C26: ='hse1'!C26 -> security | D26: ='hse1'!D26 -> Kshs. | E26: =meter!M8 -> 0 | N26: =O26-Q26 -> 11550 | O26: 11550
C27: GARBAGE FEE | E27: 150 | N27: =O27-Q27 -> 11393 | O27: 11393
C28: ADJUSTMENT (Interest late payment) | D28: KSHS. | N28: =O28-Q28 -> 10802 | O28: 10802
N29: =O29-Q29 -> 8930 | O29: 8930
C30: TOTAL PAYABLE | D30: Kshs. | E30: =SUM(E17:E29) -> 8760 | N30: =O30-Q30 -> 9570 | O30: 9570
N31: =O31-Q31 -> 11390 | O31: 11390
C32: PAID | E32: 0 | N32: =O32-Q32 -> 10750 | O32: 10750
N33: =O33-Q33 -> 11732 | O33: 11732
C34: AMOUNT DUE | E34: =E30-E32 -> 8760 | N34: =O34-Q34 -> 10934 | O34: 10934 | R34: 700
B35: NOTE | C35: PAY & VACATE, REPAIRS CHARGES OF 8,400/- REMAINS TILL NEW TENANT LEAVES, THEN WE REPAIR | N35: =O35-Q35 -> 10270 | O35: 10270
A36: a) | B36: Rent is due on or before 5th of the month. By 7th day, any rent not paid will attract interest at 2% per day. | N36: =O36-Q36 -> 10598 | O36: 10598
A37: b) | B37: Any default in Rent payment by 10th of the following month the house shall be locked without notice and belongings removed for re-letting. | N37: =O37-Q37 -> 8770 | O37: 8770
N38: =O38-Q38 -> 8770 | O38: 8770
A39: c) | B39: Amounts not cleared by last pay date will render to water disconnection. | O39: =SUM(O3:O38) -> 391268 | Q39: =SUM(Q3:Q38) -> 0
A41: d) | B41: A reconnection fee of Kshs. 1,000 will be charged and paid before supply is reconnected.
A42: e) | B42: ANY MINOR REPAIRS OCCURING AFTER 3 MONTHS OF OCCUPANCY ARE TENANT'S RESPONSIBILITY AS PER TENANCY AGREEMENT.
A43: f) | B43: The water bills are payable through the same account for monthly rent strictly through:
B44: Frebazeth Company Limited
B45: Consolidated Bank Account
B46: Kitengela Branch
B47: PAY BILL 4139271
B48: (Kindly indicate your Name & House number on the deposit slip & inform the Bank teller to capture it.)
B49: A receipt will be issued upon bank confirmation of the transaction. | O49: ……………
B51: ACC NO KT 6B
B52: E & O E
B53: NB: Kindly give the management atleast two (2) months prior notice incase you intend to terminate the tenancy for ease of logisitics.

Sheet hse7B
B2: OLE SAMEDHA APARTMENTS-Kitengela | N2: VAR | O2: TAX DUE
B3: ='hse1'!B3 -> P.O BOX 9473-00200 NAIROBI | N3: =O3-Q3 -> 10270 | O3: 10270
B4: WATER BILL | G4: BILL NO. | H4: ='hse1'!H4+7-1 -> 20242007 | N4: =O4-Q4 -> 10304 | O4: 10304
N5: =O5-Q5 -> 10988 | O5: 10988
B6: TENANT NAME | C6: AVRIL | N6: =O6-Q6 -> 11070 | O6: 11070
N7: =O7-Q7 -> 1197 | O7: 1197
B8: HOUSE NUMBER: | C8: 7B | N8: =O8-Q8 -> 9250 | O8: 9250
N9: =O9-Q9 -> 8770 | O9: 8770
B10: ISSUE DATE | C10: ='hse1'!C10 -> 27/1/2026 | N10: =O10-Q10 -> 23190 | O10: 23190
N11: =O11-Q11 -> 10910 | O11: 10910
B12: LAST PAY DATE | C12: ='hse1'!C12 -> 46144 | N12: =O12-Q12 -> 10910 | O12: 10910
N13: =O13-Q13 -> 12190 | O13: 12190
N14: =O14-Q14 -> 11070 | O14: 11070
B15: PREVIOUS READING | C15: CURRENT READING | E15: CONSUMPTION | N15: =O15-Q15 -> 9090 | O15: 9090
B16: =meter!D9 -> 630 | C16: =meter!E9 -> 630 | D16: Units | E16: =C16-B16 -> 0 | N16: =O16-Q16 -> 9420 | O16: 9420
E17: Amount (Kshs) | N17: =O17-Q17 -> 11154 | O17: 11154
C18: LAST ACCOUNT | D18: kshs. | E18: 0 | N18: =O18-Q18 -> 10430 | O18: 10430
N19: =O19-Q19 -> 11831 | O19: 11831
C20: MONTH BILL | D20: KSHS. | E20: =meter!H9 -> 0 | N20: =O20-Q20 -> 10590 | O20: 10590
N21: =O21-Q21 -> 22423 | O21: 22423
C22: PUMP/POWER CHARGES | D22: KSHS. | E22: ='hse1'!E22 -> 110 | N22: =O22-Q22 -> 9250 | O22: 9250
N23: =O23-Q23 -> 10162 | O23: 10162
C24: MONTH HOUSE RENT | D24: KSHS. | E24: 8500 | N24: =O24-Q24 -> 10270 | O24: 10270
N25: =O25-Q25 -> 11070 | O25: 11070
C26: ='hse1'!C26 -> security | D26: ='hse1'!D26 -> Kshs. | N26: =O26-Q26 -> 11550 | O26: 11550
C27: GARBAGE FEE | E27: 150 | N27: =O27-Q27 -> 11393 | O27: 11393
C28: ADJUSTMENT-interest on arrears | D28: KSHS. | E28: =IF(E18*6%*3<0,0,E18*6%*3) -> 0 | N28: =O28-Q28 -> 10802 | O28: 10802
N29: =O29-Q29 -> 8930 | O29: 8930
C30: TOTAL PAYABLE | D30: Kshs. | E30: =SUM(E17:E29) -> 8760 | N30: =O30-Q30 -> 9570 | O30: 9570
N31: =O31-Q31 -> 11390 | O31: 11390
C32: PAID | E32: 0 | N32: =O32-Q32 -> 10750 | O32: 10750
N33: =O33-Q33 -> 11732 | O33: 11732
C34: AMOUNT DUE | E34: =E30-E32 -> 8760 | N34: =O34-Q34 -> 10934 | O34: 10934 | R34: 700
B35: NOTE | N35: =O35-Q35 -> 10270 | O35: 10270
A36: a) | B36: Rent is due on or before 5th of the month. By 7th day, any rent not paid will attract interest at 2% per day. | N36: =O36-Q36 -> 10598 | O36: 10598
A37: b) | B37: Any default in Rent payment by 10th of the following month the house shall be locked without notice and belongings removed for re-letting. | N37: =O37-Q37 -> 8770 | O37: 8770
N38: =O38-Q38 -> 8770 | O38: 8770
A39: c) | B39: Amounts not cleared by last pay date will render to water disconnection. | O39: =SUM(O3:O38) -> 391268 | Q39: =SUM(Q3:Q38) -> 0
A41: d) | B41: A reconnection fee of Kshs. 1,000 will be charged and paid before supply is reconnected.
A42: e) | B42: ANY MINOR REPAIRS OCCURING AFTER 3 MONTHS OF OCCUPANCY ARE TENANT'S RESPONSIBILITY AS PER TENANCY AGREEMENT.
A43: f) | B43: The water bills are payable through the same account for monthly rent strictly through:
B44: Frebazeth Company Limited
B45: Consolidated Bank Account
B46: Kitengela Branch
B47: PAY BILL 4139271
B48: (Kindly indicate your Name & House number on the deposit slip & inform the Bank teller to capture it.)
B49: A receipt will be issued upon bank confirmation of the transaction. | O49: ……………
B51: ACC NO KT 7B
B52: E & O E
B53: NB: Kindly give the management atleast two (2) months prior notice incase you intend to terminate the tenancy for ease of logisitics.

Sheet hse8
B2: OLE SAMEDHA APARTMENTS-Kitengela | N2: VAR | O2: TAX DUE
B3: ='hse1'!B3 -> P.O BOX 9473-00200 NAIROBI | N3: =O3-Q3 -> 10270 | O3: 10270
B4: WATER BILL | G4: BILL NO. | H4: ='hse1'!H4+8-1 -> 20242008 | N4: =O4-Q4 -> 10304 | O4: 10304
N5: =O5-Q5 -> 10988 | O5: 10988
B6: TENANT NAME | C6: =meter!A10 -> JAMES | N6: =O6-Q6 -> 11070 | O6: 11070
N7: =O7-Q7 -> 1197 | O7: 1197
B8: HOUSE NUMBER: | C8: 8A | N8: =O8-Q8 -> 9250 | O8: 9250
N9: =O9-Q9 -> 8770 | O9: 8770
B10: ISSUE DATE | C10: ='hse1'!C10 -> 27/1/2026 | N10: =O10-Q10 -> 23190 | O10: 23190
N11: =O11-Q11 -> 10910 | O11: 10910
B12: LAST PAY DATE | C12: ='hse1'!C12 -> 46144 | N12: =O12-Q12 -> 10910 | O12: 10910
N13: =O13-Q13 -> 12190 | O13: 12190
N14: =O14-Q14 -> 11070 | O14: 11070
B15: PREVIOUS READING | C15: CURRENT READING | E15: CONSUMPTION | N15: =O15-Q15 -> 9090 | O15: 9090
B16: =meter!D10 -> 48 | C16: =meter!E10 -> 53 | D16: Units | E16: =C16-B16 -> 5 | N16: =O16-Q16 -> 9420 | O16: 9420
E17: Amount (Kshs.) | N17: =O17-Q17 -> 11154 | O17: 11154
C18: LAST ACCOUNT | D18: kshs. | E18: =meter!O10 -> 0 | N18: =O18-Q18 -> 10430 | O18: 10430
N19: =O19-Q19 -> 11831 | O19: 11831
C20: MONTH BILL | D20: KSHS. | E20: =meter!H10 -> 1100 | N20: =O20-Q20 -> 10590 | O20: 10590
N21: =O21-Q21 -> 22423 | O21: 22423
C22: PUMP/POWER CHARGES | D22: KSHS. | E22: ='hse1'!E22 -> 110 | N22: =O22-Q22 -> 9250 | O22: 9250
N23: =O23-Q23 -> 10162 | O23: 10162
C24: MONTH HOUSE RENT | D24: KSHS. | E24: =meter!N10 -> 10500 | N24: =O24-Q24 -> 10270 | O24: 10270
N25: =O25-Q25 -> 11070 | O25: 11070
C26: ='hse1'!C26 -> security | D26: ='hse1'!D26 -> Kshs. | E26: 500 | N26: =O26-Q26 -> 11550 | O26: 11550
C27: GARBAGE FEE | D27: Kshs. | E27: 150 | N27: =O27-Q27 -> 11393 | O27: 11393
C28: ADJUSTMENT-interest on arrears | D28: KSHS. | E28: =IF(E18*6%*3<0,0,E18*6%*3) -> 0 | N28: =O28-Q28 -> 10802 | O28: 10802
N29: =O29-Q29 -> 8930 | O29: 8930
C30: TOTAL PAYABLE | D30: Kshs. | E30: =SUM(E17:E29) -> 12360 | N30: =O30-Q30 -> 9570 | O30: 9570
N31: =O31-Q31 -> 11390 | O31: 11390
C32: PAID | E32: =meter!R10 -> 0 | N32: =O32-Q32 -> 10750 | O32: 10750
N33: =O33-Q33 -> 11732 | O33: 11732
C34: AMOUNT DUE | E34: =E30-E32 -> 12360 | N34: =O34-Q34 -> 10934 | O34: 10934 | R34: 700
B35: NOTE | N35: =O35-Q35 -> 10270 | O35: 10270
A36: a) | B36: Rent is due on or before 5th of the month. By 7th day, any rent not paid will attract interest at 2% per day. | N36: =O36-Q36 -> 10598 | O36: 10598
A37: b) | B37: Any default in Rent payment by 10th of the following month the house shall be locked without notice and belongings removed for re-letting. | N37: =O37-Q37 -> 8770 | O37: 8770
N38: =O38-Q38 -> 8770 | O38: 8770
A39: c) | B39: Amounts not cleared by last pay date will render to water disconnection. | O39: =SUM(O3:O38) -> 391268 | Q39: =SUM(Q3:Q38) -> 0
A41: d) | B41: A reconnection fee of Kshs. 1,000 will be charged and paid before supply is reconnected.
A42: e) | B42: ANY MINOR REPAIRS OCCURING AFTER 3 MONTHS OF OCCUPANCY ARE TENANT'S RESPONSIBILITY AS PER TENANCY AGREEMENT.
A43: f) | B43: The water bills are payable through the same account for monthly rent strictly through:
B44: Frebazeth Company Limited
B45: Consolidated Bank Account
B46: Kitengela Branch
B47: PAY BILL 4139271
B48: (Kindly indicate your Name & House number on the deposit slip & inform the Bank teller to capture it.)
B49: A receipt will be issued upon bank confirmation of the transaction. | O49: ……………
B51: ACC NO KT 8A
B52: E & O E
B53: NB: Kindly give the management atleast two (2) months prior notice incase you intend to terminate the tenancy for ease of logisitics.

Sheet hse9
B2: OLE SAMEDHA APARTMENTS-Kitengela | N2: VAR | O2: TAX DUE
B3: ='hse1'!B3 -> P.O BOX 9473-00200 NAIROBI | N3: =O3-Q3 -> 10270 | O3: 10270
B4: WATER BILL | G4: BILL NO. | H4: ='hse1'!H4+9-1 -> 20242009 | N4: =O4-Q4 -> 10304 | O4: 10304
N5: =O5-Q5 -> 10988 | O5: 10988
B6: TENANT NAME | C6: =meter!A11 -> CHERRYL | N6: =O6-Q6 -> 11070 | O6: 11070
N7: =O7-Q7 -> 1197 | O7: 1197
B8: HOUSE NUMBER: | C8: 9A | N8: =O8-Q8 -> 9250 | O8: 9250
N9: =O9-Q9 -> 8770 | O9: 8770
B10: ISSUE DATE | C10: ='hse1'!C10 -> 27/1/2026 | N10: =O10-Q10 -> 23190 | O10: 23190
N11: =O11-Q11 -> 10910 | O11: 10910
B12: LAST PAY DATE | C12: ='hse1'!C12 -> 46144 | N12: =O12-Q12 -> 10910 | O12: 10910
N13: =O13-Q13 -> 12190 | O13: 12190
N14: =O14-Q14 -> 11070 | O14: 11070
B15: PREVIOUS READING | C15: CURRENT READING | E15: CONSUMPTION | N15: =O15-Q15 -> 9090 | O15: 9090
B16: =meter!D11 -> 193 | C16: =meter!E11 -> 196 | D16: Units | E16: =C16-B16 -> 3 | N16: =O16-Q16 -> 9420 | O16: 9420
E17: Amount (Kshs.) | N17: =O17-Q17 -> 11154 | O17: 11154
C18: LAST ACCOUNT | D18: kshs. | E18: =meter!O11 -> 0 | N18: =O18-Q18 -> 10430 | O18: 10430
N19: =O19-Q19 -> 11831 | O19: 11831
C20: MONTH BILL | D20: KSHS. | E20: =meter!H11 -> 660 | N20: =O20-Q20 -> 10590 | O20: 10590
N21: =O21-Q21 -> 22423 | O21: 22423
C22: PUMP/POWER CHARGES | D22: KSHS. | E22: ='hse1'!E22 -> 110 | N22: =O22-Q22 -> 9250 | O22: 9250
N23: =O23-Q23 -> 10162 | O23: 10162
C24: MONTH HOUSE RENT | D24: KSHS. | E24: =meter!N11 -> 10500 | N24: =O24-Q24 -> 10270 | O24: 10270
N25: =O25-Q25 -> 11070 | O25: 11070
C26: ='hse1'!C26 -> security | D26: ='hse1'!D26 -> Kshs. | E26: 500 | N26: =O26-Q26 -> 11550 | O26: 11550
C27: GARBAGE FEE | D27: Kshs. | E27: 150 | N27: =O27-Q27 -> 11393 | O27: 11393
C28: Penalty & Interest late payment | D28: KSHS. | E28: =IF(E18*4%*1<0,0,E18*4%*1) -> 0 | N28: =O28-Q28 -> 10802 | O28: 10802
N29: =O29-Q29 -> 8930 | O29: 8930
C30: TOTAL PAYABLE | D30: Kshs. | E30: =SUM(E17:E29) -> 11920 | N30: =O30-Q30 -> 9570 | O30: 9570
N31: =O31-Q31 -> 11390 | O31: 11390
C32: PAID | E32: =meter!R11 -> 0 | N32: =O32-Q32 -> 10750 | O32: 10750
N33: =O33-Q33 -> 11732 | O33: 11732
C34: AMOUNT DUE | E34: =E30-E32 -> 11920 | N34: =O34-Q34 -> 10934 | O34: 10934 | R34: 700
B35: NOTE | N35: =O35-Q35 -> 10270 | O35: 10270
A36: a) | B36: Rent is due on or before 5th of the month. By 7th day, any rent not paid will attract interest at 2% per day. | N36: =O36-Q36 -> 10598 | O36: 10598
A37: b) | B37: Any default in Rent payment by 10th of the following month the house shall be locked without notice and belongings removed for re-letting. | N37: =O37-Q37 -> 8770 | O37: 8770
N38: =O38-Q38 -> 8770 | O38: 8770
A39: c) | B39: Amounts not cleared by last pay date will render to water disconnection. | O39: =SUM(O3:O38) -> 391268 | Q39: =SUM(Q3:Q38) -> 0
A41: d) | B41: A reconnection fee of Kshs. 1,000 will be charged and paid before supply is reconnected.
A42: e) | B42: ANY MINOR REPAIRS OCCURING AFTER 3 MONTHS OF OCCUPANCY ARE TENANT'S RESPONSIBILITY AS PER TENANCY AGREEMENT.
A43: f) | B43: The water bills are payable through the same account for monthly rent strictly through:
B44: Frebazeth Company Limited
B45: Consolidated Bank Account
B46: Kitengela Branch
B47: PAY BILL 4139271
B48: (Kindly indicate your Name & House number on the deposit slip & inform the Bank teller to capture it.)
B49: A receipt will be issued upon bank confirmation of the transaction. | O49: ……………
B51: ACC NO KT 9A
B52: E & O E
B53: NB: Kindly give the management atleast two (2) months prior notice incase you intend to terminate the tenancy for ease of logisitics.

Sheet hse10
B2: OLE SAMEDHA APARTMENTS-Kitengela | N2: VAR | O2: TAX DUE
B3: ='hse1'!B3 -> P.O BOX 9473-00200 NAIROBI | N3: =O3-Q3 -> 10270 | O3: 10270
B4: WATER BILL | G4: BILL NO. | H4: ='hse1'!H4+10-1 -> 20242010 | N4: =O4-Q4 -> 10304 | O4: 10304
N5: =O5-Q5 -> 10988 | O5: 10988
B6: TENANT NAME | C6: =meter!A12 -> JACK | N6: =O6-Q6 -> 11070 | O6: 11070
N7: =O7-Q7 -> 1197 | O7: 1197
B8: HOUSE NUMBER: | C8: 10A | N8: =O8-Q8 -> 9250 | O8: 9250
N9: =O9-Q9 -> 8770 | O9: 8770
B10: ISSUE DATE | C10: ='hse1'!C10 -> 27/1/2026 | N10: =O10-Q10 -> 23190 | O10: 23190
N11: =O11-Q11 -> 10910 | O11: 10910
B12: LAST PAY DATE | C12: ='hse1'!C12 -> 46144 | N12: =O12-Q12 -> 10910 | O12: 10910
N13: =O13-Q13 -> 12190 | O13: 12190
N14: =O14-Q14 -> 11070 | O14: 11070
B15: PREVIOUS READING | C15: CURRENT READING | E15: CONSUMPTION | N15: =O15-Q15 -> 9090 | O15: 9090
B16: =meter!D12 -> 66 | C16: =meter!E12 -> 70 | D16: Units | E16: =C16-B16 -> 4 | N16: =O16-Q16 -> 9420 | O16: 9420
E17: Amount (Kshs) | N17: =O17-Q17 -> 11154 | O17: 11154
C18: LAST ACCOUNT | D18: kshs. | N18: =O18-Q18 -> 10430 | O18: 10430
N19: =O19-Q19 -> 11831 | O19: 11831
C20: MONTH BILL | D20: KSHS. | E20: =meter!H12 -> 880 | N20: =O20-Q20 -> 10590 | O20: 10590
N21: =O21-Q21 -> 22423 | O21: 22423
C22: PUMP/POWER CHARGES | D22: KSHS. | E22: ='hse1'!E22 -> 110 | N22: =O22-Q22 -> 9250 | O22: 9250
N23: =O23-Q23 -> 10162 | O23: 10162
C24: MONTH HOUSE RENT | D24: KSHS. | E24: =meter!N12 -> 10500 | N24: =O24-Q24 -> 10270 | O24: 10270
N25: =O25-Q25 -> 11070 | O25: 11070
C26: ='hse1'!C26 -> security | D26: KSHS. | E26: 500 | N26: =O26-Q26 -> 11550 | O26: 11550
C27: GARBAGE FEE | D27: KSHS. | E27: 150 | N27: =O27-Q27 -> 11393 | O27: 11393
C28: INTEREST ON LATE PAYMENT | D28: KSHS. | E28: =IF(E18*4%*1<0,0,E18*4%*1) -> 0 | N28: =O28-Q28 -> 10802 | O28: 10802
N29: =O29-Q29 -> 8930 | O29: 8930
C30: TOTAL PAYABLE | D30: Kshs. | E30: =SUM(E17:E29) -> 12140 | N30: =O30-Q30 -> 9570 | O30: 9570
N31: =O31-Q31 -> 11390 | O31: 11390
C32: PAID | E32: =meter!R12 -> 0 | N32: =O32-Q32 -> 10750 | O32: 10750
N33: =O33-Q33 -> 11732 | O33: 11732
C34: AMOUNT DUE | E34: =E30-E32 -> 12140 | N34: =O34-Q34 -> 10934 | O34: 10934 | R34: 700
B35: NOTE | N35: =O35-Q35 -> 10270 | O35: 10270
A36: a) | B36: Rent is due on or before 5th of the month. By 7th day, any rent not paid will attract interest at 2% per day. | N36: =O36-Q36 -> 10598 | O36: 10598
A37: b) | B37: Any default in Rent payment by 10th of the following month the house shall be locked without notice and belongings removed for re-letting. | N37: =O37-Q37 -> 8770 | O37: 8770
N38: =O38-Q38 -> 8770 | O38: 8770
A39: c) | B39: Amounts not cleared by last pay date will render to water disconnection. | O39: =SUM(O3:O38) -> 391268 | Q39: =SUM(Q3:Q38) -> 0
A41: d) | B41: A reconnection fee of Kshs. 1,000 will be charged and paid before supply is reconnected.
A42: e) | B42: ANY MINOR REPAIRS OCCURING AFTER 3 MONTHS OF OCCUPANCY ARE TENANT'S RESPONSIBILITY AS PER TENANCY AGREEMENT.
A43: f) | B43: The water bills are payable through the same account for monthly rent strictly through:
B44: Frebazeth Company Limited
B45: Consolidated Bank Account
B46: Kitengela Branch
B47: PAY BILL 4139271
B48: (Kindly indicate your Name & House number on the deposit slip & inform the Bank teller to capture it.)
B49: A receipt will be issued upon bank confirmation of the transaction. | O49: ……………
B51: ACC NO KT 10A
B52: E & O E
B53: NB: Kindly give the management atleast two (2) months prior notice incase you intend to terminate the tenancy for ease of logisitics.

Sheet hse11
B2: OLE SAMEDHA APARTMENTS-Kitengela | N2: VAR | O2: TAX DUE
B3: ='hse1'!B3 -> P.O BOX 9473-00200 NAIROBI | N3: =O3-Q3 -> 10270 | O3: 10270
B4: WATER BILL | G4: BILL NO. | H4: ='hse1'!H4+11-1 -> 20242011 | N4: =O4-Q4 -> 10304 | O4: 10304
N5: =O5-Q5 -> 10988 | O5: 10988
B6: TENANT NAME | C6: =meter!A13 -> JAMES NGUGI | N6: =O6-Q6 -> 11070 | O6: 11070
N7: =O7-Q7 -> 1197 | O7: 1197
B8: HOUSE NUMBER: | C8: 11A | N8: =O8-Q8 -> 9250 | O8: 9250
N9: =O9-Q9 -> 8770 | O9: 8770
B10: ISSUE DATE | C10: ='hse1'!C10 -> 27/1/2026 | N10: =O10-Q10 -> 23190 | O10: 23190
N11: =O11-Q11 -> 10910 | O11: 10910
B12: LAST PAY DATE | C12: ='hse1'!C12 -> 46144 | N12: =O12-Q12 -> 10910 | O12: 10910
N13: =O13-Q13 -> 12190 | O13: 12190
N14: =O14-Q14 -> 11070 | O14: 11070
B15: PREVIOUS READING | C15: CURRENT READING | E15: CONSUMPTION | N15: =O15-Q15 -> 9090 | O15: 9090
B16: =meter!D13 -> 413 | C16: =meter!E13 -> 415 | D16: Units | E16: =C16-B16 -> 2 | N16: =O16-Q16 -> 9420 | O16: 9420
E17: Amount (Kshs.) | N17: =O17-Q17 -> 11154 | O17: 11154
C18: LAST ACCOUNT | D18: kshs. | E18: =meter!O13 -> 0 | N18: =O18-Q18 -> 10430 | O18: 10430
N19: =O19-Q19 -> 11831 | O19: 11831
C20: MONTH BILL | D20: KSHS. | E20: =meter!H13 -> 440 | N20: =O20-Q20 -> 10590 | O20: 10590
N21: =O21-Q21 -> 22423 | O21: 22423
C22: PUMP/POWER CHARGES | D22: KSHS. | E22: ='hse1'!E22 -> 110 | N22: =O22-Q22 -> 9250 | O22: 9250
N23: =O23-Q23 -> 10162 | O23: 10162
C24: MONTH HOUSE RENT | D24: KSHS. | E24: 9500 | N24: =O24-Q24 -> 10270 | O24: 10270
N25: =O25-Q25 -> 11070 | O25: 11070
C26: ='hse1'!C26 -> security | D26: KSHS. | E26: 500 | N26: =O26-Q26 -> 11550 | O26: 11550
C27: GARBAGE FEE | D27: KSHS. | E27: 150 | N27: =O27-Q27 -> 11393 | O27: 11393
C28: INTEREST ON LATE PAYMENT | D28: KSHS. | E28: =IF(E18*4%*1<0,0,E18*4%*1) -> 0 | N28: =O28-Q28 -> 10802 | O28: 10802
N29: =O29-Q29 -> 8930 | O29: 8930
C30: TOTAL PAYABLE | D30: Kshs. | E30: =SUM(E17:E29) -> 10700 | N30: =O30-Q30 -> 9570 | O30: 9570
N31: =O31-Q31 -> 11390 | O31: 11390
C32: PAID | E32: =meter!R13 -> 0 | N32: =O32-Q32 -> 10750 | O32: 10750
N33: =O33-Q33 -> 11732 | O33: 11732
C34: AMOUNT DUE | E34: =E30-E32 -> 10700 | N34: =O34-Q34 -> 10934 | O34: 10934 | R34: 700
B35: NOTE | N35: =O35-Q35 -> 10270 | O35: 10270
A36: a) | B36: Rent is due on or before 5th of the month. By 7th day, any rent not paid will attract interest at 2% per day. | N36: =O36-Q36 -> 10598 | O36: 10598
A37: b) | B37: Any default in Rent payment by 10th of the following month the house shall be locked without notice and belongings removed for re-letting. | N37: =O37-Q37 -> 8770 | O37: 8770
N38: =O38-Q38 -> 8770 | O38: 8770
A39: c) | B39: Amounts not cleared by last pay date will render to water disconnection. | O39: =SUM(O3:O38) -> 391268 | Q39: =SUM(Q3:Q38) -> 0
A41: d) | B41: A reconnection fee of Kshs. 1,000 will be charged and paid before supply is reconnected.
A42: e) | B42: ANY MINOR REPAIRS OCCURING AFTER 3 MONTHS OF OCCUPANCY ARE TENANT'S RESPONSIBILITY AS PER TENANCY AGREEMENT.
A43: f) | B43: The water bills are payable through the same account for monthly rent strictly through:
B44: Frebazeth Company Limited
B45: Consolidated Bank Account
B46: Kitengela Branch
B47: PAY BILL 4139271
B48: (Kindly indicate your Name & House number on the deposit slip & inform the Bank teller to capture it.)
B49: A receipt will be issued upon bank confirmation of the transaction. | O49: ……………
B51: ACC NO KT 11A
B52: E & O E
B53: NB: Kindly give the management atleast two (2) months prior notice incase you intend to terminate the tenancy for ease of logisitics.

Sheet hse12
B2: OLE SAMEDHA APARTMENTS-Kitengela | N2: VAR | O2: TAX DUE
B3: ='hse1'!B3 -> P.O BOX 9473-00200 NAIROBI | N3: =O3-Q3 -> 10270 | O3: 10270
B4: WATER BILL | H4: BILL NO. | I4: ='hse1'!H4+12-1 -> 20242012 | J4: ='hse1'!H4+12-1 -> 20242012 | N4: =O4-Q4 -> 10304 | O4: 10304
N5: =O5-Q5 -> 10988 | O5: 10988
B6: TENANT NAME | D6: =meter!A14 -> LIMO | N6: =O6-Q6 -> 11070 | O6: 11070
N7: =O7-Q7 -> 1197 | O7: 1197
B8: HOUSE NUMBER: | D8: 12A | N8: =O8-Q8 -> 9250 | O8: 9250
N9: =O9-Q9 -> 8770 | O9: 8770
B10: ISSUE DATE | D10: ='hse1'!C10 -> 27/1/2026 | N10: =O10-Q10 -> 23190 | O10: 23190
N11: =O11-Q11 -> 10910 | O11: 10910
B12: LAST PAY DATE | D12: ='hse1'!C12 -> 46144 | N12: =O12-Q12 -> 10910 | O12: 10910
N13: =O13-Q13 -> 12190 | O13: 12190
N14: =O14-Q14 -> 11070 | O14: 11070
B15: PREVIOUS READING | D15: CURRENT READING | F15: CONSUMPTION | N15: =O15-Q15 -> 9090 | O15: 9090
B16: =meter!D14 -> 212 | D16: =meter!E14 -> 224 | E16: Units | F16: =D16-B16 -> 12 | N16: =O16-Q16 -> 9420 | O16: 9420
F17: Amount (Kshs.) | N17: =O17-Q17 -> 11154 | O17: 11154
D18: LAST ACCOUNT | E18: kshs. | F18: =meter!O14 -> 677 | N18: =O18-Q18 -> 10430 | O18: 10430
N19: =O19-Q19 -> 11831 | O19: 11831
D20: MONTH BILL | E20: KSHS. | F20: =meter!H14 -> 2640 | N20: =O20-Q20 -> 10590 | O20: 10590
N21: =O21-Q21 -> 22423 | O21: 22423
D22: PUMP/POWER CHARGES | E22: KSHS. | F22: ='hse1'!E22 -> 110 | N22: =O22-Q22 -> 9250 | O22: 9250
N23: =O23-Q23 -> 10162 | O23: 10162
D24: MONTH HOUSE RENT | E24: KSHS. | F24: =meter!N14 -> 10500 | N24: =O24-Q24 -> 10270 | O24: 10270
N25: =O25-Q25 -> 11070 | O25: 11070
D26: SECURITY | E26: KSHS. | F26: 500 | N26: =O26-Q26 -> 11550 | O26: 11550
D27: GARBAGE FEE | F27: 150 | N27: =O27-Q27 -> 11393 | O27: 11393
D28: INTEREST ON LATE PAYMENT | E28: KSHS. | F28: =IF(F18*4%*1<0,0,F18*4%*1) -> 27.08 | N28: =O28-Q28 -> 10802 | O28: 10802
N29: =O29-Q29 -> 8930 | O29: 8930
C30: TOTAL PAYABLE | D30: TOTAL PAYABLE | E30: Kshs. | F30: =SUM(F17:F29) -> 14604.08 | N30: =O30-Q30 -> 9570 | O30: 9570
N31: =O31-Q31 -> 11390 | O31: 11390
C32: PAID | D32: PAID | F32: =meter!R14 -> 0 | N32: =O32-Q32 -> 10750 | O32: 10750
N33: =O33-Q33 -> 11732 | O33: 11732
C34: BALANCE C/F | D34: AMOUNT DUE | F34: =F30-F32 -> 14604.08 | N34: =O34-Q34 -> 10934 | O34: 10934 | R34: 700
B35: NOTE | N35: =O35-Q35 -> 10270 | O35: 10270
A36: a) | B36: Rent is due on or before 5th of the month. By 7th day, any rent not paid will attract interest at 2% per day. | N36: =O36-Q36 -> 10598 | O36: 10598
A37: b) | B37: Any default in Rent payment by 10th of the following month the house shall be locked without notice and belongings removed for re-letting. | N37: =O37-Q37 -> 8770 | O37: 8770
N38: =O38-Q38 -> 8770 | O38: 8770
A39: c) | B39: Amounts not cleared by last pay date will render to water disconnection. | O39: =SUM(O3:O38) -> 391268 | Q39: =SUM(Q3:Q38) -> 0
A41: d) | B41: A reconnection fee of Kshs. 1,000 will be charged and paid before supply is reconnected.
A42: e) | B42: ANY MINOR REPAIRS OCCURING AFTER 3 MONTHS OF OCCUPANCY ARE TENANT'S RESPONSIBILITY AS PER TENANCY AGREEMENT.
A43: f) | B43: The water bills are payable through the same account for monthly rent strictly through:
B44: Frebazeth Company Limited
B45: Consolidated Bank Account
B46: Kitengela Branch
B47: PAY BILL 4139271
B48: (Kindly indicate your Name & House number on the deposit slip & inform the Bank teller to capture it.)
B49: A receipt will be issued upon bank confirmation of the transaction. | O49: ……………
B51: ACC NO KT 12A
B52: E & O E
B53: NB: Kindly give the management atleast two (2) months prior notice incase you intend to terminate the tenancy for ease of logisitics.

Sheet hse13B
B2: OLE SAMEDHA APARTMENTS-Kitengela | N2: VAR | O2: TAX DUE
B3: ='hse1'!B3 -> P.O BOX 9473-00200 NAIROBI | N3: =O3-Q3 -> 10270 | O3: 10270
B4: WATER BILL | G4: BILL NO. | H4: ='hse1'!H4+13-1 -> 20242013 | N4: =O4-Q4 -> 10304 | O4: 10304
N5: =O5-Q5 -> 10988 | O5: 10988
B6: TENANT NAME | D6: =meter!A15 -> HARRIET | N6: =O6-Q6 -> 11070 | O6: 11070
N7: =O7-Q7 -> 1197 | O7: 1197
B8: HOUSE NUMBER: | D8: 13B | N8: =O8-Q8 -> 9250 | O8: 9250
N9: =O9-Q9 -> 8770 | O9: 8770
B10: ISSUE DATE | D10: ='hse1'!C10 -> 27/1/2026 | N10: =O10-Q10 -> 23190 | O10: 23190
N11: =O11-Q11 -> 10910 | O11: 10910
B12: LAST PAY DATE | D12: ='hse1'!C12 -> 46144 | N12: =O12-Q12 -> 10910 | O12: 10910
N13: =O13-Q13 -> 12190 | O13: 12190
N14: =O14-Q14 -> 11070 | O14: 11070
B15: PREVIOUS READING | D15: CURRENT READING | F15: CONSUMPTION | N15: =O15-Q15 -> 9090 | O15: 9090
B16: =meter!D15 -> 158 | D16: =meter!E15 -> 159 | E16: Units | F16: =D16-B16 -> 1 | N16: =O16-Q16 -> 9420 | O16: 9420
F17: Amount (Kshs.) | N17: =O17-Q17 -> 11154 | O17: 11154
D18: LAST ACCOUNT B/F | E18: kshs. | F18: =meter!O15 -> 0 | N18: =O18-Q18 -> 10430 | O18: 10430
N19: =O19-Q19 -> 11831 | O19: 11831
D20: MONTH BILL | E20: KSHS. | F20: =meter!H15 -> 220 | N20: =O20-Q20 -> 10590 | O20: 10590
N21: =O21-Q21 -> 22423 | O21: 22423
D22: PUMP/POWER CHARGES | E22: KSHS. | F22: ='hse1'!E22 -> 110 | N22: =O22-Q22 -> 9250 | O22: 9250
N23: =O23-Q23 -> 10162 | O23: 10162
D24: MONTH HOUSE RENT | E24: KSHS. | F24: =meter!N15 -> 8500 | N24: =O24-Q24 -> 10270 | O24: 10270
N25: =O25-Q25 -> 11070 | O25: 11070
D26: SECURITY | E26: KSHS. | F26: =meter!M15 -> 0 | N26: =O26-Q26 -> 11550 | O26: 11550
D27: GARBAGE FEE | E27: KSHS. | F27: 150 | N27: =O27-Q27 -> 11393 | O27: 11393
D28: INTEREST ON LATE PAYMENT | E28: KSHS. | F28: =IF(F18*4%*1<0,0,F18*4%*1) -> 0 | N28: =O28-Q28 -> 10802 | O28: 10802
N29: =O29-Q29 -> 8930 | O29: 8930
D30: TOTAL PAYABLE | E30: Kshs. | F30: =SUM(F17:F29) -> 8980 | N30: =O30-Q30 -> 9570 | O30: 9570
N31: =O31-Q31 -> 11390 | O31: 11390
D32: PAID | F32: =meter!R15 -> 0 | N32: =O32-Q32 -> 10750 | O32: 10750
N33: =O33-Q33 -> 11732 | O33: 11732
D34: AMOUNT DUE | F34: =F30-F32 -> 8980 | N34: =O34-Q34 -> 10934 | O34: 10934 | R34: 700
B35: NOTE | N35: =O35-Q35 -> 10270 | O35: 10270
A36: a) | B36: Rent is due on or before 5th of the month. By 7th day, any rent not paid will attract interest at 2% per day. | N36: =O36-Q36 -> 10598 | O36: 10598
A37: b) | B37: Any default in Rent payment by 10th of the following month the house shall be locked without notice and belongings removed for re-letting. | N37: =O37-Q37 -> 8770 | O37: 8770
N38: =O38-Q38 -> 8770 | O38: 8770
A39: c) | B39: Amounts not cleared by last pay date will render to water disconnection. | O39: =SUM(O3:O38) -> 391268 | Q39: =SUM(Q3:Q38) -> 0
A41: d) | B41: A reconnection fee of Kshs. 1,000 will be charged and paid before supply is reconnected.
A42: e) | B42: ANY MINOR REPAIRS OCCURING AFTER 3 MONTHS OF OCCUPANCY ARE TENANT'S RESPONSIBILITY AS PER TENANCY AGREEMENT.
A43: f) | B43: The water bills are payable through the same account for monthly rent strictly through:
B44: Frebazeth Company Limited
B45: Consolidated Bank Account
B46: Kitengela Branch
B47: PAY BILL 4139271
B48: (Kindly indicate your Name & House number on the deposit slip & inform the Bank teller to capture it.)
B49: A receipt will be issued upon bank confirmation of the transaction. | O49: ……………
B51: ACC NO KT 13B
B52: E & O E
B53: NB: Kindly give the management atleast two (2) months prior notice incase you intend to terminate the tenancy for ease of logisitics.

Sheet hse14B
B2: OLE SAMEDHA APARTMENTS-Kitengela | N2: VAR | O2: TAX DUE
B3: ='hse1'!B3 -> P.O BOX 9473-00200 NAIROBI | N3: =O3-Q3 -> 10270 | O3: 10270
B4: WATER BILL | H4: BILL NO. | I4: ='hse1'!H4+14-1 -> 20242014 | J4: ='hse1'!H4+14-1 -> 20242014 | N4: =O4-Q4 -> 10304 | O4: 10304
N5: =O5-Q5 -> 10988 | O5: 10988
B6: TENANT NAME | D6: valentine | N6: =O6-Q6 -> 11070 | O6: 11070
N7: =O7-Q7 -> 1197 | O7: 1197
B8: HOUSE NUMBER: | D8: 14B | N8: =O8-Q8 -> 9250 | O8: 9250
N9: =O9-Q9 -> 8770 | O9: 8770
B10: ISSUE DATE | D10: ='hse1'!C10 -> 27/1/2026 | N10: =O10-Q10 -> 23190 | O10: 23190
N11: =O11-Q11 -> 10910 | O11: 10910
B12: LAST PAY DATE | D12: ='hse1'!C12 -> 46144 | N12: =O12-Q12 -> 10910 | O12: 10910
N13: =O13-Q13 -> 12190 | O13: 12190
N14: =O14-Q14 -> 11070 | O14: 11070
B15: PREVIOUS READING | D15: CURRENT READING | F15: CONSUMPTION | N15: =O15-Q15 -> 9090 | O15: 9090
B16: =meter!D16 -> 714 | D16: =meter!E16 -> 716 | E16: Units | F16: =D16-B16 -> 2 | H16: ESTIMATE | N16: =O16-Q16 -> 9420 | O16: 9420
F17: Amount (Kshs.) | N17: =O17-Q17 -> 11154 | O17: 11154
D18: LAST ACCOUNT B/F | E18: kshs. | F18: =meter!O16 -> 820 | N18: =O18-Q18 -> 10430 | O18: 10430
N19: =O19-Q19 -> 11831 | O19: 11831
D20: MONTH BILL | E20: KSHS. | F20: =meter!H16 -> 440 | N20: =O20-Q20 -> 10590 | O20: 10590
N21: =O21-Q21 -> 22423 | O21: 22423
D22: PUMP/POWER CHARGES | E22: KSHS. | F22: ='hse1'!E22 -> 110 | N22: =O22-Q22 -> 9250 | O22: 9250
N23: =O23-Q23 -> 10162 | O23: 10162
D24: MONTH HOUSE RENT | E24: KSHS. | F24: 8500 | N24: =O24-Q24 -> 10270 | O24: 10270
N25: =O25-Q25 -> 11070 | O25: 11070
D26: SECURITY | E26: ='hse1'!D26 -> Kshs. | F26: 500 | N26: =O26-Q26 -> 11550 | O26: 11550
D27: GARBAGE FEE | E27: Kshs. | F27: 150 | N27: =O27-Q27 -> 11393 | O27: 11393
D28: ADJUSTMENT (Interest late payment) | E28: KSHS. | F28: =IF(F18*4%*1<0,0,F18*4%*1) -> 32.8 | N28: =O28-Q28 -> 10802 | O28: 10802
N29: =O29-Q29 -> 8930 | O29: 8930
D30: TOTAL PAYABLE | E30: Kshs. | F30: =SUM(F17:F29) -> 10552.8 | N30: =O30-Q30 -> 9570 | O30: 9570
N31: =O31-Q31 -> 11390 | O31: 11390
D32: PAID | F32: =meter!R16 -> 0 | N32: =O32-Q32 -> 10750 | O32: 10750
N33: =O33-Q33 -> 11732 | O33: 11732
D34: AMOUNT DUE | F34: =F30-F32 -> 10552.8 | N34: =O34-Q34 -> 10934 | O34: 10934 | R34: 700
C35: NOTE | N35: =O35-Q35 -> 10270 | O35: 10270
A36: a) | B36: Rent is due on or before 5th of the month. By 7th day, any rent not paid will attract interest at 2% per day. | N36: =O36-Q36 -> 10598 | O36: 10598
A37: b) | B37: Any default in Rent payment by 10th of the following month the house shall be locked without notice and belongings removed for re-letting. | N37: =O37-Q37 -> 8770 | O37: 8770
N38: =O38-Q38 -> 8770 | O38: 8770
A39: c) | B39: Amounts not cleared by last pay date will render to water disconnection. | O39: =SUM(O3:O38) -> 391268 | Q39: =SUM(Q3:Q38) -> 0
A41: d) | B41: A reconnection fee of Kshs. 1,000 will be charged and paid before supply is reconnected.
A42: e) | B42: ANY MINOR REPAIRS OCCURING AFTER 3 MONTHS OF OCCUPANCY ARE TENANT'S RESPONSIBILITY AS PER TENANCY AGREEMENT.
A43: f) | B43: The water bills are payable through the same account for monthly rent strictly through:
B44: Frebazeth Company Limited
B45: Consolidated Bank Account
B46: Kitengela Branch
B47: PAY BILL 4139271
B48: (Kindly indicate your Name & House number on the deposit slip & inform the Bank teller to capture it.)
B49: A receipt will be issued upon bank confirmation of the transaction. | O49: ……………
A50: g)
B51: ACC NO KT 14B
B52: E & O E
B53: NB: Kindly give the management atleast two (2) months prior notice incase you intend to terminate the tenancy for ease of logisitics.

Sheet hse 15
B2: OLE SAMEDHA APARTMENTS-Kitengela | N2: VAR | O2: TAX DUE
B3: ='hse1'!B3 -> P.O BOX 9473-00200 NAIROBI | N3: =O3-Q3 -> 10270 | O3: 10270
B4: WATER BILL | H4: BILL NO. | I4: ='hse1'!H4+15-1 -> 20242015 | J4: ='hse1'!H4+15-1 -> 20242015 | N4: =O4-Q4 -> 10304 | O4: 10304
N5: =O5-Q5 -> 10988 | O5: 10988
B6: TENANT NAME | D6: =meter!A17 -> ASHA | N6: =O6-Q6 -> 11070 | O6: 11070
N7: =O7-Q7 -> 1197 | O7: 1197
B8: HOUSE NUMBER: | D8: 15A | N8: =O8-Q8 -> 9250 | O8: 9250
N9: =O9-Q9 -> 8770 | O9: 8770
B10: ISSUE DATE | D10: ='hse1'!C10 -> 27/1/2026 | N10: =O10-Q10 -> 23190 | O10: 23190
N11: =O11-Q11 -> 10910 | O11: 10910
B12: LAST PAY DATE | D12: ='hse1'!C12 -> 46144 | N12: =O12-Q12 -> 10910 | O12: 10910
N13: =O13-Q13 -> 12190 | O13: 12190
N14: =O14-Q14 -> 11070 | O14: 11070
B15: PREVIOUS READING | D15: CURRENT READING | F15: CONSUMPTION | N15: =O15-Q15 -> 9090 | O15: 9090
B16: =meter!D17 -> 195 | D16: =meter!E17 -> 200 | E16: Units | F16: =D16-B16 -> 5 | N16: =O16-Q16 -> 9420 | O16: 9420
F17: Amount (Kshs) | N17: =O17-Q17 -> 11154 | O17: 11154
D18: LAST ACCOUNT B/F | E18: kshs. | F18: =meter!O17 -> 677 | N18: =O18-Q18 -> 10430 | O18: 10430
N19: =O19-Q19 -> 11831 | O19: 11831
D20: MONTH BILL | E20: KSHS. | F20: =meter!H17 -> 1100 | N20: =O20-Q20 -> 10590 | O20: 10590
N21: =O21-Q21 -> 22423 | O21: 22423
D22: PUMP/POWER CHARGES | E22: KSHS. | F22: ='hse1'!E22 -> 110 | N22: =O22-Q22 -> 9250 | O22: 9250
N23: =O23-Q23 -> 10162 | O23: 10162
D24: MONTH HOUSE RENT | E24: KSHS. | F24: =meter!N17 -> 10500 | N24: =O24-Q24 -> 10270 | O24: 10270
N25: =O25-Q25 -> 11070 | O25: 11070
D26: ='hse1'!C26 -> security | E26: ='hse1'!D26 -> Kshs. | N26: =O26-Q26 -> 11550 | O26: 11550
D27: GARBAGE FEE | E27: Kshs. | F27: 150 | N27: =O27-Q27 -> 11393 | O27: 11393
D28: ADJUSTMENT (Interest late payment) | E28: KSHS. | F28: =IF(F18*4%*1<0,0,F18*4%*1) -> 27.08 | N28: =O28-Q28 -> 10802 | O28: 10802
N29: =O29-Q29 -> 8930 | O29: 8930
C30: TOTAL PAYABLE | D30: AMOUNT PAYABLE | E30: Kshs. | F30: =SUM(F17:F29) -> 12564.08 | N30: =O30-Q30 -> 9570 | O30: 9570
N31: =O31-Q31 -> 11390 | O31: 11390
C32: PAID | E32: KSHS | F32: 5000 | N32: =O32-Q32 -> 10750 | O32: 10750
N33: =O33-Q33 -> 11732 | O33: 11732
C34: BALANCE C/F | D34: AMOUNT DUE | E34: KSHS. | F34: =F30-F32 -> 7564.08 | N34: =O34-Q34 -> 10934 | O34: 10934 | R34: 700
B35: NOTE | N35: =O35-Q35 -> 10270 | O35: 10270
A36: a) | B36: Rent is due on or before 5th of the month. By 7th day, any rent not paid will attract interest at 2% per day. | N36: =O36-Q36 -> 10598 | O36: 10598
A37: b) | B37: Any default in Rent payment by 10th of the following month the house shall be locked without notice and belongings removed for re-letting. | N37: =O37-Q37 -> 8770 | O37: 8770
N38: =O38-Q38 -> 8770 | O38: 8770
A39: c) | B39: Amounts not cleared by last pay date will render to water disconnection. | O39: =SUM(O3:O38) -> 391268 | Q39: =SUM(Q3:Q38) -> 0
A41: d) | B41: A reconnection fee of Kshs. 1,000 will be charged and paid before supply is reconnected.
A42: e) | B42: ANY MINOR REPAIRS OCCURING AFTER 3 MONTHS OF OCCUPANCY ARE TENANT'S RESPONSIBILITY AS PER TENANCY AGREEMENT.
A43: f) | B43: The water bills are payable through the same account for monthly rent strictly through:
B44: Frebazeth Company Limited
B45: Consolidated Bank Account
B46: Kitengela Branch
B47: PAY BILL 4139271
B48: (Kindly indicate your Name & House number on the deposit slip & inform the Bank teller to capture it.)
B49: A receipt will be issued upon bank confirmation of the transaction. | O49: ……………
A51: E & O E | B51: ACC NO KT 15A
A52: NB: Kindly give the management atleast two (2) months prior notice incase you intend to terminate the tenancy for ease of logisitics. | B52: E & O E
B53: NB: Kindly give the management atleast two (2) months prior notice incase you intend to terminate the tenancy for ease of logisitics.

Sheet hse16
B2: OLE SAMEDHA APARTMENTS-Kitengela | N2: VAR | O2: TAX DUE
B3: ='hse1'!B3 -> P.O BOX 9473-00200 NAIROBI | N3: =O3-Q3 -> 10270 | O3: 10270
B4: WATER BILL | H4: BILL NO. | I4: ='hse1'!H4+16-1 -> 20242016 | M4: ='hse1'!H4+16-1 -> 20242016 | N4: =O4-Q4 -> 10304 | O4: 10304
N5: =O5-Q5 -> 10988 | O5: 10988
B6: TENANT NAME | D6: =meter!A18 -> VACCANT | N6: =O6-Q6 -> 11070 | O6: 11070
N7: =O7-Q7 -> 1197 | O7: 1197
B8: HOUSE NUMBER: | D8: 16A | N8: =O8-Q8 -> 9250 | O8: 9250
N9: =O9-Q9 -> 8770 | O9: 8770
B10: ISSUE DATE | D10: ='hse1'!C10 -> 27/1/2026 | N10: =O10-Q10 -> 23190 | O10: 23190
N11: =O11-Q11 -> 10910 | O11: 10910
B12: LAST PAY DATE | D12: ='hse1'!C12 -> 46144 | N12: =O12-Q12 -> 10910 | O12: 10910
N13: =O13-Q13 -> 12190 | O13: 12190
N14: =O14-Q14 -> 11070 | O14: 11070
B15: PREVIOUS READING | D15: CURRENT READING | F15: CONSUMPTION | N15: =O15-Q15 -> 9090 | O15: 9090
B16: =meter!D18 -> 190 | D16: =meter!E18 -> 190 | E16: Units | F16: =D16-B16 -> 0 | N16: =O16-Q16 -> 9420 | O16: 9420
F17: Amount (Kshs.) | N17: =O17-Q17 -> 11154 | O17: 11154
D18: LAST ACCOUNT B/F | E18: kshs. | F18: =meter!O18 -> 677 | N18: =O18-Q18 -> 10430 | O18: 10430
N19: =O19-Q19 -> 11831 | O19: 11831
D20: MONTH BILL | E20: KSHS. | F20: =meter!H18 -> 0 | N20: =O20-Q20 -> 10590 | O20: 10590
N21: =O21-Q21 -> 22423 | O21: 22423
D22: PUMP/POWER CHARGES | E22: KSHS. | F22: ='hse1'!E22 -> 110 | N22: =O22-Q22 -> 9250 | O22: 9250
N23: =O23-Q23 -> 10162 | O23: 10162
D24: MONTH HOUSE RENT | E24: KSHS. | F24: =meter!N18 -> 10500 | N24: =O24-Q24 -> 10270 | O24: 10270
N25: =O25-Q25 -> 11070 | O25: 11070
D26: ='hse1'!C26 -> security | E26: ='hse1'!D26 -> Kshs. | F26: ='hse1'!E26 -> 500 | N26: =O26-Q26 -> 11550 | O26: 11550
D27: GARBAGE FEE | E27: Kshs. | F27: 150 | N27: =O27-Q27 -> 11393 | O27: 11393
D28: ADJUSTMENT-INTEREST LATE PAYMENT | E28: KSHS. | F28: =IF(F18*4%*1<0,0,F18*4%*1) -> 27.08 | N28: =O28-Q28 -> 10802 | O28: 10802
N29: =O29-Q29 -> 8930 | O29: 8930
D30: TOTAL PAYABLE | E30: Kshs. | F30: =SUM(F17:F29) -> 11964.08 | N30: =O30-Q30 -> 9570 | O30: 9570
N31: =O31-Q31 -> 11390 | O31: 11390
D32: PAID | F32: =meter!R18 -> 0 | N32: =O32-Q32 -> 10750 | O32: 10750
N33: =O33-Q33 -> 11732 | O33: 11732
D34: AMOUNT DUE | F34: =F30-F32 -> 11964.08 | N34: =O34-Q34 -> 10934 | O34: 10934 | R34: 700
C35: NOTE | N35: =O35-Q35 -> 10270 | O35: 10270
A36: a) | B36: Rent is due on or before 5th of the month. By 7th day, any rent not paid will attract interest at 2% per day. | N36: =O36-Q36 -> 10598 | O36: 10598
A37: b) | B37: Any default in Rent payment by 10th of the following month the house shall be locked without notice and belongings removed for re-letting. | N37: =O37-Q37 -> 8770 | O37: 8770
N38: =O38-Q38 -> 8770 | O38: 8770
A39: c) | B39: Amounts not cleared by last pay date will render to water disconnection. | O39: =SUM(O3:O38) -> 391268 | Q39: =SUM(Q3:Q38) -> 0
A41: d) | B41: A reconnection fee of Kshs. 1,000 will be charged and paid before supply is reconnected.
A42: e) | B42: ANY MINOR REPAIRS OCCURING AFTER 3 MONTHS OF OCCUPANCY ARE TENANT'S RESPONSIBILITY AS PER TENANCY AGREEMENT.
A43: f) | B43: The water bills are payable through the same account for monthly rent strictly through:
B44: Frebazeth Company Limited
B45: Consolidated Bank Account
B46: Kitengela Branch
B47: PAY BILL 4139271
B48: (Kindly indicate your Name & House number on the deposit slip & inform the Bank teller to capture it.)
B49: A receipt will be issued upon bank confirmation of the transaction. | O49: ……………
A50: g)
B51: ACC NO KT 16A
B52: E & O E
B53: NB: Kindly give the management atleast two (2) months prior notice incase you intend to terminate the tenancy for ease of logisitics.

Sheet hse17
B2: OLE SAMEDHA APARTMENTS-Kitengela | N2: VAR | O2: TAX DUE
B3: ='hse1'!B3 -> P.O BOX 9473-00200 NAIROBI | N3: =O3-Q3 -> 10270 | O3: 10270
B4: WATER BILL | H4: BILL NO. | I4: ='hse1'!H4+17-1 -> 20242017 | J4: ='hse1'!H4+17-1 -> 20242017 | N4: =O4-Q4 -> 10304 | O4: 10304
N5: =O5-Q5 -> 10988 | O5: 10988
B6: TENANT NAME | D6: =meter!A19 -> JOASH | N6: =O6-Q6 -> 11070 | O6: 11070
N7: =O7-Q7 -> 1197 | O7: 1197
B8: HOUSE NUMBER: | D8: 17A | N8: =O8-Q8 -> 9250 | O8: 9250
D9: 0775203183 | N9: =O9-Q9 -> 8770 | O9: 8770
B10: ISSUE DATE | D10: ='hse1'!C10 -> 27/1/2026 | N10: =O10-Q10 -> 23190 | O10: 23190
N11: =O11-Q11 -> 10910 | O11: 10910
B12: LAST PAY DATE | D12: ='hse1'!C12 -> 46144 | N12: =O12-Q12 -> 10910 | O12: 10910
N13: =O13-Q13 -> 12190 | O13: 12190
N14: =O14-Q14 -> 11070 | O14: 11070
B15: PREVIOUS READING | D15: CURRENT READING | F15: CONSUMPTION | N15: =O15-Q15 -> 9090 | O15: 9090
B16: =meter!D19 -> 484 | D16: =meter!E19 -> 487 | E16: Units | F16: =D16-B16 -> 3 | N16: =O16-Q16 -> 9420 | O16: 9420
F17: Amount (Kshs.) | N17: =O17-Q17 -> 11154 | O17: 11154
D18: LAST ACCOUNT B/F | E18: kshs. | F18: =meter!O19 -> 1000 | N18: =O18-Q18 -> 10430 | O18: 10430
N19: =O19-Q19 -> 11831 | O19: 11831
D20: MONTH BILL | E20: KSHS. | F20: =meter!H19 -> 660 | N20: =O20-Q20 -> 10590 | O20: 10590
N21: =O21-Q21 -> 22423 | O21: 22423
D22: PUMP/POWER CHARGES | E22: KSHS. | F22: ='hse1'!E22 -> 110 | N22: =O22-Q22 -> 9250 | O22: 9250
N23: =O23-Q23 -> 10162 | O23: 10162
D24: MONTH HOUSE RENT | E24: KSHS. | F24: 11000 | N24: =O24-Q24 -> 10270 | O24: 10270
N25: =O25-Q25 -> 11070 | O25: 11070
D26: ='hse1'!C26 -> security | E26: ='hse1'!D26 -> Kshs. | N26: =O26-Q26 -> 11550 | O26: 11550
D27: GARBAGE FEE | E27: Kshs. | F27: 150 | N27: =O27-Q27 -> 11393 | O27: 11393
D28: INTEREST LATE PAYMENT | E28: KSHS. | F28: =IF(F18*8%*1<0,0,F18*8%*1) -> 80 | N28: =O28-Q28 -> 10802 | O28: 10802
N29: =O29-Q29 -> 8930 | O29: 8930
D30: TOTAL PAYABLE | E30: Kshs. | F30: =SUM(F17:F29) -> 13000 | N30: =O30-Q30 -> 9570 | O30: 9570
N31: =O31-Q31 -> 11390 | O31: 11390
D32: PAID | F32: =meter!R19 -> 0 | N32: =O32-Q32 -> 10750 | O32: 10750
N33: =O33-Q33 -> 11732 | O33: 11732
D34: AMOUNT DUE | F34: =F30-F32 -> 13000 | N34: =O34-Q34 -> 10934 | O34: 10934 | R34: 700
C35: NOTE | N35: =O35-Q35 -> 10270 | O35: 10270
A36: a) | B36: Rent is due on or before 5th of the month. By 7th day, any rent not paid will attract interest at 2% per day. | N36: =O36-Q36 -> 10598 | O36: 10598
A37: b) | B37: Any default in Rent payment by 10th of the following month the house shall be locked without notice and belongings removed for re-letting. | N37: =O37-Q37 -> 8770 | O37: 8770
N38: =O38-Q38 -> 8770 | O38: 8770
A39: c) | B39: Amounts not cleared by last pay date will render to water disconnection. | O39: =SUM(O3:O38) -> 391268 | Q39: =SUM(Q3:Q38) -> 0
A41: d) | B41: A reconnection fee of Kshs. 1,000 will be charged and paid before supply is reconnected.
A42: e) | B42: ANY MINOR REPAIRS OCCURING AFTER 3 MONTHS OF OCCUPANCY ARE TENANT'S RESPONSIBILITY AS PER TENANCY AGREEMENT.
A43: f) | B43: The water bills are payable through the same account for monthly rent strictly through:
B44: Frebazeth Company Limited
B45: Consolidated Bank Account
B46: Kitengela Branch
B47: PAY BILL 4139271
B48: (Kindly indicate your Name & House number on the deposit slip & inform the Bank teller to capture it.)
B49: A receipt will be issued upon bank confirmation of the transaction. | O49: ……………
A50: g)
B51: ACC NO KT 17A
B52: E & O E
B53: NB: Kindly give the management atleast two (2) months prior notice incase you intend to terminate the tenancy for ease of logisitics.

Sheet hse18
B2: OLE SAMEDHA APARTMENTS-Kitengela | N2: VAR | O2: TAX DUE
B3: ='hse1'!B3 -> P.O BOX 9473-00200 NAIROBI | N3: =O3-Q3 -> 10270 | O3: 10270
B4: WATER BILL | H4: BILL NO. | I4: ='hse1'!H4+18-1 -> 20242018 | K4: ='hse1'!H4+18-1 -> 20242018 | N4: =O4-Q4 -> 10304 | O4: 10304
N5: =O5-Q5 -> 10988 | O5: 10988
B6: TENANT NAME | D6: =meter!A20 -> MOSES NJUGUNA | N6: =O6-Q6 -> 11070 | O6: 11070
N7: =O7-Q7 -> 1197 | O7: 1197
B8: HOUSE NUMBER | D8: 18A | N8: =O8-Q8 -> 9250 | O8: 9250
N9: =O9-Q9 -> 8770 | O9: 8770
B10: ISSUE DATE | D10: ='hse1'!C10 -> 27/1/2026 | N10: =O10-Q10 -> 23190 | O10: 23190
N11: =O11-Q11 -> 10910 | O11: 10910
B12: LAST PAY DATE | D12: ='hse1'!C12 -> 46144 | N12: =O12-Q12 -> 10910 | O12: 10910
N13: =O13-Q13 -> 12190 | O13: 12190
N14: =O14-Q14 -> 11070 | O14: 11070
B15: PREVIOUS READING | D15: CURRENT READING | F15: CONSUMPTION | N15: =O15-Q15 -> 9090 | O15: 9090
B16: =meter!D20 -> 210 | D16: =meter!E20 -> 213 | E16: Units | F16: =D16-B16 -> 3 | N16: =O16-Q16 -> 9420 | O16: 9420
F17: Amount (Kshs.) | N17: =O17-Q17 -> 11154 | O17: 11154
D18: LAST ACCOUNT B/F | E18: Kshs. | F18: =meter!O20 -> 1750 | N18: =O18-Q18 -> 10430 | O18: 10430
N19: =O19-Q19 -> 11831 | O19: 11831
D20: MONTH BILL | E20: KSHS. | F20: =meter!H20 -> 660 | N20: =O20-Q20 -> 10590 | O20: 10590
N21: =O21-Q21 -> 22423 | O21: 22423
D22: PUMP/POWER CHARGES | E22: KSHS. | F22: ='hse1'!E22 -> 110 | N22: =O22-Q22 -> 9250 | O22: 9250
N23: =O23-Q23 -> 10162 | O23: 10162
D24: MONTH HOUSE RENT | E24: KSHS. | F24: 10000 | N24: =O24-Q24 -> 10270 | O24: 10270
N25: =O25-Q25 -> 11070 | O25: 11070
D26: ='hse1'!C26 -> security | E26: ='hse1'!D26 -> Kshs. | F26: 500 | N26: =O26-Q26 -> 11550 | O26: 11550
D27: GARBAGE FEE | E27: Kshs. | F27: 150 | N27: =O27-Q27 -> 11393 | O27: 11393
D28: ADJUSTMENT (Interest late payment) | E28: KSHS. | F28: =IF(F18*4%*1<0,0,F18*4%*1) -> 70 | N28: =O28-Q28 -> 10802 | O28: 10802
N29: =O29-Q29 -> 8930 | O29: 8930
D30: TOTAL PAYABLE | E30: Kshs. | F30: =SUM(F17:F29) -> 13240 | N30: =O30-Q30 -> 9570 | O30: 9570
N31: =O31-Q31 -> 11390 | O31: 11390
D32: PAID | F32: =meter!R20 -> 0 | N32: =O32-Q32 -> 10750 | O32: 10750
N33: =O33-Q33 -> 11732 | O33: 11732
D34: AMOUNT DUE | F34: =F30-F32 -> 13240 | N34: =O34-Q34 -> 10934 | O34: 10934 | R34: 700
C35: NOTE | N35: =O35-Q35 -> 10270 | O35: 10270
A36: a) | B36: Rent is due on or before 5th of the month. By 7th day, any rent not paid will attract interest at 2% per day. | N36: =O36-Q36 -> 10598 | O36: 10598
A37: b) | B37: Any default in Rent payment by 10th of the following month the house shall be locked without notice and belongings removed for re-letting. | N37: =O37-Q37 -> 8770 | O37: 8770
N38: =O38-Q38 -> 8770 | O38: 8770
A39: c) | B39: Amounts not cleared by last pay date will render to water disconnection. | O39: =SUM(O3:O38) -> 391268 | Q39: =SUM(Q3:Q38) -> 0
A41: d) | B41: A reconnection fee of Kshs. 1,000 will be charged and paid before supply is reconnected.
A42: e) | B42: ANY MINOR REPAIRS OCCURING AFTER 3 MONTHS OF OCCUPANCY ARE TENANT'S RESPONSIBILITY AS PER TENANCY AGREEMENT.
A43: f) | B43: The water bills are payable through the same account for monthly rent strictly through:
B44: Frebazeth Company Limited
B45: Consolidated Bank Account
B46: Kitengela Branch
B47: PAY BILL 4139271
B48: (Kindly indicate your Name & House number on the deposit slip & inform the Bank teller to capture it.)
B49: A receipt will be issued upon bank confirmation of the transaction. | O49: ……………
A50: g)
B51: ACC NO KT 18A
B52: E & O E
B53: NB: Kindly give the management atleast two (2) months prior notice incase you intend to terminate the tenancy for ease of logisitics.

Sheet hse19
B2: OLE SAMEDHA APARTMENTS-Kitengela | N2: VAR | O2: TAX DUE
B3: ='hse1'!B3 -> P.O BOX 9473-00200 NAIROBI | N3: =O3-Q3 -> 10270 | O3: 10270
B4: WATER BILL | G4: BILL NO. | H4: ='hse1'!H4+19-1 -> 20242019 | I4: ='hse1'!H4+19-1 -> 20242019 | N4: =O4-Q4 -> 10304 | O4: 10304
G5: ='hse1'!H4+19-1 -> 20242019 | N5: =O5-Q5 -> 10988 | O5: 10988
B6: TENANT NAME | D6: =meter!A21 -> DAGLOUS | N6: =O6-Q6 -> 11070 | O6: 11070
N7: =O7-Q7 -> 1197 | O7: 1197
B8: HOUSE NUMBER: | D8: 19A | N8: =O8-Q8 -> 9250 | O8: 9250
N9: =O9-Q9 -> 8770 | O9: 8770
B10: ISSUE DATE | D10: ='hse1'!C10 -> 27/1/2026 | N10: =O10-Q10 -> 23190 | O10: 23190
N11: =O11-Q11 -> 10910 | O11: 10910
B12: LAST PAY DATE | D12: ='hse1'!C12 -> 46144 | N12: =O12-Q12 -> 10910 | O12: 10910
N13: =O13-Q13 -> 12190 | O13: 12190
N14: =O14-Q14 -> 11070 | O14: 11070
B15: PREVIOUS READING | D15: CURRENT READING | F15: CONSUMPTION | N15: =O15-Q15 -> 9090 | O15: 9090
B16: =meter!D21 -> 55 | D16: =meter!E21 -> 59 | E16: Units | F16: =D16-B16+I16 -> 4 | N16: =O16-Q16 -> 9420 | O16: 9420
F17: Amount (Kshs.) | N17: =O17-Q17 -> 11154 | O17: 11154
D18: LAST ACCOUNT B/F | E18: Kshs. | N18: =O18-Q18 -> 10430 | O18: 10430
N19: =O19-Q19 -> 11831 | O19: 11831
D20: MONTH BILL | E20: KSHS. | F20: =meter!H21 -> 880 | N20: =O20-Q20 -> 10590 | O20: 10590
N21: =O21-Q21 -> 22423 | O21: 22423
D22: PUMP/POWER CHARGES | E22: KSHS. | F22: ='hse1'!E22 -> 110 | N22: =O22-Q22 -> 9250 | O22: 9250
N23: =O23-Q23 -> 10162 | O23: 10162
D24: MONTH HOUSE RENT | E24: KSHS. | F24: =meter!N21 -> 10500 | N24: =O24-Q24 -> 10270 | O24: 10270
N25: =O25-Q25 -> 11070 | O25: 11070
D26: ='hse1'!C26 -> security | E26: ='hse1'!D26 -> Kshs. | N26: =O26-Q26 -> 11550 | O26: 11550
D27: GARBAGE FEE | E27: Kshs. | F27: 150 | N27: =O27-Q27 -> 11393 | O27: 11393
D28: ADJUSTMENT-Interest on arrears | E28: KSHS. | F28: =IF(F18*8%*1<0,0,F18*8%*1) -> 0 | N28: =O28-Q28 -> 10802 | O28: 10802
N29: =O29-Q29 -> 8930 | O29: 8930
D30: TOTAL PAYABLE | E30: Kshs. | F30: =SUM(F17:F29) -> 11640 | N30: =O30-Q30 -> 9570 | O30: 9570
N31: =O31-Q31 -> 11390 | O31: 11390
D32: PAID | F32: =meter!R21 -> 0 | N32: =O32-Q32 -> 10750 | O32: 10750
N33: =O33-Q33 -> 11732 | O33: 11732
D34: AMOUNT DUE | F34: =F30-F32 -> 11640 | N34: =O34-Q34 -> 10934 | O34: 10934 | R34: 700
C35: NOTE | N35: =O35-Q35 -> 10270 | O35: 10270
A36: a) | B36: Rent is due on or before 5th of the month. By 7th day, any rent not paid will attract interest at 2% per day. | N36: =O36-Q36 -> 10598 | O36: 10598
A37: b) | B37: Any default in Rent payment by 10th of the following month the house shall be locked without notice and belongings removed for re-letting. | N37: =O37-Q37 -> 8770 | O37: 8770
N38: =O38-Q38 -> 8770 | O38: 8770
A39: c) | B39: Amounts not cleared by last pay date will render to water disconnection. | O39: =SUM(O3:O38) -> 391268 | Q39: =SUM(Q3:Q38) -> 0
A41: d) | B41: A reconnection fee of Kshs. 1,000 will be charged and paid before supply is reconnected.
A42: e) | B42: ANY MINOR REPAIRS OCCURING AFTER 3 MONTHS OF OCCUPANCY ARE TENANT'S RESPONSIBILITY AS PER TENANCY AGREEMENT.
A43: f) | B43: The water bills are payable through the same account for monthly rent strictly through:
B44: Frebazeth Company Limited
B45: Consolidated Bank Account
B46: Kitengela Branch
B47: PAY BILL 4139271
B48: (Kindly indicate your Name & House number on the deposit slip & inform the Bank teller to capture it.)
B49: A receipt will be issued upon bank confirmation of the transaction. | O49: ……………
A50: g)
B51: ACC NO 19A
B52: E & O E
B53: NB: Kindly give the management atleast two (2) months prior notice incase you intend to terminate the tenancy for ease of logisitics.
R58: A

Sheet hse20B
B2: OLE SAMEDHA APARTMENTS-Kitengela | N2: VAR | O2: TAX DUE
B3: ='hse1'!B3 -> P.O BOX 9473-00200 NAIROBI | N3: =O3-Q3 -> 10270 | O3: 10270
B4: WATER BILL | H4: BILL NO. | I4: ='hse1'!H4+20-1 -> 20242020 | J4: ='hse1'!H4+20-1 -> 20242020 | N4: =O4-Q4 -> 10304 | O4: 10304
N5: =O5-Q5 -> 10988 | O5: 10988
B6: TENANT NAME | D6: =meter!A22 -> OWEN | N6: =O6-Q6 -> 11070 | O6: 11070
N7: =O7-Q7 -> 1197 | O7: 1197
B8: HOUSE NUMBER: | D8: 20B | N8: =O8-Q8 -> 9250 | O8: 9250
N9: =O9-Q9 -> 8770 | O9: 8770
B10: ISSUE DATE | D10: ='hse1'!C10 -> 27/1/2026 | N10: =O10-Q10 -> 23190 | O10: 23190
N11: =O11-Q11 -> 10910 | O11: 10910
B12: LAST PAY DATE | D12: ='hse1'!C12 -> 46144 | N12: =O12-Q12 -> 10910 | O12: 10910
N13: =O13-Q13 -> 12190 | O13: 12190
N14: =O14-Q14 -> 11070 | O14: 11070
B15: PREVIOUS READING | D15: CURRENT READING | F15: CONSUMPTION | N15: =O15-Q15 -> 9090 | O15: 9090
B16: =meter!D22 -> 265 | D16: =meter!E22 -> 267 | E16: Units | F16: =D16-B16 -> 2 | N16: =O16-Q16 -> 9420 | O16: 9420
N17: =O17-Q17 -> 11154 | O17: 11154
D18: LAST ACCOUNT B/F | E18: Kshs. | N18: =O18-Q18 -> 10430 | O18: 10430
N19: =O19-Q19 -> 11831 | O19: 11831
D20: MONTH BILL | E20: KSHS. | F20: =meter!H22 -> 440 | N20: =O20-Q20 -> 10590 | O20: 10590
N21: =O21-Q21 -> 22423 | O21: 22423
D22: PUMP/POWER CHARGES | E22: KSHS. | F22: 110 | N22: =O22-Q22 -> 9250 | O22: 9250
N23: =O23-Q23 -> 10162 | O23: 10162
D24: MONTH HOUSE RENT | E24: KSHS. | F24: 8500 | N24: =O24-Q24 -> 10270 | O24: 10270
N25: =O25-Q25 -> 11070 | O25: 11070
D26: security | E26: ='hse1'!D26 -> Kshs. | F26: 0 | N26: =O26-Q26 -> 11550 | O26: 11550
D27: GARBAGE FEE | E27: Kshs. | F27: 150 | N27: =O27-Q27 -> 11393 | O27: 11393
D28: ADJUSTMENT-interest on arrears | E28: KSHS. | N28: =O28-Q28 -> 10802 | O28: 10802
N29: =O29-Q29 -> 8930 | O29: 8930
D30: TOTAL PAYABLE | E30: Kshs. | F30: =SUM(F17:F29) -> 9200 | N30: =O30-Q30 -> 9570 | O30: 9570
N31: =O31-Q31 -> 11390 | O31: 11390
D32: PAID | F32: 0 | N32: =O32-Q32 -> 10750 | O32: 10750
N33: =O33-Q33 -> 11732 | O33: 11732
D34: AMOUNT DUE | F34: =F30-F32 -> 9200 | N34: =O34-Q34 -> 10934 | O34: 10934 | R34: 700
C35: NOTE | N35: =O35-Q35 -> 10270 | O35: 10270
A36: a) | B36: Rent is due on or before 5th of the month. By 7th day, any rent not paid will attract interest at 2% per day. | N36: =O36-Q36 -> 10598 | O36: 10598
A37: b) | B37: Any default in Rent payment by 10th of the following month the house shall be locked without notice and belongings removed for re-letting. | N37: =O37-Q37 -> 8770 | O37: 8770
N38: =O38-Q38 -> 8770 | O38: 8770
A39: c) | B39: Amounts not cleared by last pay date will render to water disconnection. | O39: =SUM(O3:O38) -> 391268 | Q39: =SUM(Q3:Q38) -> 0
A41: d) | B41: A reconnection fee of Kshs. 1,000 will be charged and paid before supply is reconnected.
A42: e) | B42: ANY MINOR REPAIRS OCCURING AFTER 3 MONTHS OF OCCUPANCY ARE TENANT'S RESPONSIBILITY AS PER TENANCY AGREEMENT.
A43: f) | B43: The water bills are payable through the same account for monthly rent strictly through:
B44: Frebazeth Company Limited
B45: Consolidated Bank Account
B46: Kitengela Branch
B47: PAY BILL 4139271
B48: (Kindly indicate your Name & House number on the deposit slip & inform the Bank teller to capture it.)
B49: A receipt will be issued upon bank confirmation of the transaction. | O49: ……………
A50: g)
B51: ACC NO KT 20B
B52: E & O E
B53: NB: Kindly give the management atleast two (2) months prior notice incase you intend to terminate the tenancy for ease of logisitics.

Sheet hse21B
B2: OLE SAMEDHA APARTMENTS-Kitengela | N2: VAR | O2: TAX DUE
B3: ='hse1'!B3 -> P.O BOX 9473-00200 NAIROBI | N3: =O3-Q3 -> 10270 | O3: 10270
B4: WATER BILL | H4: BILL NO. | I4: ='hse1'!H4+21-1 -> 20242021 | L4: ='hse1'!H4+21-1 -> 20242021 | N4: =O4-Q4 -> 10304 | O4: 10304
N5: =O5-Q5 -> 10988 | O5: 10988
B6: TENANT NAME | D6: =meter!A23 -> MAGRET | N6: =O6-Q6 -> 11070 | O6: 11070
N7: =O7-Q7 -> 1197 | O7: 1197
B8: HOUSE NUMBER | D8: 21B | N8: =O8-Q8 -> 9250 | O8: 9250
D9: 0723662965 | N9: =O9-Q9 -> 8770 | O9: 8770
B10: ISSUE DATE | D10: ='hse1'!C10 -> 27/1/2026 | N10: =O10-Q10 -> 23190 | O10: 23190
N11: =O11-Q11 -> 10910 | O11: 10910
B12: LAST PAY DATE | D12: ='hse1'!C12 -> 46144 | N12: =O12-Q12 -> 10910 | O12: 10910
N13: =O13-Q13 -> 12190 | O13: 12190
N14: =O14-Q14 -> 11070 | O14: 11070
B15: PREVIOUS READING | D15: CURRENT READING | F15: CONSUMPTION | N15: =O15-Q15 -> 9090 | O15: 9090
B16: =meter!D23 -> 176 | D16: =meter!E23 -> 180 | E16: Units | F16: =D16-B16 -> 4 | N16: =O16-Q16 -> 9420 | O16: 9420
F17: Amount (Kshs.) | N17: =O17-Q17 -> 11154 | O17: 11154
D18: LAST ACCOUNT B/F | E18: Kshs. | F18: =meter!O23 -> 0 | N18: =O18-Q18 -> 10430 | O18: 10430
N19: =O19-Q19 -> 11831 | O19: 11831
D20: MONTH BILL | E20: KSHS. | F20: =meter!H23 -> 880 | N20: =O20-Q20 -> 10590 | O20: 10590
N21: =O21-Q21 -> 22423 | O21: 22423
D22: PUMP/POWER CHARGES | E22: KSHS. | F22: ='hse1'!E22 -> 110 | N22: =O22-Q22 -> 9250 | O22: 9250
N23: =O23-Q23 -> 10162 | O23: 10162
D24: MONTH HOUSE RENT | E24: KSHS. | F24: =meter!N23 -> 9000 | N24: =O24-Q24 -> 10270 | O24: 10270
N25: =O25-Q25 -> 11070 | O25: 11070
D26: ='hse1'!C26 -> security | E26: ='hse1'!D26 -> Kshs. | F26: =meter!M23 -> 0 | N26: =O26-Q26 -> 11550 | O26: 11550
D27: GARBAGE FEE | E27: Kshs. | F27: 150 | N27: =O27-Q27 -> 11393 | O27: 11393
D28: INTEREST ON ARREARS | E28: KSHS. | F28: =IF(F18*4%*1<0,0,F18*4%*1) -> 0 | N28: =O28-Q28 -> 10802 | O28: 10802
N29: =O29-Q29 -> 8930 | O29: 8930
D30: TOTAL PAYABLE | E30: Kshs. | F30: =SUM(F17:F29) -> 10140 | N30: =O30-Q30 -> 9570 | O30: 9570
N31: =O31-Q31 -> 11390 | O31: 11390
D32: PAID | F32: =meter!R23 -> 0 | N32: =O32-Q32 -> 10750 | O32: 10750
N33: =O33-Q33 -> 11732 | O33: 11732
D34: AMOUNT DUE | F34: =F30-F32 -> 10140 | N34: =O34-Q34 -> 10934 | O34: 10934 | R34: 700
C35: NOTE | N35: =O35-Q35 -> 10270 | O35: 10270
A36: a) | B36: Rent is due on or before 5th of the month. By 7th day, any rent not paid will attract interest at 2% per day. | N36: =O36-Q36 -> 10598 | O36: 10598
A37: b) | B37: Any default in Rent payment by 10th of the following month the house shall be locked without notice and belongings removed for re-letting. | N37: =O37-Q37 -> 8770 | O37: 8770
N38: =O38-Q38 -> 8770 | O38: 8770
A39: c) | B39: Amounts not cleared by last pay date will render to water disconnection. | O39: =SUM(O3:O38) -> 391268 | Q39: =SUM(Q3:Q38) -> 0
A41: d) | B41: A reconnection fee of Kshs. 1,000 will be charged and paid before supply is reconnected.
A42: e) | B42: ANY MINOR REPAIRS OCCURING AFTER 3 MONTHS OF OCCUPANCY ARE TENANT'S RESPONSIBILITY AS PER TENANCY AGREEMENT.
A43: f) | B43: The water bills are payable through the same account for monthly rent strictly through:
B44: Frebazeth Company Limited
B45: Consolidated Bank Account
B46: Kitengela Branch
B47: PAY BILL 4139271
B48: (Kindly indicate your Name & House number on the deposit slip & inform the Bank teller to capture it.)
B49: A receipt will be issued upon bank confirmation of the transaction. | O49: ……………
A50: g)
B51: ACC NO KT 21B
B52: E & O E
B53: NB: Kindly give the management atleast two (2) months prior notice incase you intend to terminate the tenancy for ease of logisitics.

Sheet hse22
B2: OLE SAMEDHA APARTMENTS-Kitengela | N2: VAR | O2: TAX DUE
B3: ='hse1'!B3 -> P.O BOX 9473-00200 NAIROBI | N3: =O3-Q3 -> 10270 | O3: 10270
B4: WATER BILL | H4: BILL NO. | I4: ='hse1'!H4+22-1 -> 20242022 | J4: ='hse1'!H4+22-1 -> 20242022 | N4: =O4-Q4 -> 10304 | O4: 10304
N5: =O5-Q5 -> 10988 | O5: 10988
B6: TENANT NAME | D6: =meter!A24 -> FATUMA ZAWADI | N6: =O6-Q6 -> 11070 | O6: 11070
N7: =O7-Q7 -> 1197 | O7: 1197
B8: HOUSE NUMBER: | D8: 22A | N8: =O8-Q8 -> 9250 | O8: 9250
N9: =O9-Q9 -> 8770 | O9: 8770
B10: ISSUE DATE | D10: ='hse1'!C10 -> 27/1/2026 | N10: =O10-Q10 -> 23190 | O10: 23190
N11: =O11-Q11 -> 10910 | O11: 10910
B12: LAST PAY DATE | D12: ='hse1'!C12 -> 46144 | N12: =O12-Q12 -> 10910 | O12: 10910
N13: =O13-Q13 -> 12190 | O13: 12190
N14: =O14-Q14 -> 11070 | O14: 11070
B15: PREVIOUS READING | D15: CURRENT READING | F15: CONSUMPTION | N15: =O15-Q15 -> 9090 | O15: 9090
B16: =meter!D24 -> 290 | D16: =meter!E24 -> 292 | E16: Units | F16: =D16-B16 -> 2 | N16: =O16-Q16 -> 9420 | O16: 9420
F17: Amount (Kshs.) | N17: =O17-Q17 -> 11154 | O17: 11154
D18: LAST ACCOUNT B/F | E18: Kshs. | F18: =meter!O24 -> 0 | N18: =O18-Q18 -> 10430 | O18: 10430
N19: =O19-Q19 -> 11831 | O19: 11831
D20: MONTH BILL | E20: KSHS. | F20: =meter!H24 -> 440 | N20: =O20-Q20 -> 10590 | O20: 10590
N21: =O21-Q21 -> 22423 | O21: 22423
D22: PUMP/POWER CHARGES | E22: KSHS. | F22: ='hse1'!E22 -> 110 | N22: =O22-Q22 -> 9250 | O22: 9250
N23: =O23-Q23 -> 10162 | O23: 10162
D24: MONTH HOUSE RENT | E24: KSHS. | F24: =meter!N24 -> 10500 | N24: =O24-Q24 -> 10270 | O24: 10270
N25: =O25-Q25 -> 11070 | O25: 11070
D26: ='hse1'!C26 -> security | E26: ='hse1'!D26 -> Kshs. | N26: =O26-Q26 -> 11550 | O26: 11550
D27: GARBAGE FEE | E27: Kshs. | F27: 150 | N27: =O27-Q27 -> 11393 | O27: 11393
D28: INTEREST LATE PAYMENT | E28: KSHS. | F28: =IF(F18*4%*1<0,0,F18*4%*1) -> 0 | N28: =O28-Q28 -> 10802 | O28: 10802
N29: =O29-Q29 -> 8930 | O29: 8930
D30: TOTAL PAYABLE | E30: Kshs. | F30: =SUM(F17:F29) -> 11200 | N30: =O30-Q30 -> 9570 | O30: 9570
N31: =O31-Q31 -> 11390 | O31: 11390
D32: PAID | F32: =meter!R24 -> 0 | N32: =O32-Q32 -> 10750 | O32: 10750
N33: =O33-Q33 -> 11732 | O33: 11732
D34: AMOUNT DUE | F34: =F30-F32 -> 11200 | N34: =O34-Q34 -> 10934 | O34: 10934 | R34: 700
C35: NOTE | N35: =O35-Q35 -> 10270 | O35: 10270
A36: a) | B36: Rent is due on or before 5th of the month. By 7th day, any rent not paid will attract interest at 2% per day. | N36: =O36-Q36 -> 10598 | O36: 10598
A37: b) | B37: Any default in Rent payment by 10th of the following month the house shall be locked without notice and belongings removed for re-letting. | N37: =O37-Q37 -> 8770 | O37: 8770
N38: =O38-Q38 -> 8770 | O38: 8770
A39: c) | D39: PAY BILL 4139271 | E39: ACC NO KT 22A | O39: =SUM(O3:O38) -> 391268 | Q39: =SUM(Q3:Q38) -> 0
A41: d) | B41: A reconnection fee of Kshs. 1,000 will be charged and paid before supply is reconnected.
A42: e) | B42: ANY MINOR REPAIRS OCCURING AFTER 3 MONTHS OF OCCUPANCY ARE TENANT'S RESPONSIBILITY AS PER TENANCY AGREEMENT.
A43: f) | B43: The water bills are payable through the same account for monthly rent strictly through:
B44: Frebazeth Company Limited
B45: Consolidated Bank Account
B46: Kitengela Branch
O49: ……………
A50: g)

Sheet hse23
B1: OLE SAMEDHA APARTMENTS-Kitengela
B2: ='hse1'!B3 -> P.O BOX 9473-00200 NAIROBI | N2: VAR | O2: TAX DUE
B3: WATER BILL | N3: =O3-Q3 -> 10270 | O3: 10270
H4: BILL NO. | I4: ='hse1'!H4+23-1 -> 20242023 | K4: ='hse1'!H4+23-1 -> 20242023 | N4: =O4-Q4 -> 10304 | O4: 10304
N5: =O5-Q5 -> 10988 | O5: 10988
B6: TENANT NAME | D6: =meter!A25 -> KAMAU | N6: =O6-Q6 -> 11070 | O6: 11070
N7: =O7-Q7 -> 1197 | O7: 1197
B8: HOUSE NUMBER | D8: 23A | N8: =O8-Q8 -> 9250 | O8: 9250
N9: =O9-Q9 -> 8770 | O9: 8770
A10: ISUE DATE | B10: ISSUE DATE | D10: ='hse1'!C10 -> 27/1/2026 | N10: =O10-Q10 -> 23190 | O10: 23190
N11: =O11-Q11 -> 10910 | O11: 10910
A12: LAST PDY | B12: LAST PAY DATE | D12: ='hse1'!C12 -> 46144 | N12: =O12-Q12 -> 10910 | O12: 10910
N13: =O13-Q13 -> 12190 | O13: 12190
N14: =O14-Q14 -> 11070 | O14: 11070
B15: PREVIOUS READING | D15: CURRENT READING | F15: CONSUMPTION | N15: =O15-Q15 -> 9090 | O15: 9090
B16: =meter!D25 -> 670 | D16: =meter!E25 -> 673 | E16: Units | F16: =D16-B16 -> 3 | N16: =O16-Q16 -> 9420 | O16: 9420
F17: Amount (Kshs.) | N17: =O17-Q17 -> 11154 | O17: 11154
D18: LAST ACCOUNT B/F | E18: Kshs. | F18: =meter!O25 -> 0 | N18: =O18-Q18 -> 10430 | O18: 10430
N19: =O19-Q19 -> 11831 | O19: 11831
D20: MONTH BILL | E20: KSHS. | F20: =meter!H25 -> 660 | N20: =O20-Q20 -> 10590 | O20: 10590
N21: =O21-Q21 -> 22423 | O21: 22423
D22: PUMP/POWER CHARGES | E22: KSHS. | F22: ='hse1'!E22 -> 110 | N22: =O22-Q22 -> 9250 | O22: 9250
N23: =O23-Q23 -> 10162 | O23: 10162
D24: MONTH HOUSE RENT | E24: KSHS. | F24: =meter!N25 -> 10500 | N24: =O24-Q24 -> 10270 | O24: 10270
N25: =O25-Q25 -> 11070 | O25: 11070
D26: ='hse1'!C26 -> security | E26: ='hse1'!D26 -> Kshs. | F26: ='hse1'!E26 -> 500 | N26: =O26-Q26 -> 11550 | O26: 11550
D27: GARBAGE FEE | E27: Kshs. | F27: 150 | N27: =O27-Q27 -> 11393 | O27: 11393
D28: PENALTY LATE PAYMENT | E28: KSHS. | F28: =IF(F18*4%*1<0,0,F18*4%*1) -> 0 | N28: =O28-Q28 -> 10802 | O28: 10802
N29: =O29-Q29 -> 8930 | O29: 8930
D30: TOTAL PAYABLE | E30: Kshs. | F30: =SUM(F17:F29) -> 11920 | N30: =O30-Q30 -> 9570 | O30: 9570
N31: =O31-Q31 -> 11390 | O31: 11390
D32: PAID | F32: =meter!R25 -> 0 | N32: =O32-Q32 -> 10750 | O32: 10750
N33: =O33-Q33 -> 11732 | O33: 11732
D34: AMOUNT DUE | F34: =F30-F32 -> 11920 | N34: =O34-Q34 -> 10934 | O34: 10934 | R34: 700
C35: NOTE | N35: =O35-Q35 -> 10270 | O35: 10270
A36: a) | B36: Rent is due on or before 5th of the month. By 7th day, any rent not paid will attract interest at 2% per day. | C36: Rent is due on or before 5th of the month. By 7th day, any rent not paid will attract interest at 2% per day. | N36: =O36-Q36 -> 10598 | O36: 10598
A37: b) | B37: Any default in Rent payment by 10th of the following month the house shall be locked without notice and belongings removed for re-letting. | C37: Any default in Rent payment by 10th of the following month the house shall be locked without notice and belongings removed for re-letting. | N37: =O37-Q37 -> 8770 | O37: 8770
N38: =O38-Q38 -> 8770 | O38: 8770
A39: c) | B39: Amounts not cleared by last pay date will render to water disconnection. | C39: Amounts not cleared by last pay date will render to water disconnection. | O39: =SUM(O3:O38) -> 391268 | Q39: =SUM(Q3:Q38) -> 0
A41: d) | B41: A reconnection fee of Kshs. 1,000 will be charged and paid before supply is reconnected. | C41: A reconnection fee of Kshs. 1,000 will be charged and paid before supply is reconnected.
A42: e) | B42: ANY MINOR REPAIRS OCCURING AFTER 3 MONTHS OF OCCUPANCY ARE TENANT'S RESPONSIBILITY AS PER TENANCY AGREEMENT. | C42: ANY MINOR REPAIRS OCCURING AFTER 3 MONTHS OF OCCUPANCY ARE TENANT'S RESPONSIBILITY AS PER TENANCY AGREEMENT.
A43: f) | B43: The water bills are payable through the same account for monthly rent strictly through: | C43: The water bills are payable through the same account for monthly rent strictly through:
B44: Frebazeth Company Limited | C44: Frebazeth Company Limited
B45: Consolidated Bank Account | C45: Consolidated Bank Account
B46: Kitengela Branch | C46: Kitengela Branch
B47: A/C NO. 10171202000107 | C47: PAYBILL 4139271
B48: (Kindly indicate your Name & House number on the deposit slip & inform the Bank teller to capture it.) | C48: (Kindly indicate your Name & House number on the deposit slip & inform the Bank teller to capture it.)
B49: A receipt will be issued upon bank confirmation of the transaction. | C49: A receipt will be issued upon bank confirmation of the transaction. | O49: ……………
A50: g) | B50: MPESA, PAYBILL CONSOL BANK 508400 A/C NO. 10171202000107, Add 40/= for charges
B51: E & O E | C51: ACC NO KT 23A
B52: NB: Kindly give the management atleast two (2) months prior notice incase you intend to terminate the tenancy for ease of logisitics. | C52: E & O E
C53: NB: Kindly give the management atleast two (2) months prior notice incase you intend to terminate the tenancy for ease of logisitics.

Sheet hse24
B1: OLE SAMEDHA APARTMENTS-Kitengela
B2: ='hse1'!B3 -> P.O BOX 9473-00200 NAIROBI | N2: VAR | O2: TAX DUE
B3: WATER BILL | N3: =O3-Q3 -> 10270 | O3: 10270
H4: BILL NO. | I4: ='hse1'!H4+24-1 -> 20242024 | M4: ='hse1'!H4+24-1 -> 20242024 | N4: =O4-Q4 -> 10304 | O4: 10304
N5: =O5-Q5 -> 10988 | O5: 10988
B6: TENANT NAME | D6: =meter!A26 -> NEW TENANT | N6: =O6-Q6 -> 11070 | O6: 11070
N7: =O7-Q7 -> 1197 | O7: 1197
B8: HOUSE NUMBER: | D8: 24A | N8: =O8-Q8 -> 9250 | O8: 9250
N9: =O9-Q9 -> 8770 | O9: 8770
B10: ISSUE DATE | D10: ='hse1'!C10 -> 27/1/2026 | N10: =O10-Q10 -> 23190 | O10: 23190
N11: =O11-Q11 -> 10910 | O11: 10910
B12: LAST PAY DATE | D12: ='hse1'!C12 -> 46144 | N12: =O12-Q12 -> 10910 | O12: 10910
N13: =O13-Q13 -> 12190 | O13: 12190
N14: =O14-Q14 -> 11070 | O14: 11070
B15: PREVIOUS READING | D15: CURRENT READING | F15: CONSUMPTION | N15: =O15-Q15 -> 9090 | O15: 9090
B16: =meter!D26 -> 92 | D16: =meter!E26 -> 94 | E16: Units | F16: =D16-B16 -> 2 | N16: =O16-Q16 -> 9420 | O16: 9420
F17: Amount (Kshs.) | N17: =O17-Q17 -> 11154 | O17: 11154
D18: LAST ACCOUNT B/F | E18: Kshs. | F18: =meter!O26 -> 0 | N18: =O18-Q18 -> 10430 | O18: 10430
N19: =O19-Q19 -> 11831 | O19: 11831
D20: MONTH BILL | E20: KSHS. | F20: =meter!H26 -> 440 | N20: =O20-Q20 -> 10590 | O20: 10590
N21: =O21-Q21 -> 22423 | O21: 22423
D22: PUMP/POWER CHARGES | E22: KSHS. | F22: ='hse1'!E22 -> 110 | N22: =O22-Q22 -> 9250 | O22: 9250
N23: =O23-Q23 -> 10162 | O23: 10162
D24: MONTH HOUSE RENT | E24: KSHS. | F24: =meter!N26 -> 10500 | N24: =O24-Q24 -> 10270 | O24: 10270
N25: =O25-Q25 -> 11070 | O25: 11070
D26: ='hse1'!C26 -> security | E26: ='hse1'!D26 -> Kshs. | F26: 500 | N26: =O26-Q26 -> 11550 | O26: 11550
D27: GARBAGE FEE | E27: Kshs. | F27: 150 | N27: =O27-Q27 -> 11393 | O27: 11393
D28: INTEREST ON ARREARS | E28: KSHS. | F28: =IF(F18*4%*1<0,0,F18*4%*1) -> 0 | N28: =O28-Q28 -> 10802 | O28: 10802
N29: =O29-Q29 -> 8930 | O29: 8930
D30: TOTAL PAYABLE | E30: Kshs. | F30: =SUM(F17:F29) -> 11700 | N30: =O30-Q30 -> 9570 | O30: 9570
N31: =O31-Q31 -> 11390 | O31: 11390
D32: PAID | F32: =meter!R26 -> 0 | N32: =O32-Q32 -> 10750 | O32: 10750
N33: =O33-Q33 -> 11732 | O33: 11732
D34: AMOUNT DUE | F34: =F30-F32 -> 11700 | N34: =O34-Q34 -> 10934 | O34: 10934 | R34: 700
C35: NOTE | N35: =O35-Q35 -> 10270 | O35: 10270
A36: a) | B36: Rent is due on or before 5th of the month. By 7th day, any rent not paid will attract interest at 2% per day. | N36: =O36-Q36 -> 10598 | O36: 10598
A37: b) | B37: Any default in Rent payment by 10th of the following month the house shall be locked without notice and belongings removed for re-letting. | N37: =O37-Q37 -> 8770 | O37: 8770
N38: =O38-Q38 -> 8770 | O38: 8770
A39: c) | B39: Amounts not cleared by last pay date will render to water disconnection. | O39: =SUM(O3:O38) -> 391268 | Q39: =SUM(Q3:Q38) -> 0
A41: d) | B41: A reconnection fee of Kshs. 1,000 will be charged and paid before supply is reconnected.
A42: e) | B42: ANY MINOR REPAIRS OCCURING AFTER 3 MONTHS OF OCCUPANCY ARE TENANT'S RESPONSIBILITY AS PER TENANCY AGREEMENT.
A43: f) | B43: The water bills are payable through the same account for monthly rent strictly through:
B44: Frebazeth Company Limited
B45: Consolidated Bank Account
B46: Kitengela Branch
B47: PAY BILL 4139271
B48: (Kindly indicate your Name & House number on the deposit slip & inform the Bank teller to capture it.)
B49: A receipt will be issued upon bank confirmation of the transaction. | O49: ……………
A50: g)
B51: ACC NO KT 24A
B52: E & O E
B53: NB: Kindly give the management atleast two (2) months prior notice incase you intend to terminate the tenancy for ease of logisitics.

Sheet hse25
B1: OLE SAMEDHA APARTMENTS-Kitengela
B2: ='hse1'!B3 -> P.O BOX 9473-00200 NAIROBI | N2: VAR | O2: TAX DUE
B3: WATER BILL | N3: =O3-Q3 -> 10270 | O3: 10270
H4: BILL NO. | I4: ='hse1'!H4+25-1 -> 20242025 | K4: ='hse1'!H4+25-1 -> 20242025 | N4: =O4-Q4 -> 10304 | O4: 10304
N5: =O5-Q5 -> 10988 | O5: 10988
B6: TENANT NAME | D6: OMAR | N6: =O6-Q6 -> 11070 | O6: 11070
N7: =O7-Q7 -> 1197 | O7: 1197
B8: HOUSE NUMBER | D8: 25A | N8: =O8-Q8 -> 9250 | O8: 9250
N9: =O9-Q9 -> 8770 | O9: 8770
B10: ISSUE DATE | D10: ='hse1'!C10 -> 27/1/2026 | N10: =O10-Q10 -> 23190 | O10: 23190
N11: =O11-Q11 -> 10910 | O11: 10910
B12: LAST PAY DATE | D12: ='hse1'!C12 -> 46144 | N12: =O12-Q12 -> 10910 | O12: 10910
N13: =O13-Q13 -> 12190 | O13: 12190
N14: =O14-Q14 -> 11070 | O14: 11070
B15: PREVIOUS READING | D15: CURRENT READING | F15: CONSUMPTION | N15: =O15-Q15 -> 9090 | O15: 9090
B16: =meter!D27 -> 698 | C16: 643 | D16: =meter!E27 -> 701 | E16: Units | F16: =D16-B16 -> 3 | N16: =O16-Q16 -> 9420 | O16: 9420
F17: Amount (Kshs.) | N17: =O17-Q17 -> 11154 | O17: 11154
D18: LAST ACCOUNT B/F | E18: Kshs. | F18: =meter!O27 -> 1355 | N18: =O18-Q18 -> 10430 | O18: 10430
N19: =O19-Q19 -> 11831 | O19: 11831
D20: MONTH BILL | E20: KSHS. | F20: =meter!H27 -> 660 | N20: =O20-Q20 -> 10590 | O20: 10590
N21: =O21-Q21 -> 22423 | O21: 22423
D22: PUMP/POWER CHARGES | E22: KSHS. | F22: ='hse1'!E22 -> 110 | N22: =O22-Q22 -> 9250 | O22: 9250
N23: =O23-Q23 -> 10162 | O23: 10162
D24: MONTH HOUSE RENT | E24: KSHS. | F24: =meter!N27 -> 10500 | N24: =O24-Q24 -> 10270 | O24: 10270
N25: =O25-Q25 -> 11070 | O25: 11070
D26: ='hse1'!C26 -> security | E26: ='hse1'!D26 -> Kshs. | F26: 500 | N26: =O26-Q26 -> 11550 | O26: 11550
D27: GARBAGE FEE | E27: Kshs. | F27: 150 | N27: =O27-Q27 -> 11393 | O27: 11393
D28: INTEREST ON ARREARS | E28: KSHS. | F28: =IF(F18*4%*1<0,0,F18*4%*1) -> 54.2 | N28: =O28-Q28 -> 10802 | O28: 10802
N29: =O29-Q29 -> 8930 | O29: 8930
D30: TOTAL PAYABLE | E30: Kshs. | F30: =SUM(F17:F29) -> 13329.2 | N30: =O30-Q30 -> 9570 | O30: 9570
N31: =O31-Q31 -> 11390 | O31: 11390
D32: PAID | F32: 0 | N32: =O32-Q32 -> 10750 | O32: 10750
N33: =O33-Q33 -> 11732 | O33: 11732
D34: AMOUNT DUE | F34: =F30-F32 -> 13329.2 | N34: =O34-Q34 -> 10934 | O34: 10934 | R34: 700
C35: NOTE | N35: =O35-Q35 -> 10270 | O35: 10270
A36: a) | B36: Rent is due on or before 5th of the month. By 7th day, any rent not paid will attract interest at 2% per day. | N36: =O36-Q36 -> 10598 | O36: 10598
A37: b) | B37: Any default in Rent payment by 10th of the following month the house shall be locked without notice and belongings removed for re-letting. | N37: =O37-Q37 -> 8770 | O37: 8770
N38: =O38-Q38 -> 8770 | O38: 8770
A39: c) | B39: Amounts not cleared by last pay date will render to water disconnection. | O39: =SUM(O3:O38) -> 391268 | Q39: =SUM(Q3:Q38) -> 0
A41: d) | B41: A reconnection fee of Kshs. 1,000 will be charged and paid before supply is reconnected.
A42: e) | B42: ANY MINOR REPAIRS OCCURING AFTER 3 MONTHS OF OCCUPANCY ARE TENANT'S RESPONSIBILITY AS PER TENANCY AGREEMENT.
A43: f) | B43: The water bills are payable through the same account for monthly rent strictly through:
B44: Frebazeth Company Limited
B45: Consolidated Bank Account
B46: Kitengela Branch
B47: PAY BILL 4139271
B48: (Kindly indicate your Name & House number on the deposit slip & inform the Bank teller to capture it.)
B49: A receipt will be issued upon bank confirmation of the transaction. | O49: ……………
A50: g)
B51: ACC NO KT 25A
B52: E & O E
B53: NB: Kindly give the management atleast two (2) months prior notice incase you intend to terminate the tenancy for ease of logisitics.

Sheet hse26
B1: OLE SAMEDHA APARTMENTS-Kitengela
B2: ='hse1'!B3 -> P.O BOX 9473-00200 NAIROBI | N2: VAR | O2: TAX DUE
B3: WATER BILL | N3: =O3-Q3 -> 10270 | O3: 10270
H4: BILL NO. | I4: ='hse1'!H4+26-1 -> 20242026 | L4: ='hse1'!H4+26-1 -> 20242026 | N4: =O4-Q4 -> 10304 | O4: 10304
N5: =O5-Q5 -> 10988 | O5: 10988
B6: TENANT NAME | D6: =meter!A28 -> JOEL MAINA NDUNGU | N6: =O6-Q6 -> 11070 | O6: 11070
N7: =O7-Q7 -> 1197 | O7: 1197
B8: HOUSE NUMBER: | D8: 26A | N8: =O8-Q8 -> 9250 | O8: 9250
N9: =O9-Q9 -> 8770 | O9: 8770
B10: ISSUE DATE | D10: ='hse1'!C10 -> 27/1/2026 | N10: =O10-Q10 -> 23190 | O10: 23190 | R10: 10500
N11: =O11-Q11 -> 10910 | O11: 10910 | R11: 4200
B12: LAST PAY DATE | D12: ='hse1'!C12 -> 46144 | N12: =O12-Q12 -> 10910 | O12: 10910 | R12: =R10-R11 -> 6300
N13: =O13-Q13 -> 12190 | O13: 12190
N14: =O14-Q14 -> 11070 | O14: 11070
B15: PREVIOUS READING | D15: CURRENT READING | F15: CONSUMPTION | N15: =O15-Q15 -> 9090 | O15: 9090
B16: =meter!D28 -> 1377 | D16: =meter!E28 -> 1381 | E16: Units | F16: =D16-B16 -> 4 | N16: =O16-Q16 -> 9420 | O16: 9420
F17: Amount (Kshs.) | N17: =O17-Q17 -> 11154 | O17: 11154
D18: LAST ACCOUNT B/F | E18: Kshs. | F18: =meter!O28 -> 0 | N18: =O18-Q18 -> 10430 | O18: 10430
N19: =O19-Q19 -> 11831 | O19: 11831
D20: MONTH BILL | E20: KSHS. | F20: =meter!H28 -> 880 | N20: =O20-Q20 -> 10590 | O20: 10590
N21: =O21-Q21 -> 22423 | O21: 22423
D22: PUMP/POWER CHARGES | E22: KSHS. | F22: 110 | N22: =O22-Q22 -> 9250 | O22: 9250
N23: =O23-Q23 -> 10162 | O23: 10162
D24: MONTH HOUSE RENT | E24: KSHS. | F24: =meter!N28 -> 10000 | N24: =O24-Q24 -> 10270 | O24: 10270
N25: =O25-Q25 -> 11070 | O25: 11070
D26: ='hse1'!C26 -> security | E26: ='hse1'!D26 -> Kshs. | F26: ='hse1'!E26 -> 500 | N26: =O26-Q26 -> 11550 | O26: 11550
D27: GARBAGE FEE | E27: Kshs. | F27: 150 | N27: =O27-Q27 -> 11393 | O27: 11393
D28: Interest on rent arrears | E28: KSHS. | F28: =IF(F18*4%*1<0,0,F18*4%*1) -> 0 | N28: =O28-Q28 -> 10802 | O28: 10802
N29: =O29-Q29 -> 8930 | O29: 8930
D30: TOTAL PAYABLE | E30: Kshs. | F30: =SUM(F17:F29) -> 11640 | N30: =O30-Q30 -> 9570 | O30: 9570
N31: =O31-Q31 -> 11390 | O31: 11390
D32: PAID | F32: 0 | N32: =O32-Q32 -> 10750 | O32: 10750
N33: =O33-Q33 -> 11732 | O33: 11732
D34: AMOUNT DUE | F34: =F30-F32 -> 11640 | H34: =F34 -> 11640 | N34: =O34-Q34 -> 10934 | O34: 10934 | R34: 700
C35: NOTE | N35: =O35-Q35 -> 10270 | O35: 10270
A36: a) | B36: Rent is due on or before 5th of the month. By 7th day, any rent not paid will attract interest at 2% per day. | N36: =O36-Q36 -> 10598 | O36: 10598
A37: b) | B37: Any default in Rent payment by 10th of the following month the house shall be locked without notice and belongings removed for re-letting. | N37: =O37-Q37 -> 8770 | O37: 8770
N38: =O38-Q38 -> 8770 | O38: 8770
A39: c) | B39: Amounts not cleared by last pay date will render to water disconnection. | O39: =SUM(O3:O38) -> 391268 | Q39: =SUM(Q3:Q38) -> 0
A41: d) | B41: A reconnection fee of Kshs. 1,000 will be charged and paid before supply is reconnected.
A42: e) | B42: ANY MINOR REPAIRS OCCURING AFTER 3 MONTHS OF OCCUPANCY ARE TENANT'S RESPONSIBILITY AS PER TENANCY AGREEMENT.
A43: f) | B43: The water bills are payable through the same account for monthly rent strictly through:
B44: Frebazeth Company Limited
B45: Consolidated Bank Account
B46: Kitengela Branch
B47: PAY BILL 4139271
B48: (Kindly indicate your Name & House number on the deposit slip & inform the Bank teller to capture it.)
B49: A receipt will be issued upon bank confirmation of the transaction. | O49: ……………
A50: g)
B51: ACC NO KT 26A
B52: E & O E
B53: NB: Kindly give the management atleast two (2) months prior notice incase you intend to terminate the tenancy for ease of logisitics.

Sheet hse27B
B1: OLE SAMEDHA APARTMENTS-Kitengela
B2: ='hse1'!B3 -> P.O BOX 9473-00200 NAIROBI | O2: VAR | P2: TAX DUE
B3: WATER BILL | O3: =P3-R3 -> 10270 | P3: 10270
I4: BILL NO. | J4: ='hse1'!H4+27-1 -> 20242027 | M4: ='hse1'!H4+27-1 -> 20242027 | O4: =P4-R4 -> 10304 | P4: 10304
O5: =P5-R5 -> 10988 | P5: 10988
B6: TENANT NAME | D6: CATE | O6: =P6-R6 -> 11070 | P6: 11070
O7: =P7-R7 -> 1197 | P7: 1197
B8: HOUSE NUMBER: | D8: 27B | O8: =P8-R8 -> 9250 | P8: 9250
D9: 0722340955 | O9: =P9-R9 -> 8770 | P9: 8770
B10: ISSUE DATE | D10: ='hse1'!C10 -> 27/1/2026 | O10: =P10-R10 -> 23190 | P10: 23190
O11: =P11-R11 -> 10910 | P11: 10910
B12: LAST PAY DATE | D12: ='hse1'!C12 -> 46144 | O12: =P12-R12 -> 10910 | P12: 10910
O13: =P13-R13 -> 12190 | P13: 12190
O14: =P14-R14 -> 11070 | P14: 11070
B15: PREVIOUS READING | D15: CURRENT READING | F15: CONSUMPTION | O15: =P15-R15 -> 9090 | P15: 9090
B16: =meter!D29 -> 214 | C16: 1 | D16: =meter!E29 -> 215 | E16: Units | F16: =D16-B16 -> 1 | O16: =P16-R16 -> 9420 | P16: 9420
F17: Amount (Kshs.) | O17: =P17-R17 -> 11154 | P17: 11154
D18: LAST ACCOUNT B/F | E18: Kshs. | F18: =meter!O29 -> 1132 | O18: =P18-R18 -> 10430 | P18: 10430
O19: =P19-R19 -> 11831 | P19: 11831
D20: MONTH BILL | E20: KSHS. | F20: =meter!H29 -> 220 | O20: =P20-R20 -> 10590 | P20: 10590
O21: =P21-R21 -> 22423 | P21: 22423
D22: PUMP/POWER CHARGES | E22: KSHS. | F22: ='hse1'!E22 -> 110 | O22: =P22-R22 -> 9250 | P22: 9250
O23: =P23-R23 -> 10162 | P23: 10162
D24: MONTH HOUSE RENT | E24: KSHS. | F24: 8500 | O24: =P24-R24 -> 10270 | P24: 10270
O25: =P25-R25 -> 11070 | P25: 11070
D26: SECURITY | E26: ='hse1'!D26 -> Kshs. | O26: =P26-R26 -> 11550 | P26: 11550
D27: GARBAGE FEE | E27: Kshs. | F27: 150 | O27: =P27-R27 -> 11393 | P27: 11393
D28: ADJUSTMENT (Interest late payment) | E28: KSHS. | F28: =IF(F18*4%*1<0,0,F18*4%*1) -> 45.28 | O28: =P28-R28 -> 10802 | P28: 10802
O29: =P29-R29 -> 8930 | P29: 8930
D30: TOTAL PAYABLE | E30: Kshs. | F30: =SUM(F17:F29) -> 10157.28 | O30: =P30-R30 -> 9570 | P30: 9570
O31: =P31-R31 -> 11390 | P31: 11390
D32: PAID | F32: =meter!R29 -> 0 | O32: =P32-R32 -> 10750 | P32: 10750
O33: =P33-R33 -> 11732 | P33: 11732
D34: AMOUNT DUE | F34: =F30-F32 -> 10157.28 | O34: =P34-R34 -> 10934 | P34: 10934 | S34: 700
C35: NOTE | O35: =P35-R35 -> 10270 | P35: 10270
A36: a) | B36: Rent is due on or before 5th of the month. By 7th day, any rent not paid will attract interest at 2% per day. | O36: =P36-R36 -> 10598 | P36: 10598
A37: b) | B37: Any default in Rent payment by 10th of the following month the house shall be locked without notice and belongings removed for re-letting. | O37: =P37-R37 -> 8770 | P37: 8770
O38: =P38-R38 -> 8770 | P38: 8770
A39: c) | B39: Amounts not cleared by last pay date will render to water disconnection. | P39: =SUM(P3:P38) -> 391268 | R39: =SUM(R3:R38) -> 0
A41: d) | B41: A reconnection fee of Kshs. 1,000 will be charged and paid before supply is reconnected.
A42: e) | B42: ANY MINOR REPAIRS OCCURING AFTER 3 MONTHS OF OCCUPANCY ARE TENANT'S RESPONSIBILITY AS PER TENANCY AGREEMENT.
A43: f) | B43: The water bills are payable through the same account for monthly rent strictly through:
B44: Frebazeth Company Limited
B45: Consolidated Bank Account
B46: Kitengela Branch
B47: PAY BILL 4139271
B48: (Kindly indicate your Name & House number on the deposit slip & inform the Bank teller to capture it.)
B49: A receipt will be issued upon bank confirmation of the transaction. | O49: ……………
A50: g)
B51: ACC NO KT 27B
B52: E & O E
B53: NB: Kindly give the management atleast two (2) months prior notice incase you intend to terminate the tenancy for ease of logisitics.

Sheet hse28B
B1: OLE SAMEDHA APARTMENTS-Kitengela
B2: ='hse1'!B3 -> P.O BOX 9473-00200 NAIROBI | N2: VAR | O2: TAX DUE
B3: WATER BILL | N3: =O3-Q3 -> 10270 | O3: 10270
F4: BILL NO. | H4: ='hse1'!H4+28-1 -> 20242028 | I4: ='hse1'!H4+28-1 -> 20242028 | N4: =O4-Q4 -> 10304 | O4: 10304
N5: =O5-Q5 -> 10988 | O5: 10988
B6: TENANT NAME | D6: =meter!A30 -> TITUS | N6: =O6-Q6 -> 11070 | O6: 11070
N7: =O7-Q7 -> 1197 | O7: 1197
B8: HOUSE NUMBER: | D8: 28B | N8: =O8-Q8 -> 9250 | O8: 9250
D9: 0721324583 | N9: =O9-Q9 -> 8770 | O9: 8770
B10: ISSUE DATE | D10: ='hse1'!C10 -> 27/1/2026 | N10: =O10-Q10 -> 23190 | O10: 23190
N11: =O11-Q11 -> 10910 | O11: 10910
B12: LAST PAY DATE | D12: ='hse1'!C12 -> 46144 | N12: =O12-Q12 -> 10910 | O12: 10910
N13: =O13-Q13 -> 12190 | O13: 12190
N14: =O14-Q14 -> 11070 | O14: 11070
B15: PREVIOUS READING | D15: CURRENT READING | F15: CONSUMPTION | N15: =O15-Q15 -> 9090 | O15: 9090
B16: =meter!D30 -> 116 | D16: =meter!E30 -> 118 | E16: Units | F16: =D16-B16 -> 2 | N16: =O16-Q16 -> 9420 | O16: 9420
F17: Amount (Kshs.) | N17: =O17-Q17 -> 11154 | O17: 11154
D18: LAST ACCOUNT B/F | E18: Kshs. | F18: =meter!O30 -> 0 | N18: =O18-Q18 -> 10430 | O18: 10430
F19: 0 | N19: =O19-Q19 -> 11831 | O19: 11831
D20: MONTH BILL | E20: KSHS. | F20: =meter!H30 -> 440 | N20: =O20-Q20 -> 10590 | O20: 10590
N21: =O21-Q21 -> 22423 | O21: 22423
D22: PUMP/POWER CHARGES | E22: KSHS. | F22: ='hse1'!E22 -> 110 | N22: =O22-Q22 -> 9250 | O22: 9250
F23: 0 | N23: =O23-Q23 -> 10162 | O23: 10162
D24: MONTH HOUSE RENT | E24: KSHS. | F24: =meter!N30 -> 9000 | N24: =O24-Q24 -> 10270 | O24: 10270
F25: 0 | N25: =O25-Q25 -> 11070 | O25: 11070
D26: ='hse1'!C26 -> security | E26: ='hse1'!D26 -> Kshs. | N26: =O26-Q26 -> 11550 | O26: 11550
D27: GARBAGE FEE | E27: KSHS. | F27: 150 | N27: =O27-Q27 -> 11393 | O27: 11393
D28: INTEREST ON ARREARS | E28: KSHS. | F28: =IF(F18*4%*1<0,0,F18*4%*1) -> 0 | N28: =O28-Q28 -> 10802 | O28: 10802
F29: 0 | N29: =O29-Q29 -> 8930 | O29: 8930
D30: TOTAL PAYABLE | E30: Kshs. | F30: =SUM(F17:F29) -> 9700 | N30: =O30-Q30 -> 9570 | O30: 9570
N31: =O31-Q31 -> 11390 | O31: 11390
D32: PAID | F32: =meter!R30 -> 0 | N32: =O32-Q32 -> 10750 | O32: 10750
N33: =O33-Q33 -> 11732 | O33: 11732
D34: AMOUNT DUE | F34: =F30-F32 -> 9700 | N34: =O34-Q34 -> 10934 | O34: 10934 | R34: 700
C35: NOTE | N35: =O35-Q35 -> 10270 | O35: 10270
A36: a) | B36: Rent is due on or before 5th of the month. By 7th day, any rent not paid will attract interest at 2% per day. | N36: =O36-Q36 -> 10598 | O36: 10598
A37: b) | B37: Any default in Rent payment by 10th of the following month the house shall be locked without notice and belongings removed for re-letting. | N37: =O37-Q37 -> 8770 | O37: 8770
N38: =O38-Q38 -> 8770 | O38: 8770
A39: c) | B39: Amounts not cleared by last pay date will render to water disconnection. | O39: =SUM(O3:O38) -> 391268 | Q39: =SUM(Q3:Q38) -> 0
A41: d) | B41: A reconnection fee of Kshs. 1,000 will be charged and paid before supply is reconnected.
A42: e) | B42: ANY MINOR REPAIRS OCCURING AFTER 3 MONTHS OF OCCUPANCY ARE TENANT'S RESPONSIBILITY AS PER TENANCY AGREEMENT.
A43: f) | B43: The water bills are payable through the same account for monthly rent strictly through:
B44: Frebazeth Company Limited
B45: Consolidated Bank Account
B46: Kitengela Branch
B47: PAY BILL 4139271
B48: (Kindly indicate your Name & House number on the deposit slip & inform the Bank teller to capture it.)
B49: A receipt will be issued upon bank confirmation of the transaction. | O49: ……………
A50: g)
B51: ACC NO KT 28A
B52: E & O E
B53: NB: Kindly give the management atleast two (2) months prior notice incase you intend to terminate the tenancy for ease of logisitics.

Sheet hse29
B1: OLE SAMEDHA APARTMENTS-Kitengela
B2: ='hse1'!B3 -> P.O BOX 9473-00200 NAIROBI | N2: VAR | O2: TAX DUE
B3: WATER BILL | N3: =O3-Q3 -> 10270 | O3: 10270
H4: BILL NO. | I4: ='hse1'!H4+29-1 -> 20242029 | J4: ='hse1'!H4+29-1 -> 20242029 | N4: =O4-Q4 -> 10304 | O4: 10304
N5: =O5-Q5 -> 10988 | O5: 10988
B6: TENANT NAME | D6: =meter!A31 -> PAUL MBOK | N6: =O6-Q6 -> 11070 | O6: 11070
N7: =O7-Q7 -> 1197 | O7: 1197
B8: HOUSE NUMBER: | D8: 29A | N8: =O8-Q8 -> 9250 | O8: 9250
N9: =O9-Q9 -> 8770 | O9: 8770
B10: ISSUE DATE | D10: ='hse1'!C10 -> 27/1/2026 | N10: =O10-Q10 -> 23190 | O10: 23190
N11: =O11-Q11 -> 10910 | O11: 10910
B12: LAST PAY DATE | D12: ='hse1'!C12 -> 46144 | N12: =O12-Q12 -> 10910 | O12: 10910
N13: =O13-Q13 -> 12190 | O13: 12190
N14: =O14-Q14 -> 11070 | O14: 11070
B15: PREVIOUS READING | D15: CURRENT READING | F15: CONSUMPTION | N15: =O15-Q15 -> 9090 | O15: 9090
B16: =meter!D31 -> 612 | D16: =meter!E31 -> 615 | E16: Units | F16: =D16-B16 -> 3 | N16: =O16-Q16 -> 9420 | O16: 9420
F17: Amount (Kshs.) | N17: =O17-Q17 -> 11154 | O17: 11154
D18: LAST ACCOUNT B/F | E18: Kshs. | F18: =meter!O31 -> 0 | L18: a | N18: =O18-Q18 -> 10430 | O18: 10430
N19: =O19-Q19 -> 11831 | O19: 11831
D20: MONTH BILL | E20: KSHS. | F20: =meter!H31 -> 660 | N20: =O20-Q20 -> 10590 | O20: 10590
N21: =O21-Q21 -> 22423 | O21: 22423
D22: PUMP/POWER CHARGES | E22: KSHS. | F22: ='hse1'!E22 -> 110 | N22: =O22-Q22 -> 9250 | O22: 9250
N23: =O23-Q23 -> 10162 | O23: 10162
D24: MONTH HOUSE RENT | E24: KSHS. | F24: =meter!N31 -> 10500 | N24: =O24-Q24 -> 10270 | O24: 10270
N25: =O25-Q25 -> 11070 | O25: 11070
D26: ='hse1'!C26 -> security | E26: ='hse1'!D26 -> Kshs. | N26: =O26-Q26 -> 11550 | O26: 11550
D27: GARBAGE FEE | E27: Kshs. | F27: 150 | N27: =O27-Q27 -> 11393 | O27: 11393
D28: ADJUSTMENT | E28: KSHS. | F28: =IF(F18*4%*1<0,0,F18*4%*1) -> 0 | N28: =O28-Q28 -> 10802 | O28: 10802
N29: =O29-Q29 -> 8930 | O29: 8930
D30: TOTAL PAYABLE | E30: Kshs. | F30: =SUM(F17:F29) -> 11420 | N30: =O30-Q30 -> 9570 | O30: 9570
N31: =O31-Q31 -> 11390 | O31: 11390
D32: PAID | F32: =meter!R31 -> 0 | N32: =O32-Q32 -> 10750 | O32: 10750
N33: =O33-Q33 -> 11732 | O33: 11732
D34: AMOUNT DUE | F34: =F30-F32 -> 11420 | N34: =O34-Q34 -> 10934 | O34: 10934 | R34: 700
C35: NOTE | N35: =O35-Q35 -> 10270 | O35: 10270
A36: a) | B36: Rent is due on or before 5th of the month. By 7th day, any rent not paid will attract interest at 2% per day. | N36: =O36-Q36 -> 10598 | O36: 10598
A37: b) | B37: Any default in Rent payment by 10th of the following month the house shall be locked without notice and belongings removed for re-letting. | N37: =O37-Q37 -> 8770 | O37: 8770
N38: =O38-Q38 -> 8770 | O38: 8770
A39: c) | B39: Amounts not cleared by last pay date will render to water disconnection. | O39: =SUM(O3:O38) -> 391268 | Q39: =SUM(Q3:Q38) -> 0
A41: d) | B41: A reconnection fee of Kshs. 1,000 will be charged and paid before supply is reconnected.
A42: e) | B42: ANY MINOR REPAIRS OCCURING AFTER 3 MONTHS OF OCCUPANCY ARE TENANT'S RESPONSIBILITY AS PER TENANCY AGREEMENT.
A43: f) | B43: The water bills are payable through the same account for monthly rent strictly through:
B44: Frebazeth Company Limited
B45: Consolidated Bank Account
B46: Kitengela Branch
B47: PAY BILL 4139271
B48: (Kindly indicate your Name & House number on the deposit slip & inform the Bank teller to capture it.)
B49: A receipt will be issued upon bank confirmation of the transaction. | O49: ……………
A50: g)
B51: ACC NO KT 29A
B52: E & O E
B53: NB: Kindly give the management atleast two (2) months prior notice incase you intend to terminate the tenancy for ease of logisitics.

Sheet hse30
B1: OLE SAMEDHA APARTMENTS-Kitengela
B2: ='hse1'!B3 -> P.O BOX 9473-00200 NAIROBI | N2: VAR | O2: TAX DUE
B3: WATER BILL | N3: =O3-Q3 -> 10270 | O3: 10270
H4: BILL NO. | I4: ='hse1'!H4+30-1 -> 20242030 | J4: ='hse1'!H4+30-1 -> 20242030 | N4: =O4-Q4 -> 10304 | O4: 10304
N5: =O5-Q5 -> 10988 | O5: 10988
B6: TENANT NAME | D6: =meter!A32 -> MARY MUTHONI | N6: =O6-Q6 -> 11070 | O6: 11070
N7: =O7-Q7 -> 1197 | O7: 1197
B8: HOUSE NUMBER: | D8: 30A | N8: =O8-Q8 -> 9250 | O8: 9250
N9: =O9-Q9 -> 8770 | O9: 8770
B10: ISSUE DATE | D10: ='hse1'!C10 -> 27/1/2026 | N10: =O10-Q10 -> 23190 | O10: 23190
N11: =O11-Q11 -> 10910 | O11: 10910
B12: LAST PAY DATE | D12: ='hse1'!C12 -> 46144 | N12: =O12-Q12 -> 10910 | O12: 10910
N13: =O13-Q13 -> 12190 | O13: 12190
N14: =O14-Q14 -> 11070 | O14: 11070
B15: PREVIOUS READING | D15: CURRENT READING | F15: CONSUMPTION | N15: =O15-Q15 -> 9090 | O15: 9090
B16: =meter!D32 -> 59 | D16: =meter!E32 -> 62 | E16: Units | F16: =D16-B16 -> 3 | N16: =O16-Q16 -> 9420 | O16: 9420
F17: Amount (Kshs.) | N17: =O17-Q17 -> 11154 | O17: 11154
D18: LAST ACCOUNT B/F | E18: Kshs. | F18: =meter!O32 -> 0 | N18: =O18-Q18 -> 10430 | O18: 10430
N19: =O19-Q19 -> 11831 | O19: 11831
D20: MONTH BILL | E20: KSHS. | F20: =meter!H32 -> 660 | N20: =O20-Q20 -> 10590 | O20: 10590
N21: =O21-Q21 -> 22423 | O21: 22423
D22: PUMP/POWER CHARGES | E22: KSHS. | F22: ='hse1'!E22 -> 110 | N22: =O22-Q22 -> 9250 | O22: 9250
N23: =O23-Q23 -> 10162 | O23: 10162
D24: MONTH HOUSE RENT | E24: KSHS. | F24: =meter!N32 -> 10000 | N24: =O24-Q24 -> 10270 | O24: 10270
N25: =O25-Q25 -> 11070 | O25: 11070
D26: ='hse1'!C26 -> security | E26: ='hse1'!D26 -> Kshs. | N26: =O26-Q26 -> 11550 | O26: 11550
D27: GARBAGE FEE | E27: Kshs. | F27: 150 | N27: =O27-Q27 -> 11393 | O27: 11393
D28: ADJUSTMENT-INTEREST ON ARREARS | E28: KSHS. | F28: =IF(F18*4%*1<0,0,F18*4%*1) -> 0 | N28: =O28-Q28 -> 10802 | O28: 10802
N29: =O29-Q29 -> 8930 | O29: 8930
D30: TOTAL PAYABLE | E30: Kshs. | F30: =SUM(F17:F29) -> 10920 | N30: =O30-Q30 -> 9570 | O30: 9570
N31: =O31-Q31 -> 11390 | O31: 11390
D32: PAID | F32: =meter!R32 -> 0 | N32: =O32-Q32 -> 10750 | O32: 10750
N33: =O33-Q33 -> 11732 | O33: 11732
D34: AMOUNT DUE | F34: =F30-F32 -> 10920 | N34: =O34-Q34 -> 10934 | O34: 10934 | R34: 700
C35: NOTE | N35: =O35-Q35 -> 10270 | O35: 10270
A36: a) | B36: Rent is due on or before 5th of the month. By 7th day, any rent not paid will attract interest at 2% per day. | N36: =O36-Q36 -> 10598 | O36: 10598
A37: b) | B37: Any default in Rent payment by 10th of the following month the house shall be locked without notice and belongings removed for re-letting. | N37: =O37-Q37 -> 8770 | O37: 8770
N38: =O38-Q38 -> 8770 | O38: 8770
A39: c) | B39: Amounts not cleared by last pay date will render to water disconnection. | O39: =SUM(O3:O38) -> 391268 | Q39: =SUM(Q3:Q38) -> 0
A41: d) | B41: A reconnection fee of Kshs. 1,000 will be charged and paid before supply is reconnected.
A42: e) | B42: ANY MINOR REPAIRS OCCURING AFTER 3 MONTHS OF OCCUPANCY ARE TENANT'S RESPONSIBILITY AS PER TENANCY AGREEMENT.
A43: f) | B43: The water bills are payable through the same account for monthly rent strictly through:
B44: Frebazeth Company Limited
B45: Consolidated Bank Account
B46: Kitengela Branch
B47: PAY BILL 4139271
B48: (Kindly indicate your Name & House number on the deposit slip & inform the Bank teller to capture it.)
B49: A receipt will be issued upon bank confirmation of the transaction. | O49: ……………
A50: g)
B51: ACC NO KT 30A
B52: E & O E
B53: NB: Kindly give the management atleast two (2) months prior notice incase you intend to terminate the tenancy for ease of logisitics.

Sheet hse31
B1: OLE SAMEDHA APARTMENTS-Kitengela
B2: ='hse1'!B3 -> P.O BOX 9473-00200 NAIROBI | N2: VAR | O2: TAX DUE
B3: WATER BILL | N3: =O3-Q3 -> 10270 | O3: 10270
H4: BILL NO. | I4: ='hse1'!H4+31-1 -> 20242031 | J4: ='hse1'!H4+31-1 -> 20242031 | N4: =O4-Q4 -> 10304 | O4: 10304
N5: =O5-Q5 -> 10988 | O5: 10988
B6: TENANT NAME | D6: ALICE | N6: =O6-Q6 -> 11070 | O6: 11070
N7: =O7-Q7 -> 1197 | O7: 1197
B8: HOUSE NUMBER: | D8: 31A | N8: =O8-Q8 -> 9250 | O8: 9250
N9: =O9-Q9 -> 8770 | O9: 8770
B10: ISSUE DATE | D10: ='hse1'!C10 -> 27/1/2026 | N10: =O10-Q10 -> 23190 | O10: 23190
N11: =O11-Q11 -> 10910 | O11: 10910
B12: LAST PAY DATE | D12: ='hse1'!C12 -> 46144 | N12: =O12-Q12 -> 10910 | O12: 10910
N13: =O13-Q13 -> 12190 | O13: 12190
N14: =O14-Q14 -> 11070 | O14: 11070
B15: PREVIOUS READING | D15: CURRENT READING | F15: CONSUMPTION | N15: =O15-Q15 -> 9090 | O15: 9090
B16: =meter!D33 -> 137 | D16: =meter!E33 -> 140 | E16: Units | F16: =D16-B16 -> 3 | N16: =O16-Q16 -> 9420 | O16: 9420
F17: Amount (Kshs.) | N17: =O17-Q17 -> 11154 | O17: 11154
D18: LAST ACCOUNT B/F | E18: Kshs. | F18: 0 | N18: =O18-Q18 -> 10430 | O18: 10430
N19: =O19-Q19 -> 11831 | O19: 11831
D20: MONTH BILL | E20: KSHS. | F20: =meter!H33 -> 660 | N20: =O20-Q20 -> 10590 | O20: 10590
N21: =O21-Q21 -> 22423 | O21: 22423
D22: PUMP/POWER CHARGES | E22: KSHS. | F22: ='hse1'!E22 -> 110 | N22: =O22-Q22 -> 9250 | O22: 9250
N23: =O23-Q23 -> 10162 | O23: 10162
D24: MONTH HOUSE RENT | E24: KSHS. | F24: 11000 | N24: =O24-Q24 -> 10270 | O24: 10270
N25: =O25-Q25 -> 11070 | O25: 11070
D26: ='hse1'!C26 -> security | E26: ='hse1'!D26 -> Kshs. | N26: =O26-Q26 -> 11550 | O26: 11550
D27: GARBAGE FEE | E27: Kshs. | F27: 150 | N27: =O27-Q27 -> 11393 | O27: 11393
D28: ADJUSTMENT-INTEREST ON ARREARS | E28: KSHS. | F28: =IF(F18*4%*1<0,0,F18*4%*1) -> 0 | N28: =O28-Q28 -> 10802 | O28: 10802
N29: =O29-Q29 -> 8930 | O29: 8930
D30: TOTAL PAYABLE | E30: Kshs. | F30: =SUM(F17:F29) -> 11920 | N30: =O30-Q30 -> 9570 | O30: 9570
N31: =O31-Q31 -> 11390 | O31: 11390
D32: PAID | F32: =meter!R33 -> 0 | N32: =O32-Q32 -> 10750 | O32: 10750
N33: =O33-Q33 -> 11732 | O33: 11732
D34: AMOUNT DUE | F34: =F30-F32 -> 11920 | N34: =O34-Q34 -> 10934 | O34: 10934 | R34: 700
C35: NOTE | N35: =O35-Q35 -> 10270 | O35: 10270
A36: a) | B36: Rent is due on or before 5th of the month. By 7th day, any rent not paid will attract interest at 2% per day. | N36: =O36-Q36 -> 10598 | O36: 10598
A37: b) | B37: Any default in Rent payment by 10th of the following month the house shall be locked without notice and belongings removed for re-letting. | N37: =O37-Q37 -> 8770 | O37: 8770
N38: =O38-Q38 -> 8770 | O38: 8770
A39: c) | B39: Amounts not cleared by last pay date will render to water disconnection. | O39: =SUM(O3:O38) -> 391268 | Q39: =SUM(Q3:Q38) -> 0
A41: d) | B41: A reconnection fee of Kshs. 1,000 will be charged and paid before supply is reconnected.
A42: e) | B42: ANY MINOR REPAIRS OCCURING AFTER 3 MONTHS OF OCCUPANCY ARE TENANT'S RESPONSIBILITY AS PER TENANCY AGREEMENT.
A43: f) | B43: The water bills are payable through the same account for monthly rent strictly through:
B44: Frebazeth Company Limited
B45: Consolidated Bank Account
B46: Kitengela Branch
B47: PAY BILL 4139271
B48: (Kindly indicate your Name & House number on the deposit slip & inform the Bank teller to capture it.)
B49: A receipt will be issued upon bank confirmation of the transaction. | O49: ……………
A50: g)
B51: ACC NO KT 31A
B52: E & O E
B53: NB: Kindly give the management atleast two (2) months prior notice incase you intend to terminate the tenancy for ease of logisitics.

Sheet hse32
A1: G | B1: OLE SAMEDHA APARTMENTS-Kitengela
B2: ='hse1'!B3 -> P.O BOX 9473-00200 NAIROBI | N2: VAR | O2: TAX DUE
B3: WATER BILL | N3: =O3-Q3 -> 10270 | O3: 10270
H4: BILL NO. | I4: ='hse1'!H4+32-1 -> 20242032 | J4: ='hse1'!H4+32-1 -> 20242032 | N4: =O4-Q4 -> 10304 | O4: 10304
N5: =O5-Q5 -> 10988 | O5: 10988
B6: TENANT NAME | D6: =meter!A34 -> MIKE MUTISYA | N6: =O6-Q6 -> 11070 | O6: 11070
B7: phone no | D7: o719702040 | N7: =O7-Q7 -> 1197 | O7: 1197
B8: HOUSE NUMBER: | D8: 32A | N8: =O8-Q8 -> 9250 | O8: 9250
N9: =O9-Q9 -> 8770 | O9: 8770
B10: ISSUE DATE | D10: ='hse1'!C10 -> 27/1/2026 | N10: =O10-Q10 -> 23190 | O10: 23190
N11: =O11-Q11 -> 10910 | O11: 10910
B12: LAST PAY DATE | D12: ='hse1'!C12 -> 46144 | N12: =O12-Q12 -> 10910 | O12: 10910
N13: =O13-Q13 -> 12190 | O13: 12190
N14: =O14-Q14 -> 11070 | O14: 11070
B15: PREVIOUS READING | D15: CURRENT READING | F15: CONSUMPTION | N15: =O15-Q15 -> 9090 | O15: 9090
B16: =meter!D34 -> 582 | D16: =meter!E34 -> 588 | E16: Units | F16: =D16-B16 -> 6 | N16: =O16-Q16 -> 9420 | O16: 9420
F17: Amount (Kshs.) | N17: =O17-Q17 -> 11154 | O17: 11154
D18: LAST ACCOUNT B/F | E18: Kshs. | F18: =meter!O33 -> 1750 | N18: =O18-Q18 -> 10430 | O18: 10430
N19: =O19-Q19 -> 11831 | O19: 11831
D20: MONTH BILL | E20: KSHS. | F20: =meter!H34 -> 1320 | N20: =O20-Q20 -> 10590 | O20: 10590
N21: =O21-Q21 -> 22423 | O21: 22423
D22: PUMP/POWER CHARGES | E22: KSHS. | F22: ='hse1'!E22 -> 110 | N22: =O22-Q22 -> 9250 | O22: 9250
N23: =O23-Q23 -> 10162 | O23: 10162
D24: MONTH HOUSE RENT | E24: KSHS. | F24: =meter!N34 -> 10000 | N24: =O24-Q24 -> 10270 | O24: 10270
N25: =O25-Q25 -> 11070 | O25: 11070
N26: =O26-Q26 -> 11550 | O26: 11550
D27: GARBAGE FEE | E27: Kshs. | F27: 150 | N27: =O27-Q27 -> 11393 | O27: 11393
D28: INTEREST LATE PAYMENT | E28: KSHS. | F28: =IF(F18*4%*1<0,0,F18*4%*1) -> 70 | N28: =O28-Q28 -> 10802 | O28: 10802
N29: =O29-Q29 -> 8930 | O29: 8930
D30: TOTAL PAYABLE | E30: Kshs. | F30: =SUM(F17:F29) -> 13400 | N30: =O30-Q30 -> 9570 | O30: 9570
N31: =O31-Q31 -> 11390 | O31: 11390
D32: PAID | F32: =meter!R34 -> 0 | N32: =O32-Q32 -> 10750 | O32: 10750
N33: =O33-Q33 -> 11732 | O33: 11732
D34: AMOUNT DUE | F34: =F30-F32 -> 13400 | N34: =O34-Q34 -> 10934 | O34: 10934 | R34: 700
C35: NOTE | N35: =O35-Q35 -> 10270 | O35: 10270
A36: a) | B36: Rent is due on or before 5th of the month. By 7th day, any rent not paid will attract interest at 2% per day. | N36: =O36-Q36 -> 10598 | O36: 10598
A37: b) | B37: Any default in Rent payment by 10th of the following month the house shall be locked without notice and belongings removed for re-letting. | N37: =O37-Q37 -> 8770 | O37: 8770
N38: =O38-Q38 -> 8770 | O38: 8770
A39: c) | B39: Amounts not cleared by last pay date will render to water disconnection. | O39: =SUM(O3:O38) -> 391268 | Q39: =SUM(Q3:Q38) -> 0
A41: d) | B41: A reconnection fee of Kshs. 1,000 will be charged and paid before supply is reconnected.
A42: e) | B42: ANY MINOR REPAIRS OCCURING AFTER 3 MONTHS OF OCCUPANCY ARE TENANT'S RESPONSIBILITY AS PER TENANCY AGREEMENT.
A43: f) | B43: The water bills are payable through the same account for monthly rent strictly through:
B44: Frebazeth Company Limited
B45: Consolidated Bank Account
B46: Kitengela Branch
B47: PAY BILL 4139271
B48: (Kindly indicate your Name & House number on the deposit slip & inform the Bank teller to capture it.)
B49: A receipt will be issued upon bank confirmation of the transaction. | O49: ……………
B51: ACC NO KT 32A
B52: E & O E
B53: NB: Kindly give the management atleast two (2) months prior notice incase you intend to terminate the tenancy for ease of logisitics.

Sheet hse33
B1: OLE SAMEDHA APARTMENTS-Kitengela
B2: ='hse1'!B3 -> P.O BOX 9473-00200 NAIROBI | N2: VAR | O2: TAX DUE
B3: WATER BILL | N3: =O3-Q3 -> 10270 | O3: 10270
H4: BILL NO. | I4: ='hse1'!H4+33-1 -> 20242033 | J4: ='hse1'!H4+33-1 -> 20242033 | N4: =O4-Q4 -> 10304 | O4: 10304
N5: =O5-Q5 -> 10988 | O5: 10988
B6: TENANT NAME | D6: =meter!A35 -> NAOMI | N6: =O6-Q6 -> 11070 | O6: 11070
B7: phone no | D7: o704630666 | N7: =O7-Q7 -> 1197 | O7: 1197
B8: HOUSE NUMBER: | D8: 33A | N8: =O8-Q8 -> 9250 | O8: 9250
N9: =O9-Q9 -> 8770 | O9: 8770
B10: ISSUE DATE | D10: ='hse1'!C10 -> 27/1/2026 | N10: =O10-Q10 -> 23190 | O10: 23190
N11: =O11-Q11 -> 10910 | O11: 10910
B12: LAST PAY DATE | D12: ='hse1'!C12 -> 46144 | N12: =O12-Q12 -> 10910 | O12: 10910
N13: =O13-Q13 -> 12190 | O13: 12190
N14: =O14-Q14 -> 11070 | O14: 11070
B15: PREVIOUS READING | D15: CURRENT READING | F15: CONSUMPTION | N15: =O15-Q15 -> 9090 | O15: 9090
B16: =meter!D35 -> 51 | D16: =meter!E35 -> 55 | E16: Units | F16: =D16-B16 -> 4 | N16: =O16-Q16 -> 9420 | O16: 9420
F17: Amount (Kshs.) | N17: =O17-Q17 -> 11154 | O17: 11154
D18: LAST ACCOUNT B/F | E18: Kshs. | F18: =meter!O35 -> 677 | N18: =O18-Q18 -> 10430 | O18: 10430
N19: =O19-Q19 -> 11831 | O19: 11831
D20: MONTH BILL | E20: KSHS. | F20: =meter!H35 -> 880 | N20: =O20-Q20 -> 10590 | O20: 10590
N21: =O21-Q21 -> 22423 | O21: 22423
D22: PUMP/POWER CHARGES | E22: KSHS. | F22: ='hse1'!E22 -> 110 | N22: =O22-Q22 -> 9250 | O22: 9250
N23: =O23-Q23 -> 10162 | O23: 10162
D24: MONTH HOUSE RENT | E24: KSHS. | F24: 12000 | N24: =O24-Q24 -> 10270 | O24: 10270
N25: =O25-Q25 -> 11070 | O25: 11070
N26: =O26-Q26 -> 11550 | O26: 11550
D27: GARBAGE FEE | E27: Kshs. | F27: 150 | N27: =O27-Q27 -> 11393 | O27: 11393
D28: ADJUSTMENT | E28: KSHS. | F28: =IF(F18*4%*1<0,0,F18*4%*1) -> 27.08 | N28: =O28-Q28 -> 10802 | O28: 10802
N29: =O29-Q29 -> 8930 | O29: 8930
D30: TOTAL PAYABLE | E30: Kshs. | F30: =SUM(F17:F29) -> 13844.08 | N30: =O30-Q30 -> 9570 | O30: 9570
N31: =O31-Q31 -> 11390 | O31: 11390
D32: PAID | F32: 0 | N32: =O32-Q32 -> 10750 | O32: 10750
N33: =O33-Q33 -> 11732 | O33: 11732
D34: AMOUNT DUE | F34: =F30-F32 -> 13844.08 | N34: =O34-Q34 -> 10934 | O34: 10934 | R34: 700
C35: NOTE | N35: =O35-Q35 -> 10270 | O35: 10270
A36: a) | B36: Rent is due on or before 5th of the month. By 7th day, any rent not paid will attract interest at 2% per day. | N36: =O36-Q36 -> 10598 | O36: 10598
A37: b) | B37: Any default in Rent payment by 10th of the following month the house shall be locked without notice and belongings removed for re-letting. | N37: =O37-Q37 -> 8770 | O37: 8770
N38: =O38-Q38 -> 8770 | O38: 8770
A39: c) | B39: Amounts not cleared by last pay date will render to water disconnection. | O39: =SUM(O3:O38) -> 391268 | Q39: =SUM(Q3:Q38) -> 0
A41: d) | B41: A reconnection fee of Kshs. 1,000 will be charged and paid before supply is reconnected.
A42: e) | B42: ANY MINOR REPAIRS OCCURING AFTER 3 MONTHS OF OCCUPANCY ARE TENANT'S RESPONSIBILITY AS PER TENANCY AGREEMENT.
A43: f) | B43: The water bills are payable through the same account for monthly rent strictly through:
B44: Frebazeth Company Limited
B45: Consolidated Bank Account
B46: Kitengela Branch
C47: PAY BILL 4139271
C48: (Kindly indicate your Name & House number on the deposit slip & inform the Bank teller to capture it.)
C49: A receipt will be issued upon bank confirmation of the transaction. | O49: ……………
A50: g)
C51: ACC NO KT 33A
C52: E & O E
C53: NB: Kindly give the management atleast two (2) months prior notice incase you intend to terminate the tenancy for ease of logisitics.

Sheet hse34B
B1: OLE SAMEDHA APARTMENTS-Kitengela
B2: ='hse1'!B3 -> P.O BOX 9473-00200 NAIROBI | N2: VAR | O2: TAX DUE
B3: WATER BILL | N3: =O3-Q3 -> 10270 | O3: 10270
H4: BILL NO. | I4: ='hse1'!H4+34-1 -> 20242034 | J4: ='hse1'!H4+34-1 -> 20242034 | N4: =O4-Q4 -> 10304 | O4: 10304
N5: =O5-Q5 -> 10988 | O5: 10988
B6: TENANT NAME | D6: =meter!A36 -> SAM | N6: =O6-Q6 -> 11070 | O6: 11070
N7: =O7-Q7 -> 1197 | O7: 1197
B8: HOUSE NUMBER: | D8: 34B | N8: =O8-Q8 -> 9250 | O8: 9250
B9: phone no | D9: o796411721 | N9: =O9-Q9 -> 8770 | O9: 8770
B10: ISSUE DATE | D10: ='hse1'!C10 -> 27/1/2026 | N10: =O10-Q10 -> 23190 | O10: 23190
N11: =O11-Q11 -> 10910 | O11: 10910
B12: LAST PAY DATE | D12: ='hse1'!C12 -> 46144 | N12: =O12-Q12 -> 10910 | O12: 10910
N13: =O13-Q13 -> 12190 | O13: 12190
N14: =O14-Q14 -> 11070 | O14: 11070
B15: PREVIOUS READING | D15: CURRENT READING | F15: CONSUMPTION | N15: =O15-Q15 -> 9090 | O15: 9090
B16: =meter!D36 -> 37 | D16: =meter!E36 -> 40 | E16: Units | F16: =D16-B16 -> 3 | N16: =O16-Q16 -> 9420 | O16: 9420
F17: Amount (Kshs.) | N17: =O17-Q17 -> 11154 | O17: 11154
D18: LAST ACCOUNT B/F | E18: Kshs. | F18: =meter!O36 -> 0 | N18: =O18-Q18 -> 10430 | O18: 10430
N19: =O19-Q19 -> 11831 | O19: 11831
D20: MONTH BILL | E20: KSHS. | F20: =meter!H36 -> 660 | N20: =O20-Q20 -> 10590 | O20: 10590
N21: =O21-Q21 -> 22423 | O21: 22423
D22: PUMP/POWER CHARGES | E22: KSHS. | F22: ='hse1'!E22 -> 110 | N22: =O22-Q22 -> 9250 | O22: 9250
N23: =O23-Q23 -> 10162 | O23: 10162
D24: MONTH HOUSE RENT | E24: KSHS. | F24: =meter!N36 -> 9000 | N24: =O24-Q24 -> 10270 | O24: 10270
N25: =O25-Q25 -> 11070 | O25: 11070
N26: =O26-Q26 -> 11550 | O26: 11550
D27: GARBAGE FEE | E27: Kshs. | F27: 150 | N27: =O27-Q27 -> 11393 | O27: 11393
D28: INTEREST ON ARREARS | E28: KSHS. | F28: =IF(F18*4%*1<0,0,F18*4%*1) -> 0 | N28: =O28-Q28 -> 10802 | O28: 10802
N29: =O29-Q29 -> 8930 | O29: 8930
D30: TOTAL PAYABLE | E30: Kshs. | F30: =SUM(F17:F29) -> 9920 | N30: =O30-Q30 -> 9570 | O30: 9570
N31: =O31-Q31 -> 11390 | O31: 11390
D32: PAID | F32: =meter!R36 -> 0 | N32: =O32-Q32 -> 10750 | O32: 10750
N33: =O33-Q33 -> 11732 | O33: 11732
D34: AMOUNT DUE | F34: =F30-F32 -> 9920 | N34: =O34-Q34 -> 10934 | O34: 10934 | R34: 700
C35: NOTE | N35: =O35-Q35 -> 10270 | O35: 10270
A36: a) | B36: Rent is due on or before 5th of the month. By 7th day, any rent not paid will attract interest at 2% per day. | N36: =O36-Q36 -> 10598 | O36: 10598
A37: b) | B37: Any default in Rent payment by 10th of the following month the house shall be locked without notice and belongings removed for re-letting. | N37: =O37-Q37 -> 8770 | O37: 8770
N38: =O38-Q38 -> 8770 | O38: 8770
A39: c) | B39: Amounts not cleared by last pay date will render to water disconnection. | O39: =SUM(O3:O38) -> 391268 | Q39: =SUM(Q3:Q38) -> 0
A41: d) | B41: A reconnection fee of Kshs. 1,000 will be charged and paid before supply is reconnected.
A42: e) | B42: ANY MINOR REPAIRS OCCURING AFTER 3 MONTHS OF OCCUPANCY ARE TENANT'S RESPONSIBILITY AS PER TENANCY AGREEMENT.
A43: f) | B43: The water bills are payable through the same account for monthly rent strictly through:
B44: Frebazeth Company Limited
B45: Consolidated Bank Account
B46: Kitengela Branch
B47: PAY BILL 4139271
B48: (Kindly indicate your Name & House number on the deposit slip & inform the Bank teller to capture it.)
B49: A receipt will be issued upon bank confirmation of the transaction. | O49: ……………
A50: g)
B51: ACC NO KT 34B
B52: E & O E
B53: NB: Kindly give the management atleast two (2) months prior notice incase you intend to terminate the tenancy for ease of logisitics.

Sheet hse35B
B1: OLE SAMEDHA APARTMENTS-Kitengela
B2: ='hse1'!B3 -> P.O BOX 9473-00200 NAIROBI | N2: VAR | O2: TAX DUE
B3: WATER BILL | N3: =O3-Q3 -> 10270 | O3: 10270
H4: BILL NO. | I4: ='hse1'!H4+35-1 -> 20242035 | J4: ='hse1'!H4+35-1 -> 20242035 | N4: =O4-Q4 -> 10304 | O4: 10304
N5: =O5-Q5 -> 10988 | O5: 10988
B6: TENANT NAME | D6: =meter!A37 -> TIMOTHY | N6: =O6-Q6 -> 11070 | O6: 11070
B7: phone no | D7: o721725518 | N7: =O7-Q7 -> 1197 | O7: 1197
B8: HOUSE NUMBER: | D8: 35B | N8: =O8-Q8 -> 9250 | O8: 9250
N9: =O9-Q9 -> 8770 | O9: 8770
B10: ISSUE DATE | D10: ='hse1'!C10 -> 27/1/2026 | N10: =O10-Q10 -> 23190 | O10: 23190
N11: =O11-Q11 -> 10910 | O11: 10910
B12: LAST PAY DATE | D12: ='hse1'!C12 -> 46144 | N12: =O12-Q12 -> 10910 | O12: 10910
N13: =O13-Q13 -> 12190 | O13: 12190
N14: =O14-Q14 -> 11070 | O14: 11070
B15: PREVIOUS READING | D15: CURRENT READING | F15: CONSUMPTION | N15: =O15-Q15 -> 9090 | O15: 9090
B16: =meter!D37 -> 182 | D16: =meter!E37 -> 184 | E16: Units | F16: =D16-B16 -> 2 | H16: ESTIMATE | N16: =O16-Q16 -> 9420 | O16: 9420
F17: Amount (Kshs.) | N17: =O17-Q17 -> 11154 | O17: 11154
D18: LAST ACCOUNT B/F | E18: Kshs. | F18: =meter!O37 -> 677 | N18: =O18-Q18 -> 10430 | O18: 10430
N19: =O19-Q19 -> 11831 | O19: 11831
D20: MONTH BILL | E20: KSHS. | F20: =meter!H37 -> 440 | N20: =O20-Q20 -> 10590 | O20: 10590
N21: =O21-Q21 -> 22423 | O21: 22423
D22: PUMP/POWER CHARGES | E22: KSHS. | F22: ='hse1'!E22 -> 110 | N22: =O22-Q22 -> 9250 | O22: 9250
N23: =O23-Q23 -> 10162 | O23: 10162
D24: MONTH HOUSE RENT | E24: KSHS. | F24: 8500 | N24: =O24-Q24 -> 10270 | O24: 10270
N25: =O25-Q25 -> 11070 | O25: 11070
N26: =O26-Q26 -> 11550 | O26: 11550
D27: GARBAGE FEE | E27: Kshs. | F27: 150 | N27: =O27-Q27 -> 11393 | O27: 11393
D28: ADJUSTMENT | E28: KSHS. | F28: =IF(F18*4%*1<0,0,F18*4%*1) -> 27.08 | N28: =O28-Q28 -> 10802 | O28: 10802
N29: =O29-Q29 -> 8930 | O29: 8930
D30: TOTAL PAYABLE | E30: Kshs. | F30: =SUM(F17:F29) -> 9904.08 | N30: =O30-Q30 -> 9570 | O30: 9570
N31: =O31-Q31 -> 11390 | O31: 11390
D32: PAID | F32: =meter!R37 -> 0 | N32: =O32-Q32 -> 10750 | O32: 10750
N33: =O33-Q33 -> 11732 | O33: 11732
D34: AMOUNT DUE | F34: =F30-F32 -> 9904.08 | N34: =O34-Q34 -> 10934 | O34: 10934 | R34: 700
C35: NOTE | N35: =O35-Q35 -> 10270 | O35: 10270
A36: a) | B36: Rent is due on or before 5th of the month. By 7th day, any rent not paid will attract interest at 2% per day. | N36: =O36-Q36 -> 10598 | O36: 10598
A37: b) | B37: Any default in Rent payment by 10th of the following month the house shall be locked without notice and belongings removed for re-letting. | N37: =O37-Q37 -> 8770 | O37: 8770
N38: =O38-Q38 -> 8770 | O38: 8770
A39: c) | B39: Amounts not cleared by last pay date will render to water disconnection. | O39: =SUM(O3:O38) -> 391268 | Q39: =SUM(Q3:Q38) -> 0
A41: d) | B41: A reconnection fee of Kshs. 1,000 will be charged and paid before supply is reconnected.
A42: e) | B42: ANY MINOR REPAIRS OCCURING AFTER 3 MONTHS OF OCCUPANCY ARE TENANT'S RESPONSIBILITY AS PER TENANCY AGREEMENT.
A43: f) | B43: The water bills are payable through the same account for monthly rent strictly through:
B44: Frebazeth Company Limited
B45: Consolidated Bank Account
B46: Kitengela Branch
B47: PAY BILL 4139271
B48: (Kindly indicate your Name & House number on the deposit slip & inform the Bank teller to capture it.)
B49: A receipt will be issued upon bank confirmation of the transaction. | O49: ……………
A50: g)
B51: ACC NO KT 35B
B52: E & O E
B53: NB: Kindly give the management atleast two (2) months prior notice incase you intend to terminate the tenancy for ease of logisitics.

Sheet 36B.
B1: OLE SAMEDHA APARTMENTS-Kitengela
B2: ='hse1'!B3 -> P.O BOX 9473-00200 NAIROBI
B3: WATER BILL
H4: BILL NO. | I4: ='hse1'!H4+37-1 -> 20242037
B6: TENANT NAME | D6: =meter!A38 -> SAMWEL MUGO
B7: phone no | D7: o720304145
B8: HOUSE NUMBER: | D8: 36B
B10: ISSUE DATE | D10: ='hse1'!C10 -> 27/1/2026
B12: LAST PAY DATE | D12: ='hse1'!C12 -> 46144
B15: PREVIOUS READING | D15: CURRENT READING | F15: CONSUMPTION
B16: =meter!D38 -> 154 | D16: =meter!E38 -> 154 | E16: Units | F16: =D16-B16 -> 0
F17: Amount (Kshs.)
D18: LAST ACCOUNT B/F | E18: Kshs.
D20: MONTH BILL | E20: KSHS. | F20: =meter!H38 -> 0
D22: PUMP/POWER CHARGES | E22: KSHS. | F22: ='hse1'!E22 -> 110
D24: MONTH HOUSE RENT | E24: KSHS. | F24: =meter!N38 -> 9000
D27: GARBAGE FEE | E27: Kshs. | F27: 150
D28: INTEREST LATE PAYMENT | E28: KSHS. | F28: =IF(F18*4%*1<0,0,F18*4%*1) -> 0
D30: TOTAL PAYABLE | E30: Kshs. | F30: =SUM(F17:F29) -> 9260
D32: PAID | F32: =meter!R37 -> 0
D34: AMOUNT DUE | F34: =F30-F32 -> 9260
C35: NOTE
A36: a) | B36: Rent is due on or before 5th of the month. By 7th day, any rent not paid will attract interest at 2% per day.
A37: b) | B37: Any default in Rent payment by 10th of the following month the house shall be locked without notice and belongings removed for re-letting.
A39: c) | B39: Amounts not cleared by last pay date will render to water disconnection. | Q39: =SUM(Q3:Q38) -> 0
A41: d) | B41: A reconnection fee of Kshs. 1,000 will be charged and paid before supply is reconnected.
A42: e) | B42: ANY MINOR REPAIRS OCCURING AFTER 3 MONTHS OF OCCUPANCY ARE TENANT'S RESPONSIBILITY AS PER TENANCY AGREEMENT.
A43: f) | B43: The water bills are payable through the same account for monthly rent strictly through:
B44: Frebazeth Company Limited
B45: Consolidated Bank Account
B46: Kitengela Branch
B47: PAY BILL 4139271
B48: (Kindly indicate your Name & House number on the deposit slip & inform the Bank teller to capture it.)
B49: A receipt will be issued upon bank confirmation of the transaction. | O49: ……………
A50: g)
B51: ACC NO KT 36A
B53: NB: Kindly give the management atleast two (2) months prior notice incase you intend to terminate the tenancy for ease of logisitics.

Sheet meter
A2: NAMES | B2: HOUSE | C2: PERIOD | D2: PREVIOUS | E2: CURRENT | F2: READING | G2: RATE | H2: cost @160/= | I2: cost @200/= | J2: Fixed Charge | K2: Total H2O Bill | L2: GARBAGE FEE | N2: RENT | O2: BAL B/F | P2: INTEREST & PENALTY | Q2: TOTAL | R2: PAID | S2: BAL C/F | T2: EARLY DISCOUNT 3% | U2: REMARKS | V2: Hse No.
A3: MAUREEN | B3: 1A | C3: 46054 | D3: 32 | E3: 33 | F3: =E3-D3 -> 1 | G3: 220 | H3: =F3*G3 -> 220 | I3: 1200 | J3: 110 | K3: =H3+J3 -> 330 | L3: 150 | M3: 0 | N3: =9500+500 -> 10000 | O3: 1000 | P3: ='hse1'!E28 -> 0 | Q3: =K3+L3+M3+N3+O3+P3 -> 11480 | R3: 0 | S3: =Q3-R3 -> 11480 | V3: 1 | W3: 10700
A4: GODFREY IRONGO | B4: 2A | C4: =SUM(C3) -> 46054 | D4: 229 | E4: 232 | F4: =E4-D4 -> 3 | G4: 220 | H4: =F4*G4 -> 660 | I4: 1200 | J4: 110 | K4: =H4+J4 -> 770 | L4: 150 | M4: 0 | N4: =9500+500 -> 10000 | O4: 0 | P4: ='hse1'!E29 -> 0 | Q4: =K4+L4+M4+N4+O4+P4 -> 10920 | R4: 0 | S4: =Q4-R4 -> 10920 | V4: 2 | W4: 11800 | X4: =W4-Q4 -> 880
A5: STACY | B5: 3A | C5: =SUM(C4) -> 46054 | D5: 845 | E5: 847 | F5: =E5-D5 -> 2 | G5: 220 | H5: =F5*G5 -> 440 | I5: 600 | J5: 110 | K5: =H5+J5 -> 550 | L5: 150 | M5: 0 | N5: =10000+500 -> 10500 | O5: 2450 | Q5: =K5+L5+M5+N5+O5+P5 -> 13650 | R5: 0 | S5: =Q5-R5 -> 13650 | V5: 3 | W5: 11640 | X5: =W5-Q5 -> -2010
A6: MARY | B6: 4A | C6: =SUM(C5) -> 46054 | D6: 721 | E6: 724 | F6: =E6-D6 -> 3 | G6: 220 | H6: =F6*G6 -> 660 | I6: 400 | J6: 110 | K6: =H6+J6 -> 770 | L6: 150 | M6: 0 | N6: =9500+500 -> 10000 | O6: 5250 | P6: ='hse1'!E31 -> 0 | Q6: =K6+L6+M6+N6+O6+P6 -> 16170 | R6: 0 | S6: =Q6-R6 -> 16170 | V6: 4 | W6: 10700 | X6: =W6-Q6 -> -5470
A7: GEOFFREY | B7: 5A | C7: =SUM(C6) -> 46054 | D7: 125 | E7: 126 | F7: =E7-D7 -> 1 | G7: 220 | H7: 0 | I7: 1600 | J7: 110 | K7: =H7+J7 -> 110 | L7: 150 | M7: 0 | N7: 500 | P7: ='hse1'!E32 -> 0 | Q7: =K7+L7+M7+N7+O7+P7 -> 760 | R7: 0 | S7: =Q7-R7 -> 760 | V7: 5 | W7: 2300 | X7: =W7-Q7 -> 1540
A8: EVERLINE | B8: 6B | C8: =SUM(C7) -> 46054 | D8: 450 | E8: 450 | F8: =E8-D8 -> 0 | G8: 220 | H8: =F8*G8 -> 0 | I8: 400 | J8: 110 | K8: =H8+J8 -> 110 | L8: 150 | M8: 0 | N8: =8000+500 -> 8500 | P8: ='hse1'!E33 -> 0 | Q8: =K8+L8+M8+N8+O8+P8 -> 8760 | R8: 0 | S8: =Q8-R8 -> 8760 | V8: 6 | W8: 9420 | X8: =W8-Q8 -> 660
A9: AVRIL | B9: 7B | C9: =SUM(C8) -> 46054 | D9: 630 | E9: 630 | F9: =E9-D9 -> 0 | G9: 220 | H9: =F9*G9 -> 0 | I9: 200 | J9: 110 | K9: =H9+J9 -> 110 | L9: 150 | M9: 0 | N9: =8500+500 -> 9000 | O9: 2830 | Q9: =K9+L9+M9+N9+O9+P9 -> 12090 | R9: 0 | S9: =Q9-R9 -> 12090 | V9: 7 | W9: 9920 | X9: =W9-Q9 -> -2170
A10: JAMES | B10: 8A | C10: =SUM(C9) -> 46054 | D10: 48 | E10: 53 | F10: =E10-D10 -> 5 | G10: 220 | H10: =F10*G10 -> 1100 | I10: 1200 | J10: 110 | K10: =H10+J10 -> 1210 | L10: 150 | M10: 0 | N10: =10000+500 -> 10500 | P10: ='hse1'!E35 -> 0 | Q10: =K10+L10+M10+N10+O10+P10 -> 11860 | R10: 0 | S10: =Q10-R10 -> 11860 | V10: 8 | W10: 11860 | X10: =W10-Q10 -> 0
A11: CHERRYL | B11: 9A | C11: =SUM(C10) -> 46054 | D11: 193 | E11: 196 | F11: =E11-D11 -> 3 | G11: 220 | H11: =F11*G11 -> 660 | I11: 600 | J11: 110 | K11: =H11+J11 -> 770 | L11: 150 | M11: 0 | N11: =10000+500 -> 10500 | P11: ='hse1'!E36 -> 0 | Q11: =K11+L11+M11+N11+O11+P11 -> 11420 | R11: 0 | S11: =Q11-R11 -> 11420 | V11: 9 | W11: 11640 | X11: =W11-Q11 -> 220
A12: JACK | B12: 10A | C12: =SUM(C11) -> 46054 | D12: 66 | E12: 70 | F12: =E12-D12 -> 4 | G12: 220 | H12: =F12*G12 -> 880 | I12: 1800 | J12: 110 | K12: =H12+J12 -> 990 | L12: 150 | M12: 0 | N12: =10000+500 -> 10500 | P12: ='hse1'!E37 -> 0 | Q12: =K12+L12+M12+N12+O12+P12 -> 11640 | R12: 0 | S12: =Q12-R12 -> 11640 | V12: 10 | W12: 11860 | X12: =W12-Q12 -> 220
A13: JAMES NGUGI | B13: 11A | C13: =SUM(C12) -> 46054 | D13: 413 | E13: 415 | F13: =E13-D13 -> 2 | G13: 220 | H13: =F13*G13 -> 440 | I13: 1000 | J13: 110 | K13: =H13+J13 -> 550 | L13: 150 | M13: 0 | N13: =9500+500 -> 10000 | P13: ='hse1'!E38 -> 0 | Q13: =K13+L13+M13+N13+O13+P13 -> 10700 | R13: 0 | S13: =Q13-R13 -> 10700 | V13: 11 | W13: 11360 | X13: =W13-Q13 -> 660
A14: LIMO | B14: 12A | C14: =SUM(C13) -> 46054 | D14: 212 | E14: 224 | F14: =E14-D14 -> 12 | G14: 220 | H14: =F14*G14 -> 2640 | I14: 400 | J14: 110 | K14: =H14+J14 -> 2750 | L14: 150 | M14: 0 | N14: =10000+500 -> 10500 | O14: 677 | P14: ='hse1'!E39 -> 0 | Q14: =K14+L14+M14+N14+O14+P14 -> 14077 | R14: 0 | S14: =Q14-R14 -> 14077 | V14: 12 | W14: 12740 | X14: =W14-Q14 -> -1337
A15: HARRIET | B15: 13B | C15: =SUM(C14) -> 46054 | D15: 158 | E15: 159 | F15: =E15-D15 -> 1 | G15: 220 | H15: =F15*G15 -> 220 | I15: 800 | J15: 110 | K15: =H15+J15 -> 330 | L15: 150 | M15: 0 | N15: =8000+500 -> 8500 | P15: ='hse1'!E40 -> 0 | Q15: =K15+L15+M15+N15+O15+P15 -> 8980 | R15: 0 | S15: =Q15-R15 -> 8980 | V15: 13 | W15: 9200 | X15: =W15-Q15 -> 220
A16: VALARY | B16: 14B | C16: =SUM(C15) -> 46054 | D16: 714 | E16: 716 | F16: =E16-D16 -> 2 | G16: 220 | H16: =F16*G16 -> 440 | I16: 1600 | J16: 110 | K16: =H16+J16 -> 550 | L16: 150 | M16: 0 | N16: =8500+500 -> 9000 | O16: 820 | P16: ='hse1'!E41 -> 0 | Q16: =K16+L16+M16+N16+O16+P16 -> 10520 | R16: 0 | S16: =Q16-R16 -> 10520 | V16: 14 | W16: 11680 | X16: =W16-Q16 -> 1160
A17: ASHA | B17: 15A | C17: =SUM(C16) -> 46054 | D17: 195 | E17: 200 | F17: =E17-D17 -> 5 | G17: 220 | H17: =F17*G17 -> 1100 | I17: 600 | J17: 110 | K17: =H17+J17 -> 1210 | L17: 150 | M17: 0 | N17: =10000+500 -> 10500 | O17: 677 | P17: ='hse1'!E42 -> 0 | Q17: =K17+L17+M17+N17+O17+P17 -> 12537 | R17: 0 | S17: =Q17-R17 -> 12537 | V17: 15 | W17: 11640 | X17: =W17-Q17 -> -897
A18: VACCANT | B18: 16A | C18: =SUM(C17) -> 46054 | D18: 190 | E18: 190 | F18: =E18-D18 -> 0 | G18: 220 | H18: =F18*G18 -> 0 | I18: 400 | J18: 110 | K18: =H18+J18 -> 110 | L18: 150 | M18: 0 | N18: =10000+500 -> 10500 | O18: 677 | P18: ='hse1'!E43 -> 0 | Q18: =K18+L18+M18+N18+O18+P18 -> 11437 | R18: 0 | S18: =Q18-R18 -> 11437 | V18: 16 | W18: 11200 | X18: =W18-Q18 -> -237
A19: JOASH | B19: 17A | C19: =SUM(C18) -> 46054 | D19: 484 | E19: 487 | F19: =E19-D19 -> 3 | G19: 220 | H19: =F19*G19 -> 660 | I19: 800 | J19: 110 | K19: =H19+J19 -> 770 | L19: 150 | M19: 0 | N19: =10000+500 -> 10500 | O19: 1000 | P19: ='hse1'!E44 -> 0 | Q19: =K19+L19+M19+N19+O19+P19 -> 12420 | R19: 0 | S19: =Q19-R19 -> 12420 | V19: 17 | W19: 11860 | X19: =W19-Q19 -> -560
A20: MOSES NJUGUNA | B20: 18A | C20: =SUM(C19) -> 46054 | D20: 210 | E20: 213 | F20: =E20-D20 -> 3 | G20: 220 | H20: =F20*G20 -> 660 | I20: 600 | J20: 110 | K20: =H20+J20 -> 770 | L20: 150 | M20: 0 | N20: =10000+500 -> 10500 | O20: 1750 | P20: ='hse1'!E45 -> 0 | Q20: =K20+L20+M20+N20+O20+P20 -> 13170 | R20: 0 | S20: =Q20-R20 -> 13170 | V20: 18 | W20: 11420 | X20: =W20-Q20 -> -1750
A21: DAGLOUS | B21: 19A | C21: =SUM(C20) -> 46054 | D21: 55 | E21: 59 | F21: =E21-D21 -> 4 | G21: 220 | H21: =F21*G21 -> 880 | I21: 800 | J21: 110 | K21: =H21+J21 -> 990 | L21: 150 | M21: 0 | N21: =10000+500 -> 10500 | O21: 548 | P21: ='hse1'!E46 -> 0 | Q21: =K21+L21+M21+N21+O21+P21 -> 12188 | R21: 0 | S21: =Q21-R21 -> 12188 | V21: 19 | W21: 11640 | X21: =W21-Q21 -> -548
A22: OWEN | B22: 20B | C22: =SUM(C21) -> 46054 | D22: 265 | E22: 267 | F22: =E22-D22 -> 2 | G22: 220 | H22: =F22*G22 -> 440 | I22: 400 | J22: 110 | K22: =H22+J22 -> 550 | L22: 150 | M22: 0 | N22: =8500+500 -> 9000 | P22: ='hse1'!E47 -> 0 | Q22: =K22+L22+M22+N22+O22+P22 -> 9700 | R22: 0 | S22: =Q22-R22 -> 9700 | V22: 20 | W22: 9480 | X22: =W22-Q22 -> -220
A23: MAGRET | B23: 21B | C23: =SUM(C22) -> 46054 | D23: 176 | E23: 180 | F23: =E23-D23 -> 4 | G23: 220 | H23: =F23*G23 -> 880 | I23: 400 | J23: 110 | K23: =H23+J23 -> 990 | L23: 150 | M23: 0 | N23: =8500+500 -> 9000 | P23: ='hse1'!E48 -> 0 | Q23: =K23+L23+M23+N23+O23+P23 -> 10140 | R23: 0 | S23: =Q23-R23 -> 10140 | V23: 21 | W23: 10360 | X23: =W23-Q23 -> 220
A24: FATUMA ZAWADI | B24: 22A | C24: =SUM(C23) -> 46054 | D24: 290 | E24: 292 | F24: =E24-D24 -> 2 | G24: 220 | H24: =F24*G24 -> 440 | I24: 400 | J24: 110 | K24: =H24+J24 -> 550 | L24: 150 | M24: 0 | N24: =10000+500 -> 10500 | P24: ='hse1'!E49 -> 0 | Q24: =K24+L24+M24+N24+O24+P24 -> 11200 | R24: 0 | S24: =Q24-R24 -> 11200 | V24: 22 | W24: 10980 | X24: =W24-Q24 -> -220
A25: KAMAU | B25: 23A | C25: =SUM(C24) -> 46054 | D25: 670 | E25: 673 | F25: =E25-D25 -> 3 | G25: 220 | H25: =F25*G25 -> 660 | I25: 1400 | J25: 110 | K25: =H25+J25 -> 770 | L25: 150 | M25: 0 | N25: =10000+500 -> 10500 | P25: ='hse1'!E50 -> 0 | Q25: =K25+L25+M25+N25+O25+P25 -> 11420 | R25: 0 | S25: =Q25-R25 -> 11420 | V25: 23 | W25: 10980 | X25: =W25-Q25 -> -440
A26: NEW TENANT | B26: 24A | C26: =SUM(C25) -> 46054 | D26: 92 | E26: 94 | F26: =E26-D26 -> 2 | G26: 220 | H26: =F26*G26 -> 440 | I26: 1200 | J26: 110 | K26: =H26+J26 -> 550 | L26: 150 | M26: 0 | N26: =10000+500 -> 10500 | P26: ='hse1'!E51 -> 0 | Q26: =K26+L26+M26+N26+O26+P26 -> 11200 | R26: 0 | S26: =Q26-R26 -> 11200 | V26: 24 | W26: 11200 | X26: =W26-Q26 -> 0
A27: OMAR | B27: 25A | C27: =SUM(C26) -> 46054 | D27: 698 | E27: 701 | F27: =E27-D27 -> 3 | G27: 220 | H27: =F27*G27 -> 660 | I27: 200 | J27: 110 | K27: =H27+J27 -> 770 | L27: 150 | M27: 0 | N27: =10000+500 -> 10500 | O27: 1355 | P27: ='hse1'!E52 -> 0 | Q27: =K27+L27+M27+N27+O27+P27 -> 12775 | R27: 0 | S27: =Q27-R27 -> 12775 | V27: 25 | W27: 11420 | X27: =W27-Q27 -> -1355
A28: JOEL MAINA NDUNGU | B28: 26A | C28: =SUM(C27) -> 46054 | D28: 1377 | E28: 1381 | F28: =E28-D28 -> 4 | G28: 220 | H28: =F28*G28 -> 880 | I28: 800 | J28: 110 | K28: =H28+J28 -> 990 | L28: 150 | M28: 0 | N28: =9500+500 -> 10000 | P28: ='hse1'!E53 -> 0 | Q28: =K28+L28+M28+N28+O28+P28 -> 11140 | R28: 0 | S28: =Q28-R28 -> 11140 | V28: 26 | W28: 10920 | X28: =W28-Q28 -> -220
A29: CATE | B29: 27B | C29: =SUM(C28) -> 46054 | D29: 214 | E29: 215 | F29: =E29-D29 -> 1 | G29: 220 | H29: =F29*G29 -> 220 | I29: 400 | J29: 110 | K29: =H29+J29 -> 330 | L29: 150 | M29: 0 | N29: =8500+500 -> 9000 | O29: 1132 | P29: ='hse1'!E54 -> 0 | Q29: =K29+L29+M29+N29+O29+P29 -> 10612 | R29: 0 | S29: =Q29-R29 -> 10612 | T29: =Q29*3% -> 318.36 | U29: ECBKL 28/2/2018 | V29: 27B | W29: 9700 | X29: =W29-Q29 -> -912
A30: TITUS | B30: 28B | C30: =SUM(C29) -> 46054 | D30: 116 | E30: 118 | F30: =E30-D30 -> 2 | G30: 220 | H30: =F30*G30 -> 440 | I30: 200 | J30: 110 | K30: =H30+J30 -> 550 | L30: 150 | M30: 0 | N30: =8500+500 -> 9000 | P30: ='hse1'!E55 -> 0 | Q30: =K30+L30+M30+N30+O30+P30 -> 9700 | R30: 0 | S30: =Q30-R30 -> 9700 | V30: 28B | W30: 10140 | X30: =W30-Q30 -> 440
A31: PAUL MBOK | B31: 29A | C31: =SUM(C30) -> 46054 | D31: 612 | E31: 615 | F31: =E31-D31 -> 3 | G31: 220 | H31: =F31*G31 -> 660 | I31: 800 | J31: 110 | K31: =H31+J31 -> 770 | L31: 150 | M31: 0 | N31: =10000+500 -> 10500 | P31: 0 | Q31: =K31+L31+M31+N31+O31+P31 -> 11420 | R31: 0 | S31: =Q31-R31 -> 11420 | V31: 29 | W31: 13620 | X31: =W31-Q31 -> 2200
A32: MARY MUTHONI | B32: 30A | C32: =SUM(C31) -> 46054 | D32: 59 | E32: 62 | F32: =E32-D32 -> 3 | G32: 220 | H32: =F32*G32 -> 660 | I32: 400 | J32: 110 | K32: =H32+J32 -> 770 | L32: 150 | M32: 0 | N32: =9500+500 -> 10000 | P32: ='hse1'!E57 -> 0 | Q32: =K32+L32+M32+N32+O32+P32 -> 10920 | R32: 0 | S32: =Q32-R32 -> 10920 | V32: 30 | W32: 10700 | X32: =W32-Q32 -> -220
A33: ALICE | B33: 31A | C33: =SUM(C32) -> 46054 | D33: 137 | E33: 140 | F33: =E33-D33 -> 3 | G33: 220 | H33: =F33*G33 -> 660 | I33: 400 | J33: 110 | K33: =H33+J33 -> 770 | L33: 150 | M33: 0 | N33: =10000+500 -> 10500 | O33: 1750 | P33: 0 | Q33: 0 | R33: 0 | S33: =Q33-R33 -> 0 | V33: 31 | W33: 11420 | X33: =W33-Q33 -> 11420
A34: MIKE MUTISYA | B34: 32A | C34: =SUM(C33) -> 46054 | D34: 582 | E34: 588 | F34: =E34-D34 -> 6 | G34: 220 | H34: =F34*G34 -> 1320 | I34: 1200 | J34: 110 | K34: =H34+J34 -> 1430 | L34: 150 | M34: 0 | N34: =9500+500 -> 10000 | P34: ='hse1'!E59 -> 0 | Q34: =K34+L34+M34+N34+O33+P34 -> 13330 | R34: 0 | S34: =Q34-R34 -> 13330 | V34: 32 | W34: 11580 | X34: =W34-Q34 -> -1750
A35: NAOMI | B35: 33A | C35: =SUM(C34) -> 46054 | D35: 51 | E35: 55 | F35: =E35-D35 -> 4 | G35: 220 | H35: =F35*G35 -> 880 | I35: 400 | J35: 110 | K35: =H35+J35 -> 990 | L35: 150 | M35: 0 | N35: =10000+500 -> 10500 | O35: 677 | P35: 0 | Q35: =K35+L35+M35+N35+O35+P35 -> 12317 | R35: 0 | S35: =Q35-R35 -> 12317 | V35: 33 | W35: 11420 | X35: =W35-Q35 -> -897
A36: SAM | B36: 34B | C36: =SUM(C35) -> 46054 | D36: 37 | E36: 40 | F36: =E36-D36 -> 3 | G36: 220 | H36: =F36*G36 -> 660 | I36: 200 | J36: 110 | K36: =H36+J36 -> 770 | L36: 150 | M36: 0 | N36: =8500+500 -> 9000 | P36: ='hse1'!E61 -> 0 | Q36: =K36+L36+M36+N36+O36+P36 -> 9920 | R36: 0 | S36: =Q36-R36 -> 9920 | V36: 34 | W36: 10580 | X36: =W36-Q36 -> 660
A37: TIMOTHY | B37: 35B | C37: =SUM(C36) -> 46054 | D37: 182 | E37: 184 | F37: =E37-D37 -> 2 | G37: 220 | H37: =F37*G37 -> 440 | I37: 800 | J37: 110 | K37: =H37+J37 -> 550 | L37: 150 | M37: 0 | N37: =8500+500 -> 9000 | O37: 677 | P37: ='hse1'!E62 -> 0 | Q37: =K37+L37+M37+N37+O37+P37 -> 10377 | R37: 0 | S37: =Q37-R37 -> 10377 | V37: 35 | W37: 10360 | X37: =W37-Q37 -> -17
A38: SAMWEL MUGO | B38: 36B | C38: =SUM(C37) -> 46054 | D38: 154 | E38: 154 | F38: =E38-D38 -> 0 | G38: 220 | H38: =F38*G38 -> 0 | I38: 600 | J38: 110 | K38: =H38+J38 -> 110 | L38: 150 | M38: 0 | N38: =8500+500 -> 9000 | P38: ='hse1'!E63 -> 0 | Q38: =K38+L38+M38+N38+O38+P38 -> 9260 | R38: 0 | S38: =Q38-R38 -> 9260 | V38: 37B | W38: 9700 | X38: =W38-Q38 -> 440
B39: TOTAL | F39: =SUM(F3:F38) -> 101 | G39: 220 | H39: =SUM(H3:H38) -> 22000 | I39: =SUM(I3:I38) -> 26400 | J39: =SUM(J3:J38) -> 3960 | K39: =SUM(K3:K38) -> 25960 | L39: =SUM(L3:L38) -> 5400 | M39: 0 | N39: =SUM(N3:N38) -> 347000 | P39: =SUM(P3:P38) -> 0 | Q39: =SUM(Q3:Q38) -> 390210 | R39: =SUM(R3:R38) -> 0 | S39: =SUM(S3:S38) -> 390210 | T39: =SUM(T3:T38) -> 318.36 | U39: =SUM(U3:U38) -> 0 | V39: 0 | W39: 389140 | X39: =W39-Q39 -> -1070
B40: TOTAL | F40: 130 | H40: 25400 | J40: 3850 | K40: 29250 | L40: 5400 | Q40: 391268 | R40: 889.28 | S40: 395681.28 | T40: 0 | U40: 395681.28
B41: CURRENT | G41: 200 | H41: =G43*120 -> 24000 | J41: LOSS | Q41: 21000 | U41: PAYMENTS | V41: 135266 | X41: =Q41-W41 -> 21000
B42: UNITS | F42: =F41-F40 -> -130 | G42: 200 | Q42: 18000
B43: TOTAL SALT WATER JOYCE KAMAU | F43: 115 | G43: 200 | H43: =E43*F43 -> 0 | J43: =H39+J39-H43 -> 25960 | K43: EPZ BILL | Q43: 185000
B44: EPZ WATER BILL AMOUNT | F44: =E44-D44 -> 0 | J44: VARIANCE | M44: =H45-J43 -> -25960 | O44: =SUM(O43-O39) -> 0 | Q44: 155000 | V44: 20000 | W44: SECURITY
B45: WATER IN 3TANKS YET TO CONSUMED | G45: 4 | H45: =H43+H44 -> 0 | Q45: =Q41+Q42+Q43+Q44 -> 379000 | R45: Frebazeth Company Limited
B46: STAIRCASE WASHING &security caretaker&Watering flowers | G46: =F42-G47-G45-G43 -> -435 | H46: Expenditure of plot | J46: =G46*120 -> -52200 | Q46: =Q39-Q45 -> 11210 | R46: Consolidated Bank Account
B47: CONSUMED UNITS | G47: =F39 -> 101 | R47: Kitengela Branch
F48: =F39 -> 101 | G48: =F48*G38 -> 22220 | H48: 16065 | J48: BILL 0CTOBER | R48: A/C NO. 10171202000107/ 0120285090900 | W48: WAGES-JOSHUA
A49: READING BY TABIBU ON 28 AUGUST 2024 | O49: ……………
F50: =E53-F39 -> -101 | H50: =216 -> 216 | K50: 5,12,16
F51: =F50*F53 -> -11615 | G51: =E53*F53 -> 0 | H51: =H48/H50 -> 74.375
F53: 115 | G53: =F53*E53 -> 0 | H53: =E53*F53 -> 0
F54: 130 | H54: =E54*F54 -> 0 | J54: =E53-F39 -> -101 | M54: 23310 | N54: BILL
O62: RDTM | P62: balance 6/6/2016 | Q62: 79802.9
O63: CBKL | Q63: 49425.4
O64: KC | Q64: 971265.95

Sheet Sheet3

Sheet Sheet4

Sheet Sheet1
L16: 101456
L17: 21
L18: 1364
L19: 81411 | M19: salary
L21: =L16-L19 -> 20045
L22: =L19-55000 -> 26411

Sheet Sheet2
I1: MAY | J1: JUNE | K1: JUL
I2: 8300 | J2: 21000 | K2: 9962
I3: 9608 | J3: 9962 | K3: 10623
I4: 9608 | J4: 11039 | K4: 8510
I5: 7525 | J5: 10117 | K5: 10100
I6: 11000 | J6: 10778
I7: 8985 | J7: 10750
I8: 7857 | J8: 8510
I9: 6000 | J9: 11230
I10: 9005 | J10: 8500
I11: 10665 | J11: 10590
I12: 9335 | J12: 10400
I13: 8040 | J13: 10000
I14: 8000 | J14: 10840
I15: 10560 | J15: 10200 | K15: 11200
I16: 11000 | J16: 10225 | K16: 11360
I17: 9421 | J17: 9000 | K17: 9787
I18: 10000 | J18: 9945 | K18: 9130
I19: 10700 | J19: 10000 | K19: 10250
I20: 10055 | J20: 5000 | K20: 10740
I21: 10200 | J21: 8900 | K21: 10910
I22: 1977 | J22: 9962 | K22: 9000
I23: 10155 | J23: 10583 | K23: 10353
I24: 10000 | J24: 11200 | K24: 10910
I25: 8000 | J25: 9930 | K25: 8930
I26: 9925 | J26: 8662 | K26: 1200
... I32: 10000 | J32: 10860 | K32: 6000
I33: 5520 | K33: 8500
I34: 9805 | K34: 10430
I35: 20000 | K35: 10000
E36: 119472 | I36: 7000 | K36: 10000
E37: 64399 | I37: 5000 | K37: 11000
E38: =SUM(E36:E37) -> 183871 | I38: 20000 | K38: 8950
I39: 13000 | K39: 11230
I40: 10910 | K40: 400
K41: 7800
K42: 1000
K43: 8000
K44: 6294
I45: =SUM(I2:I44) -> 366751 | J45: =SUM(J2:J44) -> 307193 | K45: =SUM(K2:K44) -> 301808
