Workbook

Sheet FROM BOREHOLE
B2: SAMEDHA BOREHOLE | N2: VAR | O2: TAX DUE
B3: P.O BOX 9473-00200 NAIROBI | N3: =O3-Q3 -> 10270 | O3: 10270
B4: WATER BILL | G4: BILL NO. | H4: 20242001 | N4: =O4-Q4 -> 10304 | O4: 10304
N5: =O5-Q5 -> 10988 | O5: 10988
B6: NAME | C6: =meter!A3 -> From Borehole | N6: =O6-Q6 -> 11070 | O6: 11070
N7: =O7-Q7 -> 1197 | O7: 1197
N8: =O8-Q8 -> 9250 | O8: 9250
N9: =O9-Q9 -> 8770 | O9: 8770
B10: ISSUE DATE | C10: 29TH JAN 2025 | N10: =O10-Q10 -> 23190 | O10: 23190
N11: =O11-Q11 -> 10910 | O11: 10910
B12: LAST PAY DATE | C12: 5TH FEB 2026 | N12: =O12-Q12 -> 10910 | O12: 10910
N13: =O13-Q13 -> 12190 | O13: 12190
N14: =O14-Q14 -> 11070 | O14: 11070
B15: PREVIOUS READING | C15: CURRENT READING | E15: CONSUMPTION (Units) | N15: =O15-Q15 -> 9090 | O15: 9090
B16: =meter!D3 -> 227 | C16: =meter!E3 -> 1280 | D16: Units | E16: =C16-B16 -> 1053 | N16: =O16-Q16 -> 9420 | O16: 9420
E17: AMOUNT KSHS | N17: =O17-Q17 -> 11154 | O17: 11154
C18: LAST ACCOUNT B/F | D18: Kshs. | E18: =meter!J3 -> 0 | N18: =O18-Q18 -> 10430 | O18: 10430
N19: =O19-Q19 -> 11831 | O19: 11831
C20: MONTH Water BILL | D20: Kshs. | E20: =meter!H3 -> 105300 | N20: =O20-Q20 -> 10590 | O20: 10590
N21: =O21-Q21 -> 22423 | O21: 22423
N22: =O22-Q22 -> 9250 | O22: 9250
N23: =O23-Q23 -> 10162 | O23: 10162
N24: =O24-Q24 -> 10270 | O24: 10270
N25: =O25-Q25 -> 11070 | O25: 11070
N26: =O26-Q26 -> 11550 | O26: 11550
N27: =O27-Q27 -> 11393 | O27: 11393
N28: =O28-Q28 -> 10802 | O28: 10802
N29: =O29-Q29 -> 8930 | O29: 8930
C30: TOTAL PAYABLE | D30: Kshs. | E30: =E18+E20+E22+E24+E26+E27+E28 -> 105300 | N30: =O30-Q30 -> 9570 | O30: 9570
N31: =O31-Q31 -> 11390 | O31: 11390
C32: PAID | E32: 0 | N32: =O32-Q32 -> 10750 | O32: 10750
N33: =O33-Q33 -> 11732 | O33: 11732
C34: AMOUNT DUE | E34: =E30-E32 -> 105300 | N34: =O34-Q34 -> 10934 | O34: 10934 | R34: 700
B35: NOTE | N35: =O35-Q35 -> 10270 | O35: 10270
N36: =O36-Q36 -> 10598 | O36: 10598
A37: b) | N37: =O37-Q37 -> 8770 | O37: 8770
N38: =O38-Q38 -> 8770 | O38: 8770
A39: c) | O39: =SUM(O3:O38) -> 391268 | Q39: =SUM(Q3:Q38) -> 0
A41: d)
A42: e)
A43: f)
O49: ……………

Sheet OUT BOREHOLE
B2: SAMEDHA BOREHOLE | N2: VAR | O2: TAX DUE
B3: ='FROM BOREHOLE'!B3 -> P.O BOX 9473-00200 NAIROBI | N3: =O3-Q3 -> 10270 | O3: 10270
B4: WATER BILL | F4: BILL NO. | G4: ='FROM BOREHOLE'!H4+2-1 -> 20242002 | N4: =O4-Q4 -> 10304 | O4: 10304
N5: =O5-Q5 -> 10988 | O5: 10988
B6: NAME | D6: =meter!A4 -> Out Borehole | N6: =O6-Q6 -> 11070 | O6: 11070
N7: =O7-Q7 -> 1197 | O7: 1197
N8: =O8-Q8 -> 9250 | O8: 9250
N9: =O9-Q9 -> 8770 | O9: 8770
B10: ISSUE DATE | D10: ='FROM BOREHOLE'!C10 -> 29TH JAN 2025 | N10: =O10-Q10 -> 23190 | O10: 23190
N11: =O11-Q11 -> 10910 | O11: 10910
B12: LAST PAY DATE | D12: ='FROM BOREHOLE'!C12 -> 5TH FEB 2026 | N12: =O12-Q12 -> 10910 | O12: 10910
N13: =O13-Q13 -> 12190 | O13: 12190
N14: =O14-Q14 -> 11070 | O14: 11070
B15: PREVIOUS READING | D15: CURRENT READING | F15: CONSUMPTION (Units) | N15: =O15-Q15 -> 9090 | O15: 9090
B16: =meter!D4 -> 15801 | D16: =meter!E4 -> 16894 | E16: Units | F16: =D16-B16 -> 1093 | N16: =O16-Q16 -> 9420 | O16: 9420
F17: Amount (Kshs.) | N17: =O17-Q17 -> 11154 | O17: 11154
D18: LAST COUNT | F18: =meter!J4 -> 0 | N18: =O18-Q18 -> 10430 | O18: 10430
N19: =O19-Q19 -> 11831 | O19: 11831
D20: MONTH BILL | E20: Kshs. | F20: =meter!H4 -> 109300 | N20: =O20-Q20 -> 10590 | O20: 10590
N21: =O21-Q21 -> 22423 | O21: 22423
N22: =O22-Q22 -> 9250 | O22: 9250
N23: =O23-Q23 -> 10162 | O23: 10162
N24: =O24-Q24 -> 10270 | O24: 10270
N25: =O25-Q25 -> 11070 | O25: 11070
N26: =O26-Q26 -> 11550 | O26: 11550
N27: =O27-Q27 -> 11393 | O27: 11393
N28: =O28-Q28 -> 10802 | O28: 10802
N29: =O29-Q29 -> 8930 | O29: 8930
D30: TOTAL PAYABLE | E30: Kshs. | F30: =SUM(F17:F29) -> 109300 | N30: =O30-Q30 -> 9570 | O30: 9570
N31: =O31-Q31 -> 11390 | O31: 11390
D32: PAID | F32: 0 | N32: =O32-Q32 -> 10750 | O32: 10750
N33: =O33-Q33 -> 11732 | O33: 11732
D34: AMOUNT DUE | F34: =F30-F32 -> 109300 | N34: =O34-Q34 -> 10934 | O34: 10934 | R34: 700
C35: NOTE | N35: =O35-Q35 -> 10270 | O35: 10270
B36: a) | N36: =O36-Q36 -> 10598 | O36: 10598
B37: b) | N37: =O37-Q37 -> 8770 | O37: 8770
N38: =O38-Q38 -> 8770 | O38: 8770
B39: c) | O39: =SUM(O3:O38) -> 391268 | Q39: =SUM(Q3:Q38) -> 0
B41: d)
B42: e)
B43: f)
O49: ……………

Sheet NEW OUT B
B2: SAMEDHA BOREHOLE | N2: VAR | O2: TAX DUE
B3: ='FROM BOREHOLE'!B3 -> P.O BOX 9473-00200 NAIROBI | N3: =O3-Q3 -> 10270 | O3: 10270
B4: WATER BILL | G4: BILL NO. | H4: ='FROM BOREHOLE'!H4+3-1 -> 20242003 | N4: =O4-Q4 -> 10304 | O4: 10304
N5: =O5-Q5 -> 10988 | O5: 10988
B6: NAME | C6: =meter!A5 -> New Out Borehole | N6: =O6-Q6 -> 11070 | O6: 11070
N7: =O7-Q7 -> 1197 | O7: 1197
N8: =O8-Q8 -> 9250 | O8: 9250
N9: =O9-Q9 -> 8770 | O9: 8770
B10: ISSUE DATE | C10: ='FROM BOREHOLE'!C10 -> 29TH JAN 2025 | N10: =O10-Q10 -> 23190 | O10: 23190
N11: =O11-Q11 -> 10910 | O11: 10910
B12: LAST PAY DATE | C12: ='FROM BOREHOLE'!C12 -> 5TH FEB 2026 | N12: =O12-Q12 -> 10910 | O12: 10910
N13: =O13-Q13 -> 12190 | O13: 12190
N14: =O14-Q14 -> 11070 | O14: 11070
B15: PREVIOUS READING | C15: CURRENT READING | E15: CONSUMPTION (Units) | N15: =O15-Q15 -> 9090 | O15: 9090
B16: =meter!D5 -> 11651 | C16: =meter!E5 -> 12600 | D16: Units | E16: =C16-B16 -> 949 | N16: =O16-Q16 -> 9420 | O16: 9420
E17: Amount (Kshs.) | N17: =O17-Q17 -> 11154 | O17: 11154
C18: LAST ACCOUNT B/F | D18: Kshs. | E18: =meter!J5 -> 0 | N18: =O18-Q18 -> 10430 | O18: 10430
N19: =O19-Q19 -> 11831 | O19: 11831
C20: MONTH BILL | D20: Kshs. | E20: =meter!H5 -> 94900 | N20: =O20-Q20 -> 10590 | O20: 10590
N21: =O21-Q21 -> 22423 | O21: 22423
N22: =O22-Q22 -> 9250 | O22: 9250
N23: =O23-Q23 -> 10162 | O23: 10162
N24: =O24-Q24 -> 10270 | O24: 10270
N25: =O25-Q25 -> 11070 | O25: 11070
N26: =O26-Q26 -> 11550 | O26: 11550
N27: =O27-Q27 -> 11393 | O27: 11393
N28: =O28-Q28 -> 10802 | O28: 10802
N29: =O29-Q29 -> 8930 | O29: 8930
C30: TOTAL PAYABLE | D30: Kshs. | E30: =SUM(E17:E29) -> 94900 | N30: =O30-Q30 -> 9570 | O30: 9570
N31: =O31-Q31 -> 11390 | O31: 11390
C32: PAID | E32: =meter!L5 -> 0 | N32: =O32-Q32 -> 10750 | O32: 10750
N33: =O33-Q33 -> 11732 | O33: 11732
C34: AMOUNT DUE | E34: =E30-E32 -> 94900 | N34: =O34-Q34 -> 10934 | O34: 10934 | R34: 700
B35: NOTE | N35: =O35-Q35 -> 10270 | O35: 10270
A36: a) | N36: =O36-Q36 -> 10598 | O36: 10598
A37: b) | N37: =O37-Q37 -> 8770 | O37: 8770
N38: =O38-Q38 -> 8770 | O38: 8770
A39: c) | O39: =SUM(O3:O38) -> 391268 | Q39: =SUM(Q3:Q38) -> 0
A41: d)
A42: e)
A43: f)
O49: ……………

Sheet LORRY
B2: SAMEDHA BOREHOLE | N2: VAR | O2: TAX DUE
B3: ='FROM BOREHOLE'!B3 -> P.O BOX 9473-00200 NAIROBI | N3: =O3-Q3 -> 10270 | O3: 10270
B4: WATER BILL | G4: BILL NO. | H4: ='FROM BOREHOLE'!H4+4-1 -> 20242004 | N4: =O4-Q4 -> 10304 | O4: 10304
N5: =O5-Q5 -> 10988 | O5: 10988
B6: NAME | C6: =meter!A6 -> Lorry Water | N6: =O6-Q6 -> 11070 | O6: 11070
N7: =O7-Q7 -> 1197 | O7: 1197
N8: =O8-Q8 -> 9250 | O8: 9250
N9: =O9-Q9 -> 8770 | O9: 8770
B10: ISSUE DATE | C10: ='FROM BOREHOLE'!C10 -> 29TH JAN 2025 | N10: =O10-Q10 -> 23190 | O10: 23190
N11: =O11-Q11 -> 10910 | O11: 10910
B12: LAST PAY DATE | C12: ='FROM BOREHOLE'!C12 -> 5TH FEB 2026 | N12: =O12-Q12 -> 10910 | O12: 10910
N13: =O13-Q13 -> 12190 | O13: 12190
N14: =O14-Q14 -> 11070 | O14: 11070
B15: PREVIOUS READING | C15: CURRENT READING | E15: CONSUMPTION | N15: =O15-Q15 -> 9090 | O15: 9090
B16: =meter!D6 -> 9968 | C16: =meter!E6 -> 9968 | D16: Units | E16: =C16-B16 -> 0 | N16: =O16-Q16 -> 9420 | O16: 9420
E17: Amount (Kshs) | N17: =O17-Q17 -> 11154 | O17: 11154
C18: LAST ACCOUNT B/F | D18: Kshs. | E18: =meter!J6 -> 0 | N18: =O18-Q18 -> 10430 | O18: 10430
N19: =O19-Q19 -> 11831 | O19: 11831
C20: MONTH BILL | D20: Kshs. | E20: =meter!H6 -> 0 | N20: =O20-Q20 -> 10590 | O20: 10590
N21: =O21-Q21 -> 22423 | O21: 22423
N22: =O22-Q22 -> 9250 | O22: 9250
N23: =O23-Q23 -> 10162 | O23: 10162
N24: =O24-Q24 -> 10270 | O24: 10270
N25: =O25-Q25 -> 11070 | O25: 11070
N26: =O26-Q26 -> 11550 | O26: 11550
N27: =O27-Q27 -> 11393 | O27: 11393
N28: =O28-Q28 -> 10802 | O28: 10802
N29: =O29-Q29 -> 8930 | O29: 8930
C30: TOTAL PAYABLE | D30: Kshs. | E30: =SUM(E17:E29) -> 0 | N30: =O30-Q30 -> 9570 | O30: 9570
N31: =O31-Q31 -> 11390 | O31: 11390
C32: PAID | E32: =meter!L6 -> 0 | N32: =O32-Q32 -> 10750 | O32: 10750
N33: =O33-Q33 -> 11732 | O33: 11732
C34: AMOUNT DUE | E34: =E30-E32 -> 0 | N34: =O34-Q34 -> 10934 | O34: 10934 | R34: 700
B35: NOTE | N35: =O35-Q35 -> 10270 | O35: 10270
N36: =O36-Q36 -> 10598 | O36: 10598
N37: =O37-Q37 -> 8770 | O37: 8770
N38: =O38-Q38 -> 8770 | O38: 8770
O39: =SUM(O3:O38) -> 391268 | Q39: =SUM(Q3:Q38) -> 0
O49: ……………

Sheet PASSION
B2: SAMEDHA BOREHOLE | N2: VAR | O2: TAX DUE
B3: ='FROM BOREHOLE'!B3 -> P.O BOX 9473-00200 NAIROBI | N3: =O3-Q3 -> 10270 | O3: 10270
B4: WATER BILL | G4: BILL NO. | H4: ='FROM BOREHOLE'!H4+5-1 -> 20242005 | N4: =O4-Q4 -> 10304 | O4: 10304
N5: =O5-Q5 -> 10988 | O5: 10988
B6: NAME | C6: =meter!A7 -> PASSION FARM A | N6: =O6-Q6 -> 11070 | O6: 11070
N7: =O7-Q7 -> 1197 | O7: 1197
N8: =O8-Q8 -> 9250 | O8: 9250
N9: =O9-Q9 -> 8770 | O9: 8770
B10: ISSUE DATE | C10: ='FROM BOREHOLE'!C10 -> 29TH JAN 2025 | N10: =O10-Q10 -> 23190 | O10: 23190
N11: =O11-Q11 -> 10910 | O11: 10910
B12: LAST PAY DATE | C12: ='FROM BOREHOLE'!C12 -> 5TH FEB 2026 | N12: =O12-Q12 -> 10910 | O12: 10910
N13: =O13-Q13 -> 12190 | O13: 12190
N14: =O14-Q14 -> 11070 | O14: 11070
B15: PREVIOUS READING | C15: CURRENT READING | E15: CONSUMPTION (Units) | N15: =O15-Q15 -> 9090 | O15: 9090
B16: =meter!D7 -> 6881 | C16: =meter!E7 -> 0 | D16: Units | E16: =C16-B16 -> -6881 | N16: =O16-Q16 -> 9420 | O16: 9420
E17: Amount(Kshs) | N17: =O17-Q17 -> 11154 | O17: 11154
C18: LAST ACCOUNT B/F | D18: Kshs. | E18: =meter!J7 -> 0 | N18: =O18-Q18 -> 10430 | O18: 10430
N19: =O19-Q19 -> 11831 | O19: 11831
C20: MONTH BILL | D20: Kshs. | E20: =meter!H7 -> -688100 | N20: =O20-Q20 -> 10590 | O20: 10590
N21: =O21-Q21 -> 22423 | O21: 22423
N22: =O22-Q22 -> 9250 | O22: 9250
N23: =O23-Q23 -> 10162 | O23: 10162
N24: =O24-Q24 -> 10270 | O24: 10270
N25: =O25-Q25 -> 11070 | O25: 11070
N26: =O26-Q26 -> 11550 | O26: 11550
N27: =O27-Q27 -> 11393 | O27: 11393
N28: =O28-Q28 -> 10802 | O28: 10802
N29: =O29-Q29 -> 8930 | O29: 8930
C30: TOTAL PAYABLE | D30: Kshs. | E30: =SUM(E17:E29) -> -688100 | N30: =O30-Q30 -> 9570 | O30: 9570
N31: =O31-Q31 -> 11390 | O31: 11390
C32: PAID | E32: =meter!L7 -> 0 | N32: =O32-Q32 -> 10750 | O32: 10750
N33: =O33-Q33 -> 11732 | O33: 11732
C34: AMOUNT DUE | E34: =E30-E32 -> -688100 | N34: =O34-Q34 -> 10934 | O34: 10934 | R34: 700
B35: NOTE | N35: =O35-Q35 -> 10270 | O35: 10270
A36: a) | N36: =O36-Q36 -> 10598 | O36: 10598
A37: b) | N37: =O37-Q37 -> 8770 | O37: 8770
N38: =O38-Q38 -> 8770 | O38: 8770
A39: c) | O39: =SUM(O3:O38) -> 391268 | Q39: =SUM(Q3:Q38) -> 0
A41: d)
A42: e)
A43: f)
O49: ……………
A51: E & O E

Sheet BLOCK A
B2: SAMEDHA BOREHOLE | N2: VAR | O2: TAX DUE
B3: ='FROM BOREHOLE'!B3 -> P.O BOX 9473-00200 NAIROBI | N3: =O3-Q3 -> 10270 | O3: 10270
B4: WATER BILL | F4: BILL NO. | G4: BILL NO. | H4: ='FROM BOREHOLE'!H4+6-1 -> 20242006 | N4: =O4-Q4 -> 10304 | O4: 10304
N5: =O5-Q5 -> 10988 | O5: 10988
B6: NAME | C6: BLOCK A | N6: =O6-Q6 -> 11070 | O6: 11070
N7: =O7-Q7 -> 1197 | O7: 1197
N8: =O8-Q8 -> 9250 | O8: 9250
N9: =O9-Q9 -> 8770 | O9: 8770
B10: ISSUE DATE | C10: ='FROM BOREHOLE'!C10 -> 29TH JAN 2025 | N10: =O10-Q10 -> 23190 | O10: 23190
N11: =O11-Q11 -> 10910 | O11: 10910
B12: LAST PAY DATE | C12: ='FROM BOREHOLE'!C12 -> 5TH FEB 2026 | N12: =O12-Q12 -> 10910 | O12: 10910
N13: =O13-Q13 -> 12190 | O13: 12190
N14: =O14-Q14 -> 11070 | O14: 11070
B15: PREVIOUS READING | C15: CURRENT READING | E15: CONSUMPTION | N15: =O15-Q15 -> 9090 | O15: 9090
B16: =meter!D8 -> 4256 | C16: =meter!E8 -> 4256 | D16: Units | E16: =C16-B16 -> 0 | N16: =O16-Q16 -> 9420 | O16: 9420
E17: Amount(Kshs) | N17: =O17-Q17 -> 11154 | O17: 11154
C18: LAST ACCOUNT | D18: kshs. | E18: =meter!J8 -> 0 | N18: =O18-Q18 -> 10430 | O18: 10430
N19: =O19-Q19 -> 11831 | O19: 11831
C20: MONTH BILL | D20: KSHS. | E20: =meter!H8 -> 0 | N20: =O20-Q20 -> 10590 | O20: 10590
N21: =O21-Q21 -> 22423 | O21: 22423
N22: =O22-Q22 -> 9250 | O22: 9250
N23: =O23-Q23 -> 10162 | O23: 10162
N24: =O24-Q24 -> 10270 | O24: 10270
N25: =O25-Q25 -> 11070 | O25: 11070
C26: ='FROM BOREHOLE'!C26 -> 0 | N26: =O26-Q26 -> 11550 | O26: 11550
N27: =O27-Q27 -> 11393 | O27: 11393
N28: =O28-Q28 -> 10802 | O28: 10802
N29: =O29-Q29 -> 8930 | O29: 8930
C30: TOTAL PAYABLE | D30: Kshs. | E30: =SUM(E17:E29) -> 0 | N30: =O30-Q30 -> 9570 | O30: 9570
N31: =O31-Q31 -> 11390 | O31: 11390
C32: PAID | E32: 0 | N32: =O32-Q32 -> 10750 | O32: 10750
N33: =O33-Q33 -> 11732 | O33: 11732
C34: AMOUNT DUE | E34: =E30-E32 -> 0 | N34: =O34-Q34 -> 10934 | O34: 10934 | R34: 700
B35: NOTE | N35: =O35-Q35 -> 10270 | O35: 10270
A36: a) | N36: =O36-Q36 -> 10598 | O36: 10598
A37: b) | N37: =O37-Q37 -> 8770 | O37: 8770
N38: =O38-Q38 -> 8770 | O38: 8770
A39: c) | O39: =SUM(O3:O38) -> 391268 | Q39: =SUM(Q3:Q38) -> 0
A41: d)
A42: e)
A43: f)
O49: ……………

Sheet BLOCK B
B2: SAMEDHA BOREHOLE | N2: VAR | O2: TAX DUE
B3: ='FROM BOREHOLE'!B3 -> P.O BOX 9473-00200 NAIROBI | N3: =O3-Q3 -> 10270 | O3: 10270
B4: WATER BILL | G4: BILL NO. | H4: ='FROM BOREHOLE'!H4+7-1 -> 20242007 | N4: =O4-Q4 -> 10304 | O4: 10304
N5: =O5-Q5 -> 10988 | O5: 10988
B6: NAME | C6: =meter!A9 -> BLOCK B | N6: =O6-Q6 -> 11070 | O6: 11070
N7: =O7-Q7 -> 1197 | O7: 1197
N8: =O8-Q8 -> 9250 | O8: 9250
N9: =O9-Q9 -> 8770 | O9: 8770
B10: ISSUE DATE | C10: ='FROM BOREHOLE'!C10 -> 29TH JAN 2025 | N10: =O10-Q10 -> 23190 | O10: 23190
N11: =O11-Q11 -> 10910 | O11: 10910
B12: LAST PAY DATE | C12: ='FROM BOREHOLE'!C12 -> 5TH FEB 2026 | N12: =O12-Q12 -> 10910 | O12: 10910
N13: =O13-Q13 -> 12190 | O13: 12190
N14: =O14-Q14 -> 11070 | O14: 11070
B15: PREVIOUS READING | C15: CURRENT READING | E15: CONSUMPTION | N15: =O15-Q15 -> 9090 | O15: 9090
B16: =meter!D9 -> 1099 | C16: =meter!E9 -> 1099 | D16: Units | E16: =C16-B16 -> 0 | N16: =O16-Q16 -> 9420 | O16: 9420
E17: Amount (Kshs) | N17: =O17-Q17 -> 11154 | O17: 11154
C18: LAST ACCOUNT | D18: kshs. | E18: =meter!J9 -> 0 | N18: =O18-Q18 -> 10430 | O18: 10430
N19: =O19-Q19 -> 11831 | O19: 11831
C20: MONTH BILL | D20: KSHS. | E20: =meter!H9 -> 0 | N20: =O20-Q20 -> 10590 | O20: 10590
N21: =O21-Q21 -> 22423 | O21: 22423
N22: =O22-Q22 -> 9250 | O22: 9250
N23: =O23-Q23 -> 10162 | O23: 10162
N24: =O24-Q24 -> 10270 | O24: 10270
N25: =O25-Q25 -> 11070 | O25: 11070
C26: ='FROM BOREHOLE'!C26 -> 0 | D26: ='FROM BOREHOLE'!D26 -> 0 | N26: =O26-Q26 -> 11550 | O26: 11550
N27: =O27-Q27 -> 11393 | O27: 11393
E28: =IF(E18*6%*3<0,0,E18*6%*3) -> 0 | N28: =O28-Q28 -> 10802 | O28: 10802
N29: =O29-Q29 -> 8930 | O29: 8930
C30: TOTAL PAYABLE | D30: Kshs. | E30: =SUM(E17:E29) -> 0 | N30: =O30-Q30 -> 9570 | O30: 9570
N31: =O31-Q31 -> 11390 | O31: 11390
C32: PAID | E32: 0 | N32: =O32-Q32 -> 10750 | O32: 10750
N33: =O33-Q33 -> 11732 | O33: 11732
C34: AMOUNT DUE | E34: =E30-E32 -> 0 | N34: =O34-Q34 -> 10934 | O34: 10934 | R34: 700
B35: NOTE | N35: =O35-Q35 -> 10270 | O35: 10270
A36: a) | N36: =O36-Q36 -> 10598 | O36: 10598
A37: b) | N37: =O37-Q37 -> 8770 | O37: 8770
N38: =O38-Q38 -> 8770 | O38: 8770
A39: c) | O39: =SUM(O3:O38) -> 391268 | Q39: =SUM(Q3:Q38) -> 0
A41: d)
A42: e)
A43: f)
O49: ……………

Sheet NEW BLOCK
B2: SAMEDHA BOREHOLE | N2: VAR | O2: TAX DUE
B3: ='FROM BOREHOLE'!B3 -> P.O BOX 9473-00200 NAIROBI | N3: =O3-Q3 -> 10270 | O3: 10270
B4: WATER BILL | G4: BILL NO. | H4: ='FROM BOREHOLE'!H4+8-1 -> 20242008 | N4: =O4-Q4 -> 10304 | O4: 10304
N5: =O5-Q5 -> 10988 | O5: 10988
B6: NAME | C6: =meter!A10 -> NEW BLOCK | N6: =O6-Q6 -> 11070 | O6: 11070
N7: =O7-Q7 -> 1197 | O7: 1197
N8: =O8-Q8 -> 9250 | O8: 9250
N9: =O9-Q9 -> 8770 | O9: 8770
B10: ISSUE DATE | C10: ='FROM BOREHOLE'!C10 -> 29TH JAN 2025 | N10: =O10-Q10 -> 23190 | O10: 23190
N11: =O11-Q11 -> 10910 | O11: 10910
B12: LAST PAY DATE | C12: ='FROM BOREHOLE'!C12 -> 5TH FEB 2026 | N12: =O12-Q12 -> 10910 | O12: 10910
N13: =O13-Q13 -> 12190 | O13: 12190
N14: =O14-Q14 -> 11070 | O14: 11070
B15: PREVIOUS READING | C15: CURRENT READING | E15: CONSUMPTION | N15: =O15-Q15 -> 9090 | O15: 9090
B16: =meter!D10 -> 4205 | C16: =meter!E10 -> 4205 | D16: Units | E16: =C16-B16 -> 0 | N16: =O16-Q16 -> 9420 | O16: 9420
E17: Amount (Kshs.) | N17: =O17-Q17 -> 11154 | O17: 11154
C18: LAST ACCOUNT | D18: kshs. | E18: =meter!J10 -> 0 | N18: =O18-Q18 -> 10430 | O18: 10430
N19: =O19-Q19 -> 11831 | O19: 11831
C20: MONTH BILL | D20: KSHS. | E20: =meter!H10 -> 0 | N20: =O20-Q20 -> 10590 | O20: 10590
N21: =O21-Q21 -> 22423 | O21: 22423
N22: =O22-Q22 -> 9250 | O22: 9250
N23: =O23-Q23 -> 10162 | O23: 10162
N24: =O24-Q24 -> 10270 | O24: 10270
N25: =O25-Q25 -> 11070 | O25: 11070
N26: =O26-Q26 -> 11550 | O26: 11550
N27: =O27-Q27 -> 11393 | O27: 11393
N28: =O28-Q28 -> 10802 | O28: 10802
N29: =O29-Q29 -> 8930 | O29: 8930
C30: TOTAL PAYABLE | D30: Kshs. | E30: =SUM(E17:E29) -> 0 | N30: =O30-Q30 -> 9570 | O30: 9570
N31: =O31-Q31 -> 11390 | O31: 11390
C32: PAID | E32: =meter!L10 -> 0 | N32: =O32-Q32 -> 10750 | O32: 10750
N33: =O33-Q33 -> 11732 | O33: 11732
C34: AMOUNT DUE | E34: =E30-E32 -> 0 | N34: =O34-Q34 -> 10934 | O34: 10934 | R34: 700
B35: NOTE | N35: =O35-Q35 -> 10270 | O35: 10270
A36: a) | N36: =O36-Q36 -> 10598 | O36: 10598
A37: b) | N37: =O37-Q37 -> 8770 | O37: 8770
N38: =O38-Q38 -> 8770 | O38: 8770
A39: c) | O39: =SUM(O3:O38) -> 391268 | Q39: =SUM(Q3:Q38) -> 0
A41: d)
A42: e)
A43: f)
O49: ……………

Sheet HOUSE JOHN
B2: SAMEDHA BOREHOLE | N2: VAR | O2: TAX DUE
B3: ='FROM BOREHOLE'!B3 -> P.O BOX 9473-00200 NAIROBI | N3: =O3-Q3 -> 10270 | O3: 10270
B4: WATER BILL | G4: BILL NO. | H4: ='FROM BOREHOLE'!H4+9-1 -> 20242009 | N4: =O4-Q4 -> 10304 | O4: 10304
N5: =O5-Q5 -> 10988 | O5: 10988
B6: NAME | C6: =meter!A11 -> HOUSE JOHN | N6: =O6-Q6 -> 11070 | O6: 11070
N7: =O7-Q7 -> 1197 | O7: 1197
N8: =O8-Q8 -> 9250 | O8: 9250
N9: =O9-Q9 -> 8770 | O9: 8770
B10: ISSUE DATE | C10: ='FROM BOREHOLE'!C10 -> 29TH JAN 2025 | N10: =O10-Q10 -> 23190 | O10: 23190
N11: =O11-Q11 -> 10910 | O11: 10910
B12: LAST PAY DATE | C12: ='FROM BOREHOLE'!C12 -> 5TH FEB 2026 | N12: =O12-Q12 -> 10910 | O12: 10910
N13: =O13-Q13 -> 12190 | O13: 12190
N14: =O14-Q14 -> 11070 | O14: 11070
B15: PREVIOUS READING | C15: CURRENT READING | E15: CONSUMPTION | N15: =O15-Q15 -> 9090 | O15: 9090
B16: =meter!D11 -> 56 | C16: =meter!E11 -> 56 | D16: Units | E16: =C16-B16 -> 0 | N16: =O16-Q16 -> 9420 | O16: 9420
E17: Amount (Kshs.) | N17: =O17-Q17 -> 11154 | O17: 11154
C18: LAST ACCOUNT | D18: kshs. | E18: =meter!J11 -> 0 | N18: =O18-Q18 -> 10430 | O18: 10430
N19: =O19-Q19 -> 11831 | O19: 11831
C20: MONTH BILL | D20: KSHS. | E20: =meter!H11 -> 0 | N20: =O20-Q20 -> 10590 | O20: 10590
N21: =O21-Q21 -> 22423 | O21: 22423
N22: =O22-Q22 -> 9250 | O22: 9250
N23: =O23-Q23 -> 10162 | O23: 10162
N24: =O24-Q24 -> 10270 | O24: 10270
N25: =O25-Q25 -> 11070 | O25: 11070
N26: =O26-Q26 -> 11550 | O26: 11550
N27: =O27-Q27 -> 11393 | O27: 11393
E28: =IF(E18*4%*1<0,0,E18*4%*1) -> 0 | N28: =O28-Q28 -> 10802 | O28: 10802
N29: =O29-Q29 -> 8930 | O29: 8930
C30: TOTAL PAYABLE | D30: Kshs. | E30: =SUM(E17:E29) -> 0 | N30: =O30-Q30 -> 9570 | O30: 9570
N31: =O31-Q31 -> 11390 | O31: 11390
C32: PAID | E32: =meter!L11 -> 0 | N32: =O32-Q32 -> 10750 | O32: 10750
N33: =O33-Q33 -> 11732 | O33: 11732
C34: AMOUNT DUE | E34: =E30-E32 -> 0 | N34: =O34-Q34 -> 10934 | O34: 10934 | R34: 700
B35: NOTE | N35: =O35-Q35 -> 10270 | O35: 10270
A36: a) | N36: =O36-Q36 -> 10598 | O36: 10598
A37: b) | N37: =O37-Q37 -> 8770 | O37: 8770
N38: =O38-Q38 -> 8770 | O38: 8770
A39: c) | O39: =SUM(O3:O38) -> 391268 | Q39: =SUM(Q3:Q38) -> 0
A41: d)
A42: e)
A43: f)
O49: ……………

Sheet KAYAVA
B2: SAMEDHA BOREHOLE | N2: VAR | O2: TAX DUE
B3: ='FROM BOREHOLE'!B3 -> P.O BOX 9473-00200 NAIROBI | N3: =O3-Q3 -> 10270 | O3: 10270
B4: WATER BILL | G4: BILL NO. | H4: ='FROM BOREHOLE'!H4+10-1 -> 20242010 | N4: =O4-Q4 -> 10304 | O4: 10304
N5: =O5-Q5 -> 10988 | O5: 10988
B6: NAME | C6: =meter!A12 -> KAYAVA | N6: =O6-Q6 -> 11070 | O6: 11070
N7: =O7-Q7 -> 1197 | O7: 1197
N8: =O8-Q8 -> 9250 | O8: 9250
N9: =O9-Q9 -> 8770 | O9: 8770
B10: ISSUE DATE | C10: ='FROM BOREHOLE'!C10 -> 29TH JAN 2025 | N10: =O10-Q10 -> 23190 | O10: 23190
N11: =O11-Q11 -> 10910 | O11: 10910
B12: LAST PAY DATE | C12: ='FROM BOREHOLE'!C12 -> 5TH FEB 2026 | N12: =O12-Q12 -> 10910 | O12: 10910
N13: =O13-Q13 -> 12190 | O13: 12190
N14: =O14-Q14 -> 11070 | O14: 11070
B15: PREVIOUS READING | C15: CURRENT READING | E15: CONSUMPTION | N15: =O15-Q15 -> 9090 | O15: 9090
B16: =meter!D12 -> 1808 | C16: =meter!E12 -> 0 | D16: Units | E16: =C16-B16 -> -1808 | N16: =O16-Q16 -> 9420 | O16: 9420
E17: Amount (Kshs) | N17: =O17-Q17 -> 11154 | O17: 11154
C18: LAST ACCOUNT | D18: kshs. | E18: =meter!J12 -> 0 | N18: =O18-Q18 -> 10430 | O18: 10430
N19: =O19-Q19 -> 11831 | O19: 11831
C20: MONTH BILL | D20: KSHS. | E20: =meter!H12 -> -180800 | N20: =O20-Q20 -> 10590 | O20: 10590
N21: =O21-Q21 -> 22423 | O21: 22423
E22: ='FROM BOREHOLE'!E22 -> 0 | N22: =O22-Q22 -> 9250 | O22: 9250
N23: =O23-Q23 -> 10162 | O23: 10162
N24: =O24-Q24 -> 10270 | O24: 10270
N25: =O25-Q25 -> 11070 | O25: 11070
N26: =O26-Q26 -> 11550 | O26: 11550
N27: =O27-Q27 -> 11393 | O27: 11393
N28: =O28-Q28 -> 10802 | O28: 10802
N29: =O29-Q29 -> 8930 | O29: 8930
C30: TOTAL PAYABLE | D30: Kshs. | E30: =SUM(E17:E29) -> -180800 | N30: =O30-Q30 -> 9570 | O30: 9570
N31: =O31-Q31 -> 11390 | O31: 11390
C32: PAID | E32: =meter!L12 -> 0 | N32: =O32-Q32 -> 10750 | O32: 10750
N33: =O33-Q33 -> 11732 | O33: 11732
C34: AMOUNT DUE | E34: =E30-E32 -> -180800 | N34: =O34-Q34 -> 10934 | O34: 10934 | R34: 700
B35: NOTE | N35: =O35-Q35 -> 10270 | O35: 10270
A36: a) | B36: KINDLY PAY FOR WATER LATEST BY 5TH OF THE MONTH AND FORWARD SMS OR WHATSAPP TO 0702325121 | N36: =O36-Q36 -> 10598 | O36: 10598
A37: b) | N37: =O37-Q37 -> 8770 | O37: 8770
N38: =O38-Q38 -> 8770 | O38: 8770
A39: c) | O39: =SUM(O3:O38) -> 391268 | Q39: =SUM(Q3:Q38) -> 0
A41: d)
A42: e)
A43: f)
B47: TILL 4536508
O49: ……………

Sheet VINCENT
B2: SAMEDHA BOREHOLE | N2: VAR | O2: TAX DUE
B3: ='FROM BOREHOLE'!B3 -> P.O BOX 9473-00200 NAIROBI | N3: =O3-Q3 -> 10270 | O3: 10270
B4: WATER BILL | G4: BILL NO. | H4: ='FROM BOREHOLE'!H4+11-1 -> 20242011 | N4: =O4-Q4 -> 10304 | O4: 10304
N5: =O5-Q5 -> 10988 | O5: 10988
B6: NAME | C6: =meter!A13 -> Mr Vincent | N6: =O6-Q6 -> 11070 | O6: 11070
N7: =O7-Q7 -> 1197 | O7: 1197
N8: =O8-Q8 -> 9250 | O8: 9250
N9: =O9-Q9 -> 8770 | O9: 8770
B10: ISSUE DATE | C10: 29TH DEC 2025 | N10: =O10-Q10 -> 23190 | O10: 23190
N11: =O11-Q11 -> 10910 | O11: 10910
B12: LAST PAY DATE | C12: 5TH JAN 2026 | N12: =O12-Q12 -> 10910 | O12: 10910
N13: =O13-Q13 -> 12190 | O13: 12190
N14: =O14-Q14 -> 11070 | O14: 11070
B15: PREVIOUS READING | C15: CURRENT READING | E15: CONSUMPTION | N15: =O15-Q15 -> 9090 | O15: 9090
B16: =meter!D13 -> 2728 | C16: =meter!E13 -> 2773 | D16: Units | E16: =C16-B16 -> 45 | N16: =O16-Q16 -> 9420 | O16: 9420
E17: Amount (Kshs.) | N17: =O17-Q17 -> 11154 | O17: 11154
C18: LAST ACCOUNT | D18: kshs. | E18: =meter!J13 -> 0 | N18: =O18-Q18 -> 10430 | O18: 10430
N19: =O19-Q19 -> 11831 | O19: 11831
C20: MONTH BILL | D20: KSHS. | E20: =meter!H13 -> 4500 | N20: =O20-Q20 -> 10590 | O20: 10590
N21: =O21-Q21 -> 22423 | O21: 22423
N22: =O22-Q22 -> 9250 | O22: 9250
N23: =O23-Q23 -> 10162 | O23: 10162
N24: =O24-Q24 -> 10270 | O24: 10270
N25: =O25-Q25 -> 11070 | O25: 11070
N26: =O26-Q26 -> 11550 | O26: 11550
N27: =O27-Q27 -> 11393 | O27: 11393
N28: =O28-Q28 -> 10802 | O28: 10802
N29: =O29-Q29 -> 8930 | O29: 8930
C30: TOTAL PAYABLE | D30: Kshs. | E30: =SUM(E17:E29) -> 4500 | N30: =O30-Q30 -> 9570 | O30: 9570
N31: =O31-Q31 -> 11390 | O31: 11390
C32: PAID | E32: =meter!L13 -> 0 | N32: =O32-Q32 -> 10750 | O32: 10750
N33: =O33-Q33 -> 11732 | O33: 11732
C34: AMOUNT DUE | E34: =E30-E32 -> 4500 | N34: =O34-Q34 -> 10934 | O34: 10934 | R34: 700
B35: NOTE | N35: =O35-Q35 -> 10270 | O35: 10270
A36: a) | B36: KINDLY PAY FOR WATER LATEST BY 5TH OF THE MONTH AND FORWARD SMS OR WHATSAPP TO 0702325121 | N36: =O36-Q36 -> 10598 | O36: 10598
A37: b) | N37: =O37-Q37 -> 8770 | O37: 8770
N38: =O38-Q38 -> 8770 | O38: 8770
A39: c) | O39: =SUM(O3:O38) -> 391268 | Q39: =SUM(Q3:Q38) -> 0
A41: d)
A42: e)
A43: f)
B47: PAYBILL 4139271 ACC NO KSJ 1
O49: ……………

Sheet WAMALWA
B2: SAMEDHA BOREHOLE | N2: VAR | O2: TAX DUE
B3: ='FROM BOREHOLE'!B3 -> P.O BOX 9473-00200 NAIROBI | N3: =O3-Q3 -> 10270 | O3: 10270
B4: WATER BILL | H4: BILL NO. | I4: ='FROM BOREHOLE'!H4+12-1 -> 20242012 | J4: ='FROM BOREHOLE'!H4+12-1 -> 20242012 | N4: =O4-Q4 -> 10304 | O4: 10304
N5: =O5-Q5 -> 10988 | O5: 10988
B6: NAME | D6: =meter!A14 -> Mr Wamalwa | N6: =O6-Q6 -> 11070 | O6: 11070
N7: =O7-Q7 -> 1197 | O7: 1197
N8: =O8-Q8 -> 9250 | O8: 9250
N9: =O9-Q9 -> 8770 | O9: 8770
B10: ISSUE DATE | D10: 29TH DEC 2025 | N10: =O10-Q10 -> 23190 | O10: 23190
N11: =O11-Q11 -> 10910 | O11: 10910
B12: LAST PAY DATE | D12: 5TH JAN 2026 | N12: =O12-Q12 -> 10910 | O12: 10910
N13: =O13-Q13 -> 12190 | O13: 12190
N14: =O14-Q14 -> 11070 | O14: 11070
B15: PREVIOUS READING | D15: CURRENT READING | F15: CONSUMPTION | N15: =O15-Q15 -> 9090 | O15: 9090
B16: =meter!D14 -> 918 | D16: =meter!E14 -> 938 | E16: Units | F16: =D16-B16 -> 20 | N16: =O16-Q16 -> 9420 | O16: 9420
F17: Amount (Kshs.) | N17: =O17-Q17 -> 11154 | O17: 11154
D18: LAST ACCOUNT | E18: kshs. | F18: =meter!J14 -> 2500 | N18: =O18-Q18 -> 10430 | O18: 10430
N19: =O19-Q19 -> 11831 | O19: 11831
D20: MONTH BILL | E20: KSHS. | F20: =meter!H14 -> 2000 | N20: =O20-Q20 -> 10590 | O20: 10590
N21: =O21-Q21 -> 22423 | O21: 22423
N22: =O22-Q22 -> 9250 | O22: 9250
N23: =O23-Q23 -> 10162 | O23: 10162
N24: =O24-Q24 -> 10270 | O24: 10270
N25: =O25-Q25 -> 11070 | O25: 11070
N26: =O26-Q26 -> 11550 | O26: 11550
N27: =O27-Q27 -> 11393 | O27: 11393
N28: =O28-Q28 -> 10802 | O28: 10802
N29: =O29-Q29 -> 8930 | O29: 8930
C30: TOTAL PAYABLE | D30: TOTAL PAYABLE | E30: Kshs. | F30: =SUM(F17:F29) -> 4500 | N30: =O30-Q30 -> 9570 | O30: 9570
N31: =O31-Q31 -> 11390 | O31: 11390
C32: PAID | D32: PAID | F32: =meter!L14 -> 0 | N32: =O32-Q32 -> 10750 | O32: 10750
N33: =O33-Q33 -> 11732 | O33: 11732
C34: BALANCE C/F | D34: AMOUNT DUE | F34: =F30-F32 -> 4500 | N34: =O34-Q34 -> 10934 | O34: 10934 | R34: 700
B35: NOTE | N35: =O35-Q35 -> 10270 | O35: 10270
A36: a) | B36: KINDLY PAY FOR WATER LATEST BY 5TH OF THE MONTH AND FORWARD SMS OR WHATSAPP TO 0702325121 | N36: =O36-Q36 -> 10598 | O36: 10598
A37: b) | N37: =O37-Q37 -> 8770 | O37: 8770
N38: =O38-Q38 -> 8770 | O38: 8770
A39: c) | O39: =SUM(O3:O38) -> 391268 | Q39: =SUM(Q3:Q38) -> 0
A41: d)
A42: e)
A43: f)
B47: PAYBILL 4139271 ACC NO KSJ 2
O49: ……………

Sheet MWITA
B2: SAMEDHA BOREHOLE | N2: VAR | O2: TAX DUE
B3: ='FROM BOREHOLE'!B3 -> P.O BOX 9473-00200 NAIROBI | N3: =O3-Q3 -> 10270 | O3: 10270
B4: WATER BILL | G4: BILL NO. | H4: ='FROM BOREHOLE'!H4+13-1 -> 20242013 | N4: =O4-Q4 -> 10304 | O4: 10304
N5: =O5-Q5 -> 10988 | O5: 10988
B6: NAME | D6: =meter!A15 -> Mr Mwita | N6: =O6-Q6 -> 11070 | O6: 11070
N7: =O7-Q7 -> 1197 | O7: 1197
N8: =O8-Q8 -> 9250 | O8: 9250
N9: =O9-Q9 -> 8770 | O9: 8770
B10: ISSUE DATE | D10: ='FROM BOREHOLE'!C10 -> 29TH JAN 2025 | N10: =O10-Q10 -> 23190 | O10: 23190
N11: =O11-Q11 -> 10910 | O11: 10910
B12: LAST PAY DATE | D12: ='FROM BOREHOLE'!C12 -> 5TH FEB 2026 | N12: =O12-Q12 -> 10910 | O12: 10910
N13: =O13-Q13 -> 12190 | O13: 12190
N14: =O14-Q14 -> 11070 | O14: 11070
B15: PREVIOUS READING | D15: CURRENT READING | F15: CONSUMPTION | N15: =O15-Q15 -> 9090 | O15: 9090
B16: =meter!D15 -> 67 | D16: =meter!E15 -> 72 | E16: Units | F16: =D16-B16 -> 5 | N16: =O16-Q16 -> 9420 | O16: 9420
F17: Amount (Kshs.) | N17: =O17-Q17 -> 11154 | O17: 11154
D18: LAST ACCOUNT B/F | E18: kshs. | F18: =meter!J15 -> 0 | N18: =O18-Q18 -> 10430 | O18: 10430
N19: =O19-Q19 -> 11831 | O19: 11831
D20: MONTH BILL | E20: KSHS. | F20: =meter!H15 -> 500 | N20: =O20-Q20 -> 10590 | O20: 10590
N21: =O21-Q21 -> 22423 | O21: 22423
N22: =O22-Q22 -> 9250 | O22: 9250
N23: =O23-Q23 -> 10162 | O23: 10162
N24: =O24-Q24 -> 10270 | O24: 10270
N25: =O25-Q25 -> 11070 | O25: 11070
N26: =O26-Q26 -> 11550 | O26: 11550
N27: =O27-Q27 -> 11393 | O27: 11393
N28: =O28-Q28 -> 10802 | O28: 10802
N29: =O29-Q29 -> 8930 | O29: 8930
D30: TOTAL PAYABLE | E30: Kshs. | F30: =SUM(F17:F29) -> 500 | N30: =O30-Q30 -> 9570 | O30: 9570
N31: =O31-Q31 -> 11390 | O31: 11390
D32: PAID | F32: =meter!L15 -> 0 | N32: =O32-Q32 -> 10750 | O32: 10750
N33: =O33-Q33 -> 11732 | O33: 11732
D34: AMOUNT DUE | F34: =F30-F32 -> 500 | N34: =O34-Q34 -> 10934 | O34: 10934 | R34: 700
B35: NOTE | N35: =O35-Q35 -> 10270 | O35: 10270
A36: a) | B36: KINDLY PAY FOR WATER LATEST BY 5TH OF THE MONTH AND FORWARD SMS OR WHATSAPP TO 0702325121 | N36: =O36-Q36 -> 10598 | O36: 10598
A37: b) | N37: =O37-Q37 -> 8770 | O37: 8770
N38: =O38-Q38 -> 8770 | O38: 8770
A39: c) | O39: =SUM(O3:O38) -> 391268 | Q39: =SUM(Q3:Q38) -> 0
A41: d)
A42: e)
A43: f)
B47: PAYBILL 4139271 PAYBILL KSJ3
O49: ……………

Sheet NYARANDI
B2: SAMEDHA BOREHOLE | N2: VAR | O2: TAX DUE
B3: ='FROM BOREHOLE'!B3 -> P.O BOX 9473-00200 NAIROBI | N3: =O3-Q3 -> 10270 | O3: 10270
B4: WATER BILL | H4: BILL NO. | I4: ='FROM BOREHOLE'!H4+14-1 -> 20242014 | J4: ='FROM BOREHOLE'!H4+14-1 -> 20242014 | N4: =O4-Q4 -> 10304 | O4: 10304
N5: =O5-Q5 -> 10988 | O5: 10988
B6: NAME | D6: =meter!A16 -> Andrew nyarandi | N6: =O6-Q6 -> 11070 | O6: 11070
N7: =O7-Q7 -> 1197 | O7: 1197
N8: =O8-Q8 -> 9250 | O8: 9250
N9: =O9-Q9 -> 8770 | O9: 8770
B10: ISSUE DATE | D10: ='FROM BOREHOLE'!C10 -> 29TH JAN 2025 | N10: =O10-Q10 -> 23190 | O10: 23190
N11: =O11-Q11 -> 10910 | O11: 10910
B12: LAST PAY DATE | D12: ='FROM BOREHOLE'!C12 -> 5TH FEB 2026 | N12: =O12-Q12 -> 10910 | O12: 10910
N13: =O13-Q13 -> 12190 | O13: 12190
N14: =O14-Q14 -> 11070 | O14: 11070
B15: PREVIOUS READING | D15: CURRENT READING | F15: CONSUMPTION | N15: =O15-Q15 -> 9090 | O15: 9090
B16: =meter!D16 -> 235 | D16: =meter!E16 -> 254 | E16: Units | F16: =D16-B16 -> 19 | H16: ESTIMATE | N16: =O16-Q16 -> 9420 | O16: 9420
F17: Amount (Kshs.) | N17: =O17-Q17 -> 11154 | O17: 11154
D18: LAST ACCOUNT B/F | E18: kshs. | F18: =meter!J16 -> 0 | N18: =O18-Q18 -> 10430 | O18: 10430
N19: =O19-Q19 -> 11831 | O19: 11831
D20: MONTH BILL | E20: KSHS. | F20: =meter!H16 -> 1900 | N20: =O20-Q20 -> 10590 | O20: 10590
N21: =O21-Q21 -> 22423 | O21: 22423
N22: =O22-Q22 -> 9250 | O22: 9250
N23: =O23-Q23 -> 10162 | O23: 10162
N24: =O24-Q24 -> 10270 | O24: 10270
N25: =O25-Q25 -> 11070 | O25: 11070
N26: =O26-Q26 -> 11550 | O26: 11550
N27: =O27-Q27 -> 11393 | O27: 11393
N28: =O28-Q28 -> 10802 | O28: 10802
N29: =O29-Q29 -> 8930 | O29: 8930
D30: TOTAL PAYABLE | E30: Kshs. | F30: =SUM(F17:F29) -> 1900 | N30: =O30-Q30 -> 9570 | O30: 9570
N31: =O31-Q31 -> 11390 | O31: 11390
D32: PAID | F32: =meter!L16 -> 0 | N32: =O32-Q32 -> 10750 | O32: 10750
N33: =O33-Q33 -> 11732 | O33: 11732
D34: AMOUNT DUE | F34: =F30-F32 -> 1900 | N34: =O34-Q34 -> 10934 | O34: 10934 | R34: 700
C35: NOTE | N35: =O35-Q35 -> 10270 | O35: 10270
A36: a) | B36: KINDLY PAY FOR WATER LATEST BY 5TH OF THE MONTH AND FORWARD SMS OR WHATSAPP TO 0702325121 | N36: =O36-Q36 -> 10598 | O36: 10598
A37: b) | N37: =O37-Q37 -> 8770 | O37: 8770
N38: =O38-Q38 -> 8770 | O38: 8770
A39: c) | O39: =SUM(O3:O38) -> 391268 | Q39: =SUM(Q3:Q38) -> 0
A41: d)
A42: e)
A43: f)
B47: PAYBILL 4139271 ACC NO KSJ 4
O49: ……………
A50: g)

Sheet NAMBOKAH
B2: SAMEDHA BOREHOLE | N2: VAR | O2: TAX DUE
B3: ='FROM BOREHOLE'!B3 -> P.O BOX 9473-00200 NAIROBI | N3: =O3-Q3 -> 10270 | O3: 10270
B4: WATER BILL | H4: BILL NO. | I4: ='FROM BOREHOLE'!H4+15-1 -> 20242015 | J4: ='FROM BOREHOLE'!H4+15-1 -> 20242015 | N4: =O4-Q4 -> 10304 | O4: 10304
N5: =O5-Q5 -> 10988 | O5: 10988
B6: NAME | D6: =meter!A17 -> NAMBOKAH | N6: =O6-Q6 -> 11070 | O6: 11070
N7: =O7-Q7 -> 1197 | O7: 1197
N8: =O8-Q8 -> 9250 | O8: 9250
N9: =O9-Q9 -> 8770 | O9: 8770
B10: ISSUE DATE | D10: ='FROM BOREHOLE'!C10 -> 29TH JAN 2025 | N10: =O10-Q10 -> 23190 | O10: 23190
N11: =O11-Q11 -> 10910 | O11: 10910
B12: LAST PAY DATE | D12: ='FROM BOREHOLE'!C12 -> 5TH FEB 2026 | N12: =O12-Q12 -> 10910 | O12: 10910
N13: =O13-Q13 -> 12190 | O13: 12190
N14: =O14-Q14 -> 11070 | O14: 11070
B15: PREVIOUS READING | D15: CURRENT READING | F15: CONSUMPTION | N15: =O15-Q15 -> 9090 | O15: 9090
B16: =meter!D17 -> 152 | D16: =meter!E17 -> 0 | E16: Units | F16: =D16-B16 -> -152 | N16: =O16-Q16 -> 9420 | O16: 9420
F17: Amount (Kshs) | N17: =O17-Q17 -> 11154 | O17: 11154
D18: LAST ACCOUNT B/F | E18: kshs. | F18: =meter!J17 -> 0 | N18: =O18-Q18 -> 10430 | O18: 10430
N19: =O19-Q19 -> 11831 | O19: 11831
D20: MONTH BILL | E20: KSHS. | F20: =meter!H17 -> -15200 | N20: =O20-Q20 -> 10590 | O20: 10590
N21: =O21-Q21 -> 22423 | O21: 22423
N22: =O22-Q22 -> 9250 | O22: 9250
N23: =O23-Q23 -> 10162 | O23: 10162
N24: =O24-Q24 -> 10270 | O24: 10270
N25: =O25-Q25 -> 11070 | O25: 11070
N26: =O26-Q26 -> 11550 | O26: 11550
N27: =O27-Q27 -> 11393 | O27: 11393
N28: =O28-Q28 -> 10802 | O28: 10802
N29: =O29-Q29 -> 8930 | O29: 8930
C30: TOTAL PAYABLE | D30: AMOUNT PAYABLE | E30: Kshs. | F30: =SUM(F17:F29) -> -15200 | N30: =O30-Q30 -> 9570 | O30: 9570
N31: =O31-Q31 -> 11390 | O31: 11390
C32: PAID | E32: KSHS | F32: =meter!L17 -> 0 | N32: =O32-Q32 -> 10750 | O32: 10750
N33: =O33-Q33 -> 11732 | O33: 11732
C34: BALANCE C/F | D34: AMOUNT DUE | E34: KSHS. | F34: =F30-F32 -> -15200 | N34: =O34-Q34 -> 10934 | O34: 10934 | R34: 700
B35: NOTE | N35: =O35-Q35 -> 10270 | O35: 10270
A36: a) | B36: KINDLY PAY FOR WATER LATEST BY 5TH OF THE MONTH AND FORWARD SMS OR WHATSAPP TO 0702325121 | N36: =O36-Q36 -> 10598 | O36: 10598
A37: b) | N37: =O37-Q37 -> 8770 | O37: 8770
N38: =O38-Q38 -> 8770 | O38: 8770
A39: c) | O39: =SUM(O3:O38) -> 391268 | Q39: =SUM(Q3:Q38) -> 0
A41: d)
A42: e)
A43: f)
B47: PAYBLL 4139271 ACC NO KSJ 5
O49: ……………

Sheet KIMANI
B2: SAMEDHA BOREHOLE | N2: VAR | O2: TAX DUE
B3: ='FROM BOREHOLE'!B3 -> P.O BOX 9473-00200 NAIROBI | N3: =O3-Q3 -> 10270 | O3: 10270
B4: WATER BILL | H4: BILL NO. | I4: ='FROM BOREHOLE'!H4+16-1 -> 20242016 | M4: ='FROM BOREHOLE'!H4+16-1 -> 20242016 | N4: =O4-Q4 -> 10304 | O4: 10304
N5: =O5-Q5 -> 10988 | O5: 10988
B6: NAME | D6: =meter!A18 -> KIMANI | N6: =O6-Q6 -> 11070 | O6: 11070
N7: =O7-Q7 -> 1197 | O7: 1197
N8: =O8-Q8 -> 9250 | O8: 9250
N9: =O9-Q9 -> 8770 | O9: 8770
B10: ISSUE DATE | D10: ='FROM BOREHOLE'!C10 -> 29TH JAN 2025 | N10: =O10-Q10 -> 23190 | O10: 23190
N11: =O11-Q11 -> 10910 | O11: 10910
B12: LAST PAY DATE | D12: ='FROM BOREHOLE'!C12 -> 5TH FEB 2026 | N12: =O12-Q12 -> 10910 | O12: 10910
N13: =O13-Q13 -> 12190 | O13: 12190
N14: =O14-Q14 -> 11070 | O14: 11070
B15: PREVIOUS READING | D15: CURRENT READING | F15: CONSUMPTION | N15: =O15-Q15 -> 9090 | O15: 9090
B16: =meter!D18 -> 33 | D16: =meter!E18 -> 41 | E16: Units | F16: =D16-B16 -> 8 | N16: =O16-Q16 -> 9420 | O16: 9420
F17: Amount (Kshs.) | N17: =O17-Q17 -> 11154 | O17: 11154
D18: LAST ACCOUNT B/F | E18: kshs. | F18: =meter!J18 -> 0 | N18: =O18-Q18 -> 10430 | O18: 10430
N19: =O19-Q19 -> 11831 | O19: 11831
D20: MONTH BILL | E20: KSHS. | F20: =meter!H18 -> 800 | N20: =O20-Q20 -> 10590 | O20: 10590
N21: =O21-Q21 -> 22423 | O21: 22423
N22: =O22-Q22 -> 9250 | O22: 9250
N23: =O23-Q23 -> 10162 | O23: 10162
N24: =O24-Q24 -> 10270 | O24: 10270
N25: =O25-Q25 -> 11070 | O25: 11070
N26: =O26-Q26 -> 11550 | O26: 11550
N27: =O27-Q27 -> 11393 | O27: 11393
N28: =O28-Q28 -> 10802 | O28: 10802
N29: =O29-Q29 -> 8930 | O29: 8930
D30: TOTAL PAYABLE | E30: Kshs. | F30: =SUM(F17:F29) -> 800 | N30: =O30-Q30 -> 9570 | O30: 9570
N31: =O31-Q31 -> 11390 | O31: 11390
D32: PAID | F32: =meter!L18 -> 0 | N32: =O32-Q32 -> 10750 | O32: 10750
N33: =O33-Q33 -> 11732 | O33: 11732
D34: AMOUNT DUE | F34: =F30-F32 -> 800 | N34: =O34-Q34 -> 10934 | O34: 10934 | R34: 700
C35: NOTE | N35: =O35-Q35 -> 10270 | O35: 10270
A36: a) | B36: KINDLY PAY FOR WATER LATEST BY 5TH OF THE MONTH AND FORWARD SMS OR WHATSAPP TO 0702325121 | N36: =O36-Q36 -> 10598 | O36: 10598
A37: b) | N37: =O37-Q37 -> 8770 | O37: 8770
N38: =O38-Q38 -> 8770 | O38: 8770
A39: c) | O39: =SUM(O3:O38) -> 391268 | Q39: =SUM(Q3:Q38) -> 0
A41: d)
A42: e)
A43: f)
B47: PAYBILL 4139271 ACC NO KSJ 6
O49: ……………
A50: g)

Sheet AGNES
B2: SAMEDHA BOREHOLE | N2: VAR | O2: TAX DUE
B3: ='FROM BOREHOLE'!B3 -> P.O BOX 9473-00200 NAIROBI | N3: =O3-Q3 -> 10270 | O3: 10270
B4: WATER BILL | H4: BILL NO. | I4: ='FROM BOREHOLE'!H4+17-1 -> 20242017 | J4: ='FROM BOREHOLE'!H4+17-1 -> 20242017 | N4: =O4-Q4 -> 10304 | O4: 10304
N5: =O5-Q5 -> 10988 | O5: 10988
B6: NAME | D6: =meter!A19 -> Agnes | N6: =O6-Q6 -> 11070 | O6: 11070
N7: =O7-Q7 -> 1197 | O7: 1197
N8: =O8-Q8 -> 9250 | O8: 9250
N9: =O9-Q9 -> 8770 | O9: 8770
B10: ISSUE DATE | D10: ='FROM BOREHOLE'!C10 -> 29TH JAN 2025 | N10: =O10-Q10 -> 23190 | O10: 23190
N11: =O11-Q11 -> 10910 | O11: 10910
B12: LAST PAY DATE | D12: ='FROM BOREHOLE'!C12 -> 5TH FEB 2026 | N12: =O12-Q12 -> 10910 | O12: 10910
N13: =O13-Q13 -> 12190 | O13: 12190
N14: =O14-Q14 -> 11070 | O14: 11070
B15: PREVIOUS READING | D15: CURRENT READING | F15: CONSUMPTION | N15: =O15-Q15 -> 9090 | O15: 9090
B16: =meter!D19 -> 14 | D16: =meter!E19 -> 14 | E16: Units | F16: =D16-B16 -> 0 | N16: =O16-Q16 -> 9420 | O16: 9420
F17: Amount (Kshs.) | N17: =O17-Q17 -> 11154 | O17: 11154
D18: LAST ACCOUNT B/F | E18: kshs. | F18: =meter!J19 -> 0 | N18: =O18-Q18 -> 10430 | O18: 10430
N19: =O19-Q19 -> 11831 | O19: 11831
D20: MONTH BILL | E20: KSHS. | F20: =meter!H19 -> 0 | N20: =O20-Q20 -> 10590 | O20: 10590
N21: =O21-Q21 -> 22423 | O21: 22423
N22: =O22-Q22 -> 9250 | O22: 9250
N23: =O23-Q23 -> 10162 | O23: 10162
N24: =O24-Q24 -> 10270 | O24: 10270
N25: =O25-Q25 -> 11070 | O25: 11070
N26: =O26-Q26 -> 11550 | O26: 11550
N27: =O27-Q27 -> 11393 | O27: 11393
N28: =O28-Q28 -> 10802 | O28: 10802
N29: =O29-Q29 -> 8930 | O29: 8930
D30: TOTAL PAYABLE | E30: Kshs. | F30: =SUM(F17:F29) -> 0 | N30: =O30-Q30 -> 9570 | O30: 9570
N31: =O31-Q31 -> 11390 | O31: 11390
D32: PAID | F32: =meter!L19 -> 0 | N32: =O32-Q32 -> 10750 | O32: 10750
N33: =O33-Q33 -> 11732 | O33: 11732
D34: AMOUNT DUE | F34: =F30-F32 -> 0 | N34: =O34-Q34 -> 10934 | O34: 10934 | R34: 700
C35: NOTE | N35: =O35-Q35 -> 10270 | O35: 10270
A36: a) | B36: KINDLY PAY FOR WATER LATEST BY 5TH OF THE MONTH AND FORWARD SMS OR WHATSAPP TO 0702325121 | N36: =O36-Q36 -> 10598 | O36: 10598
A37: b) | N37: =O37-Q37 -> 8770 | O37: 8770
N38: =O38-Q38 -> 8770 | O38: 8770
A39: c) | O39: =SUM(O3:O38) -> 391268 | Q39: =SUM(Q3:Q38) -> 0
A41: d)
A42: e)
A43: f)
B47: PAYBILL 4139271 ACC NO KSJ 7
O49: ……………
A50: g)

Sheet NANCY
B2: SAMEDHA BOREHOLE | N2: VAR | O2: TAX DUE
B3: ='FROM BOREHOLE'!B3 -> P.O BOX 9473-00200 NAIROBI | N3: =O3-Q3 -> 10270 | O3: 10270
B4: WATER BILL | H4: BILL NO. | I4: ='FROM BOREHOLE'!H4+18-1 -> 20242018 | K4: ='FROM BOREHOLE'!H4+18-1 -> 20242018 | N4: =O4-Q4 -> 10304 | O4: 10304
N5: =O5-Q5 -> 10988 | O5: 10988
B6: NAME | D6: =meter!A20 -> Nancy | N6: =O6-Q6 -> 11070 | O6: 11070
N7: =O7-Q7 -> 1197 | O7: 1197
N8: =O8-Q8 -> 9250 | O8: 9250
N9: =O9-Q9 -> 8770 | O9: 8770
B10: ISSUE DATE | D10: ='FROM BOREHOLE'!C10 -> 29TH JAN 2025 | N10: =O10-Q10 -> 23190 | O10: 23190
N11: =O11-Q11 -> 10910 | O11: 10910
B12: LAST PAY DATE | D12: ='FROM BOREHOLE'!C12 -> 5TH FEB 2026 | N12: =O12-Q12 -> 10910 | O12: 10910
N13: =O13-Q13 -> 12190 | O13: 12190
N14: =O14-Q14 -> 11070 | O14: 11070
B15: PREVIOUS READING | D15: CURRENT READING | F15: CONSUMPTION | N15: =O15-Q15 -> 9090 | O15: 9090
B16: =meter!D20 -> 289 | D16: =meter!E20 -> 0 | E16: Units | F16: =D16-B16 -> -289 | N16: =O16-Q16 -> 9420 | O16: 9420
F17: Amount (Kshs.) | N17: =O17-Q17 -> 11154 | O17: 11154
D18: LAST ACCOUNT B/F | E18: Kshs. | F18: =meter!J20 -> 0 | N18: =O18-Q18 -> 10430 | O18: 10430
N19: =O19-Q19 -> 11831 | O19: 11831
D20: MONTH BILL | E20: KSHS. | F20: =meter!H20 -> -28900 | N20: =O20-Q20 -> 10590 | O20: 10590
N21: =O21-Q21 -> 22423 | O21: 22423
N22: =O22-Q22 -> 9250 | O22: 9250
N23: =O23-Q23 -> 10162 | O23: 10162
N24: =O24-Q24 -> 10270 | O24: 10270
N25: =O25-Q25 -> 11070 | O25: 11070
N26: =O26-Q26 -> 11550 | O26: 11550
N27: =O27-Q27 -> 11393 | O27: 11393
N28: =O28-Q28 -> 10802 | O28: 10802
N29: =O29-Q29 -> 8930 | O29: 8930
D30: TOTAL PAYABLE | E30: Kshs. | F30: =SUM(F17:F29) -> -28900 | N30: =O30-Q30 -> 9570 | O30: 9570
N31: =O31-Q31 -> 11390 | O31: 11390
D32: PAID | F32: =meter!L20 -> 0 | N32: =O32-Q32 -> 10750 | O32: 10750
N33: =O33-Q33 -> 11732 | O33: 11732
D34: AMOUNT DUE | F34: =F30-F32 -> -28900 | N34: =O34-Q34 -> 10934 | O34: 10934 | R34: 700
C35: NOTE | N35: =O35-Q35 -> 10270 | O35: 10270
A36: a) | B36: KINDLY PAY FOR WATER LATEST BY 5TH OF THE MONTH AND FORWARD SMS OR WHATSAPP TO 0702325121 | N36: =O36-Q36 -> 10598 | O36: 10598
A37: b) | N37: =O37-Q37 -> 8770 | O37: 8770
N38: =O38-Q38 -> 8770 | O38: 8770
A39: c) | O39: =SUM(O3:O38) -> 391268 | Q39: =SUM(Q3:Q38) -> 0
A41: d)
A42: e)
A43: f)
B47: PAYBILL 4139271 ACC NO KSJ 8
O49: ……………
A50: g)

Sheet KURGAT
B2: SAMEDHA BOREHOLE | N2: VAR | O2: TAX DUE
B3: ='FROM BOREHOLE'!B3 -> P.O BOX 9473-00200 NAIROBI | N3: =O3-Q3 -> 10270 | O3: 10270
B4: WATER BILL | G4: BILL NO. | H4: ='FROM BOREHOLE'!H4+19-1 -> 20242019 | I4: ='FROM BOREHOLE'!H4+19-1 -> 20242019 | N4: =O4-Q4 -> 10304 | O4: 10304
G5: ='FROM BOREHOLE'!H4+19-1 -> 20242019 | N5: =O5-Q5 -> 10988 | O5: 10988
B6: NAME | D6: =meter!A21 -> Kurgat samson | N6: =O6-Q6 -> 11070 | O6: 11070
N7: =O7-Q7 -> 1197 | O7: 1197
N8: =O8-Q8 -> 9250 | O8: 9250
N9: =O9-Q9 -> 8770 | O9: 8770
B10: ISSUE DATE | D10: ='FROM BOREHOLE'!C10 -> 29TH JAN 2025 | N10: =O10-Q10 -> 23190 | O10: 23190
N11: =O11-Q11 -> 10910 | O11: 10910
B12: LAST PAY DATE | D12: ='FROM BOREHOLE'!C12 -> 5TH FEB 2026 | N12: =O12-Q12 -> 10910 | O12: 10910
N13: =O13-Q13 -> 12190 | O13: 12190
N14: =O14-Q14 -> 11070 | O14: 11070
B15: PREVIOUS READING | D15: CURRENT READING | F15: CONSUMPTION | N15: =O15-Q15 -> 9090 | O15: 9090
B16: =meter!D21 -> 300 | D16: =meter!E21 -> 0 | E16: Units | F16: =D16-B16+I16 -> -300 | N16: =O16-Q16 -> 9420 | O16: 9420
F17: Amount (Kshs.) | N17: =O17-Q17 -> 11154 | O17: 11154
D18: LAST ACCOUNT B/F | E18: Kshs. | F18: =meter!J21 -> 0 | N18: =O18-Q18 -> 10430 | O18: 10430
N19: =O19-Q19 -> 11831 | O19: 11831
D20: MONTH BILL | E20: KSHS. | F20: =meter!H21 -> -30000 | N20: =O20-Q20 -> 10590 | O20: 10590
N21: =O21-Q21 -> 22423 | O21: 22423
N22: =O22-Q22 -> 9250 | O22: 9250
N23: =O23-Q23 -> 10162 | O23: 10162
N24: =O24-Q24 -> 10270 | O24: 10270
N25: =O25-Q25 -> 11070 | O25: 11070
N26: =O26-Q26 -> 11550 | O26: 11550
N27: =O27-Q27 -> 11393 | O27: 11393
N28: =O28-Q28 -> 10802 | O28: 10802
N29: =O29-Q29 -> 8930 | O29: 8930
D30: TOTAL PAYABLE | E30: Kshs. | F30: =SUM(F17:F29) -> -30000 | N30: =O30-Q30 -> 9570 | O30: 9570
N31: =O31-Q31 -> 11390 | O31: 11390
D32: PAID | F32: =meter!L21 -> 0 | N32: =O32-Q32 -> 10750 | O32: 10750
N33: =O33-Q33 -> 11732 | O33: 11732
D34: AMOUNT DUE | F34: =F30-F32 -> -30000 | N34: =O34-Q34 -> 10934 | O34: 10934 | R34: 700
C35: NOTE | N35: =O35-Q35 -> 10270 | O35: 10270
A36: a) | B36: KINDLY PAY FOR WATER LATEST BY 5TH OF THE MONTH AND FORWARD SMS OR WHATSAPP TO 0702325121 | N36: =O36-Q36 -> 10598 | O36: 10598
A37: b) | N37: =O37-Q37 -> 8770 | O37: 8770
N38: =O38-Q38 -> 8770 | O38: 8770
A39: c) | O39: =SUM(O3:O38) -> 391268 | Q39: =SUM(Q3:Q38) -> 0
A41: d)
A42: e)
A43: f)
B47: PAYBILL 4139271 ACC NO KSJ 10
O49: ……………
A50: g)
R58: A

Sheet JANE 
B2: SAMEDHA BOREHOLE | N2: VAR | O2: TAX DUE
B3: ='FROM BOREHOLE'!B3 -> P.O BOX 9473-00200 NAIROBI | N3: =O3-Q3 -> 10270 | O3: 10270
B4: WATER BILL | H4: BILL NO. | I4: ='FROM BOREHOLE'!H4+20-1 -> 20242020 | J4: ='FROM BOREHOLE'!H4+20-1 -> 20242020 | N4: =O4-Q4 -> 10304 | O4: 10304
N5: =O5-Q5 -> 10988 | O5: 10988
B6: NAME | D6: =meter!A22 -> Jane Mwangi | N6: =O6-Q6 -> 11070 | O6: 11070
N7: =O7-Q7 -> 1197 | O7: 1197
N8: =O8-Q8 -> 9250 | O8: 9250
N9: =O9-Q9 -> 8770 | O9: 8770
B10: ISSUE DATE | D10: ='FROM BOREHOLE'!C10 -> 29TH JAN 2025 | N10: =O10-Q10 -> 23190 | O10: 23190
N11: =O11-Q11 -> 10910 | O11: 10910
B12: LAST PAY DATE | D12: ='FROM BOREHOLE'!C12 -> 5TH FEB 2026 | N12: =O12-Q12 -> 10910 | O12: 10910
N13: =O13-Q13 -> 12190 | O13: 12190
N14: =O14-Q14 -> 11070 | O14: 11070
B15: PREVIOUS READING | D15: CURRENT READING | F15: CONSUMPTION | N15: =O15-Q15 -> 9090 | O15: 9090
B16: =meter!D22 -> 264 | D16: =meter!E22 -> 278 | E16: Units | F16: =D16-B16 -> 14 | N16: =O16-Q16 -> 9420 | O16: 9420
N17: =O17-Q17 -> 11154 | O17: 11154
D18: LAST ACCOUNT B/F | E18: Kshs. | F18: =meter!J22 -> 0 | N18: =O18-Q18 -> 10430 | O18: 10430
N19: =O19-Q19 -> 11831 | O19: 11831
D20: MONTH BILL | E20: KSHS. | F20: =meter!H22 -> 1400 | N20: =O20-Q20 -> 10590 | O20: 10590
N21: =O21-Q21 -> 22423 | O21: 22423
N22: =O22-Q22 -> 9250 | O22: 9250
N23: =O23-Q23 -> 10162 | O23: 10162
N24: =O24-Q24 -> 10270 | O24: 10270
N25: =O25-Q25 -> 11070 | O25: 11070
N26: =O26-Q26 -> 11550 | O26: 11550
N27: =O27-Q27 -> 11393 | O27: 11393
N28: =O28-Q28 -> 10802 | O28: 10802
N29: =O29-Q29 -> 8930 | O29: 8930
D30: TOTAL PAYABLE | E30: Kshs. | F30: =SUM(F17:F29) -> 1400 | N30: =O30-Q30 -> 9570 | O30: 9570
N31: =O31-Q31 -> 11390 | O31: 11390
D32: PAID | N32: =O32-Q32 -> 10750 | O32: 10750
N33: =O33-Q33 -> 11732 | O33: 11732
D34: AMOUNT DUE | F34: =F30-F32 -> 1400 | N34: =O34-Q34 -> 10934 | O34: 10934 | R34: 700
C35: NOTE | N35: =O35-Q35 -> 10270 | O35: 10270
A36: a) | B36: KINDLY PAY FOR WATER LATEST BY 5TH OF THE MONTH AND FORWARD SMS OR WHATSAPP TO 0702325121 | N36: =O36-Q36 -> 10598 | O36: 10598
A37: b) | N37: =O37-Q37 -> 8770 | O37: 8770
N38: =O38-Q38 -> 8770 | O38: 8770
A39: c) | O39: =SUM(O3:O38) -> 391268 | Q39: =SUM(Q3:Q38) -> 0
A41: d)
A42: e)
A43: f)
B47: PAYBILL 4139271 ACC NO KSJ 11
O49: ……………
A50: g)

Sheet BRIAN
B2: SAMEDHA BOREHOLE | N2: VAR | O2: TAX DUE
B3: ='FROM BOREHOLE'!B3 -> P.O BOX 9473-00200 NAIROBI | N3: =O3-Q3 -> 10270 | O3: 10270
B4: WATER BILL | H4: BILL NO. | I4: ='FROM BOREHOLE'!H4+21-1 -> 20242021 | L4: ='FROM BOREHOLE'!H4+21-1 -> 20242021 | N4: =O4-Q4 -> 10304 | O4: 10304
N5: =O5-Q5 -> 10988 | O5: 10988
B6: NAME | D6: =meter!A23 -> Brian murithi | N6: =O6-Q6 -> 11070 | O6: 11070
N7: =O7-Q7 -> 1197 | O7: 1197
N8: =O8-Q8 -> 9250 | O8: 9250
N9: =O9-Q9 -> 8770 | O9: 8770
B10: ISSUE DATE | D10: ='FROM BOREHOLE'!C10 -> 29TH JAN 2025 | N10: =O10-Q10 -> 23190 | O10: 23190
N11: =O11-Q11 -> 10910 | O11: 10910
B12: LAST PAY DATE | D12: ='FROM BOREHOLE'!C12 -> 5TH FEB 2026 | N12: =O12-Q12 -> 10910 | O12: 10910
N13: =O13-Q13 -> 12190 | O13: 12190
N14: =O14-Q14 -> 11070 | O14: 11070
B15: PREVIOUS READING | D15: CURRENT READING | F15: CONSUMPTION | N15: =O15-Q15 -> 9090 | O15: 9090
B16: =meter!D23 -> 1164 | D16: =meter!E23 -> 1184 | E16: Units | F16: =D16-B16 -> 20 | N16: =O16-Q16 -> 9420 | O16: 9420
F17: Amount (Kshs.) | N17: =O17-Q17 -> 11154 | O17: 11154
D18: LAST ACCOUNT B/F | E18: Kshs. | F18: =meter!J23 -> 0 | N18: =O18-Q18 -> 10430 | O18: 10430
N19: =O19-Q19 -> 11831 | O19: 11831
D20: MONTH BILL | E20: KSHS. | F20: =meter!H23 -> 2000 | N20: =O20-Q20 -> 10590 | O20: 10590
N21: =O21-Q21 -> 22423 | O21: 22423
N22: =O22-Q22 -> 9250 | O22: 9250
N23: =O23-Q23 -> 10162 | O23: 10162
N24: =O24-Q24 -> 10270 | O24: 10270
N25: =O25-Q25 -> 11070 | O25: 11070
N26: =O26-Q26 -> 11550 | O26: 11550
N27: =O27-Q27 -> 11393 | O27: 11393
N28: =O28-Q28 -> 10802 | O28: 10802
N29: =O29-Q29 -> 8930 | O29: 8930
D30: TOTAL PAYABLE | E30: Kshs. | F30: =SUM(F17:F29) -> 2000 | N30: =O30-Q30 -> 9570 | O30: 9570
N31: =O31-Q31 -> 11390 | O31: 11390
D32: PAID | F32: =meter!L23 -> 0 | N32: =O32-Q32 -> 10750 | O32: 10750
N33: =O33-Q33 -> 11732 | O33: 11732
D34: AMOUNT DUE | F34: =F30-F32 -> 2000 | N34: =O34-Q34 -> 10934 | O34: 10934 | R34: 700
C35: NOTE | N35: =O35-Q35 -> 10270 | O35: 10270
A36: a) | B36: KINDLY PAY FOR WATER LATEST BY 5TH OF THE MONTH AND FORWARD SMS OR WHATSAPP TO 0702325121 | N36: =O36-Q36 -> 10598 | O36: 10598
A37: b) | N37: =O37-Q37 -> 8770 | O37: 8770
N38: =O38-Q38 -> 8770 | O38: 8770
A39: c) | O39: =SUM(O3:O38) -> 391268 | Q39: =SUM(Q3:Q38) -> 0
A41: d)
A42: e)
A43: f)
B47: PAY BLL 4139271 ACC NO KSJ 12
O49: ……………
A50: g)

Sheet UKA
B2: SAMEDHA BOREHOLE | N2: VAR | O2: TAX DUE
B3: ='FROM BOREHOLE'!B3 -> P.O BOX 9473-00200 NAIROBI | N3: =O3-Q3 -> 10270 | O3: 10270
B4: WATER BILL | H4: BILL NO. | I4: ='FROM BOREHOLE'!H4+22-1 -> 20242022 | J4: ='FROM BOREHOLE'!H4+22-1 -> 20242022 | N4: =O4-Q4 -> 10304 | O4: 10304
N5: =O5-Q5 -> 10988 | O5: 10988
B6: NAME | D6: =meter!A24 -> Daniel uka | N6: =O6-Q6 -> 11070 | O6: 11070
N7: =O7-Q7 -> 1197 | O7: 1197
N8: =O8-Q8 -> 9250 | O8: 9250
N9: =O9-Q9 -> 8770 | O9: 8770
B10: ISSUE DATE | D10: ='FROM BOREHOLE'!C10 -> 29TH JAN 2025 | N10: =O10-Q10 -> 23190 | O10: 23190
N11: =O11-Q11 -> 10910 | O11: 10910
B12: LAST PAY DATE | D12: ='FROM BOREHOLE'!C12 -> 5TH FEB 2026 | N12: =O12-Q12 -> 10910 | O12: 10910
N13: =O13-Q13 -> 12190 | O13: 12190
N14: =O14-Q14 -> 11070 | O14: 11070
B15: PREVIOUS READING | D15: CURRENT READING | F15: CONSUMPTION | N15: =O15-Q15 -> 9090 | O15: 9090
B16: =meter!D24 -> 820 | D16: =meter!E24 -> 836 | E16: Units | F16: =D16-B16 -> 16 | N16: =O16-Q16 -> 9420 | O16: 9420
F17: Amount (Kshs.) | N17: =O17-Q17 -> 11154 | O17: 11154
D18: LAST ACCOUNT B/F | E18: Kshs. | F18: =meter!J24 -> 0 | N18: =O18-Q18 -> 10430 | O18: 10430
N19: =O19-Q19 -> 11831 | O19: 11831
D20: MONTH BILL | E20: KSHS. | F20: =meter!H24 -> 1600 | N20: =O20-Q20 -> 10590 | O20: 10590
N21: =O21-Q21 -> 22423 | O21: 22423
N22: =O22-Q22 -> 9250 | O22: 9250
N23: =O23-Q23 -> 10162 | O23: 10162
N24: =O24-Q24 -> 10270 | O24: 10270
N25: =O25-Q25 -> 11070 | O25: 11070
N26: =O26-Q26 -> 11550 | O26: 11550
N27: =O27-Q27 -> 11393 | O27: 11393
N28: =O28-Q28 -> 10802 | O28: 10802
N29: =O29-Q29 -> 8930 | O29: 8930
D30: TOTAL PAYABLE | E30: Kshs. | F30: =SUM(F17:F29) -> 1600 | N30: =O30-Q30 -> 9570 | O30: 9570
N31: =O31-Q31 -> 11390 | O31: 11390
D32: PAID | F32: =meter!L24 -> 0 | N32: =O32-Q32 -> 10750 | O32: 10750
N33: =O33-Q33 -> 11732 | O33: 11732
D34: AMOUNT DUE | F34: =F30-F32 -> 1600 | N34: =O34-Q34 -> 10934 | O34: 10934 | R34: 700
C35: NOTE | N35: =O35-Q35 -> 10270 | O35: 10270
A36: a) | B36: KINDLY PAY FOR WATER LATEST BY 5TH OF THE MONTH AND FORWARD SMS OR WHATSAPP TO 0702325121 | N36: =O36-Q36 -> 10598 | O36: 10598
A37: b) | N37: =O37-Q37 -> 8770 | O37: 8770
N38: =O38-Q38 -> 8770 | O38: 8770
A39: c) | B39: PAYBILL 4139271 ACC NO KSJ 13 | O39: =SUM(O3:O38) -> 391268 | Q39: =SUM(Q3:Q38) -> 0
A41: d)
A42: e)
A43: f)
O49: ……………
A50: g)

Sheet DANSTON
B1: OLE SAMEDHA APARTMENTS-Kitengela
B2: ='FROM BOREHOLE'!B3 -> P.O BOX 9473-00200 NAIROBI | D2: SAMEDHA BOREHOLE | N2: VAR | O2: TAX DUE
B3: WATER BILL | N3: =O3-Q3 -> 10270 | O3: 10270
H4: BILL NO. | I4: ='FROM BOREHOLE'!H4+23-1 -> 20242023 | K4: ='FROM BOREHOLE'!H4+23-1 -> 20242023 | N4: =O4-Q4 -> 10304 | O4: 10304
N5: =O5-Q5 -> 10988 | O5: 10988
A6: NAME | B6: TENANT NAME | D6: =meter!A25 -> Danstone amaitsa | N6: =O6-Q6 -> 11070 | O6: 11070
N7: =O7-Q7 -> 1197 | O7: 1197
B8: HOUSE NUMBER | N8: =O8-Q8 -> 9250 | O8: 9250
N9: =O9-Q9 -> 8770 | O9: 8770
A10: ISUE DATE | B10: ISSUE DATE | D10: ='FROM BOREHOLE'!C10 -> 29TH JAN 2025 | N10: =O10-Q10 -> 23190 | O10: 23190
N11: =O11-Q11 -> 10910 | O11: 10910
A12: LAST PDY | B12: LAST PAY DATE | D12: ='FROM BOREHOLE'!C12 -> 5TH FEB 2026 | N12: =O12-Q12 -> 10910 | O12: 10910
N13: =O13-Q13 -> 12190 | O13: 12190
N14: =O14-Q14 -> 11070 | O14: 11070
B15: PREVIOUS READING | D15: CURRENT READING | F15: CONSUMPTION | N15: =O15-Q15 -> 9090 | O15: 9090
B16: =meter!D25 -> 724 | D16: =meter!E25 -> 796 | E16: Units | F16: =D16-B16 -> 72 | N16: =O16-Q16 -> 9420 | O16: 9420
F17: Amount (Kshs.) | N17: =O17-Q17 -> 11154 | O17: 11154
D18: LAST ACCOUNT B/F | E18: Kshs. | F18: =meter!J25 -> 3400 | N18: =O18-Q18 -> 10430 | O18: 10430
N19: =O19-Q19 -> 11831 | O19: 11831
D20: MONTH BILL | F20: =meter!H25 -> 7200 | N20: =O20-Q20 -> 10590 | O20: 10590
N21: =O21-Q21 -> 22423 | O21: 22423
N22: =O22-Q22 -> 9250 | O22: 9250
N23: =O23-Q23 -> 10162 | O23: 10162
N24: =O24-Q24 -> 10270 | O24: 10270
N25: =O25-Q25 -> 11070 | O25: 11070
N26: =O26-Q26 -> 11550 | O26: 11550
N27: =O27-Q27 -> 11393 | O27: 11393
N28: =O28-Q28 -> 10802 | O28: 10802
N29: =O29-Q29 -> 8930 | O29: 8930
D30: TOTAL PAYABLE | E30: Kshs. | F30: =SUM(F17:F29) -> 10600 | N30: =O30-Q30 -> 9570 | O30: 9570
N31: =O31-Q31 -> 11390 | O31: 11390
D32: PAID | F32: =meter!L25 -> 0 | N32: =O32-Q32 -> 10750 | O32: 10750
N33: =O33-Q33 -> 11732 | O33: 11732
D34: AMOUNT DUE | F34: =F30-F32 -> 10600 | N34: =O34-Q34 -> 10934 | O34: 10934 | R34: 700
C35: NOTE | N35: =O35-Q35 -> 10270 | O35: 10270
A36: a) | B36: Rent is due on or before 5th of the month. By 7th day, any rent not paid will attract interest at 2% per day. | C36: KINDLY PAY FOR WATER LATEST BY 5TH OF THE MONTH AND FORWARD SMS OR WHATSAPP TO 0702325121 | O36: 10598
A37: b) | B37: Any default in Rent payment by 10th of the following month the house shall be locked without notice and belongings removed for re-letting. | O37: 8770
O38: 8770
A39: c) | B39: Amounts not cleared by last pay date will render to water disconnection. | O39: =SUM(O3:O38) -> 391268 | Q39: =SUM(Q3:Q38) -> 0
A41: d) | B41: A reconnection fee of Kshs. 1,000 will be charged and paid before supply is reconnected.
A42: e) | B42: ANY MINOR REPAIRS OCCURING AFTER 3 MONTHS OF OCCUPANCY ARE TENANT'S RESPONSIBILITY AS PER TENANCY AGREEMENT.
A43: f) | B43: The water bills are payable through the same account for monthly rent strictly through:
B44: Frebazeth Company Limited
B45: Consolidated Bank Account
B46: Kitengela Branch
B47: A/C NO. 10171202000107 | C47: PAYBILL 4139271 ACC NO KSJ 14
B48: (Kindly indicate your Name & House number on the deposit slip & inform the Bank teller to capture it.)
B49: A receipt will be issued upon bank confirmation of the transaction. | O49: ……………
A50: g) | B50: MPESA, PAYBILL CONSOL BANK 508400 A/C NO. 10171202000107, Add 40/= for charges
B51: E & O E
B52: NB: Kindly give the management atleast two (2) months prior notice incase you intend to terminate the tenancy for ease of logisitics.

Sheet ERICK
B1: SAMEDHA BOREHOLE
B2: ='FROM BOREHOLE'!B3 -> P.O BOX 9473-00200 NAIROBI | N2: VAR | O2: TAX DUE
B3: WATER BILL | N3: =O3-Q3 -> 10270 | O3: 10270
H4: BILL NO. | I4: ='FROM BOREHOLE'!H4+24-1 -> 20242024 | M4: ='FROM BOREHOLE'!H4+24-1 -> 20242024 | N4: =O4-Q4 -> 10304 | O4: 10304
N5: =O5-Q5 -> 10988 | O5: 10988
B6: NAME | D6: =meter!A26 -> Eric | N6: =O6-Q6 -> 11070 | O6: 11070
N7: =O7-Q7 -> 1197 | O7: 1197
N8: =O8-Q8 -> 9250 | O8: 9250
N9: =O9-Q9 -> 8770 | O9: 8770
B10: ISSUE DATE | D10: ='FROM BOREHOLE'!C10 -> 29TH JAN 2025 | N10: =O10-Q10 -> 23190 | O10: 23190
N11: =O11-Q11 -> 10910 | O11: 10910
B12: LAST PAY DATE | D12: ='FROM BOREHOLE'!C12 -> 5TH FEB 2026 | N12: =O12-Q12 -> 10910 | O12: 10910
N13: =O13-Q13 -> 12190 | O13: 12190
N14: =O14-Q14 -> 11070 | O14: 11070
B15: PREVIOUS READING | D15: CURRENT READING | F15: CONSUMPTION | N15: =O15-Q15 -> 9090 | O15: 9090
B16: =meter!D26 -> 155 | D16: =meter!E26 -> 159 | E16: Units | F16: =D16-B16 -> 4 | N16: =O16-Q16 -> 9420 | O16: 9420
F17: Amount (Kshs.) | N17: =O17-Q17 -> 11154 | O17: 11154
D18: LAST ACCOUNT B/F | E18: Kshs. | F18: =meter!J26 -> 0 | N18: =O18-Q18 -> 10430 | O18: 10430
N19: =O19-Q19 -> 11831 | O19: 11831
D20: MONTH BILL | E20: KSHS. | F20: =meter!H26 -> 400 | N20: =O20-Q20 -> 10590 | O20: 10590
N21: =O21-Q21 -> 22423 | O21: 22423
N22: =O22-Q22 -> 9250 | O22: 9250
N23: =O23-Q23 -> 10162 | O23: 10162
N24: =O24-Q24 -> 10270 | O24: 10270
N25: =O25-Q25 -> 11070 | O25: 11070
N26: =O26-Q26 -> 11550 | O26: 11550
N27: =O27-Q27 -> 11393 | O27: 11393
N28: =O28-Q28 -> 10802 | O28: 10802
N29: =O29-Q29 -> 8930 | O29: 8930
D30: TOTAL PAYABLE | E30: Kshs. | F30: =SUM(F17:F29) -> 400 | N30: =O30-Q30 -> 9570 | O30: 9570
N31: =O31-Q31 -> 11390 | O31: 11390
D32: PAID | F32: =meter!L26 -> 0 | N32: =O32-Q32 -> 10750 | O32: 10750
N33: =O33-Q33 -> 11732 | O33: 11732
D34: AMOUNT DUE | F34: =F30-F32 -> 400 | N34: =O34-Q34 -> 10934 | O34: 10934 | R34: 700
C35: NOTE | N35: =O35-Q35 -> 10270 | O35: 10270
A36: a) | B36: KINDLY PAY FOR WATER LATEST BY 5TH OF THE MONTH AND FORWARD SMS OR WHATSAPP TO 0702325121 | N36: =O36-Q36 -> 10598 | O36: 10598
A37: b) | N37: =O37-Q37 -> 8770 | O37: 8770
N38: =O38-Q38 -> 8770 | O38: 8770
A39: c) | O39: =SUM(O3:O38) -> 391268 | Q39: =SUM(Q3:Q38) -> 0
A41: d)
A42: e)
A43: f)
B47: PAY BLL 4139271 ACC NO KSJ 15
O49: ……………
A50: g)

Sheet PAMELA
B1: SAMEDHA BOREHOLE
B2: ='FROM BOREHOLE'!B3 -> P.O BOX 9473-00200 NAIROBI | N2: VAR | O2: TAX DUE
B3: WATER BILL | N3: =O3-Q3 -> 10270 | O3: 10270
H4: BILL NO. | I4: ='FROM BOREHOLE'!H4+25-1 -> 20242025 | K4: ='FROM BOREHOLE'!H4+25-1 -> 20242025 | N4: =O4-Q4 -> 10304 | O4: 10304
N5: =O5-Q5 -> 10988 | O5: 10988
B6: NAME | D6: =meter!A27 -> Pamela | N6: =O6-Q6 -> 11070 | O6: 11070
N7: =O7-Q7 -> 1197 | O7: 1197
N8: =O8-Q8 -> 9250 | O8: 9250
N9: =O9-Q9 -> 8770 | O9: 8770
B10: ISSUE DATE | D10: ='FROM BOREHOLE'!C10 -> 29TH JAN 2025 | N10: =O10-Q10 -> 23190 | O10: 23190
N11: =O11-Q11 -> 10910 | O11: 10910
B12: LAST PAY DATE | D12: ='FROM BOREHOLE'!C12 -> 5TH FEB 2026 | N12: =O12-Q12 -> 10910 | O12: 10910
N13: =O13-Q13 -> 12190 | O13: 12190
N14: =O14-Q14 -> 11070 | O14: 11070
B15: PREVIOUS READING | D15: CURRENT READING | F15: CONSUMPTION | N15: =O15-Q15 -> 9090 | O15: 9090
B16: =meter!D27 -> 217 | C16: 643 | D16: =meter!E27 -> 223 | E16: Units | F16: =D16-B16 -> 6 | N16: =O16-Q16 -> 9420 | O16: 9420
F17: Amount (Kshs.) | N17: =O17-Q17 -> 11154 | O17: 11154
D18: LAST ACCOUNT B/F | E18: Kshs. | F18: =meter!J27 -> 0 | N18: =O18-Q18 -> 10430 | O18: 10430
N19: =O19-Q19 -> 11831 | O19: 11831
D20: MONTH BILL | E20: KSHS. | F20: =meter!H27 -> 600 | N20: =O20-Q20 -> 10590 | O20: 10590
N21: =O21-Q21 -> 22423 | O21: 22423
N22: =O22-Q22 -> 9250 | O22: 9250
N23: =O23-Q23 -> 10162 | O23: 10162
N24: =O24-Q24 -> 10270 | O24: 10270
N25: =O25-Q25 -> 11070 | O25: 11070
N26: =O26-Q26 -> 11550 | O26: 11550
N27: =O27-Q27 -> 11393 | O27: 11393
F28: =IF(F18*4%*1<0,0,F18*4%*1) -> 0 | N28: =O28-Q28 -> 10802 | O28: 10802
N29: =O29-Q29 -> 8930 | O29: 8930
D30: TOTAL PAYABLE | E30: Kshs. | F30: =SUM(F17:F29) -> 600 | N30: =O30-Q30 -> 9570 | O30: 9570
N31: =O31-Q31 -> 11390 | O31: 11390
D32: PAID | F32: =meter!L27 -> 0 | N32: =O32-Q32 -> 10750 | O32: 10750
N33: =O33-Q33 -> 11732 | O33: 11732
D34: AMOUNT DUE | F34: =F30-F32 -> 600 | N34: =O34-Q34 -> 10934 | O34: 10934 | R34: 700
C35: NOTE | N35: =O35-Q35 -> 10270 | O35: 10270
A36: a) | B36: KINDLY PAY FOR WATER LATEST BY 5TH OF THE MONTH AND FORWARD SMS OR WHATSAPP TO 0702325121 | N36: =O36-Q36 -> 10598 | O36: 10598
A37: b) | N37: =O37-Q37 -> 8770 | O37: 8770
N38: =O38-Q38 -> 8770 | O38: 8770
A39: c) | O39: =SUM(O3:O38) -> 391268 | Q39: =SUM(Q3:Q38) -> 0
A41: d)
A42: e)
A43: f)
B47: PAY BLL 4139271 ACC NO KSJ 16
O49: ……………
A50: g)

Sheet BISMARK
B1: OLE SAMEDHA BOREHOLE KISAJU
B2: ='FROM BOREHOLE'!B3 -> P.O BOX 9473-00200 NAIROBI | N2: VAR | O2: TAX DUE
B3: WATER BILL | N3: =O3-Q3 -> 10270 | O3: 10270
H4: BILL NO. | I4: ='FROM BOREHOLE'!H4+30-1 -> 20242030 | J4: ='FROM BOREHOLE'!H4+30-1 -> 20242030 | N4: =O4-Q4 -> 10304 | O4: 10304
N5: =O5-Q5 -> 10988 | O5: 10988
B6: NAME | D6: BISMARK NYAKUNDI | N6: =O6-Q6 -> 11070 | O6: 11070
N7: =O7-Q7 -> 1197 | O7: 1197
N8: =O8-Q8 -> 9250 | O8: 9250
N9: =O9-Q9 -> 8770 | O9: 8770
B10: ISSUE DATE | D10: ='FROM BOREHOLE'!C10 -> 29TH JAN 2025 | N10: =O10-Q10 -> 23190 | O10: 23190
N11: =O11-Q11 -> 10910 | O11: 10910
B12: LAST PAY DATE | D12: ='FROM BOREHOLE'!C12 -> 5TH FEB 2026 | N12: =O12-Q12 -> 10910 | O12: 10910
N13: =O13-Q13 -> 12190 | O13: 12190
N14: =O14-Q14 -> 11070 | O14: 11070
B15: PREVIOUS READING | D15: CURRENT READING | F15: CONSUMPTION | N15: =O15-Q15 -> 9090 | O15: 9090
B16: =meter!D28 -> 302 | D16: =meter!E28 -> 0 | E16: Units | F16: =D16-B16 -> -302 | N16: =O16-Q16 -> 9420 | O16: 9420
F17: Amount (Kshs.) | N17: =O17-Q17 -> 11154 | O17: 11154
D18: LAST ACCOUNT B/F | E18: Kshs. | F18: =meter!J28 -> 0 | N18: =O18-Q18 -> 10430 | O18: 10430
N19: =O19-Q19 -> 11831 | O19: 11831
D20: MONTH BILL | E20: KSHS. | F20: =meter!H28 -> -30200 | N20: =O20-Q20 -> 10590 | O20: 10590
N21: =O21-Q21 -> 22423 | O21: 22423
N22: =O22-Q22 -> 9250 | O22: 9250
N23: =O23-Q23 -> 10162 | O23: 10162
N24: =O24-Q24 -> 10270 | O24: 10270
N25: =O25-Q25 -> 11070 | O25: 11070
N26: =O26-Q26 -> 11550 | O26: 11550
N27: =O27-Q27 -> 11393 | O27: 11393
N28: =O28-Q28 -> 10802 | O28: 10802
N29: =O29-Q29 -> 8930 | O29: 8930
D30: TOTAL PAYABLE | E30: Kshs. | F30: =SUM(F17:F29) -> -30200 | N30: =O30-Q30 -> 9570 | O30: 9570
N31: =O31-Q31 -> 11390 | O31: 11390
D32: PAID | F32: =meter!L32 -> 0 | N32: =O32-Q32 -> 10750 | O32: 10750
N33: =O33-Q33 -> 11732 | O33: 11732
D34: AMOUNT DUE | F34: =F30-F32 -> -30200 | N34: =O34-Q34 -> 10934 | O34: 10934 | R34: 700
C35: NOTE | N35: =O35-Q35 -> 10270 | O35: 10270
A36: a) | D36: KINDLY PAY FOR WATER LATEST BY 5TH OF THE MONTH AND FORWARD SMS OR WHATSAPP TO 0702325121 | N36: =O36-Q36 -> 10598 | O36: 10598
A37: b) | N37: =O37-Q37 -> 8770 | O37: 8770
N38: =O38-Q38 -> 8770 | O38: 8770
A39: c) | O39: =SUM(O3:O38) -> 391268 | Q39: =SUM(Q3:Q38) -> 0
A41: d)
A42: e)
A43: f)
B47: PAY BILL 4139271 ACC NO KSJ 17
O49: ……………
A50: g)

Sheet PATRICK
B1: SAMEDHA BOREHOLE
B2: ='FROM BOREHOLE'!B3 -> P.O BOX 9473-00200 NAIROBI | N2: VAR | O2: TAX DUE
B3: WATER BILL | N3: =O3-Q3 -> 10270 | O3: 10270
H4: BILL NO. | I4: ='FROM BOREHOLE'!H4+31-1 -> 20242031 | J4: ='FROM BOREHOLE'!H4+31-1 -> 20242031 | N4: =O4-Q4 -> 10304 | O4: 10304
N5: =O5-Q5 -> 10988 | O5: 10988
B6: NAME | D6: =meter!A29 -> Patrick | N6: =O6-Q6 -> 11070 | O6: 11070
N7: =O7-Q7 -> 1197 | O7: 1197
N8: =O8-Q8 -> 9250 | O8: 9250
N9: =O9-Q9 -> 8770 | O9: 8770
B10: ISSUE DATE | D10: ='FROM BOREHOLE'!C10 -> 29TH JAN 2025 | N10: =O10-Q10 -> 23190 | O10: 23190
N11: =O11-Q11 -> 10910 | O11: 10910
B12: LAST PAY DATE | D12: ='FROM BOREHOLE'!C12 -> 5TH FEB 2026 | N12: =O12-Q12 -> 10910 | O12: 10910
N13: =O13-Q13 -> 12190 | O13: 12190
N14: =O14-Q14 -> 11070 | O14: 11070
B15: PREVIOUS READING | D15: CURRENT READING | F15: CONSUMPTION | N15: =O15-Q15 -> 9090 | O15: 9090
B16: =meter!D29 -> 211 | D16: =meter!E29 -> 214 | E16: Units | F16: =D16-B16 -> 3 | N16: =O16-Q16 -> 9420 | O16: 9420
F17: Amount (Kshs.) | N17: =O17-Q17 -> 11154 | O17: 11154
D18: LAST ACCOUNT B/F | E18: Kshs. | F18: =meter!J29 -> 0 | N18: =O18-Q18 -> 10430 | O18: 10430
N19: =O19-Q19 -> 11831 | O19: 11831
D20: MONTH BILL | E20: KSHS. | F20: =meter!H29 -> 300 | N20: =O20-Q20 -> 10590 | O20: 10590
N21: =O21-Q21 -> 22423 | O21: 22423
N22: =O22-Q22 -> 9250 | O22: 9250
N23: =O23-Q23 -> 10162 | O23: 10162
N24: =O24-Q24 -> 10270 | O24: 10270
N25: =O25-Q25 -> 11070 | O25: 11070
N26: =O26-Q26 -> 11550 | O26: 11550
N27: =O27-Q27 -> 11393 | O27: 11393
F28: =IF(F18*4%*1<0,0,F18*4%*1) -> 0 | N28: =O28-Q28 -> 10802 | O28: 10802
N29: =O29-Q29 -> 8930 | O29: 8930
D30: TOTAL PAYABLE | E30: Kshs. | F30: =SUM(F17:F29) -> 300 | N30: =O30-Q30 -> 9570 | O30: 9570
N31: =O31-Q31 -> 11390 | O31: 11390
D32: PAID | F32: =meter!L33 -> 0 | N32: =O32-Q32 -> 10750 | O32: 10750
N33: =O33-Q33 -> 11732 | O33: 11732
D34: AMOUNT DUE | F34: =F30-F32 -> 300 | N34: =O34-Q34 -> 10934 | O34: 10934 | R34: 700
C35: NOTE | N35: =O35-Q35 -> 10270 | O35: 10270
A36: a) | B36: KINDLY PAY FOR WATER LATEST BY 5TH OF THE MONTH AND FORWARD SMS OR WHATSAPP TO 0702325121 | N36: =O36-Q36 -> 10598 | O36: 10598
A37: b) | N37: =O37-Q37 -> 8770 | O37: 8770
N38: =O38-Q38 -> 8770 | O38: 8770
A39: c) | O39: =SUM(O3:O38) -> 391268 | Q39: =SUM(Q3:Q38) -> 0
A41: d)
A42: e)
A43: f)
B47: PAYBILL 4139271 ACC NO KSJ 18
O49: ……………
A50: g)

Sheet JACKY
A1: G | B1: SAMEDHA BOREHOLE
B2: ='FROM BOREHOLE'!B3 -> P.O BOX 9473-00200 NAIROBI | N2: VAR | O2: TAX DUE
B3: WATER BILL | N3: =O3-Q3 -> 10270 | O3: 10270
H4: BILL NO. | I4: ='FROM BOREHOLE'!H4+32-1 -> 20242032 | J4: ='FROM BOREHOLE'!H4+32-1 -> 20242032 | N4: =O4-Q4 -> 10304 | O4: 10304
N5: =O5-Q5 -> 10988 | O5: 10988
B6: NAME | D6: =meter!A30 -> Jacky | N6: =O6-Q6 -> 11070 | O6: 11070
N7: =O7-Q7 -> 1197 | O7: 1197
N8: =O8-Q8 -> 9250 | O8: 9250
N9: =O9-Q9 -> 8770 | O9: 8770
B10: ISSUE DATE | D10: ='FROM BOREHOLE'!C10 -> 29TH JAN 2025 | N10: =O10-Q10 -> 23190 | O10: 23190
N11: =O11-Q11 -> 10910 | O11: 10910
B12: LAST PAY DATE | D12: ='FROM BOREHOLE'!C12 -> 5TH FEB 2026 | N12: =O12-Q12 -> 10910 | O12: 10910
N13: =O13-Q13 -> 12190 | O13: 12190
N14: =O14-Q14 -> 11070 | O14: 11070
B15: PREVIOUS READING | D15: CURRENT READING | F15: CONSUMPTION | N15: =O15-Q15 -> 9090 | O15: 9090
B16: =meter!D30 -> 117 | D16: =meter!E30 -> 119 | E16: Units | F16: =D16-B16 -> 2 | N16: =O16-Q16 -> 9420 | O16: 9420
F17: Amount (Kshs.) | N17: =O17-Q17 -> 11154 | O17: 11154
D18: LAST ACCOUNT B/F | E18: Kshs. | F18: =meter!J30 -> 3700 | N18: =O18-Q18 -> 10430 | O18: 10430
N19: =O19-Q19 -> 11831 | O19: 11831
D20: MONTH BILL | E20: KSHS. | F20: =meter!H30 -> 200 | N20: =O20-Q20 -> 10590 | O20: 10590
N21: =O21-Q21 -> 22423 | O21: 22423
N22: =O22-Q22 -> 9250 | O22: 9250
N23: =O23-Q23 -> 10162 | O23: 10162
N24: =O24-Q24 -> 10270 | O24: 10270
N25: =O25-Q25 -> 11070 | O25: 11070
N26: =O26-Q26 -> 11550 | O26: 11550
N27: =O27-Q27 -> 11393 | O27: 11393
N28: =O28-Q28 -> 10802 | O28: 10802
N29: =O29-Q29 -> 8930 | O29: 8930
D30: TOTAL PAYABLE | E30: Kshs. | F30: =SUM(F17:F29) -> 3900 | N30: =O30-Q30 -> 9570 | O30: 9570
N31: =O31-Q31 -> 11390 | O31: 11390
D32: PAID | F32: =meter!L34 -> 0 | N32: =O32-Q32 -> 10750 | O32: 10750
N33: =O33-Q33 -> 11732 | O33: 11732
D34: AMOUNT DUE | F34: =F30-F32 -> 3900 | N34: =O34-Q34 -> 10934 | O34: 10934 | R34: 700
C35: NOTE | N35: =O35-Q35 -> 10270 | O35: 10270
A36: a) | B36: KINDLY PAY FOR WATER LATEST BY 5TH OF THE MONTH AND FORWARD SMS OR WHATSAPP TO 0702325121 | N36: =O36-Q36 -> 10598 | O36: 10598
A37: b) | N37: =O37-Q37 -> 8770 | O37: 8770
N38: =O38-Q38 -> 8770 | O38: 8770
A39: c) | O39: =SUM(O3:O38) -> 391268 | Q39: =SUM(Q3:Q38) -> 0
A41: d)
A42: e)
A43: f)
A47: PAYBLL 4139271 ACC NO KSJ 19
O49: ……………

Sheet NAOMI
B1: SAMEDHA BOREHOLE
B2: ='FROM BOREHOLE'!B3 -> P.O BOX 9473-00200 NAIROBI | N2: VAR | O2: TAX DUE
B3: WATER BILL | N3: =O3-Q3 -> 10270 | O3: 10270
H4: BILL NO. | I4: ='FROM BOREHOLE'!H4+33-1 -> 20242033 | J4: ='FROM BOREHOLE'!H4+33-1 -> 20242033 | N4: =O4-Q4 -> 10304 | O4: 10304
N5: =O5-Q5 -> 10988 | O5: 10988
B6: NAME | D6: =meter!A31 -> NAOMI | N6: =O6-Q6 -> 11070 | O6: 11070
N7: =O7-Q7 -> 1197 | O7: 1197
N8: =O8-Q8 -> 9250 | O8: 9250
N9: =O9-Q9 -> 8770 | O9: 8770
B10: ISSUE DATE | D10: ='FROM BOREHOLE'!C10 -> 29TH JAN 2025 | N10: =O10-Q10 -> 23190 | O10: 23190
N11: =O11-Q11 -> 10910 | O11: 10910
B12: LAST PAY DATE | D12: ='FROM BOREHOLE'!C12 -> 5TH FEB 2026 | N12: =O12-Q12 -> 10910 | O12: 10910
N13: =O13-Q13 -> 12190 | O13: 12190
N14: =O14-Q14 -> 11070 | O14: 11070
B15: PREVIOUS READING | D15: CURRENT READING | F15: CONSUMPTION | N15: =O15-Q15 -> 9090 | O15: 9090
B16: =meter!D31 -> 155 | D16: =meter!E31 -> 211 | E16: Units | F16: =D16-B16 -> 56 | N16: =O16-Q16 -> 9420 | O16: 9420
F17: Amount (Kshs.) | N17: =O17-Q17 -> 11154 | O17: 11154
D18: LAST ACCOUNT B/F | E18: Kshs. | F18: =meter!J31 -> 0 | N18: =O18-Q18 -> 10430 | O18: 10430
N19: =O19-Q19 -> 11831 | O19: 11831
D20: MONTH BILL | E20: KSHS. | F20: =meter!H31 -> 5600 | N20: =O20-Q20 -> 10590 | O20: 10590
N21: =O21-Q21 -> 22423 | O21: 22423
N22: =O22-Q22 -> 9250 | O22: 9250
N23: =O23-Q23 -> 10162 | O23: 10162
N24: =O24-Q24 -> 10270 | O24: 10270
N25: =O25-Q25 -> 11070 | O25: 11070
N26: =O26-Q26 -> 11550 | O26: 11550
N27: =O27-Q27 -> 11393 | O27: 11393
N28: =O28-Q28 -> 10802 | O28: 10802
N29: =O29-Q29 -> 8930 | O29: 8930
D30: TOTAL PAYABLE | E30: Kshs. | F30: =SUM(F17:F29) -> 5600 | N30: =O30-Q30 -> 9570 | O30: 9570
N31: =O31-Q31 -> 11390 | O31: 11390
D32: PAID | F32: 0 | N32: =O32-Q32 -> 10750 | O32: 10750
N33: =O33-Q33 -> 11732 | O33: 11732
D34: AMOUNT DUE | F34: =F30-F32 -> 5600 | N34: =O34-Q34 -> 10934 | O34: 10934 | R34: 700
C35: NOTE | N35: =O35-Q35 -> 10270 | O35: 10270
A36: a) | N36: =O36-Q36 -> 10598 | O36: 10598
A37: b) | N37: =O37-Q37 -> 8770 | O37: 8770
N38: =O38-Q38 -> 8770 | O38: 8770
A39: c) | O39: =SUM(O3:O38) -> 391268 | Q39: =SUM(Q3:Q38) -> 0
A41: d)
A42: e)
A43: f)
B47: KINDLY PAY FOR WATER LATEST BY 5TH OF THE MONTH AND FORWARD SMS OR WHATSAPP TO 0702325121
O49: ……………
A50: g)
C51: PAY BILL 4139271 ACC NO KSJ 20

Sheet JOSEPH
B1: SAMEDHA BOREHOLE
B2: ='FROM BOREHOLE'!B3 -> P.O BOX 9473-00200 NAIROBI | N2: VAR | O2: TAX DUE
B3: WATER BILL | N3: =O3-Q3 -> 10270 | O3: 10270
H4: BILL NO. | I4: ='FROM BOREHOLE'!H4+34-1 -> 20242034 | J4: ='FROM BOREHOLE'!H4+34-1 -> 20242034 | N4: =O4-Q4 -> 10304 | O4: 10304
N5: =O5-Q5 -> 10988 | O5: 10988
B6: NAME | D6: =meter!A32 -> SALMA SPROUTS LTD | N6: =O6-Q6 -> 11070 | O6: 11070
N7: =O7-Q7 -> 1197 | O7: 1197
N8: =O8-Q8 -> 9250 | O8: 9250
N9: =O9-Q9 -> 8770 | O9: 8770
B10: ISSUE DATE | D10: ='FROM BOREHOLE'!C10 -> 29TH JAN 2025 | N10: =O10-Q10 -> 23190 | O10: 23190
N11: =O11-Q11 -> 10910 | O11: 10910
B12: LAST PAY DATE | D12: ='FROM BOREHOLE'!C12 -> 5TH FEB 2026 | N12: =O12-Q12 -> 10910 | O12: 10910
N13: =O13-Q13 -> 12190 | O13: 12190
N14: =O14-Q14 -> 11070 | O14: 11070
B15: PREVIOUS READING | D15: CURRENT READING | F15: CONSUMPTION | N15: =O15-Q15 -> 9090 | O15: 9090
B16: =meter!D32 -> 95 | D16: =meter!E32 -> 453 | E16: Units | F16: =D16-B16 -> 358 | N16: =O16-Q16 -> 9420 | O16: 9420
F17: Amount (Kshs.) | N17: =O17-Q17 -> 11154 | O17: 11154
D18: LAST ACCOUNT B/F | E18: Kshs. | F18: =meter!J32 -> 0 | N18: =O18-Q18 -> 10430 | O18: 10430
N19: =O19-Q19 -> 11831 | O19: 11831
D20: MONTH BILL | E20: KSHS. | F20: =meter!H32 -> 35800 | N20: =O20-Q20 -> 10590 | O20: 10590
N21: =O21-Q21 -> 22423 | O21: 22423
N22: =O22-Q22 -> 9250 | O22: 9250
N23: =O23-Q23 -> 10162 | O23: 10162
N24: =O24-Q24 -> 10270 | O24: 10270
N25: =O25-Q25 -> 11070 | O25: 11070
N26: =O26-Q26 -> 11550 | O26: 11550
N27: =O27-Q27 -> 11393 | O27: 11393
N28: =O28-Q28 -> 10802 | O28: 10802
N29: =O29-Q29 -> 8930 | O29: 8930
D30: TOTAL PAYABLE | E30: Kshs. | F30: =SUM(F17:F29) -> 35800 | N30: =O30-Q30 -> 9570 | O30: 9570
N31: =O31-Q31 -> 11390 | O31: 11390
D32: PAID | F32: =meter!L36 -> 0 | N32: =O32-Q32 -> 10750 | O32: 10750
N33: =O33-Q33 -> 11732 | O33: 11732
D34: AMOUNT DUE | F34: =F30-F32 -> 35800 | N34: =O34-Q34 -> 10934 | O34: 10934 | R34: 700
C35: NOTE | N35: =O35-Q35 -> 10270 | O35: 10270
A36: a) | N36: =O36-Q36 -> 10598 | O36: 10598
A37: b) | N37: =O37-Q37 -> 8770 | O37: 8770
N38: =O38-Q38 -> 8770 | O38: 8770
A39: c) | O39: =SUM(O3:O38) -> 391268 | Q39: =SUM(Q3:Q38) -> 0
A41: d)
A42: e)
A43: f)
B47: KINDLY PAY FOR WATER LATEST BY 5TH OF THE MONTH AND FORWARD SMS OR WHATSAPP TO 0702325121
O49: ……………
A50: g)
B51: PAY BILL 4139271 ACC NO KSJ 21

Sheet meter
A2: NAMES | B2: NO | C2: PERIOD | D2: PRVIOUS | E2: CURRENT | F2: READING | G2: RATE | H2: TOTAL WATER BILL | I2: FIXED CHARGE | J2: Bal + /- | K2: Total Bill | L2: PAID | M2: BAL C/F | N2: EARLY DISCOUNT 3% | O2: REMARKS
A3: From Borehole | B3: 1 | C3: 46023 | D3: 227 | E3: 1280 | F3: =E3-D3 -> 1053 | G3: 100 | H3: =F3*G3 -> 105300 | I3: 0 | J3: 0 | K3: =H3+I3+J3 -> 105300 | L3: 0 | M3: =#REF!-L3 -> #REF!
A4: Out Borehole | B4: 2 | C4: 46023 | D4: 15801 | E4: 16894 | F4: =E4-D4 -> 1093 | G4: 100 | H4: =F4*G4 -> 109300 | I4: 0 | J4: 0 | K4: =H4+I4+J4 -> 109300 | L4: 0 | M4: =#REF!-L4 -> #REF!
A5: New Out Borehole | B5: 3 | C5: =SUM(C4) -> 46023 | D5: 11651 | E5: 12600 | F5: =E5-D5 -> 949 | G5: 100 | H5: =F5*G5 -> 94900 | I5: 0 | J5: 0 | K5: =H5+I5+J5 -> 94900 | L5: 0 | M5: =#REF!-L5 -> #REF!
A6: Lorry Water | B6: 4 | C6: =SUM(C5) -> 46023 | D6: 9968 | E6: 9968 | F6: =E6-D6 -> 0 | G6: 100 | H6: =F6*G6 -> 0 | I6: 0 | J6: 0 | K6: =H6+I6+J6 -> 0 | L6: 0 | M6: =#REF!-L6 -> #REF!
A7: PASSION FARM A | B7: 5 | C7: =SUM(C6) -> 46023 | D7: 6881 | F7: =E7-D7 -> -6881 | G7: 100 | H7: =F7*G7 -> -688100 | I7: 0 | J7: 0 | K7: =H7+I7+J7 -> -688100 | L7: 0 | M7: =#REF!-L7 -> #REF!
A8: BLOCK A | B8: 6 | C8: =SUM(C7) -> 46023 | D8: 4256 | E8: 4256 | F8: =E8-D8 -> 0 | G8: 100 | H8: =F8*G8 -> 0 | I8: 0 | J8: 0 | K8: =H8+I8+J8 -> 0 | L8: 0 | M8: =#REF!-L8 -> #REF!
A9: BLOCK B | B9: 7 | C9: =SUM(C8) -> 46023 | D9: 1099 | E9: 1099 | F9: =E9-D9 -> 0 | G9: 100 | H9: =F9*G9 -> 0 | I9: 0 | J9: 0 | K9: =H9+I9+J9 -> 0 | L9: 0 | M9: =#REF!-L9 -> #REF!
A10: NEW BLOCK | B10: 8 | C10: =SUM(C9) -> 46023 | D10: 4205 | E10: 4205 | F10: =E10-D10 -> 0 | G10: 100 | H10: =F10*G10 -> 0 | I10: 0 | J10: 0 | K10: =H10+I10+J10 -> 0 | L10: 0 | M10: =#REF!-L10 -> #REF!
A11: HOUSE JOHN | B11: 9 | C11: =SUM(C10) -> 46023 | D11: 56 | E11: 56 | F11: =E11-D11 -> 0 | G11: 100 | H11: =F11*G11 -> 0 | I11: 0 | J11: 0 | K11: =H11+I11+J11 -> 0 | L11: 0 | M11: =#REF!-L11 -> #REF!
A12: KAYAVA | B12: 10 | C12: =SUM(C11) -> 46023 | D12: 1808 | F12: =E12-D12 -> -1808 | G12: 100 | H12: =F12*G12 -> -180800 | I12: 0 | J12: 0 | K12: =H12+I12+J12 -> -180800 | L12: 0 | M12: =#REF!-L12 -> #REF!
A13: Mr Vincent | B13: 11 | C13: =SUM(C12) -> 46023 | D13: 2728 | E13: 2773 | F13: =E13-D13 -> 45 | G13: 100 | H13: =F13*G13 -> 4500 | I13: 0 | J13: 0 | K13: =H13+I13+J13 -> 4500 | L13: 0 | M13: =#REF!-L13 -> #REF!
A14: Mr Wamalwa | B14: 12 | C14: =SUM(C13) -> 46023 | D14: 918 | E14: 938 | F14: =E14-D14 -> 20 | G14: 100 | H14: =F14*G14 -> 2000 | I14: 0 | J14: 2500 | K14: =H14+I14+J14 -> 4500 | L14: 0 | M14: =#REF!-L14 -> #REF!
A15: Mr Mwita | B15: 13 | C15: =SUM(C14) -> 46023 | D15: 67 | E15: 72 | F15: =E15-D15 -> 5 | G15: 100 | H15: =F15*G15 -> 500 | I15: 0 | J15: 0 | K15: =H15+I15+J15 -> 500 | L15: 0 | M15: =#REF!-L15 -> #REF!
A16: Andrew nyarandi | B16: 14 | C16: =SUM(C15) -> 46023 | D16: 235 | E16: 254 | F16: =E16-D16 -> 19 | G16: 100 | H16: =F16*G16 -> 1900 | I16: 0 | J16: 0 | K16: =H16+I16+J16 -> 1900 | L16: 0 | M16: =#REF!-L16 -> #REF!
A17: NAMBOKAH | B17: 15 | C17: =SUM(C16) -> 46023 | D17: 152 | F17: =E17-D17 -> -152 | G17: 100 | H17: =F17*G17 -> -15200 | I17: 0 | J17: 0 | K17: =H17+I17+J17 -> -15200 | L17: 0 | M17: =#REF!-L17 -> #REF!
A18: KIMANI | B18: 16 | C18: =SUM(C17) -> 46023 | D18: 33 | E18: 41 | F18: =E18-D18 -> 8 | G18: 100 | H18: =F18*G18 -> 800 | I18: 0 | J18: 0 | K18: =H18+I18+J18 -> 800 | L18: 0 | M18: =#REF!-L18 -> #REF!
A19: Agnes | B19: 17 | C19: =SUM(C18) -> 46023 | D19: 14 | E19: 14 | F19: =E19-D19 -> 0 | G19: 100 | H19: =F19*G19 -> 0 | I19: 0 | J19: 0 | K19: =H19+I19+J19 -> 0 | L19: 0 | M19: =#REF!-L19 -> #REF!
A20: Nancy | B20: 18 | C20: =SUM(C19) -> 46023 | D20: 289 | F20: =E20-D20 -> -289 | G20: 100 | H20: =F20*G20 -> -28900 | I20: 0 | J20: 0 | K20: =H20+I20+J20 -> -28900 | L20: 0 | M20: =#REF!-L20 -> #REF!
A21: Kurgat samson | B21: 19 | C21: =SUM(C20) -> 46023 | D21: 300 | F21: =E21-D21 -> -300 | G21: 100 | H21: =F21*G21 -> -30000 | I21: 0 | J21: 0 | K21: =H21+I21+J21 -> -30000 | L21: 0 | M21: =#REF!-L21 -> #REF!
A22: Jane Mwangi | B22: 20 | C22: =SUM(C21) -> 46023 | D22: 264 | E22: 278 | F22: =E22-D22 -> 14 | G22: 100 | H22: =F22*G22 -> 1400 | I22: 0 | J22: 0 | K22: =H22+I22+J22 -> 1400 | L22: 0 | M22: =#REF!-L22 -> #REF!
A23: Brian murithi | B23: 21 | C23: =SUM(C22) -> 46023 | D23: 1164 | E23: 1184 | F23: =E23-D23 -> 20 | G23: 100 | H23: =F23*G23 -> 2000 | I23: 0 | K23: =H23+I23+J23 -> 2000 | L23: 0 | M23: =#REF!-L23 -> #REF!
A24: Daniel uka | B24: 22 | C24: =SUM(C23) -> 46023 | D24: 820 | E24: 836 | F24: =E24-D24 -> 16 | G24: 100 | H24: =F24*G24 -> 1600 | I24: 0 | J24: 0 | K24: =H24+I24+J24 -> 1600 | L24: 0 | M24: =#REF!-L24 -> #REF!
A25: Danstone amaitsa | B25: 23 | C25: =SUM(C24) -> 46023 | D25: 724 | E25: 796 | F25: =E25-D25 -> 72 | G25: 100 | H25: =F25*G25 -> 7200 | I25: 0 | J25: 3400 | K25: =H25+I25+J25 -> 10600 | L25: 0 | M25: =#REF!-L25 -> #REF!
A26: Eric | B26: 24 | C26: =SUM(C25) -> 46023 | D26: 155 | E26: 159 | F26: =E26-D26 -> 4 | G26: 100 | H26: =F26*G26 -> 400 | I26: 0 | J26: 0 | K26: =H26+I26+J26 -> 400 | L26: 0 | M26: =#REF!-L26 -> #REF!
A27: Pamela | B27: 25 | C27: =SUM(C26) -> 46023 | D27: 217 | E27: 223 | F27: =E27-D27 -> 6 | G27: 100 | H27: =F27*G27 -> 600 | I27: 0 | J27: 0 | K27: =H27+I27+J27 -> 600 | L27: 0 | M27: =#REF!-L27 -> #REF!
A28: Nyakundi BISMARK | B28: 26 | C28: =SUM(C27) -> 46023 | D28: 302 | F28: =E28-D28 -> -302 | G28: 100 | H28: =F28*G28 -> -30200 | I28: 0 | J28: 0 | K28: =H28+I28+J28 -> -30200 | L28: 0 | M28: =#REF!-L28 -> #REF!
A29: Patrick | B29: 27 | C29: =SUM(C28) -> 46023 | D29: 211 | E29: 214 | F29: =E29-D29 -> 3 | G29: 100 | H29: =F29*G29 -> 300 | I29: 0 | J29: 0 | K29: =H29+I29+J29 -> 300 | L29: 0 | M29: =#REF!-L29 -> #REF! | N29: =#REF!*3% -> #REF! | O29: ECBKL 28/2/2018
A30: Jacky | B30: 28 | C30: =SUM(C29) -> 46023 | D30: 117 | E30: 119 | F30: =E30-D30 -> 2 | G30: 100 | H30: =F30*G30 -> 200 | I30: 0 | J30: 3700 | K30: =H30+I30+J30 -> 3900 | L30: 0 | M30: =#REF!-L30 -> #REF!
A31: NAOMI | B31: 29 | C31: =SUM(C30) -> 46023 | D31: 155 | E31: 211 | F31: =E31-D31 -> 56 | G31: 100 | H31: =F31*G31 -> 5600 | I31: 0 | J31: 0 | K31: =H31+I31+J31 -> 5600 | L31: 0 | M31: =#REF!-L31 -> #REF!
A32: SALMA SPROUTS LTD | B32: 30 | C32: =SUM(C31) -> 46023 | D32: 95 | E32: 453 | F32: =E32-D32 -> 358 | G32: 100 | H32: =F32*G32 -> 35800 | I32: 0 | J32: 0 | K32: =H32+I32+J32 -> 35800 | L32: 0 | M32: =#REF!-L32 -> #REF!
I33: TOTAL | J33: =SUM(J3:J32) -> 9600

Sheet N6
B2: ='FROM BOREHOLE'!B3 -> P.O BOX 9473-00200 NAIROBI | N2: VAR | O2: TAX DUE
B3: WATER BILL | N3: =O3-Q3 -> 10270 | O3: 10270
H4: BILL NO. | I4: ='FROM BOREHOLE'!H4+35-1 -> 20242035 | J4: ='FROM BOREHOLE'!H4+35-1 -> 20242035 | N4: =O4-Q4 -> 10304 | O4: 10304
N5: =O5-Q5 -> 10988 | O5: 10988
B6: NAME | D6: =meter!A37 -> 0 | N6: =O6-Q6 -> 11070 | O6: 11070
N7: =O7-Q7 -> 1197 | O7: 1197
N8: =O8-Q8 -> 9250 | O8: 9250
N9: =O9-Q9 -> 8770 | O9: 8770
B10: ISSUE DATE | D10: ='FROM BOREHOLE'!C10 -> 29TH JAN 2025 | N10: =O10-Q10 -> 23190 | O10: 23190
N11: =O11-Q11 -> 10910 | O11: 10910
B12: LAST PAY DATE | D12: ='FROM BOREHOLE'!C12 -> 5TH FEB 2026 | N12: =O12-Q12 -> 10910 | O12: 10910
N13: =O13-Q13 -> 12190 | O13: 12190
N14: =O14-Q14 -> 11070 | O14: 11070
B15: PREVIOUS READING | D15: CURRENT READING | F15: CONSUMPTION | N15: =O15-Q15 -> 9090 | O15: 9090
B16: =meter!D37 -> 0 | D16: =meter!E37 -> 0 | E16: Units | F16: =D16-B16 -> 0 | H16: ESTIMATE | N16: =O16-Q16 -> 9420 | O16: 9420
F17: Amount (Kshs.) | N17: =O17-Q17 -> 11154 | O17: 11154
D18: LAST ACCOUNT B/F | E18: Kshs. | N18: =O18-Q18 -> 10430 | O18: 10430
N19: =O19-Q19 -> 11831 | O19: 11831
D20: MONTH BILL | E20: KSHS. | F20: =meter!H37 -> 0 | N20: =O20-Q20 -> 10590 | O20: 10590
N21: =O21-Q21 -> 22423 | O21: 22423
N22: =O22-Q22 -> 9250 | O22: 9250
N23: =O23-Q23 -> 10162 | O23: 10162
N24: =O24-Q24 -> 10270 | O24: 10270
N25: =O25-Q25 -> 11070 | O25: 11070
N26: =O26-Q26 -> 11550 | O26: 11550
N27: =O27-Q27 -> 11393 | O27: 11393
N28: =O28-Q28 -> 10802 | O28: 10802
N29: =O29-Q29 -> 8930 | O29: 8930
D30: TOTAL PAYABLE | E30: Kshs. | F30: =SUM(F17:F29) -> 0 | N30: =O30-Q30 -> 9570 | O30: 9570
N31: =O31-Q31 -> 11390 | O31: 11390
D32: PAID | F32: =meter!L37 -> 0 | N32: =O32-Q32 -> 10750 | O32: 10750
N33: =O33-Q33 -> 11732 | O33: 11732
D34: AMOUNT DUE | F34: =F30-F32 -> 0 | N34: =O34-Q34 -> 10934 | O34: 10934 | R34: 700
C35: NOTE | N35: =O35-Q35 -> 10270 | O35: 10270
A36: a) | N36: =O36-Q36 -> 10598 | O36: 10598
A37: b) | N37: =O37-Q37 -> 8770 | O37: 8770
N38: =O38-Q38 -> 8770 | O38: 8770
A39: c) | O39: =SUM(O3:O38) -> 391268 | Q39: =SUM(Q3:Q38) -> 0
A41: d)
A42: e)
A43: f)
O49: ……………
A50: g)

Sheet N7
B1: OLE SAMEDHA APARTMENTS-Kitengela
B2: ='FROM BOREHOLE'!B3 -> P.O BOX 9473-00200 NAIROBI
B3: WATER BILL
H4: BILL NO. | I4: ='FROM BOREHOLE'!H4+37-1 -> 20242037
B6: NAME | D6: =meter!A38 -> 0
B10: ISSUE DATE | D10: ='FROM BOREHOLE'!C10 -> 29TH JAN 2025
B12: LAST PAY DATE | D12: ='FROM BOREHOLE'!C12 -> 5TH FEB 2026
B15: PREVIOUS READING | D15: CURRENT READING | F15: CONSUMPTION
B16: =meter!D38 -> 0 | D16: =meter!E38 -> 0 | E16: Units | F16: =D16-B16 -> 0
F17: Amount (Kshs.)
D18: LAST ACCOUNT B/F | E18: Kshs.
D20: MONTH BILL | E20: KSHS. | F20: =meter!H38 -> 0
D30: TOTAL PAYABLE | E30: Kshs. | F30: =SUM(F17:F29) -> 0
D32: PAID | F32: =meter!L37 -> 0
D34: AMOUNT DUE | F34: =F30-F32 -> 0
C35: NOTE
A36: a)
A37: b)
A39: c) | Q39: =SUM(Q3:Q38) -> 0
A41: d)
A42: e)
A43: f)
O49: ……………
A50: g)

Sheet Sheet3

Sheet Sheet4

Sheet Sheet1
L16: 101456
L17: 21
L18: 1364
L19: 81411 | M19: salary
L21: =L16-L19 -> 20045
L22: =L19-55000 -> 26411

Sheet Sheet2
I1: MAY | J1: JUNE | K1: JUL
I2: 8300 | J2: 21000 | K2: 9962
I3: 9608 | J3: 9962 | K3: 10623
I4: 9608 | J4: 11039 | K4: 8510
I5: 7525 | J5: 10117 | K5: 10100
I6: 11000 | J6: 10778
I7: 8985 | J7: 10750
I8: 7857 | J8: 8510
I9: 6000 | J9: 11230
I10: 9005 | J10: 8500
I11: 10665 | J11: 10590
I12: 9335 | J12: 10400
I13: 8040 | J13: 10000
I14: 8000 | J14: 10840
I15: 10560 | J15: 10200 | K15: 11200
I16: 11000 | J16: 10225 | K16: 11360
I17: 9421 | J17: 9000 | K17: 9787
I18: 10000 | J18: 9945 | K18: 9130
I19: 10700 | J19: 10000 | K19: 10250
I20: 10055 | J20: 5000 | K20: 10740
I21: 10200 | J21: 8900 | K21: 10910
I22: 1977 | J22: 9962 | K22: 9000
I23: 10155 | J23: 10583 | K23: 10353
I24: 10000 | J24: 11200 | K24: 10910
I25: 8000 | J25: 9930 | K25: 8930
I26: 9925 | J26: 8662 | K26: 1200
... I32: 10000 | J32: 10860 | K32: 6000
I33: 5520 | K33: 8500
I34: 9805 | K34: 10430
I35: 20000 | K35: 10000
E36: 119472 | I36: 7000 | K36: 10000
E37: 64399 | I37: 5000 | K37: 11000
E38: =SUM(E36:E37) -> 183871 | I38: 20000 | K38: 8950
I39: 13000 | K39: 11230
I40: 10910 | K40: 400
K41: 7800
K42: 1000
K43: 8000
K44: 6294
I45: =SUM(I2:I44) -> 366751 | J45: =SUM(J2:J44) -> 307193 | K45: =SUM(K2:K44) -> 301808
