Workbook

Sheet 1A
B1: OLE SAMEDHA PREMIER HOSTELS
B2: P.O BOX 9473-00200 NAIROBI | N2: VAR | O2: TAX DUE
B3: WATER BILL | G3: BILL NO. | H3: 38 | N3: =O3-Q3 -> 10270 | O3: 10270
N4: =O4-Q4 -> 10304 | O4: 10304
B5: TENANT NAME | C5: =meter!B4 -> ABDI NALMA | N5: =O5-Q5 -> 10988 | O5: 10988
N6: =O6-Q6 -> 11070 | O6: 11070
B7: HOUSE NUMBER | C7: 1A | N7: =O7-Q7 -> 1197 | O7: 1197
N8: =O8-Q8 -> 9250 | O8: 9250
B9: ISSUE DATE | C9: 30TH JAN 2026 | N9: =O9-Q9 -> 8770 | O9: 8770
N10: =O10-Q10 -> 23190 | O10: 23190
B11: LAST PAY DATE | C11: 5TH FEB 2026 | N11: =O11-Q11 -> 10910 | O11: 10910
N12: =O12-Q12 -> 10910 | O12: 10910
N13: =O13-Q13 -> 12190 | O13: 12190
B14: PREVIOUS READING | C14: CURRENT READING | E14: CONSUMPTION (Units) | N14: =O14-Q14 -> 11070 | O14: 11070
B15: =meter!E4 -> 23 | C15: =meter!F4 -> 24 | D15: Units | E15: =C15-B15 -> 1 | N15: =O15-Q15 -> 9090 | O15: 9090
E16: AMOUNT KSHS | N16: =O16-Q16 -> 9420 | O16: 9420
C17: LAST ACCOUNT B/F | D17: Kshs. | E17: =meter!O4 -> 0 | N17: =O17-Q17 -> 11154 | O17: 11154
N18: =O18-Q18 -> 10430 | O18: 10430
C19: MONTH Water BILL | D19: Kshs. | E19: =meter!I4 -> 150 | N19: =O19-Q19 -> 11831 | O19: 11831
N20: =O20-Q20 -> 10590 | O20: 10590
C21: PUMP/POWER CHARGES | D21: Kshs. | E21: =meter!J4 -> 0 | N21: =O21-Q21 -> 22423 | O21: 22423
N22: =O22-Q22 -> 9250 | O22: 9250
C23: MONTH HOUSE RENT | D23: Kshs. | E23: =meter!N4 -> 7000 | N23: =O23-Q23 -> 10162 | O23: 10162
N24: =O24-Q24 -> 10270 | O24: 10270
C25: SECURITY | D25: Kshs. | E25: 0 | N25: =O25-Q25 -> 11070 | O25: 11070
C26: GARBAGE FEE | D26: Kshs. | N26: =O26-Q26 -> 11550 | O26: 11550
C27: LATE PAY INTEREST | D27: Kshs. | E27: =IF(E17*6%*3<0,0,E17*6%*3) -> 0 | N27: =O27-Q27 -> 11393 | O27: 11393
N28: =O28-Q28 -> 10802 | O28: 10802
C29: TOTAL PAYABLE | D29: Kshs. | E29: =E17+E19+E21+E23+E25+E26+E27 -> 7150 | N29: =O29-Q29 -> 8930 | O29: 8930
N30: =O30-Q30 -> 9570 | O30: 9570
C31: PAID | E31: =meter!T4 -> 0 | N31: =O31-Q31 -> 11390 | O31: 11390
N32: =O32-Q32 -> 10750 | O32: 10750
C33: AMOUNT DUE | E33: =E29-E31 -> 7150 | N33: =O33-Q33 -> 11732 | O33: 11732
B34: NOTE | N34: =O34-Q34 -> 10934 | O34: 10934 | R34: 700
N35: =O35-Q35 -> 10270 | O35: 10270
B36: PAY BILL 4139271 ACC NO UM 1A | N36: =O36-Q36 -> 10598 | O36: 10598
N37: =O37-Q37 -> 8770 | O37: 8770
N38: =O38-Q38 -> 8770 | O38: 8770
O39: =SUM(O3:O38) -> 391268 | Q39: =SUM(Q3:Q38) -> 0

Sheet 2A
B2: OLE SAMEDHA PREMIER HOSTELS | N2: VAR | O2: TAX DUE
B3: ='1A'!B2 -> P.O BOX 9473-00200 NAIROBI | N3: =O3-Q3 -> 10270 | O3: 10270
B4: WATER BILL | F4: BILL NO. | G4: ='1A'!H3+2-1 -> 39 | N4: =O4-Q4 -> 10304 | O4: 10304
N5: =O5-Q5 -> 10988 | O5: 10988
B6: TENANT NAME | D6: =meter!B5 -> NEW TENANT | N6: =O6-Q6 -> 11070 | O6: 11070
N7: =O7-Q7 -> 1197 | O7: 1197
B8: HOUSE NUMBER | D8: 2A | N8: =O8-Q8 -> 9250 | O8: 9250
N9: =O9-Q9 -> 8770 | O9: 8770
B10: ISSUE DATE | D10: ='1A'!C9 -> 30TH JAN 2026 | N10: =O10-Q10 -> 23190 | O10: 23190
N11: =O11-Q11 -> 10910 | O11: 10910
B12: LAST PAY DATE | D12: ='1A'!C11 -> 5TH FEB 2026 | N12: =O12-Q12 -> 10910 | O12: 10910
N13: =O13-Q13 -> 12190 | O13: 12190
N14: =O14-Q14 -> 11070 | O14: 11070
B15: PREVIOUS READING | D15: CURRENT READING | F15: CONSUMPTION (Units) | N15: =O15-Q15 -> 9090 | O15: 9090
B16: =meter!E5 -> 34 | D16: =meter!F5 -> 37 | E16: Units | F16: =D16-B16 -> 3 | N16: =O16-Q16 -> 9420 | O16: 9420
F17: Amount (Kshs.) | N17: =O17-Q17 -> 11154 | O17: 11154
D18: LAST ACCOUNT B/F | E18: Kshs. | F18: =meter!O5 -> 0 | N18: =O18-Q18 -> 10430 | O18: 10430
N19: =O19-Q19 -> 11831 | O19: 11831
D20: MONTH BILL | E20: Kshs. | F20: =meter!I5 -> 450 | N20: =O20-Q20 -> 10590 | O20: 10590
N21: =O21-Q21 -> 22423 | O21: 22423
D22: PUMP/POWER CHARGES | E22: Kshs. | F22: ='1A'!E21 -> 0 | N22: =O22-Q22 -> 9250 | O22: 9250
N23: =O23-Q23 -> 10162 | O23: 10162
D24: MONTH HOUSE RENT | E24: Kshs. | F24: =meter!N5 -> 7000 | N24: =O24-Q24 -> 10270 | O24: 10270
N25: =O25-Q25 -> 11070 | O25: 11070
D26: ='1A'!C25 -> SECURITY | E26: Kshs. | F26: ='1A'!E25 -> 0 | N26: =O26-Q26 -> 11550 | O26: 11550
D27: GARBAGE FEE | N27: =O27-Q27 -> 11393 | O27: 11393
D28: INTEREST ON ARREARS | E28: Kshs. | F28: =IF(F18*6%*3<0,0,F18*6%*3) -> 0 | N28: =O28-Q28 -> 10802 | O28: 10802
F29: 0 | N29: =O29-Q29 -> 8930 | O29: 8930
D30: TOTAL PAYABLE | E30: Kshs. | F30: =SUM(F17:F29) -> 7450 | N30: =O30-Q30 -> 9570 | O30: 9570
N31: =O31-Q31 -> 11390 | O31: 11390
D32: PAID | F32: =meter!T5 -> 0 | N32: =O32-Q32 -> 10750 | O32: 10750
N33: =O33-Q33 -> 11732 | O33: 11732
D34: AMOUNT DUE | F34: =F30-F32 -> 7450 | N34: =O34-Q34 -> 10934 | O34: 10934 | R34: 700
C35: NOTE | N35: =O35-Q35 -> 10270 | O35: 10270
N36: =O36-Q36 -> 10598 | O36: 10598
B37: PAY BILL 4139271 ACC NO UM 2A | N37: =O37-Q37 -> 8770 | O37: 8770
N38: =O38-Q38 -> 8770 | O38: 8770
O39: =SUM(O3:O38) -> 391268 | Q39: =SUM(Q3:Q38) -> 0
A43: f) | B43: .
A51: E & O E | B51: .
A52: NB: Kindly give the management atleast two (2) months prior notice incase you intend to terminate the tenancy for ease of logisitics. | B52: .

Sheet 3A
B2: OLE SAMEDHA PREMIER HOSTELS | N2: VAR | O2: TAX DUE
B3: ='1A'!B2 -> P.O BOX 9473-00200 NAIROBI | N3: =O3-Q3 -> 10270 | O3: 10270
B4: WATER BILL | G4: BILL NO. | H4: ='1A'!H3+3-1 -> 40 | N4: =O4-Q4 -> 10304 | O4: 10304
N5: =O5-Q5 -> 10988 | O5: 10988
B6: TENANT NAME | C6: =meter!B6 -> RAMADHAN | N6: =O6-Q6 -> 11070 | O6: 11070
N7: =O7-Q7 -> 1197 | O7: 1197
B8: HOUSE NUMBER: | C8: 3A | N8: =O8-Q8 -> 9250 | O8: 9250
N9: =O9-Q9 -> 8770 | O9: 8770
B10: ISSUE DATE | C10: ='1A'!C9 -> 30TH JAN 2026 | N10: =O10-Q10 -> 23190 | O10: 23190
N11: =O11-Q11 -> 10910 | O11: 10910
B12: LAST PAY DATE | C12: ='1A'!C11 -> 5TH FEB 2026 | N12: =O12-Q12 -> 10910 | O12: 10910
N13: =O13-Q13 -> 12190 | O13: 12190
N14: =O14-Q14 -> 11070 | O14: 11070
B15: PREVIOUS READING | C15: CURRENT READING | E15: CONSUMPTION (Units) | N15: =O15-Q15 -> 9090 | O15: 9090
B16: =meter!E6 -> 14 | C16: =meter!F6 -> 15 | D16: Units | E16: =C16-B16 -> 1 | N16: =O16-Q16 -> 9420 | O16: 9420
E17: Amount (Kshs.) | N17: =O17-Q17 -> 11154 | O17: 11154
C18: LAST ACCOUNT B/F | D18: Kshs. | E18: =meter!O6 -> 0 | N18: =O18-Q18 -> 10430 | O18: 10430
N19: =O19-Q19 -> 11831 | O19: 11831
C20: MONTH BILL | D20: Kshs. | E20: =meter!I6 -> 150 | N20: =O20-Q20 -> 10590 | O20: 10590
N21: =O21-Q21 -> 22423 | O21: 22423
C22: PUMP/POWER CHARGES | D22: Kshs. | E22: =meter!J6 -> 0 | N22: =O22-Q22 -> 9250 | O22: 9250
N23: =O23-Q23 -> 10162 | O23: 10162
C24: MONTH HOUSE RENT | D24: Kshs. | E24: =meter!N6 -> 7000 | N24: =O24-Q24 -> 10270 | O24: 10270
N25: =O25-Q25 -> 11070 | O25: 11070
C26: SECURITY | D26: Kshs. | E26: 0 | N26: =O26-Q26 -> 11550 | O26: 11550
C27: GARBAGE FEE | D27: Kshs. | N27: =O27-Q27 -> 11393 | O27: 11393
C28: ADJUSTMENT | D28: Kshs. | E28: =IF(E18*6%*3<0,0,E18*6%*3) -> 0 | N28: =O28-Q28 -> 10802 | O28: 10802
N29: =O29-Q29 -> 8930 | O29: 8930
C30: TOTAL PAYABLE | D30: Kshs. | E30: =SUM(E17:E29) -> 7150 | N30: =O30-Q30 -> 9570 | O30: 9570
N31: =O31-Q31 -> 11390 | O31: 11390
C32: PAID | E32: =meter!T6 -> 0 | N32: =O32-Q32 -> 10750 | O32: 10750
N33: =O33-Q33 -> 11732 | O33: 11732
C34: AMOUNT DUE | E34: =E30-E32 -> 7150 | N34: =O34-Q34 -> 10934 | O34: 10934 | R34: 700
B35: NOTE | N35: =O35-Q35 -> 10270 | O35: 10270
N36: =O36-Q36 -> 10598 | O36: 10598
N37: =O37-Q37 -> 8770 | O37: 8770
B38: PAYBILL 4139271 ACC NO UM 3A | N38: =O38-Q38 -> 8770 | O38: 8770
O39: =SUM(O3:O38) -> 391268 | Q39: =SUM(Q3:Q38) -> 0

Sheet 4A
B2: OLE SAMEDHA PREMIER HOSTELS | N2: VAR | O2: TAX DUE
B3: ='1A'!B2 -> P.O BOX 9473-00200 NAIROBI | N3: =O3-Q3 -> 10270 | O3: 10270
B4: WATER BILL | G4: BILL NO. | H4: ='1A'!H3+4-1 -> 41 | N4: =O4-Q4 -> 10304 | O4: 10304
N5: =O5-Q5 -> 10988 | O5: 10988
B6: TENANT NAME | C6: =meter!B7 -> NASRA | N6: =O6-Q6 -> 11070 | O6: 11070
N7: =O7-Q7 -> 1197 | O7: 1197
B8: HOUSE NUMBER: | C8: 4A | N8: =O8-Q8 -> 9250 | O8: 9250
N9: =O9-Q9 -> 8770 | O9: 8770
B10: ISSUE DATE | C10: ='1A'!C9 -> 30TH JAN 2026 | N10: =O10-Q10 -> 23190 | O10: 23190
N11: =O11-Q11 -> 10910 | O11: 10910
B12: LAST PAY DATE | C12: ='1A'!C11 -> 5TH FEB 2026 | N12: =O12-Q12 -> 10910 | O12: 10910
N13: =O13-Q13 -> 12190 | O13: 12190
N14: =O14-Q14 -> 11070 | O14: 11070
B15: PREVIOUS READING | C15: CURRENT READING | E15: CONSUMPTION | N15: =O15-Q15 -> 9090 | O15: 9090
B16: =meter!E7 -> 10 | C16: =meter!F7 -> 12 | D16: Units | E16: =C16-B16 -> 2 | N16: =O16-Q16 -> 9420 | O16: 9420
E17: Amount (Kshs) | N17: =O17-Q17 -> 11154 | O17: 11154
C18: LAST ACCOUNT B/F | D18: Kshs. | E18: =meter!O7 -> 451 | N18: =O18-Q18 -> 10430 | O18: 10430
N19: =O19-Q19 -> 11831 | O19: 11831
C20: MONTH BILL | D20: Kshs. | E20: =meter!I7 -> 300 | N20: =O20-Q20 -> 10590 | O20: 10590
N21: =O21-Q21 -> 22423 | O21: 22423
C22: PUMP/POWER CHARGES | D22: Kshs. | E22: =meter!J7 -> 0 | N22: =O22-Q22 -> 9250 | O22: 9250
N23: =O23-Q23 -> 10162 | O23: 10162
C24: MONTH HOUSE RENT | D24: Kshs. | E24: =meter!N7 -> 7000 | N24: =O24-Q24 -> 10270 | O24: 10270
N25: =O25-Q25 -> 11070 | O25: 11070
C26: SECURITY | D26: Kshs. | E26: =meter!M7 -> 0 | N26: =O26-Q26 -> 11550 | O26: 11550
C27: GARBAGE FEE | D27: Kshs. | N27: =O27-Q27 -> 11393 | O27: 11393
C28: INTEREST ON ARREARS | D28: Kshs. | E28: =IF(E18*6%*3<0,0,E18*6%*3) -> 81.18 | N28: =O28-Q28 -> 10802 | O28: 10802
N29: =O29-Q29 -> 8930 | O29: 8930
C30: TOTAL PAYABLE | D30: Kshs. | E30: =SUM(E17:E29) -> 7832.18 | N30: =O30-Q30 -> 9570 | O30: 9570
N31: =O31-Q31 -> 11390 | O31: 11390
C32: PAID | E32: =meter!T7 -> 0 | N32: =O32-Q32 -> 10750 | O32: 10750
N33: =O33-Q33 -> 11732 | O33: 11732
C34: AMOUNT DUE | E34: =E30-E32 -> 7832.18 | N34: =O34-Q34 -> 10934 | O34: 10934 | R34: 700
B35: NOTE | N35: =O35-Q35 -> 10270 | O35: 10270
N36: =O36-Q36 -> 10598 | O36: 10598
C37: PAY BILL 4139271 ACC NO UM 4A | N37: =O37-Q37 -> 8770 | O37: 8770
N38: =O38-Q38 -> 8770 | O38: 8770
O39: =SUM(O3:O38) -> 391268 | Q39: =SUM(Q3:Q38) -> 0

Sheet 5A
B2: OLE SAMEDHA PREMIER HOSTELS | N2: VAR | O2: TAX DUE
B3: ='1A'!B2 -> P.O BOX 9473-00200 NAIROBI | N3: =O3-Q3 -> 10270 | O3: 10270
B4: WATER BILL | G4: BILL NO. | H4: ='1A'!H3+5-1 -> 42 | N4: =O4-Q4 -> 10304 | O4: 10304
N5: =O5-Q5 -> 10988 | O5: 10988
B6: TENANT NAME | C6: =meter!B8 -> NADYA JAMAL & AMINA ABDUL | N6: =O6-Q6 -> 11070 | O6: 11070
N7: =O7-Q7 -> 1197 | O7: 1197
B8: HOUSE NUMBER; | C8: 5A | N8: =O8-Q8 -> 9250 | O8: 9250
N9: =O9-Q9 -> 8770 | O9: 8770
B10: ISSUE DATE | C10: ='1A'!C9 -> 30TH JAN 2026 | N10: =O10-Q10 -> 23190 | O10: 23190
N11: =O11-Q11 -> 10910 | O11: 10910
B12: LAST PAY DATE | C12: ='1A'!C11 -> 5TH FEB 2026 | N12: =O12-Q12 -> 10910 | O12: 10910
N13: =O13-Q13 -> 12190 | O13: 12190
N14: =O14-Q14 -> 11070 | O14: 11070
B15: PREVIOUS READING | C15: CURRENT READING | E15: CONSUMPTION (Units) | N15: =O15-Q15 -> 9090 | O15: 9090
B16: =meter!E8 -> 18 | C16: =meter!F8 -> 21 | D16: Units | E16: =C16-B16 -> 3 | N16: =O16-Q16 -> 9420 | O16: 9420
E17: Amount(Kshs) | N17: =O17-Q17 -> 11154 | O17: 11154
C18: LAST ACCOUNT B/F | D18: Kshs. | E18: =meter!O8 -> 451 | N18: =O18-Q18 -> 10430 | O18: 10430
N19: =O19-Q19 -> 11831 | O19: 11831
C20: MONTH BILL | D20: Kshs. | E20: =meter!I8 -> 450 | N20: =O20-Q20 -> 10590 | O20: 10590
N21: =O21-Q21 -> 22423 | O21: 22423
C22: PUMP/POWER CHARGES | D22: Kshs. | E22: ='1A'!E21 -> 0 | N22: =O22-Q22 -> 9250 | O22: 9250
N23: =O23-Q23 -> 10162 | O23: 10162
C24: MONTH HOUSE RENT | D24: Kshs. | E24: =meter!N8 -> 7000 | N24: =O24-Q24 -> 10270 | O24: 10270
N25: =O25-Q25 -> 11070 | O25: 11070
C26: ='1A'!C25 -> SECURITY | D26: ='1A'!D25 -> Kshs. | E26: =meter!M8 -> 0 | N26: =O26-Q26 -> 11550 | O26: 11550
C27: GARBAGE FEE | D27: Kshs. | N27: =O27-Q27 -> 11393 | O27: 11393
C28: INTEREST ON ARREARS | D28: Kshs. | E28: =IF(E18*6%*3<0,0,E18*6%*3) -> 81.18 | N28: =O28-Q28 -> 10802 | O28: 10802
N29: =O29-Q29 -> 8930 | O29: 8930
C30: TOTAL PAYABLE | D30: Kshs. | E30: =SUM(E17:E29) -> 7982.18 | N30: =O30-Q30 -> 9570 | O30: 9570
N31: =O31-Q31 -> 11390 | O31: 11390
C32: PAID | E32: =meter!T8 -> 0 | N32: =O32-Q32 -> 10750 | O32: 10750
N33: =O33-Q33 -> 11732 | O33: 11732
C34: AMOUNT DUE | E34: =E30-E32 -> 7982.18 | N34: =O34-Q34 -> 10934 | O34: 10934 | R34: 700
B35: NOTE | N35: =O35-Q35 -> 10270 | O35: 10270
C36: PAY BILL 4139271 ACC NO UM 5A | N36: =O36-Q36 -> 10598 | O36: 10598
N37: =O37-Q37 -> 8770 | O37: 8770
N38: =O38-Q38 -> 8770 | O38: 8770
O39: =SUM(O3:O38) -> 391268 | Q39: =SUM(Q3:Q38) -> 0

Sheet 6A
B2: OLE SAMEDHA PREMIER HOSTELS | N2: VAR | O2: TAX DUE
B3: ='1A'!B2 -> P.O BOX 9473-00200 NAIROBI | N3: =O3-Q3 -> 10270 | O3: 10270
B4: WATER BILL | F4: BILL NO. | G4: BILL NO. | H4: ='1A'!H3+6-1 -> 43 | N4: =O4-Q4 -> 10304 | O4: 10304
N5: =O5-Q5 -> 10988 | O5: 10988
B6: TENANT NAME | C6: =meter!B9 -> 0 | N6: =O6-Q6 -> 11070 | O6: 11070
N7: =O7-Q7 -> 1197 | O7: 1197
B8: HOUSE NUMBER: | C8: 6A | N8: =O8-Q8 -> 9250 | O8: 9250
N9: =O9-Q9 -> 8770 | O9: 8770
B10: ISSUE DATE | C10: ='1A'!C9 -> 30TH JAN 2026 | N10: =O10-Q10 -> 23190 | O10: 23190
N11: =O11-Q11 -> 10910 | O11: 10910
B12: LAST PAY DATE | C12: ='1A'!C11 -> 5TH FEB 2026 | N12: =O12-Q12 -> 10910 | O12: 10910
N13: =O13-Q13 -> 12190 | O13: 12190
N14: =O14-Q14 -> 11070 | O14: 11070
B15: PREVIOUS READING | C15: CURRENT READING | E15: CONSUMPTION | N15: =O15-Q15 -> 9090 | O15: 9090
B16: =meter!E9 -> 11 | C16: =meter!F9 -> 11 | D16: Units | E16: =C16-B16 -> 0 | N16: =O16-Q16 -> 9420 | O16: 9420
E17: Amount(Kshs) | N17: =O17-Q17 -> 11154 | O17: 11154
C18: LAST ACCOUNT | D18: kshs. | E18: =meter!O9 -> 580 | N18: =O18-Q18 -> 10430 | O18: 10430
N19: =O19-Q19 -> 11831 | O19: 11831
C20: MONTH BILL | D20: KSHS. | E20: =meter!I9 -> 0 | N20: =O20-Q20 -> 10590 | O20: 10590
N21: =O21-Q21 -> 22423 | O21: 22423
C22: PUMP/POWER CHARGES | D22: KSHS. | E22: ='1A'!E21 -> 0 | N22: =O22-Q22 -> 9250 | O22: 9250
N23: =O23-Q23 -> 10162 | O23: 10162
C24: MONTH HOUSE RENT | D24: KSHS. | E24: =meter!N9 -> 6000 | N24: =O24-Q24 -> 10270 | O24: 10270
N25: =O25-Q25 -> 11070 | O25: 11070
C26: ='1A'!C25 -> SECURITY | D26: ='1A'!D25 -> Kshs. | E26: =meter!M9 -> 0 | N26: =O26-Q26 -> 11550 | O26: 11550
C27: GARBAGE FEE | N27: =O27-Q27 -> 11393 | O27: 11393
C28: ADJUSTMENT (Interest late payment) | D28: KSHS. | N28: =O28-Q28 -> 10802 | O28: 10802
N29: =O29-Q29 -> 8930 | O29: 8930
C30: TOTAL PAYABLE | D30: Kshs. | E30: =SUM(E17:E29) -> 6580 | N30: =O30-Q30 -> 9570 | O30: 9570
N31: =O31-Q31 -> 11390 | O31: 11390
C32: PAID | E32: =meter!T9 -> 0 | N32: =O32-Q32 -> 10750 | O32: 10750
N33: =O33-Q33 -> 11732 | O33: 11732
C34: AMOUNT DUE | E34: =E30-E32 -> 6580 | N34: =O34-Q34 -> 10934 | O34: 10934 | R34: 700
B35: NOTE | C35: PAY & VACATE, REPAIRS CHARGES OF 8,400/- REMAINS TILL NEW TENANT LEAVES, THEN WE REPAIR | N35: =O35-Q35 -> 10270 | O35: 10270
N36: =O36-Q36 -> 10598 | O36: 10598
C37: PAY BILL 4139271 ACC NO UM 6A | N37: =O37-Q37 -> 8770 | O37: 8770
N38: =O38-Q38 -> 8770 | O38: 8770
O39: =SUM(O3:O38) -> 391268 | Q39: =SUM(Q3:Q38) -> 0

Sheet 1B
B2: OLE SAMEDHA PREMIER HOSTELS | N2: VAR | O2: TAX DUE
B3: ='1A'!B2 -> P.O BOX 9473-00200 NAIROBI | N3: =O3-Q3 -> 10270 | O3: 10270
B4: WATER BILL | G4: BILL NO. | H4: ='1A'!H3+7-1 -> 44 | N4: =O4-Q4 -> 10304 | O4: 10304
N5: =O5-Q5 -> 10988 | O5: 10988
B6: TENANT NAME | C6: =meter!B10 -> MOHAMED | N6: =O6-Q6 -> 11070 | O6: 11070
N7: =O7-Q7 -> 1197 | O7: 1197
B8: HOUSE NUMBER: | C8: 1B | N8: =O8-Q8 -> 9250 | O8: 9250
C9: 072 | N9: =O9-Q9 -> 8770 | O9: 8770
B10: ISSUE DATE | C10: ='1A'!C9 -> 30TH JAN 2026 | N10: =O10-Q10 -> 23190 | O10: 23190
N11: =O11-Q11 -> 10910 | O11: 10910
B12: LAST PAY DATE | C12: ='1A'!C11 -> 5TH FEB 2026 | N12: =O12-Q12 -> 10910 | O12: 10910
N13: =O13-Q13 -> 12190 | O13: 12190
N14: =O14-Q14 -> 11070 | O14: 11070
B15: PREVIOUS READING | C15: CURRENT READING | E15: CONSUMPTION | N15: =O15-Q15 -> 9090 | O15: 9090
B16: =meter!E10 -> 9 | C16: =meter!F10 -> 10 | D16: Units | E16: =C16-B16 -> 1 | N16: =O16-Q16 -> 9420 | O16: 9420
E17: Amount (Kshs) | N17: =O17-Q17 -> 11154 | O17: 11154
C18: LAST ACCOUNT | D18: kshs. | E18: =meter!O10 -> 0 | N18: =O18-Q18 -> 10430 | O18: 10430
N19: =O19-Q19 -> 11831 | O19: 11831
C20: MONTH BILL | D20: KSHS. | E20: =meter!I10 -> 150 | N20: =O20-Q20 -> 10590 | O20: 10590
N21: =O21-Q21 -> 22423 | O21: 22423
C22: PUMP/POWER CHARGES | D22: KSHS. | E22: ='1A'!E21 -> 0 | N22: =O22-Q22 -> 9250 | O22: 9250
N23: =O23-Q23 -> 10162 | O23: 10162
C24: MONTH HOUSE RENT | D24: KSHS. | E24: =meter!N10 -> 7000 | N24: =O24-Q24 -> 10270 | O24: 10270
N25: =O25-Q25 -> 11070 | O25: 11070
C26: ='1A'!C25 -> SECURITY | D26: ='1A'!D25 -> Kshs. | E26: ='1A'!E25 -> 0 | N26: =O26-Q26 -> 11550 | O26: 11550
C27: GARBAGE FEE | N27: =O27-Q27 -> 11393 | O27: 11393
C28: ADJUSTMENT-interest on arrears | D28: KSHS. | E28: =IF(E18*6%*3<0,0,E18*6%*3) -> 0 | N28: =O28-Q28 -> 10802 | O28: 10802
N29: =O29-Q29 -> 8930 | O29: 8930
C30: TOTAL PAYABLE | D30: Kshs. | E30: =SUM(E17:E29) -> 7150 | N30: =O30-Q30 -> 9570 | O30: 9570
N31: =O31-Q31 -> 11390 | O31: 11390
C32: PAID | E32: =meter!T11 -> 0 | N32: =O32-Q32 -> 10750 | O32: 10750
N33: =O33-Q33 -> 11732 | O33: 11732
C34: AMOUNT DUE | E34: =E30-E32 -> 7150 | N34: =O34-Q34 -> 10934 | O34: 10934 | R34: 700
B35: NOTE | N35: =O35-Q35 -> 10270 | O35: 10270
C36: PAY BILL 4139271 ACC NO UM 1B | N36: =O36-Q36 -> 10598 | O36: 10598
N37: =O37-Q37 -> 8770 | O37: 8770
N38: =O38-Q38 -> 8770 | O38: 8770
O39: =SUM(O3:O38) -> 391268 | Q39: =SUM(Q3:Q38) -> 0

Sheet 2B
B2: OLE SAMEDHA PREMIER HOSTELS | N2: VAR | O2: TAX DUE
B3: ='1A'!B2 -> P.O BOX 9473-00200 NAIROBI | N3: =O3-Q3 -> 10270 | O3: 10270
B4: WATER BILL | G4: BILL NO. | H4: ='1A'!H3+8-1 -> 45 | N4: =O4-Q4 -> 10304 | O4: 10304
N5: =O5-Q5 -> 10988 | O5: 10988
B6: TENANT NAME | C6: =meter!B11 -> 0 | N6: =O6-Q6 -> 11070 | O6: 11070
N7: =O7-Q7 -> 1197 | O7: 1197
B8: HOUSE NUMBER: | C8: 2B | N8: =O8-Q8 -> 9250 | O8: 9250
N9: =O9-Q9 -> 8770 | O9: 8770
B10: ISSUE DATE | C10: ='1A'!C9 -> 30TH JAN 2026 | N10: =O10-Q10 -> 23190 | O10: 23190
N11: =O11-Q11 -> 10910 | O11: 10910
B12: LAST PAY DATE | C12: ='1A'!C11 -> 5TH FEB 2026 | N12: =O12-Q12 -> 10910 | O12: 10910
N13: =O13-Q13 -> 12190 | O13: 12190
N14: =O14-Q14 -> 11070 | O14: 11070
B15: PREVIOUS READING | C15: CURRENT READING | E15: CONSUMPTION | N15: =O15-Q15 -> 9090 | O15: 9090
B16: =meter!E11 -> 13 | C16: =meter!F11 -> 15 | D16: Units | E16: =C16-B16 -> 2 | N16: =O16-Q16 -> 9420 | O16: 9420
E17: Amount (Kshs.) | N17: =O17-Q17 -> 11154 | O17: 11154
C18: LAST ACCOUNT | D18: kshs. | E18: =meter!O11 -> 0 | N18: =O18-Q18 -> 10430 | O18: 10430
N19: =O19-Q19 -> 11831 | O19: 11831
C20: MONTH BILL | D20: KSHS. | E20: =meter!I11 -> 300 | N20: =O20-Q20 -> 10590 | O20: 10590
N21: =O21-Q21 -> 22423 | O21: 22423
C22: PUMP/POWER CHARGES | D22: KSHS. | E22: ='1A'!E21 -> 0 | N22: =O22-Q22 -> 9250 | O22: 9250
N23: =O23-Q23 -> 10162 | O23: 10162
C24: MONTH HOUSE RENT | D24: KSHS. | E24: =meter!N11 -> 7000 | N24: =O24-Q24 -> 10270 | O24: 10270
N25: =O25-Q25 -> 11070 | O25: 11070
C26: ='1A'!C25 -> SECURITY | D26: ='1A'!D25 -> Kshs. | E26: ='1A'!E25 -> 0 | N26: =O26-Q26 -> 11550 | O26: 11550
C27: GARBAGE FEE | D27: Kshs. | N27: =O27-Q27 -> 11393 | O27: 11393
C28: ADJUSTMENT-interest on arrears | D28: KSHS. | E28: =IF(E18*6%*3<0,0,E18*6%*3) -> 0 | N28: =O28-Q28 -> 10802 | O28: 10802
N29: =O29-Q29 -> 8930 | O29: 8930
C30: TOTAL PAYABLE | D30: Kshs. | E30: =SUM(E17:E29) -> 7300 | N30: =O30-Q30 -> 9570 | O30: 9570
N31: =O31-Q31 -> 11390 | O31: 11390
C32: PAID | E32: =meter!T11 -> 0 | N32: =O32-Q32 -> 10750 | O32: 10750
N33: =O33-Q33 -> 11732 | O33: 11732
C34: AMOUNT DUE | E34: =E30-E32 -> 7300 | N34: =O34-Q34 -> 10934 | O34: 10934 | R34: 700
N35: =O35-Q35 -> 10270 | O35: 10270
C36: PAY BILL 4139271 ACC NO UM 2B | N36: =O36-Q36 -> 10598 | O36: 10598
N37: =O37-Q37 -> 8770 | O37: 8770
N38: =O38-Q38 -> 8770 | O38: 8770
O39: =SUM(O3:O38) -> 391268 | Q39: =SUM(Q3:Q38) -> 0

Sheet 3B
B2: OLE SAMEDHA PREMIER HOSTELS | N2: VAR | O2: TAX DUE
B3: ='1A'!B2 -> P.O BOX 9473-00200 NAIROBI | N3: =O3-Q3 -> 10270 | O3: 10270
B4: WATER BILL | G4: BILL NO. | H4: ='1A'!H3+9-1 -> 46 | N4: =O4-Q4 -> 10304 | O4: 10304
N5: =O5-Q5 -> 10988 | O5: 10988
B6: TENANT NAME | C6: =meter!B12 -> NEW | N6: =O6-Q6 -> 11070 | O6: 11070
N7: =O7-Q7 -> 1197 | O7: 1197
B8: HOUSE NUMBER: | C8: 3B | N8: =O8-Q8 -> 9250 | O8: 9250
N9: =O9-Q9 -> 8770 | O9: 8770
B10: ISSUE DATE | C10: ='1A'!C9 -> 30TH JAN 2026 | N10: =O10-Q10 -> 23190 | O10: 23190
N11: =O11-Q11 -> 10910 | O11: 10910
B12: LAST PAY DATE | C12: ='1A'!C11 -> 5TH FEB 2026 | N12: =O12-Q12 -> 10910 | O12: 10910
N13: =O13-Q13 -> 12190 | O13: 12190
N14: =O14-Q14 -> 11070 | O14: 11070
B15: PREVIOUS READING | C15: CURRENT READING | E15: CONSUMPTION | N15: =O15-Q15 -> 9090 | O15: 9090
B16: =meter!E12 -> 10 | C16: =meter!F12 -> 15 | D16: Units | E16: =C16-B16 -> 5 | N16: =O16-Q16 -> 9420 | O16: 9420
E17: Amount (Kshs.) | N17: =O17-Q17 -> 11154 | O17: 11154
C18: LAST ACCOUNT | D18: kshs. | E18: =meter!O12 -> 0 | N18: =O18-Q18 -> 10430 | O18: 10430
N19: =O19-Q19 -> 11831 | O19: 11831
C20: MONTH BILL | D20: KSHS. | E20: =meter!I12 -> 750 | N20: =O20-Q20 -> 10590 | O20: 10590
N21: =O21-Q21 -> 22423 | O21: 22423
C22: PUMP/POWER CHARGES | D22: KSHS. | E22: ='1A'!E21 -> 0 | N22: =O22-Q22 -> 9250 | O22: 9250
N23: =O23-Q23 -> 10162 | O23: 10162
C24: MONTH HOUSE RENT | D24: KSHS. | E24: =meter!N12 -> 7000 | N24: =O24-Q24 -> 10270 | O24: 10270
N25: =O25-Q25 -> 11070 | O25: 11070
C26: ='1A'!C25 -> SECURITY | D26: ='1A'!D25 -> Kshs. | E26: ='1A'!E25 -> 0 | N26: =O26-Q26 -> 11550 | O26: 11550
C27: GARBAGE FEE | D27: Kshs. | N27: =O27-Q27 -> 11393 | O27: 11393
C28: Penalty & Interest late payment | D28: KSHS. | E28: =IF(E18*4%*1<0,0,E18*4%*1) -> 0 | N28: =O28-Q28 -> 10802 | O28: 10802
N29: =O29-Q29 -> 8930 | O29: 8930
C30: TOTAL PAYABLE | D30: Kshs. | E30: =SUM(E17:E29) -> 7750 | N30: =O30-Q30 -> 9570 | O30: 9570
N31: =O31-Q31 -> 11390 | O31: 11390
C32: PAID | E32: =meter!T12 -> 0 | N32: =O32-Q32 -> 10750 | O32: 10750
N33: =O33-Q33 -> 11732 | O33: 11732
C34: AMOUNT DUE | E34: =E30-E32 -> 7750 | N34: =O34-Q34 -> 10934 | O34: 10934 | R34: 700
B35: NOTE | N35: =O35-Q35 -> 10270 | O35: 10270
N36: =O36-Q36 -> 10598 | O36: 10598
C37: PAY BILL 4139271 ACC NO UM 3B | N37: =O37-Q37 -> 8770 | O37: 8770
N38: =O38-Q38 -> 8770 | O38: 8770
O39: =SUM(O3:O38) -> 391268 | Q39: =SUM(Q3:Q38) -> 0

Sheet 4B
B2: OLE SAMEDHA PREMIER HOSTELS | N2: VAR | O2: TAX DUE
B3: ='1A'!B2 -> P.O BOX 9473-00200 NAIROBI | N3: =O3-Q3 -> 10270 | O3: 10270
B4: WATER BILL | G4: BILL NO. | H4: ='1A'!H3+10-1 -> 47 | N4: =O4-Q4 -> 10304 | O4: 10304
N5: =O5-Q5 -> 10988 | O5: 10988
B6: TENANT NAME | C6: =meter!B13 -> 0 | N6: =O6-Q6 -> 11070 | O6: 11070
N7: =O7-Q7 -> 1197 | O7: 1197
B8: HOUSE NUMBER: | C8: 4B | N8: =O8-Q8 -> 9250 | O8: 9250
N9: =O9-Q9 -> 8770 | O9: 8770
B10: ISSUE DATE | C10: ='1A'!C9 -> 30TH JAN 2026 | N10: =O10-Q10 -> 23190 | O10: 23190
N11: =O11-Q11 -> 10910 | O11: 10910
B12: LAST PAY DATE | C12: ='1A'!C11 -> 5TH FEB 2026 | N12: =O12-Q12 -> 10910 | O12: 10910
N13: =O13-Q13 -> 12190 | O13: 12190
N14: =O14-Q14 -> 11070 | O14: 11070
B15: PREVIOUS READING | C15: CURRENT READING | E15: CONSUMPTION | N15: =O15-Q15 -> 9090 | O15: 9090
B16: =meter!E13 -> 16 | C16: =meter!F13 -> 17 | D16: Units | E16: =C16-B16 -> 1 | N16: =O16-Q16 -> 9420 | O16: 9420
E17: Amount (Kshs) | N17: =O17-Q17 -> 11154 | O17: 11154
C18: LAST ACCOUNT | D18: kshs. | E18: =meter!O13 -> 0 | N18: =O18-Q18 -> 10430 | O18: 10430
N19: =O19-Q19 -> 11831 | O19: 11831
C20: MONTH BILL | D20: KSHS. | E20: =meter!I13 -> 150 | N20: =O20-Q20 -> 10590 | O20: 10590
N21: =O21-Q21 -> 22423 | O21: 22423
C22: PUMP/POWER CHARGES | D22: KSHS. | E22: ='1A'!E21 -> 0 | N22: =O22-Q22 -> 9250 | O22: 9250
N23: =O23-Q23 -> 10162 | O23: 10162
C24: MONTH HOUSE RENT | D24: KSHS. | E24: =meter!N13 -> 7000 | N24: =O24-Q24 -> 10270 | O24: 10270
N25: =O25-Q25 -> 11070 | O25: 11070
C26: ='1A'!C25 -> SECURITY | D26: KSHS. | E26: =meter!M13 -> 0 | N26: =O26-Q26 -> 11550 | O26: 11550
C27: GARBAGE FEE | D27: KSHS. | N27: =O27-Q27 -> 11393 | O27: 11393
C28: INTEREST ON LATE PAYMENT | D28: KSHS. | E28: =IF(E18*4%*1<0,0,E18*4%*1) -> 0 | N28: =O28-Q28 -> 10802 | O28: 10802
N29: =O29-Q29 -> 8930 | O29: 8930
C30: TOTAL PAYABLE | D30: Kshs. | E30: =SUM(E17:E29) -> 7150 | N30: =O30-Q30 -> 9570 | O30: 9570
N31: =O31-Q31 -> 11390 | O31: 11390
C32: PAID | E32: =meter!T13 -> 0 | N32: =O32-Q32 -> 10750 | O32: 10750
N33: =O33-Q33 -> 11732 | O33: 11732
C34: AMOUNT DUE | E34: =E30-E32 -> 7150 | N34: =O34-Q34 -> 10934 | O34: 10934 | R34: 700
B35: NOTE | N35: =O35-Q35 -> 10270 | O35: 10270
C36: PAY BILL 4139271 ACC NO UM 4B | N36: =O36-Q36 -> 10598 | O36: 10598
N37: =O37-Q37 -> 8770 | O37: 8770
N38: =O38-Q38 -> 8770 | O38: 8770
O39: =SUM(O3:O38) -> 391268 | Q39: =SUM(Q3:Q38) -> 0

Sheet 5B
B2: OLE SAMEDHA PREMIER HOSTELS | N2: VAR | O2: TAX DUE
B3: ='1A'!B2 -> P.O BOX 9473-00200 NAIROBI | N3: =O3-Q3 -> 10270 | O3: 10270
B4: WATER BILL | G4: BILL NO. | H4: ='1A'!H3+11-1 -> 48 | N4: =O4-Q4 -> 10304 | O4: 10304
N5: =O5-Q5 -> 10988 | O5: 10988
B6: TENANT NAME | C6: =meter!B14 -> 0 | N6: =O6-Q6 -> 11070 | O6: 11070
N7: =O7-Q7 -> 1197 | O7: 1197
B8: HOUSE NUMBER: | C8: 5B | N8: =O8-Q8 -> 9250 | O8: 9250
N9: =O9-Q9 -> 8770 | O9: 8770
B10: ISSUE DATE | C10: ='1A'!C9 -> 30TH JAN 2026 | N10: =O10-Q10 -> 23190 | O10: 23190
N11: =O11-Q11 -> 10910 | O11: 10910
B12: LAST PAY DATE | C12: ='1A'!C11 -> 5TH FEB 2026 | N12: =O12-Q12 -> 10910 | O12: 10910
N13: =O13-Q13 -> 12190 | O13: 12190
N14: =O14-Q14 -> 11070 | O14: 11070
B15: PREVIOUS READING | C15: CURRENT READING | E15: CONSUMPTION | N15: =O15-Q15 -> 9090 | O15: 9090
B16: =meter!E14 -> 1 | C16: =meter!F14 -> 1 | D16: Units | E16: =C16-B16 -> 0 | N16: =O16-Q16 -> 9420 | O16: 9420
E17: Amount (Kshs.) | N17: =O17-Q17 -> 11154 | O17: 11154
C18: LAST ACCOUNT | D18: kshs. | E18: =meter!O14 -> 451 | N18: =O18-Q18 -> 10430 | O18: 10430
N19: =O19-Q19 -> 11831 | O19: 11831
C20: MONTH BILL | D20: KSHS. | E20: =meter!I14 -> 0 | N20: =O20-Q20 -> 10590 | O20: 10590
N21: =O21-Q21 -> 22423 | O21: 22423
C22: PUMP/POWER CHARGES | D22: KSHS. | E22: ='1A'!E21 -> 0 | N22: =O22-Q22 -> 9250 | O22: 9250
N23: =O23-Q23 -> 10162 | O23: 10162
C24: MONTH HOUSE RENT | D24: KSHS. | E24: =meter!N14 -> 7000 | N24: =O24-Q24 -> 10270 | O24: 10270
N25: =O25-Q25 -> 11070 | O25: 11070
C26: ='1A'!C25 -> SECURITY | D26: KSHS. | E26: ='1A'!E25 -> 0 | N26: =O26-Q26 -> 11550 | O26: 11550
C27: GARBAGE FEE | D27: KSHS. | N27: =O27-Q27 -> 11393 | O27: 11393
C28: INTEREST ON LATE PAYMENT | D28: KSHS. | E28: =IF(E18*4%*1<0,0,E18*4%*1) -> 18.04 | N28: =O28-Q28 -> 10802 | O28: 10802
N29: =O29-Q29 -> 8930 | O29: 8930
C30: TOTAL PAYABLE | D30: Kshs. | E30: =SUM(E17:E29) -> 7469.04 | N30: =O30-Q30 -> 9570 | O30: 9570
N31: =O31-Q31 -> 11390 | O31: 11390
C32: PAID | E32: =meter!T14 -> 0 | N32: =O32-Q32 -> 10750 | O32: 10750
N33: =O33-Q33 -> 11732 | O33: 11732
C34: AMOUNT DUE | E34: =E30-E32 -> 7469.04 | N34: =O34-Q34 -> 10934 | O34: 10934 | R34: 700
N35: =O35-Q35 -> 10270 | O35: 10270
C36: PAYBILL 4139271 ACC NO UM 5B | N36: =O36-Q36 -> 10598 | O36: 10598
N37: =O37-Q37 -> 8770 | O37: 8770
N38: =O38-Q38 -> 8770 | O38: 8770
O39: =SUM(O3:O38) -> 391268 | Q39: =SUM(Q3:Q38) -> 0

Sheet 6B
B2: OLE SAMEDHA PREMIER HOSTELS | N2: VAR | O2: TAX DUE
B3: ='1A'!B2 -> P.O BOX 9473-00200 NAIROBI | N3: =O3-Q3 -> 10270 | O3: 10270
B4: WATER BILL | H4: BILL NO. | I4: ='1A'!H3+12-1 -> 49 | J4: ='1A'!H3+12-1 -> 49 | N4: =O4-Q4 -> 10304 | O4: 10304
N5: =O5-Q5 -> 10988 | O5: 10988
B6: TENANT NAME | D6: =meter!B15 -> MUNIRA | N6: =O6-Q6 -> 11070 | O6: 11070
N7: =O7-Q7 -> 1197 | O7: 1197
B8: HOUSE NUMBER: | D8: 6B | N8: =O8-Q8 -> 9250 | O8: 9250
N9: =O9-Q9 -> 8770 | O9: 8770
B10: ISSUE DATE | D10: ='1A'!C9 -> 30TH JAN 2026 | N10: =O10-Q10 -> 23190 | O10: 23190
N11: =O11-Q11 -> 10910 | O11: 10910
B12: LAST PAY DATE | D12: ='1A'!C11 -> 5TH FEB 2026 | N12: =O12-Q12 -> 10910 | O12: 10910
N13: =O13-Q13 -> 12190 | O13: 12190
N14: =O14-Q14 -> 11070 | O14: 11070
B15: PREVIOUS READING | D15: CURRENT READING | F15: CONSUMPTION | N15: =O15-Q15 -> 9090 | O15: 9090
B16: =meter!E15 -> 23 | D16: =meter!F15 -> 27 | E16: Units | F16: =D16-B16 -> 4 | N16: =O16-Q16 -> 9420 | O16: 9420
F17: Amount (Kshs.) | N17: =O17-Q17 -> 11154 | O17: 11154
D18: LAST ACCOUNT | E18: kshs. | F18: =meter!O15 -> 0 | N18: =O18-Q18 -> 10430 | O18: 10430
N19: =O19-Q19 -> 11831 | O19: 11831
D20: MONTH BILL | E20: KSHS. | F20: =meter!I15 -> 600 | N20: =O20-Q20 -> 10590 | O20: 10590
N21: =O21-Q21 -> 22423 | O21: 22423
D22: PUMP/POWER CHARGES | E22: KSHS. | F22: ='1A'!E21 -> 0 | N22: =O22-Q22 -> 9250 | O22: 9250
N23: =O23-Q23 -> 10162 | O23: 10162
D24: MONTH HOUSE RENT | E24: KSHS. | F24: =meter!N15 -> 8000 | N24: =O24-Q24 -> 10270 | O24: 10270
N25: =O25-Q25 -> 11070 | O25: 11070
D26: SECURITY | E26: KSHS. | F26: =meter!M15 -> 0 | N26: =O26-Q26 -> 11550 | O26: 11550
D27: GARBAGE FEE | N27: =O27-Q27 -> 11393 | O27: 11393
D28: INTEREST ON LATE PAYMENT | E28: KSHS. | F28: =IF(F18*4%*1<0,0,F18*4%*1) -> 0 | N28: =O28-Q28 -> 10802 | O28: 10802
N29: =O29-Q29 -> 8930 | O29: 8930
C30: TOTAL PAYABLE | D30: TOTAL PAYABLE | E30: Kshs. | F30: =SUM(F17:F29) -> 8600 | N30: =O30-Q30 -> 9570 | O30: 9570
N31: =O31-Q31 -> 11390 | O31: 11390
C32: PAID | D32: PAID | F32: =meter!T15 -> 0 | N32: =O32-Q32 -> 10750 | O32: 10750
N33: =O33-Q33 -> 11732 | O33: 11732
C34: BALANCE C/F | D34: AMOUNT DUE | F34: =F30-F32 -> 8600 | N34: =O34-Q34 -> 10934 | O34: 10934 | R34: 700
B35: NOTE | N35: =O35-Q35 -> 10270 | O35: 10270
D36: PAY BILL 4139271 ACC NO UM 6B | N36: =O36-Q36 -> 10598 | O36: 10598
N37: =O37-Q37 -> 8770 | O37: 8770
N38: =O38-Q38 -> 8770 | O38: 8770
O39: =SUM(O3:O38) -> 391268 | Q39: =SUM(Q3:Q38) -> 0

Sheet 1C
B2: OLE SAMEDHA PREMIER HOSTELS | N2: VAR | O2: TAX DUE
B3: ='1A'!B2 -> P.O BOX 9473-00200 NAIROBI | N3: =O3-Q3 -> 10270 | O3: 10270
B4: WATER BILL | G4: BILL NO. | H4: ='1A'!H3+13-1 -> 50 | N4: =O4-Q4 -> 10304 | O4: 10304
N5: =O5-Q5 -> 10988 | O5: 10988
B6: TENANT NAME | D6: =meter!B16 -> RIDHWAN | N6: =O6-Q6 -> 11070 | O6: 11070
N7: =O7-Q7 -> 1197 | O7: 1197
B8: HOUSE NUMBER: | D8: 1C | N8: =O8-Q8 -> 9250 | O8: 9250
N9: =O9-Q9 -> 8770 | O9: 8770
B10: ISSUE DATE | D10: ='1A'!C9 -> 30TH JAN 2026 | N10: =O10-Q10 -> 23190 | O10: 23190
N11: =O11-Q11 -> 10910 | O11: 10910
B12: LAST PAY DATE | D12: ='1A'!C11 -> 5TH FEB 2026 | N12: =O12-Q12 -> 10910 | O12: 10910
N13: =O13-Q13 -> 12190 | O13: 12190
N14: =O14-Q14 -> 11070 | O14: 11070
B15: PREVIOUS READING | D15: CURRENT READING | F15: CONSUMPTION | N15: =O15-Q15 -> 9090 | O15: 9090
B16: =meter!E16 -> 13 | D16: =meter!F16 -> 13 | E16: Units | F16: =D16-B16 -> 0 | N16: =O16-Q16 -> 9420 | O16: 9420
F17: Amount (Kshs.) | N17: =O17-Q17 -> 11154 | O17: 11154
D18: LAST ACCOUNT B/F | E18: kshs. | F18: =meter!O16 -> 0 | N18: =O18-Q18 -> 10430 | O18: 10430
N19: =O19-Q19 -> 11831 | O19: 11831
D20: MONTH BILL | E20: KSHS. | F20: =meter!I16 -> 0 | N20: =O20-Q20 -> 10590 | O20: 10590
N21: =O21-Q21 -> 22423 | O21: 22423
D22: PUMP/POWER CHARGES | E22: KSHS. | F22: ='1A'!E21 -> 0 | N22: =O22-Q22 -> 9250 | O22: 9250
N23: =O23-Q23 -> 10162 | O23: 10162
D24: MONTH HOUSE RENT | E24: KSHS. | F24: =meter!N16 -> 8000 | N24: =O24-Q24 -> 10270 | O24: 10270
N25: =O25-Q25 -> 11070 | O25: 11070
D26: SECURITY | E26: KSHS. | F26: =meter!M16 -> 0 | N26: =O26-Q26 -> 11550 | O26: 11550
D27: GARBAGE FEE | E27: KSHS. | N27: =O27-Q27 -> 11393 | O27: 11393
D28: INTEREST ON LATE PAYMENT | E28: KSHS. | F28: =IF(F18*4%*1<0,0,F18*4%*1) -> 0 | N28: =O28-Q28 -> 10802 | O28: 10802
N29: =O29-Q29 -> 8930 | O29: 8930
D30: TOTAL PAYABLE | E30: Kshs. | F30: =SUM(F17:F29) -> 8000 | N30: =O30-Q30 -> 9570 | O30: 9570
N31: =O31-Q31 -> 11390 | O31: 11390
D32: PAID | F32: =meter!T16 -> 0 | N32: =O32-Q32 -> 10750 | O32: 10750
N33: =O33-Q33 -> 11732 | O33: 11732
D34: AMOUNT DUE | F34: =F30-F32 -> 8000 | N34: =O34-Q34 -> 10934 | O34: 10934 | R34: 700
N35: =O35-Q35 -> 10270 | O35: 10270
D36: PAY BILL 4139271 ACC NO UM 1C | N36: =O36-Q36 -> 10598 | O36: 10598
N37: =O37-Q37 -> 8770 | O37: 8770
N38: =O38-Q38 -> 8770 | O38: 8770
O39: =SUM(O3:O38) -> 391268 | Q39: =SUM(Q3:Q38) -> 0

Sheet 2C
B2: OLE SAMEDHA APARTMENTS-Kitengela | D2: OLE SAMEDHA PREMIER HOSTELS | N2: VAR | O2: TAX DUE
B3: ='1A'!B2 -> P.O BOX 9473-00200 NAIROBI | N3: =O3-Q3 -> 10270 | O3: 10270
B4: WATER BILL | H4: BILL NO. | I4: ='1A'!H3+14-1 -> 51 | J4: ='1A'!H3+14-1 -> 51 | N4: =O4-Q4 -> 10304 | O4: 10304
N5: =O5-Q5 -> 10988 | O5: 10988
B6: TENANT NAME | D6: =meter!B17 -> 0 | N6: =O6-Q6 -> 11070 | O6: 11070
N7: =O7-Q7 -> 1197 | O7: 1197
B8: HOUSE NUMBER: | D8: 2C | N8: =O8-Q8 -> 9250 | O8: 9250
N9: =O9-Q9 -> 8770 | O9: 8770
B10: ISSUE DATE | D10: ='1A'!C9 -> 30TH JAN 2026 | N10: =O10-Q10 -> 23190 | O10: 23190
N11: =O11-Q11 -> 10910 | O11: 10910
B12: LAST PAY DATE | D12: ='1A'!C11 -> 5TH FEB 2026 | N12: =O12-Q12 -> 10910 | O12: 10910
N13: =O13-Q13 -> 12190 | O13: 12190
N14: =O14-Q14 -> 11070 | O14: 11070
B15: PREVIOUS READING | D15: CURRENT READING | F15: CONSUMPTION | N15: =O15-Q15 -> 9090 | O15: 9090
B16: =meter!E17 -> 45 | D16: =meter!F17 -> 45 | E16: Units | F16: =D16-B16 -> 0 | H16: ESTIMATE | N16: =O16-Q16 -> 9420 | O16: 9420
F17: Amount (Kshs.) | N17: =O17-Q17 -> 11154 | O17: 11154
D18: LAST ACCOUNT B/F | E18: kshs. | F18: =meter!O17 -> 516 | N18: =O18-Q18 -> 10430 | O18: 10430
N19: =O19-Q19 -> 11831 | O19: 11831
D20: MONTH BILL | E20: KSHS. | F20: =meter!I17 -> 0 | N20: =O20-Q20 -> 10590 | O20: 10590
N21: =O21-Q21 -> 22423 | O21: 22423
D22: PUMP/POWER CHARGES | E22: KSHS. | F22: ='1A'!E21 -> 0 | N22: =O22-Q22 -> 9250 | O22: 9250
N23: =O23-Q23 -> 10162 | O23: 10162
D24: MONTH HOUSE RENT | E24: KSHS. | F24: =meter!N17 -> 8000 | N24: =O24-Q24 -> 10270 | O24: 10270
N25: =O25-Q25 -> 11070 | O25: 11070
D26: ='1A'!C25 -> SECURITY | E26: ='1A'!D25 -> Kshs. | F26: ='1A'!E25 -> 0 | N26: =O26-Q26 -> 11550 | O26: 11550
D27: GARBAGE FEE | E27: Kshs. | N27: =O27-Q27 -> 11393 | O27: 11393
D28: ADJUSTMENT (Interest late payment) | E28: KSHS. | F28: =IF(F18*4%*1<0,0,F18*4%*1) -> 20.64 | N28: =O28-Q28 -> 10802 | O28: 10802
N29: =O29-Q29 -> 8930 | O29: 8930
D30: TOTAL PAYABLE | E30: Kshs. | F30: =SUM(F17:F29) -> 8536.64 | N30: =O30-Q30 -> 9570 | O30: 9570
N31: =O31-Q31 -> 11390 | O31: 11390
D32: PAID | F32: =meter!T17 -> 0 | N32: =O32-Q32 -> 10750 | O32: 10750
N33: =O33-Q33 -> 11732 | O33: 11732
D34: AMOUNT DUE | F34: =F30-F32 -> 8536.64 | N34: =O34-Q34 -> 10934 | O34: 10934 | R34: 700
C35: NOTE | N35: =O35-Q35 -> 10270 | O35: 10270
N36: =O36-Q36 -> 10598 | O36: 10598
D37: PAY BILL 4139271 ACC NO UM 2C | N37: =O37-Q37 -> 8770 | O37: 8770
N38: =O38-Q38 -> 8770 | O38: 8770
O39: =SUM(O3:O38) -> 391268 | Q39: =SUM(Q3:Q38) -> 0

Sheet 3C
B2: OLE SAMEDHA PREMIER HOSTELS | N2: VAR | O2: TAX DUE
B3: ='1A'!B2 -> P.O BOX 9473-00200 NAIROBI | N3: =O3-Q3 -> 10270 | O3: 10270
B4: WATER BILL | H4: BILL NO. | I4: ='1A'!H3+15-1 -> 52 | J4: ='1A'!H3+15-1 -> 52 | N4: =O4-Q4 -> 10304 | O4: 10304
N5: =O5-Q5 -> 10988 | O5: 10988
B6: TENANT NAME | D6: =meter!B18 -> AHMED | N6: =O6-Q6 -> 11070 | O6: 11070
N7: =O7-Q7 -> 1197 | O7: 1197
B8: HOUSE NUMBER: | D8: 3C | N8: =O8-Q8 -> 9250 | O8: 9250
N9: =O9-Q9 -> 8770 | O9: 8770
B10: ISSUE DATE | D10: ='1A'!C9 -> 30TH JAN 2026 | N10: =O10-Q10 -> 23190 | O10: 23190
N11: =O11-Q11 -> 10910 | O11: 10910
B12: LAST PAY DATE | D12: ='1A'!C11 -> 5TH FEB 2026 | N12: =O12-Q12 -> 10910 | O12: 10910
N13: =O13-Q13 -> 12190 | O13: 12190
N14: =O14-Q14 -> 11070 | O14: 11070
B15: PREVIOUS READING | D15: CURRENT READING | F15: CONSUMPTION | N15: =O15-Q15 -> 9090 | O15: 9090
B16: =meter!E18 -> 52 | D16: =meter!F18 -> 52 | E16: Units | F16: =D16-B16 -> 0 | N16: =O16-Q16 -> 9420 | O16: 9420
F17: Amount (Kshs) | N17: =O17-Q17 -> 11154 | O17: 11154
D18: LAST ACCOUNT B/F | E18: kshs. | F18: =meter!O18 -> 0 | N18: =O18-Q18 -> 10430 | O18: 10430
N19: =O19-Q19 -> 11831 | O19: 11831
D20: MONTH BILL | E20: KSHS. | F20: =meter!I18 -> 0 | N20: =O20-Q20 -> 10590 | O20: 10590
N21: =O21-Q21 -> 22423 | O21: 22423
D22: PUMP/POWER CHARGES | E22: KSHS. | F22: ='1A'!E21 -> 0 | N22: =O22-Q22 -> 9250 | O22: 9250
N23: =O23-Q23 -> 10162 | O23: 10162
D24: MONTH HOUSE RENT | E24: KSHS. | F24: =meter!N18 -> 10000 | N24: =O24-Q24 -> 10270 | O24: 10270
N25: =O25-Q25 -> 11070 | O25: 11070
D26: ='1A'!C25 -> SECURITY | E26: ='1A'!D25 -> Kshs. | F26: ='1A'!E25 -> 0 | N26: =O26-Q26 -> 11550 | O26: 11550
D27: GARBAGE FEE | E27: Kshs. | N27: =O27-Q27 -> 11393 | O27: 11393
D28: ADJUSTMENT (Interest late payment) | E28: KSHS. | F28: =IF(F18*4%*1<0,0,F18*4%*1) -> 0 | N28: =O28-Q28 -> 10802 | O28: 10802
N29: =O29-Q29 -> 8930 | O29: 8930
C30: TOTAL PAYABLE | D30: AMOUNT PAYABLE | E30: Kshs. | F30: =SUM(F17:F29) -> 10000 | N30: =O30-Q30 -> 9570 | O30: 9570
N31: =O31-Q31 -> 11390 | O31: 11390
C32: PAID | E32: KSHS | F32: =meter!T18 -> 0 | N32: =O32-Q32 -> 10750 | O32: 10750
N33: =O33-Q33 -> 11732 | O33: 11732
C34: BALANCE C/F | D34: AMOUNT DUE | E34: KSHS. | F34: =F30-F32 -> 10000 | N34: =O34-Q34 -> 10934 | O34: 10934 | R34: 700
B35: NOTE | N35: =O35-Q35 -> 10270 | O35: 10270
D36: PAY BILL 4139271 ACC NO UM 3C | N36: =O36-Q36 -> 10598 | O36: 10598
N37: =O37-Q37 -> 8770 | O37: 8770
N38: =O38-Q38 -> 8770 | O38: 8770
O39: =SUM(O3:O38) -> 391268 | Q39: =SUM(Q3:Q38) -> 0

Sheet 4C
B2: OLE SAMEDHA PREMIER HOSTELS | N2: VAR | O2: TAX DUE
B3: ='1A'!B2 -> P.O BOX 9473-00200 NAIROBI | N3: =O3-Q3 -> 10270 | O3: 10270
B4: WATER BILL | H4: BILL NO. | I4: ='1A'!H3+16-1 -> 53 | M4: ='1A'!H3+16-1 -> 53 | N4: =O4-Q4 -> 10304 | O4: 10304
N5: =O5-Q5 -> 10988 | O5: 10988
B6: TENANT NAME | D6: =meter!B19 -> ABASS | N6: =O6-Q6 -> 11070 | O6: 11070
N7: =O7-Q7 -> 1197 | O7: 1197
B8: HOUSE NUMBER: | D8: 4C | N8: =O8-Q8 -> 9250 | O8: 9250
N9: =O9-Q9 -> 8770 | O9: 8770
B10: ISSUE DATE | D10: ='1A'!C9 -> 30TH JAN 2026 | N10: =O10-Q10 -> 23190 | O10: 23190
N11: =O11-Q11 -> 10910 | O11: 10910
B12: LAST PAY DATE | D12: ='1A'!C11 -> 5TH FEB 2026 | N12: =O12-Q12 -> 10910 | O12: 10910
N13: =O13-Q13 -> 12190 | O13: 12190
N14: =O14-Q14 -> 11070 | O14: 11070
B15: PREVIOUS READING | D15: CURRENT READING | F15: CONSUMPTION | N15: =O15-Q15 -> 9090 | O15: 9090
B16: =meter!E19 -> 11 | D16: =meter!F19 -> 12 | E16: Units | F16: =D16-B16 -> 1 | N16: =O16-Q16 -> 9420 | O16: 9420
F17: Amount (Kshs.) | N17: =O17-Q17 -> 11154 | O17: 11154
D18: LAST ACCOUNT B/F | E18: kshs. | F18: =meter!O19 -> 516 | N18: =O18-Q18 -> 10430 | O18: 10430
N19: =O19-Q19 -> 11831 | O19: 11831
D20: MONTH BILL | E20: KSHS. | F20: =meter!I19 -> 150 | N20: =O20-Q20 -> 10590 | O20: 10590
N21: =O21-Q21 -> 22423 | O21: 22423
D22: PUMP/POWER CHARGES | E22: KSHS. | F22: ='1A'!E21 -> 0 | N22: =O22-Q22 -> 9250 | O22: 9250
N23: =O23-Q23 -> 10162 | O23: 10162
D24: MONTH HOUSE RENT | E24: KSHS. | F24: =meter!N19 -> 8000 | N24: =O24-Q24 -> 10270 | O24: 10270
N25: =O25-Q25 -> 11070 | O25: 11070
D26: ='1A'!C25 -> SECURITY | E26: ='1A'!D25 -> Kshs. | F26: ='1A'!E25 -> 0 | N26: =O26-Q26 -> 11550 | O26: 11550
D27: GARBAGE FEE | E27: Kshs. | N27: =O27-Q27 -> 11393 | O27: 11393
D28: ADJUSTMENT-INTEREST LATE PAYMENT | E28: KSHS. | F28: =IF(F18*4%*1<0,0,F18*4%*1) -> 20.64 | N28: =O28-Q28 -> 10802 | O28: 10802
N29: =O29-Q29 -> 8930 | O29: 8930
D30: TOTAL PAYABLE | E30: Kshs. | F30: =SUM(F17:F29) -> 8686.64 | N30: =O30-Q30 -> 9570 | O30: 9570
N31: =O31-Q31 -> 11390 | O31: 11390
D32: PAID | F32: =meter!T19 -> 0 | N32: =O32-Q32 -> 10750 | O32: 10750
N33: =O33-Q33 -> 11732 | O33: 11732
D34: AMOUNT DUE | F34: =F30-F32 -> 8686.64 | N34: =O34-Q34 -> 10934 | O34: 10934 | R34: 700
C35: NOTE | N35: =O35-Q35 -> 10270 | O35: 10270
D36: PAYBILL 4139271 ACC NO UM 4C | N36: =O36-Q36 -> 10598 | O36: 10598
N37: =O37-Q37 -> 8770 | O37: 8770
N38: =O38-Q38 -> 8770 | O38: 8770
O39: =SUM(O3:O38) -> 391268 | Q39: =SUM(Q3:Q38) -> 0

Sheet 5C
B2: OLE SAMEDHA APARTMENTS-Kitengela | D2: OLE SAMEDHA PREMIER HOSTELS | N2: VAR | O2: TAX DUE
B3: ='1A'!B2 -> P.O BOX 9473-00200 NAIROBI | N3: =O3-Q3 -> 10270 | O3: 10270
B4: WATER BILL | H4: BILL NO. | I4: ='1A'!H3+17-1 -> 54 | J4: ='1A'!H3+17-1 -> 54 | N4: =O4-Q4 -> 10304 | O4: 10304
N5: =O5-Q5 -> 10988 | O5: 10988
B6: TENANT NAME | D6: =meter!B20 -> 0 | N6: =O6-Q6 -> 11070 | O6: 11070
N7: =O7-Q7 -> 1197 | O7: 1197
B8: HOUSE NUMBER: | D8: 5C | N8: =O8-Q8 -> 9250 | O8: 9250
D9: 0775203183 | N9: =O9-Q9 -> 8770 | O9: 8770
B10: ISSUE DATE | D10: ='1A'!C9 -> 30TH JAN 2026 | N10: =O10-Q10 -> 23190 | O10: 23190
N11: =O11-Q11 -> 10910 | O11: 10910
B12: LAST PAY DATE | D12: ='1A'!C11 -> 5TH FEB 2026 | N12: =O12-Q12 -> 10910 | O12: 10910
N13: =O13-Q13 -> 12190 | O13: 12190
N14: =O14-Q14 -> 11070 | O14: 11070
B15: PREVIOUS READING | D15: CURRENT READING | F15: CONSUMPTION | N15: =O15-Q15 -> 9090 | O15: 9090
B16: =meter!E20 -> 12 | D16: =meter!F20 -> 12 | E16: Units | F16: =D16-B16 -> 0 | N16: =O16-Q16 -> 9420 | O16: 9420
F17: Amount (Kshs.) | N17: =O17-Q17 -> 11154 | O17: 11154
D18: LAST ACCOUNT B/F | E18: kshs. | F18: =meter!O20 -> 0 | N18: =O18-Q18 -> 10430 | O18: 10430
N19: =O19-Q19 -> 11831 | O19: 11831
D20: MONTH BILL | E20: KSHS. | F20: =meter!I20 -> 0 | N20: =O20-Q20 -> 10590 | O20: 10590
N21: =O21-Q21 -> 22423 | O21: 22423
D22: PUMP/POWER CHARGES | E22: KSHS. | F22: ='1A'!E21 -> 0 | N22: =O22-Q22 -> 9250 | O22: 9250
N23: =O23-Q23 -> 10162 | O23: 10162
D24: MONTH HOUSE RENT | E24: KSHS. | F24: =meter!N20 -> 8000 | N24: =O24-Q24 -> 10270 | O24: 10270
N25: =O25-Q25 -> 11070 | O25: 11070
D26: ='1A'!C25 -> SECURITY | E26: ='1A'!D25 -> Kshs. | F26: ='1A'!E25 -> 0 | N26: =O26-Q26 -> 11550 | O26: 11550
D27: GARBAGE FEE | E27: Kshs. | N27: =O27-Q27 -> 11393 | O27: 11393
D28: INTEREST LATE PAYMENT | E28: KSHS. | F28: =IF(F18*8%*1<0,0,F18*8%*1) -> 0 | N28: =O28-Q28 -> 10802 | O28: 10802
N29: =O29-Q29 -> 8930 | O29: 8930
D30: TOTAL PAYABLE | E30: Kshs. | F30: =SUM(F17:F29) -> 8000 | N30: =O30-Q30 -> 9570 | O30: 9570
N31: =O31-Q31 -> 11390 | O31: 11390
D32: PAID | F32: =meter!T20 -> 0 | N32: =O32-Q32 -> 10750 | O32: 10750
N33: =O33-Q33 -> 11732 | O33: 11732
D34: AMOUNT DUE | F34: =F30-F32 -> 8000 | N34: =O34-Q34 -> 10934 | O34: 10934 | R34: 700
C35: NOTE | N35: =O35-Q35 -> 10270 | O35: 10270
N36: =O36-Q36 -> 10598 | O36: 10598
D37: PAY BILL 4139271 ACC NO UM 5C | N37: =O37-Q37 -> 8770 | O37: 8770
N38: =O38-Q38 -> 8770 | O38: 8770
O39: =SUM(O3:O38) -> 391268 | Q39: =SUM(Q3:Q38) -> 0

Sheet 6C
B2: OLE SAMEDHA PREMIER HOSTELS | N2: VAR | O2: TAX DUE
B3: ='1A'!B2 -> P.O BOX 9473-00200 NAIROBI | N3: =O3-Q3 -> 10270 | O3: 10270
B4: WATER BILL | H4: BILL NO. | I4: ='1A'!H3+18-1 -> 55 | K4: ='1A'!H3+18-1 -> 55 | N4: =O4-Q4 -> 10304 | O4: 10304
N5: =O5-Q5 -> 10988 | O5: 10988
B6: TENANT NAME | D6: =meter!B21 -> KHADIJA | N6: =O6-Q6 -> 11070 | O6: 11070
N7: =O7-Q7 -> 1197 | O7: 1197
B8: HOUSE NUMBER | D8: 6C | N8: =O8-Q8 -> 9250 | O8: 9250
N9: =O9-Q9 -> 8770 | O9: 8770
B10: ISSUE DATE | D10: ='1A'!C9 -> 30TH JAN 2026 | N10: =O10-Q10 -> 23190 | O10: 23190
N11: =O11-Q11 -> 10910 | O11: 10910
B12: LAST PAY DATE | D12: ='1A'!C11 -> 5TH FEB 2026 | N12: =O12-Q12 -> 10910 | O12: 10910
N13: =O13-Q13 -> 12190 | O13: 12190
N14: =O14-Q14 -> 11070 | O14: 11070
B15: PREVIOUS READING | D15: CURRENT READING | F15: CONSUMPTION | N15: =O15-Q15 -> 9090 | O15: 9090
B16: =meter!E21 -> 17 | D16: =meter!F21 -> 20 | E16: Units | F16: =D16-B16 -> 3 | N16: =O16-Q16 -> 9420 | O16: 9420
F17: Amount (Kshs.) | N17: =O17-Q17 -> 11154 | O17: 11154
D18: LAST ACCOUNT B/F | E18: Kshs. | F18: =meter!O21 -> 0 | N18: =O18-Q18 -> 10430 | O18: 10430
N19: =O19-Q19 -> 11831 | O19: 11831
D20: MONTH BILL | E20: KSHS. | F20: =meter!I21 -> 450 | N20: =O20-Q20 -> 10590 | O20: 10590
N21: =O21-Q21 -> 22423 | O21: 22423
D22: PUMP/POWER CHARGES | E22: KSHS. | F22: ='1A'!E21 -> 0 | N22: =O22-Q22 -> 9250 | O22: 9250
N23: =O23-Q23 -> 10162 | O23: 10162
D24: MONTH HOUSE RENT | E24: KSHS. | F24: =meter!N21 -> 10000 | N24: =O24-Q24 -> 10270 | O24: 10270
N25: =O25-Q25 -> 11070 | O25: 11070
D26: ='1A'!C25 -> SECURITY | E26: ='1A'!D25 -> Kshs. | F26: 0 | N26: =O26-Q26 -> 11550 | O26: 11550
D27: GARBAGE FEE | E27: Kshs. | N27: =O27-Q27 -> 11393 | O27: 11393
D28: ADJUSTMENT (Interest late payment) | E28: KSHS. | F28: =IF(F18*4%*1<0,0,F18*4%*1) -> 0 | N28: =O28-Q28 -> 10802 | O28: 10802
N29: =O29-Q29 -> 8930 | O29: 8930
D30: TOTAL PAYABLE | E30: Kshs. | F30: =SUM(F17:F29) -> 10450 | N30: =O30-Q30 -> 9570 | O30: 9570
N31: =O31-Q31 -> 11390 | O31: 11390
D32: PAID | F32: =meter!T21 -> 0 | N32: =O32-Q32 -> 10750 | O32: 10750
N33: =O33-Q33 -> 11732 | O33: 11732
D34: AMOUNT DUE | F34: =F30-F32 -> 10450 | N34: =O34-Q34 -> 10934 | O34: 10934 | R34: 700
C35: NOTE | N35: =O35-Q35 -> 10270 | O35: 10270
D36: PAY BILL 4139271 ACC NO UM 6C | N36: =O36-Q36 -> 10598 | O36: 10598
N37: =O37-Q37 -> 8770 | O37: 8770
N38: =O38-Q38 -> 8770 | O38: 8770
O39: =SUM(O3:O38) -> 391268 | Q39: =SUM(Q3:Q38) -> 0

Sheet 1D
B2: OLE SAMEDHA PREMIER HOSTELS | N2: VAR | O2: TAX DUE
B3: ='1A'!B2 -> P.O BOX 9473-00200 NAIROBI | N3: =O3-Q3 -> 10270 | O3: 10270
B4: WATER BILL | G4: BILL NO. | H4: ='1A'!H3+19-1 -> 56 | I4: ='1A'!H3+19-1 -> 56 | N4: =O4-Q4 -> 10304 | O4: 10304
G5: ='1A'!H3+19-1 -> 56 | N5: =O5-Q5 -> 10988 | O5: 10988
B6: TENANT NAME | D6: =meter!B22 -> AIRHA | N6: =O6-Q6 -> 11070 | O6: 11070
N7: =O7-Q7 -> 1197 | O7: 1197
B8: HOUSE NUMBER: | D8: 1D | N8: =O8-Q8 -> 9250 | O8: 9250
N9: =O9-Q9 -> 8770 | O9: 8770
B10: ISSUE DATE | D10: ='1A'!C9 -> 30TH JAN 2026 | N10: =O10-Q10 -> 23190 | O10: 23190
N11: =O11-Q11 -> 10910 | O11: 10910
B12: LAST PAY DATE | D12: ='1A'!C11 -> 5TH FEB 2026 | N12: =O12-Q12 -> 10910 | O12: 10910
N13: =O13-Q13 -> 12190 | O13: 12190
N14: =O14-Q14 -> 11070 | O14: 11070
B15: PREVIOUS READING | D15: CURRENT READING | F15: CONSUMPTION | N15: =O15-Q15 -> 9090 | O15: 9090
B16: =meter!E22 -> 12 | D16: =meter!F22 -> 15 | E16: Units | F16: =D16-B16+I16 -> 3 | N16: =O16-Q16 -> 9420 | O16: 9420
F17: Amount (Kshs.) | N17: =O17-Q17 -> 11154 | O17: 11154
D18: LAST ACCOUNT B/F | E18: Kshs. | F18: =meter!O22 -> 0 | N18: =O18-Q18 -> 10430 | O18: 10430
N19: =O19-Q19 -> 11831 | O19: 11831
D20: MONTH BILL | E20: KSHS. | F20: =meter!I22 -> 450 | N20: =O20-Q20 -> 10590 | O20: 10590
N21: =O21-Q21 -> 22423 | O21: 22423
D22: PUMP/POWER CHARGES | E22: KSHS. | F22: ='1A'!E21 -> 0 | N22: =O22-Q22 -> 9250 | O22: 9250
N23: =O23-Q23 -> 10162 | O23: 10162
D24: MONTH HOUSE RENT | E24: KSHS. | F24: =meter!N22 -> 8000 | N24: =O24-Q24 -> 10270 | O24: 10270
N25: =O25-Q25 -> 11070 | O25: 11070
D26: ='1A'!C25 -> SECURITY | E26: ='1A'!D25 -> Kshs. | F26: 0 | N26: =O26-Q26 -> 11550 | O26: 11550
D27: GARBAGE FEE | E27: Kshs. | N27: =O27-Q27 -> 11393 | O27: 11393
D28: ADJUSTMENT-Interest on arrears | E28: KSHS. | F28: =IF(F18*8%*1<0,0,F18*8%*1) -> 0 | N28: =O28-Q28 -> 10802 | O28: 10802
N29: =O29-Q29 -> 8930 | O29: 8930
D30: TOTAL PAYABLE | E30: Kshs. | F30: =SUM(F17:F29) -> 8450 | N30: =O30-Q30 -> 9570 | O30: 9570
N31: =O31-Q31 -> 11390 | O31: 11390
D32: PAID | F32: =meter!T22 -> 0 | N32: =O32-Q32 -> 10750 | O32: 10750
N33: =O33-Q33 -> 11732 | O33: 11732
D34: AMOUNT DUE | F34: =F30-F32 -> 8450 | N34: =O34-Q34 -> 10934 | O34: 10934 | R34: 700
C35: NOTE | N35: =O35-Q35 -> 10270 | O35: 10270
D36: PAY BILL 4139271 ACC NO UM 1D | N36: =O36-Q36 -> 10598 | O36: 10598
N37: =O37-Q37 -> 8770 | O37: 8770
N38: =O38-Q38 -> 8770 | O38: 8770
O39: =SUM(O3:O38) -> 391268 | Q39: =SUM(Q3:Q38) -> 0
R58: A

Sheet 2D
B2: OLE SAMEDHA PREMIER HOSTELS | N2: VAR | O2: TAX DUE
B3: ='1A'!B2 -> P.O BOX 9473-00200 NAIROBI | N3: =O3-Q3 -> 10270 | O3: 10270
B4: WATER BILL | H4: BILL NO. | I4: ='1A'!H3+20-1 -> 57 | J4: ='1A'!H3+20-1 -> 57 | N4: =O4-Q4 -> 10304 | O4: 10304
N5: =O5-Q5 -> 10988 | O5: 10988
B6: TENANT NAME | D6: =meter!B23 -> MOHAMMED | N6: =O6-Q6 -> 11070 | O6: 11070
N7: =O7-Q7 -> 1197 | O7: 1197
B8: HOUSE NUMBER: | D8: 2D | N8: =O8-Q8 -> 9250 | O8: 9250
N9: =O9-Q9 -> 8770 | O9: 8770
B10: ISSUE DATE | D10: ='1A'!C9 -> 30TH JAN 2026 | N10: =O10-Q10 -> 23190 | O10: 23190
N11: =O11-Q11 -> 10910 | O11: 10910
B12: LAST PAY DATE | D12: ='1A'!C11 -> 5TH FEB 2026 | N12: =O12-Q12 -> 10910 | O12: 10910
N13: =O13-Q13 -> 12190 | O13: 12190
N14: =O14-Q14 -> 11070 | O14: 11070
B15: PREVIOUS READING | D15: CURRENT READING | F15: CONSUMPTION | N15: =O15-Q15 -> 9090 | O15: 9090
B16: =meter!E23 -> 21 | D16: =meter!F23 -> 28 | E16: Units | F16: =D16-B16 -> 7 | N16: =O16-Q16 -> 9420 | O16: 9420
F17: Amount (Kshs.) | N17: =O17-Q17 -> 11154 | O17: 11154
D18: LAST ACCOUNT B/F | E18: Kshs. | F18: =meter!O23 -> 0 | N18: =O18-Q18 -> 10430 | O18: 10430
N19: =O19-Q19 -> 11831 | O19: 11831
D20: MONTH BILL | E20: KSHS. | F20: =meter!I23 -> 1050 | N20: =O20-Q20 -> 10590 | O20: 10590
N21: =O21-Q21 -> 22423 | O21: 22423
D22: PUMP/POWER CHARGES | E22: KSHS. | F22: ='1A'!E21 -> 0 | N22: =O22-Q22 -> 9250 | O22: 9250
N23: =O23-Q23 -> 10162 | O23: 10162
D24: MONTH HOUSE RENT | E24: KSHS. | F24: =meter!N23 -> 8000 | N24: =O24-Q24 -> 10270 | O24: 10270
N25: =O25-Q25 -> 11070 | O25: 11070
D26: ='1A'!C25 -> SECURITY | E26: ='1A'!D25 -> Kshs. | F26: ='1A'!E25 -> 0 | N26: =O26-Q26 -> 11550 | O26: 11550
D27: GARBAGE FEE | E27: Kshs. | N27: =O27-Q27 -> 11393 | O27: 11393
D28: ADJUSTMENT-interest on arrears | E28: KSHS. | F28: =IF(F18*4%*1<0,0,F18*4%*1) -> 0 | N28: =O28-Q28 -> 10802 | O28: 10802
N29: =O29-Q29 -> 8930 | O29: 8930
D30: TOTAL PAYABLE | E30: Kshs. | F30: =SUM(F17:F29) -> 9050 | N30: =O30-Q30 -> 9570 | O30: 9570
N31: =O31-Q31 -> 11390 | O31: 11390
D32: PAID | F32: =meter!T23 -> 0 | N32: =O32-Q32 -> 10750 | O32: 10750
N33: =O33-Q33 -> 11732 | O33: 11732
D34: AMOUNT DUE | F34: =F30-F32 -> 9050 | N34: =O34-Q34 -> 10934 | O34: 10934 | R34: 700
C35: NOTE | N35: =O35-Q35 -> 10270 | O35: 10270
N36: =O36-Q36 -> 10598 | O36: 10598
D37: PAY BILL 4139271 ACC NO UM 2D | N37: =O37-Q37 -> 8770 | O37: 8770
N38: =O38-Q38 -> 8770 | O38: 8770
O39: =SUM(O3:O38) -> 391268 | Q39: =SUM(Q3:Q38) -> 0

Sheet 3D
B2: OLE SAMEDHA PREMIER HOSTELS | N2: VAR | O2: TAX DUE
B3: ='1A'!B2 -> P.O BOX 9473-00200 NAIROBI | N3: =O3-Q3 -> 10270 | O3: 10270
B4: WATER BILL | H4: BILL NO. | I4: ='1A'!H3+21-1 -> 58 | L4: ='1A'!H3+21-1 -> 58 | N4: =O4-Q4 -> 10304 | O4: 10304
N5: =O5-Q5 -> 10988 | O5: 10988
B6: TENANT NAME | D6: =meter!B24 -> RIYAQ MOHAMMED | N6: =O6-Q6 -> 11070 | O6: 11070
N7: =O7-Q7 -> 1197 | O7: 1197
B8: HOUSE NUMBER | D8: 3D | N8: =O8-Q8 -> 9250 | O8: 9250
D9: 0723662965 | N9: =O9-Q9 -> 8770 | O9: 8770
B10: ISSUE DATE | D10: ='1A'!C9 -> 30TH JAN 2026 | N10: =O10-Q10 -> 23190 | O10: 23190
N11: =O11-Q11 -> 10910 | O11: 10910
B12: LAST PAY DATE | D12: ='1A'!C11 -> 5TH FEB 2026 | N12: =O12-Q12 -> 10910 | O12: 10910
N13: =O13-Q13 -> 12190 | O13: 12190
N14: =O14-Q14 -> 11070 | O14: 11070
B15: PREVIOUS READING | D15: CURRENT READING | F15: CONSUMPTION | N15: =O15-Q15 -> 9090 | O15: 9090
B16: =meter!E24 -> 23 | D16: =meter!F24 -> 25 | E16: Units | F16: =D16-B16 -> 2 | N16: =O16-Q16 -> 9420 | O16: 9420
F17: Amount (Kshs.) | N17: =O17-Q17 -> 11154 | O17: 11154
D18: LAST ACCOUNT B/F | E18: Kshs. | F18: =meter!O24 -> 0 | N18: =O18-Q18 -> 10430 | O18: 10430
N19: =O19-Q19 -> 11831 | O19: 11831
D20: MONTH BILL | E20: KSHS. | F20: =meter!I24 -> 300 | N20: =O20-Q20 -> 10590 | O20: 10590
N21: =O21-Q21 -> 22423 | O21: 22423
D22: PUMP/POWER CHARGES | E22: KSHS. | F22: ='1A'!E21 -> 0 | N22: =O22-Q22 -> 9250 | O22: 9250
N23: =O23-Q23 -> 10162 | O23: 10162
D24: MONTH HOUSE RENT | E24: KSHS. | F24: =meter!N24 -> 8000 | N24: =O24-Q24 -> 10270 | O24: 10270
N25: =O25-Q25 -> 11070 | O25: 11070
D26: ='1A'!C25 -> SECURITY | E26: ='1A'!D25 -> Kshs. | F26: =meter!M24 -> 0 | N26: =O26-Q26 -> 11550 | O26: 11550
D27: GARBAGE FEE | E27: Kshs. | N27: =O27-Q27 -> 11393 | O27: 11393
D28: INTEREST ON ARREARS | E28: KSHS. | F28: =IF(F18*4%*1<0,0,F18*4%*1) -> 0 | N28: =O28-Q28 -> 10802 | O28: 10802
N29: =O29-Q29 -> 8930 | O29: 8930
D30: TOTAL PAYABLE | E30: Kshs. | F30: =SUM(F17:F29) -> 8300 | N30: =O30-Q30 -> 9570 | O30: 9570
N31: =O31-Q31 -> 11390 | O31: 11390
D32: PAID | F32: =meter!T24 -> 0 | N32: =O32-Q32 -> 10750 | O32: 10750
N33: =O33-Q33 -> 11732 | O33: 11732
D34: AMOUNT DUE | F34: =F30-F32 -> 8300 | N34: =O34-Q34 -> 10934 | O34: 10934 | R34: 700
C35: NOTE | N35: =O35-Q35 -> 10270 | O35: 10270
D36: PAY BILL 4139271 ACC NO UM 3D | N36: =O36-Q36 -> 10598 | O36: 10598
N37: =O37-Q37 -> 8770 | O37: 8770
N38: =O38-Q38 -> 8770 | O38: 8770
O39: =SUM(O3:O38) -> 391268 | Q39: =SUM(Q3:Q38) -> 0

Sheet 4D
B2: OLE SAMEDHA APARTMENTS-Kitengela | D2: OLE SAMEDHA PREMIER HOSTELS | N2: VAR | O2: TAX DUE
B3: ='1A'!B2 -> P.O BOX 9473-00200 NAIROBI | N3: =O3-Q3 -> 10270 | O3: 10270
B4: WATER BILL | H4: BILL NO. | I4: ='1A'!H3+22-1 -> 59 | J4: ='1A'!H3+22-1 -> 59 | N4: =O4-Q4 -> 10304 | O4: 10304
N5: =O5-Q5 -> 10988 | O5: 10988
B6: TENANT NAME | D6: =meter!B25 -> RID WAH ABDULLAH | N6: =O6-Q6 -> 11070 | O6: 11070
N7: =O7-Q7 -> 1197 | O7: 1197
B8: HOUSE NUMBER: | D8: 4D | N8: =O8-Q8 -> 9250 | O8: 9250
N9: =O9-Q9 -> 8770 | O9: 8770
B10: ISSUE DATE | D10: ='1A'!C9 -> 30TH JAN 2026 | N10: =O10-Q10 -> 23190 | O10: 23190
N11: =O11-Q11 -> 10910 | O11: 10910
B12: LAST PAY DATE | D12: ='1A'!C11 -> 5TH FEB 2026 | N12: =O12-Q12 -> 10910 | O12: 10910
N13: =O13-Q13 -> 12190 | O13: 12190
N14: =O14-Q14 -> 11070 | O14: 11070
B15: PREVIOUS READING | D15: CURRENT READING | F15: CONSUMPTION | N15: =O15-Q15 -> 9090 | O15: 9090
B16: =meter!E25 -> 14 | D16: =meter!F25 -> 16 | E16: Units | F16: =D16-B16 -> 2 | N16: =O16-Q16 -> 9420 | O16: 9420
F17: Amount (Kshs.) | N17: =O17-Q17 -> 11154 | O17: 11154
D18: LAST ACCOUNT B/F | E18: Kshs. | F18: =meter!O25 -> 774 | N18: =O18-Q18 -> 10430 | O18: 10430
N19: =O19-Q19 -> 11831 | O19: 11831
D20: MONTH BILL | E20: KSHS. | F20: =meter!I25 -> 300 | N20: =O20-Q20 -> 10590 | O20: 10590
N21: =O21-Q21 -> 22423 | O21: 22423
D22: PUMP/POWER CHARGES | E22: KSHS. | F22: ='1A'!E21 -> 0 | N22: =O22-Q22 -> 9250 | O22: 9250
N23: =O23-Q23 -> 10162 | O23: 10162
D24: MONTH HOUSE RENT | E24: KSHS. | F24: =meter!N25 -> 8000 | N24: =O24-Q24 -> 10270 | O24: 10270
N25: =O25-Q25 -> 11070 | O25: 11070
D26: ='1A'!C25 -> SECURITY | E26: ='1A'!D25 -> Kshs. | F26: ='1A'!E25 -> 0 | N26: =O26-Q26 -> 11550 | O26: 11550
D27: GARBAGE FEE | E27: Kshs. | N27: =O27-Q27 -> 11393 | O27: 11393
D28: INTEREST LATE PAYMENT | E28: KSHS. | F28: =IF(F18*4%*1<0,0,F18*4%*1) -> 30.96 | N28: =O28-Q28 -> 10802 | O28: 10802
N29: =O29-Q29 -> 8930 | O29: 8930
D30: TOTAL PAYABLE | E30: Kshs. | F30: =SUM(F17:F29) -> 9104.96 | N30: =O30-Q30 -> 9570 | O30: 9570
N31: =O31-Q31 -> 11390 | O31: 11390
D32: PAID | F32: =meter!T25 -> 0 | N32: =O32-Q32 -> 10750 | O32: 10750
N33: =O33-Q33 -> 11732 | O33: 11732
D34: AMOUNT DUE | F34: =F30-F32 -> 9104.96 | N34: =O34-Q34 -> 10934 | O34: 10934 | R34: 700
C35: NOTE | N35: =O35-Q35 -> 10270 | O35: 10270
D36: PAY BILL 4139271 ACC NO UM 4D | N36: =O36-Q36 -> 10598 | O36: 10598
N37: =O37-Q37 -> 8770 | O37: 8770
N38: =O38-Q38 -> 8770 | O38: 8770
O39: =SUM(O3:O38) -> 391268 | Q39: =SUM(Q3:Q38) -> 0

Sheet 5D
B1: OLE SAMEDHA APARTMENTS-Kitengela | D1: OLE SAMEDHA PREMIER HOSTELS
B2: ='1A'!B2 -> P.O BOX 9473-00200 NAIROBI | N2: VAR | O2: TAX DUE
B3: WATER BILL | N3: =O3-Q3 -> 10270 | O3: 10270
H4: BILL NO. | I4: ='1A'!H3+23-1 -> 60 | K4: ='1A'!H3+23-1 -> 60 | N4: =O4-Q4 -> 10304 | O4: 10304
N5: =O5-Q5 -> 10988 | O5: 10988
B6: TENANT NAME | D6: =meter!B26 -> NASRA | N6: =O6-Q6 -> 11070 | O6: 11070
N7: =O7-Q7 -> 1197 | O7: 1197
B8: HOUSE NUMBER | D8: 5D | N8: =O8-Q8 -> 9250 | O8: 9250
N9: =O9-Q9 -> 8770 | O9: 8770
B10: ISSUE DATE | D10: ='1A'!C9 -> 30TH JAN 2026 | N10: =O10-Q10 -> 23190 | O10: 23190
N11: =O11-Q11 -> 10910 | O11: 10910
B12: LAST PAY DATE | D12: ='1A'!C11 -> 5TH FEB 2026 | N12: =O12-Q12 -> 10910 | O12: 10910
N13: =O13-Q13 -> 12190 | O13: 12190
N14: =O14-Q14 -> 11070 | O14: 11070
B15: PREVIOUS READING | D15: CURRENT READING | F15: CONSUMPTION | N15: =O15-Q15 -> 9090 | O15: 9090
B16: =meter!E26 -> 25 | D16: =meter!F26 -> 28 | E16: Units | F16: =D16-B16 -> 3 | N16: =O16-Q16 -> 9420 | O16: 9420
F17: Amount (Kshs.) | N17: =O17-Q17 -> 11154 | O17: 11154
D18: LAST ACCOUNT B/F | E18: Kshs. | F18: =meter!O26 -> 0 | N18: =O18-Q18 -> 10430 | O18: 10430
N19: =O19-Q19 -> 11831 | O19: 11831
D20: MONTH BILL | E20: KSHS. | F20: =meter!I26 -> 450 | N20: =O20-Q20 -> 10590 | O20: 10590
N21: =O21-Q21 -> 22423 | O21: 22423
D22: PUMP/POWER CHARGES | E22: KSHS. | F22: ='1A'!E21 -> 0 | N22: =O22-Q22 -> 9250 | O22: 9250
N23: =O23-Q23 -> 10162 | O23: 10162
D24: MONTH HOUSE RENT | E24: KSHS. | F24: =meter!N26 -> 8000 | N24: =O24-Q24 -> 10270 | O24: 10270
N25: =O25-Q25 -> 11070 | O25: 11070
D26: ='1A'!C25 -> SECURITY | E26: ='1A'!D25 -> Kshs. | F26: ='1A'!E25 -> 0 | N26: =O26-Q26 -> 11550 | O26: 11550
D27: GARBAGE FEE | E27: Kshs. | N27: =O27-Q27 -> 11393 | O27: 11393
D28: PENALTY LATE PAYMENT | E28: KSHS. | F28: =IF(F18*4%*1<0,0,F18*4%*1) -> 0 | N28: =O28-Q28 -> 10802 | O28: 10802
N29: =O29-Q29 -> 8930 | O29: 8930
D30: TOTAL PAYABLE | E30: Kshs. | F30: =SUM(F17:F29) -> 8450 | N30: =O30-Q30 -> 9570 | O30: 9570
N31: =O31-Q31 -> 11390 | O31: 11390
D32: PAID | F32: =meter!T26 -> 0 | N32: =O32-Q32 -> 10750 | O32: 10750
N33: =O33-Q33 -> 11732 | O33: 11732
D34: AMOUNT DUE | F34: =F30-F32 -> 8450 | N34: =O34-Q34 -> 10934 | O34: 10934 | R34: 700
D35: PAY BILL 4139271 ACC NO UM 5D | N35: =O35-Q35 -> 10270 | O35: 10270
B36: Rent is due on or before 5th of the month. By 7th day, any rent not paid will attract interest at 2% per day. | N36: =O36-Q36 -> 10598 | O36: 10598
B37: Any default in Rent payment by 10th of the following month the house shall be locked without notice and belongings removed for re-letting. | N37: =O37-Q37 -> 8770 | O37: 8770
N38: =O38-Q38 -> 8770 | O38: 8770
B39: Amounts not cleared by last pay date will render to water disconnection. | O39: =SUM(O3:O38) -> 391268 | Q39: =SUM(Q3:Q38) -> 0
B41: A reconnection fee of Kshs. 1,000 will be charged and paid before supply is reconnected.
B42: ANY MINOR REPAIRS OCCURING AFTER 3 MONTHS OF OCCUPANCY ARE TENANT'S RESPONSIBILITY AS PER TENANCY AGREEMENT.
B43: The water bills are payable through the same account for monthly rent strictly through:
B45: CFC STANBIC BANK Limited
B46: KENYATTA AVE Branch
B47: A/C NO. 0100000717635
B48: (Kindly indicate your Name & House number on the deposit slip & inform the Bank teller to capture it.)
B49: A receipt will be issued upon bank confirmation of the transaction.
B50: MPESA, PAYBILL CFC STANBIC BANK 600100 A/C NO. 0100000717635, Add 40/= for charges

Sheet 6D
B1: OLE SAMEDHA PREMIER HOSTELS
B2: ='1A'!B2 -> P.O BOX 9473-00200 NAIROBI | N2: VAR | O2: TAX DUE
B3: WATER BILL | N3: =O3-Q3 -> 10270 | O3: 10270
H4: BILL NO. | I4: ='1A'!H3+24-1 -> 61 | M4: ='1A'!H3+24-1 -> 61 | N4: =O4-Q4 -> 10304 | O4: 10304
N5: =O5-Q5 -> 10988 | O5: 10988
B6: TENANT NAME | D6: =meter!B27 -> 0 | N6: =O6-Q6 -> 11070 | O6: 11070
N7: =O7-Q7 -> 1197 | O7: 1197
B8: HOUSE NUMBER: | D8: 6D | N8: =O8-Q8 -> 9250 | O8: 9250
N9: =O9-Q9 -> 8770 | O9: 8770
B10: ISSUE DATE | D10: ='1A'!C9 -> 30TH JAN 2026 | N10: =O10-Q10 -> 23190 | O10: 23190
N11: =O11-Q11 -> 10910 | O11: 10910
B12: LAST PAY DATE | D12: ='1A'!C11 -> 5TH FEB 2026 | N12: =O12-Q12 -> 10910 | O12: 10910
N13: =O13-Q13 -> 12190 | O13: 12190
N14: =O14-Q14 -> 11070 | O14: 11070
B15: PREVIOUS READING | D15: CURRENT READING | F15: CONSUMPTION | N15: =O15-Q15 -> 9090 | O15: 9090
B16: =meter!E27 -> 28 | D16: =meter!F27 -> 29 | E16: Units | F16: =D16-B16 -> 1 | N16: =O16-Q16 -> 9420 | O16: 9420
F17: Amount (Kshs.) | N17: =O17-Q17 -> 11154 | O17: 11154
D18: LAST ACCOUNT B/F | E18: Kshs. | F18: =meter!O27 -> 484 | N18: =O18-Q18 -> 10430 | O18: 10430
N19: =O19-Q19 -> 11831 | O19: 11831
D20: MONTH BILL | E20: KSHS. | F20: =meter!I27 -> 150 | N20: =O20-Q20 -> 10590 | O20: 10590
N21: =O21-Q21 -> 22423 | O21: 22423
D22: PUMP/POWER CHARGES | E22: KSHS. | F22: ='1A'!E21 -> 0 | N22: =O22-Q22 -> 9250 | O22: 9250
N23: =O23-Q23 -> 10162 | O23: 10162
D24: MONTH HOUSE RENT | E24: KSHS. | F24: =meter!N27 -> 7500 | N24: =O24-Q24 -> 10270 | O24: 10270
N25: =O25-Q25 -> 11070 | O25: 11070
D26: ='1A'!C25 -> SECURITY | E26: ='1A'!D25 -> Kshs. | F26: ='1A'!E25 -> 0 | N26: =O26-Q26 -> 11550 | O26: 11550
D27: GARBAGE FEE | E27: Kshs. | N27: =O27-Q27 -> 11393 | O27: 11393
D28: INTEREST ON ARREARS | E28: KSHS. | F28: =IF(F18*4%*1<0,0,F18*4%*1) -> 19.36 | N28: =O28-Q28 -> 10802 | O28: 10802
N29: =O29-Q29 -> 8930 | O29: 8930
D30: TOTAL PAYABLE | E30: Kshs. | F30: =SUM(F17:F29) -> 8153.36 | N30: =O30-Q30 -> 9570 | O30: 9570
N31: =O31-Q31 -> 11390 | O31: 11390
D32: PAID | F32: =meter!T27 -> 0 | N32: =O32-Q32 -> 10750 | O32: 10750
N33: =O33-Q33 -> 11732 | O33: 11732
D34: AMOUNT DUE | F34: =F30-F32 -> 8153.36 | N34: =O34-Q34 -> 10934 | O34: 10934 | R34: 700
N35: =O35-Q35 -> 10270 | O35: 10270
D36: PAY BILL 4139271 ACC NO UM 6D | N36: =O36-Q36 -> 10598 | O36: 10598
N37: =O37-Q37 -> 8770 | O37: 8770
N38: =O38-Q38 -> 8770 | O38: 8770
O39: =SUM(O3:O38) -> 391268 | Q39: =SUM(Q3:Q38) -> 0

Sheet 1E
B1: OLE SAMEDHA PREMIER HOSTELS
B2: ='1A'!B2 -> P.O BOX 9473-00200 NAIROBI | N2: VAR | O2: TAX DUE
B3: WATER BILL | N3: =O3-Q3 -> 10270 | O3: 10270
H4: BILL NO. | I4: ='1A'!H3+25-1 -> 62 | K4: ='1A'!H3+25-1 -> 62 | N4: =O4-Q4 -> 10304 | O4: 10304
N5: =O5-Q5 -> 10988 | O5: 10988
B6: TENANT NAME | D6: =meter!B28 -> SALIM ABDULL | N6: =O6-Q6 -> 11070 | O6: 11070
N7: =O7-Q7 -> 1197 | O7: 1197
B8: HOUSE NUMBER | D8: 1E | N8: =O8-Q8 -> 9250 | O8: 9250
N9: =O9-Q9 -> 8770 | O9: 8770
B10: ISSUE DATE | D10: ='1A'!C9 -> 30TH JAN 2026 | N10: =O10-Q10 -> 23190 | O10: 23190
N11: =O11-Q11 -> 10910 | O11: 10910
B12: LAST PAY DATE | D12: ='1A'!C11 -> 5TH FEB 2026 | N12: =O12-Q12 -> 10910 | O12: 10910
N13: =O13-Q13 -> 12190 | O13: 12190
N14: =O14-Q14 -> 11070 | O14: 11070
B15: PREVIOUS READING | D15: CURRENT READING | F15: CONSUMPTION | N15: =O15-Q15 -> 9090 | O15: 9090
B16: =meter!E28 -> 35 | D16: =meter!F28 -> 35 | E16: Units | F16: =D16-B16 -> 0 | N16: =O16-Q16 -> 9420 | O16: 9420
F17: Amount (Kshs.) | N17: =O17-Q17 -> 11154 | O17: 11154
D18: LAST ACCOUNT B/F | E18: Kshs. | F18: =meter!O28 -> 0 | N18: =O18-Q18 -> 10430 | O18: 10430
N19: =O19-Q19 -> 11831 | O19: 11831
D20: MONTH BILL | E20: KSHS. | F20: =meter!I28 -> 0 | N20: =O20-Q20 -> 10590 | O20: 10590
N21: =O21-Q21 -> 22423 | O21: 22423
D22: PUMP/POWER CHARGES | E22: KSHS. | F22: ='1A'!E21 -> 0 | N22: =O22-Q22 -> 9250 | O22: 9250
N23: =O23-Q23 -> 10162 | O23: 10162
D24: MONTH HOUSE RENT | E24: KSHS. | F24: =meter!N28 -> 8000 | N24: =O24-Q24 -> 10270 | O24: 10270
N25: =O25-Q25 -> 11070 | O25: 11070
D26: ='1A'!C25 -> SECURITY | E26: ='1A'!D25 -> Kshs. | F26: ='1A'!E25 -> 0 | N26: =O26-Q26 -> 11550 | O26: 11550
D27: GARBAGE FEE | E27: Kshs. | N27: =O27-Q27 -> 11393 | O27: 11393
D28: INTEREST ON ARREARS | E28: KSHS. | F28: =IF(F18*4%*1<0,0,F18*4%*1) -> 0 | N28: =O28-Q28 -> 10802 | O28: 10802
N29: =O29-Q29 -> 8930 | O29: 8930
D30: TOTAL PAYABLE | E30: Kshs. | F30: =SUM(F17:F29) -> 8000 | N30: =O30-Q30 -> 9570 | O30: 9570
N31: =O31-Q31 -> 11390 | O31: 11390
D32: PAID | F32: =meter!T28 -> 0 | N32: =O32-Q32 -> 10750 | O32: 10750
N33: =O33-Q33 -> 11732 | O33: 11732
D34: AMOUNT DUE | F34: =F30-F32 -> 8000 | N34: =O34-Q34 -> 10934 | O34: 10934 | R34: 700
C35: NOTE | N35: =O35-Q35 -> 10270 | O35: 10270
N36: =O36-Q36 -> 10598 | O36: 10598
D37: PAY BILL 4139271 ACC NO UM 1E | N37: =O37-Q37 -> 8770 | O37: 8770
N38: =O38-Q38 -> 8770 | O38: 8770
O39: =SUM(O3:O38) -> 391268 | Q39: =SUM(Q3:Q38) -> 0

Sheet 2E
B1: OLE SAMEDHA APARTMENTS-Kitengela | D1: OLE SAMEDHA PREMIER HOSTELS
B2: ='1A'!B2 -> P.O BOX 9473-00200 NAIROBI | N2: VAR | O2: TAX DUE
B3: WATER BILL | N3: =O3-Q3 -> 10270 | O3: 10270
H4: BILL NO. | I4: ='1A'!H3+27-1 -> 64 | L4: ='1A'!H3+27-1 -> 64 | N4: =O4-Q4 -> 10304 | O4: 10304
N5: =O5-Q5 -> 10988 | O5: 10988
B6: TENANT NAME | D6: =meter!B29 -> QATRA | N6: =O6-Q6 -> 11070 | O6: 11070
N7: =O7-Q7 -> 1197 | O7: 1197
B8: HOUSE NUMBER: | D8: 2E | N8: =O8-Q8 -> 9250 | O8: 9250
N9: =O9-Q9 -> 8770 | O9: 8770
B10: ISSUE DATE | D10: ='1A'!C9 -> 30TH JAN 2026 | N10: =O10-Q10 -> 23190 | O10: 23190
N11: =O11-Q11 -> 10910 | O11: 10910
B12: LAST PAY DATE | D12: ='1A'!C11 -> 5TH FEB 2026 | N12: =O12-Q12 -> 10910 | O12: 10910
N13: =O13-Q13 -> 12190 | O13: 12190
N14: =O14-Q14 -> 11070 | O14: 11070
B15: PREVIOUS READING | D15: CURRENT READING | F15: CONSUMPTION | N15: =O15-Q15 -> 9090 | O15: 9090
B16: =meter!E30 -> 20 | D16: =meter!F30 -> 21 | E16: Units | F16: =D16-B16 -> 1 | N16: =O16-Q16 -> 9420 | O16: 9420
F17: Amount (Kshs.) | N17: =O17-Q17 -> 11154 | O17: 11154
D18: LAST ACCOUNT B/F | E18: Kshs. | F18: =meter!O30 -> 0 | N18: =O18-Q18 -> 10430 | O18: 10430
N19: =O19-Q19 -> 11831 | O19: 11831
D20: MONTH BILL | E20: KSHS. | F20: =meter!I30 -> 150 | N20: =O20-Q20 -> 10590 | O20: 10590
N21: =O21-Q21 -> 22423 | O21: 22423
D22: PUMP/POWER CHARGES | E22: KSHS. | F22: ='1A'!E21 -> 0 | N22: =O22-Q22 -> 9250 | O22: 9250
N23: =O23-Q23 -> 10162 | O23: 10162
D24: MONTH HOUSE RENT | E24: KSHS. | F24: =meter!N30 -> 7000 | N24: =O24-Q24 -> 10270 | O24: 10270
N25: =O25-Q25 -> 11070 | O25: 11070
D26: ='1A'!C25 -> SECURITY | E26: ='1A'!D25 -> Kshs. | F26: ='1A'!E25 -> 0 | N26: =O26-Q26 -> 11550 | O26: 11550
D27: GARBAGE FEE | E27: Kshs. | N27: =O27-Q27 -> 11393 | O27: 11393
D28: ADJUSTMENT (Interest late payment) | E28: KSHS. | F28: =IF(F18*4%*1<0,0,F18*4%*1) -> 0 | N28: =O28-Q28 -> 10802 | O28: 10802
N29: =O29-Q29 -> 8930 | O29: 8930
D30: TOTAL PAYABLE | E30: Kshs. | F30: =SUM(F17:F29) -> 7150 | N30: =O30-Q30 -> 9570 | O30: 9570
N31: =O31-Q31 -> 11390 | O31: 11390
D32: PAID | F32: =meter!T30 -> 0 | N32: =O32-Q32 -> 10750 | O32: 10750
N33: =O33-Q33 -> 11732 | O33: 11732
D34: AMOUNT DUE | F34: =F30-F32 -> 7150 | N34: =O34-Q34 -> 10934 | O34: 10934 | R34: 700
C35: NOTE | N35: =O35-Q35 -> 10270 | O35: 10270
N36: =O36-Q36 -> 10598 | O36: 10598
D37: PAY BILL 4139271 ACC NO UM 2E | N37: =O37-Q37 -> 8770 | O37: 8770
N38: =O38-Q38 -> 8770 | O38: 8770
O39: =SUM(O3:O38) -> 391268 | Q39: =SUM(Q3:Q38) -> 0

Sheet 3E
B1: OLE SAMEDHA PREMIER HOSTELS
B2: ='1A'!B2 -> P.O BOX 9473-00200 NAIROBI | N2: VAR | O2: TAX DUE
B3: WATER BILL | N3: =O3-Q3 -> 10270 | O3: 10270
H4: BILL NO. | I4: ='1A'!H3+26-1 -> 63 | L4: ='1A'!H3+26-1 -> 63 | N4: =O4-Q4 -> 10304 | O4: 10304
N5: =O5-Q5 -> 10988 | O5: 10988
B6: TENANT NAME | D6: =meter!B30 -> BAHATI | N6: =O6-Q6 -> 11070 | O6: 11070
N7: =O7-Q7 -> 1197 | O7: 1197
B8: HOUSE NUMBER: | D8: 3E | N8: =O8-Q8 -> 9250 | O8: 9250
N9: =O9-Q9 -> 8770 | O9: 8770
B10: ISSUE DATE | D10: ='1A'!C9 -> 30TH JAN 2026 | N10: =O10-Q10 -> 23190 | O10: 23190 | R10: 10500
N11: =O11-Q11 -> 10910 | O11: 10910 | R11: 4200
B12: LAST PAY DATE | D12: ='1A'!C11 -> 5TH FEB 2026 | N12: =O12-Q12 -> 10910 | O12: 10910 | R12: =R10-R11 -> 6300
N13: =O13-Q13 -> 12190 | O13: 12190
N14: =O14-Q14 -> 11070 | O14: 11070
B15: PREVIOUS READING | D15: CURRENT READING | F15: CONSUMPTION | N15: =O15-Q15 -> 9090 | O15: 9090
B16: =meter!E29 -> 28 | D16: =meter!F29 -> 32 | E16: Units | F16: =D16-B16 -> 4 | N16: =O16-Q16 -> 9420 | O16: 9420
F17: Amount (Kshs.) | N17: =O17-Q17 -> 11154 | O17: 11154
D18: LAST ACCOUNT B/F | E18: Kshs. | F18: =meter!O29 -> 0 | N18: =O18-Q18 -> 10430 | O18: 10430
N19: =O19-Q19 -> 11831 | O19: 11831
D20: MONTH BILL | E20: KSHS. | F20: =meter!I29 -> 600 | N20: =O20-Q20 -> 10590 | O20: 10590
N21: =O21-Q21 -> 22423 | O21: 22423
D22: PUMP/POWER CHARGES | E22: KSHS. | F22: ='1A'!E21 -> 0 | N22: =O22-Q22 -> 9250 | O22: 9250
N23: =O23-Q23 -> 10162 | O23: 10162
D24: MONTH HOUSE RENT | E24: KSHS. | F24: =meter!N29 -> 8000 | N24: =O24-Q24 -> 10270 | O24: 10270
N25: =O25-Q25 -> 11070 | O25: 11070
D26: ='1A'!C25 -> SECURITY | E26: ='1A'!D25 -> Kshs. | F26: ='1A'!E25 -> 0 | N26: =O26-Q26 -> 11550 | O26: 11550
D27: GARBAGE FEE | E27: Kshs. | N27: =O27-Q27 -> 11393 | O27: 11393
D28: Interest on rent arrears | E28: KSHS. | F28: =IF(F18*4%*1<0,0,F18*4%*1) -> 0 | N28: =O28-Q28 -> 10802 | O28: 10802
N29: =O29-Q29 -> 8930 | O29: 8930
D30: TOTAL PAYABLE | E30: Kshs. | F30: =SUM(F17:F29) -> 8600 | N30: =O30-Q30 -> 9570 | O30: 9570
N31: =O31-Q31 -> 11390 | O31: 11390
D32: PAID | F32: =meter!T29 -> 0 | N32: =O32-Q32 -> 10750 | O32: 10750
N33: =O33-Q33 -> 11732 | O33: 11732
D34: AMOUNT DUE | F34: =F30-F32 -> 8600 | N34: =O34-Q34 -> 10934 | O34: 10934 | R34: 700
C35: NOTE | N35: =O35-Q35 -> 10270 | O35: 10270
N36: =O36-Q36 -> 10598 | O36: 10598
D37: PAY BILL 4139271 ACC NO UM 3E | N37: =O37-Q37 -> 8770 | O37: 8770
N38: =O38-Q38 -> 8770 | O38: 8770
O39: =SUM(O3:O38) -> 391268 | Q39: =SUM(Q3:Q38) -> 0

Sheet 4E
B1: OLE SAMEDHA PREMIER HOSTELS
B2: ='1A'!B2 -> P.O BOX 9473-00200 NAIROBI | N2: VAR | O2: TAX DUE
B3: WATER BILL | N3: =O3-Q3 -> 10270 | O3: 10270
F4: BILL NO. | H4: ='1A'!H3+28-1 -> 65 | I4: ='1A'!H3+28-1 -> 65 | N4: =O4-Q4 -> 10304 | O4: 10304
N5: =O5-Q5 -> 10988 | O5: 10988
B6: TENANT NAME | D6: =meter!B31 -> ABDUL | N6: =O6-Q6 -> 11070 | O6: 11070
N7: =O7-Q7 -> 1197 | O7: 1197
B8: HOUSE NUMBER: | D8: 4E | N8: =O8-Q8 -> 9250 | O8: 9250
N9: =O9-Q9 -> 8770 | O9: 8770
B10: ISSUE DATE | D10: ='1A'!C9 -> 30TH JAN 2026 | N10: =O10-Q10 -> 23190 | O10: 23190
N11: =O11-Q11 -> 10910 | O11: 10910
B12: LAST PAY DATE | D12: ='1A'!C11 -> 5TH FEB 2026 | N12: =O12-Q12 -> 10910 | O12: 10910
N13: =O13-Q13 -> 12190 | O13: 12190
N14: =O14-Q14 -> 11070 | O14: 11070
B15: PREVIOUS READING | D15: CURRENT READING | F15: CONSUMPTION | N15: =O15-Q15 -> 9090 | O15: 9090
B16: =meter!E31 -> 29 | D16: =meter!F31 -> 30 | E16: Units | F16: =D16-B16 -> 1 | N16: =O16-Q16 -> 9420 | O16: 9420
F17: Amount (Kshs.) | N17: =O17-Q17 -> 11154 | O17: 11154
D18: LAST ACCOUNT B/F | E18: Kshs. | F18: =meter!O31 -> 900 | N18: =O18-Q18 -> 10430 | O18: 10430
F19: 0 | N19: =O19-Q19 -> 11831 | O19: 11831
D20: MONTH BILL | E20: KSHS. | F20: =meter!I31 -> 150 | N20: =O20-Q20 -> 10590 | O20: 10590
N21: =O21-Q21 -> 22423 | O21: 22423
D22: PUMP/POWER CHARGES | E22: KSHS. | F22: ='1A'!E21 -> 0 | N22: =O22-Q22 -> 9250 | O22: 9250
F23: 0 | N23: =O23-Q23 -> 10162 | O23: 10162
D24: MONTH HOUSE RENT | E24: KSHS. | F24: =meter!N31 -> 7000 | N24: =O24-Q24 -> 10270 | O24: 10270
F25: 0 | N25: =O25-Q25 -> 11070 | O25: 11070
D26: ='1A'!C25 -> SECURITY | E26: ='1A'!D25 -> Kshs. | F26: ='1A'!E25 -> 0 | N26: =O26-Q26 -> 11550 | O26: 11550
D27: GARBAGE FEE | E27: KSHS. | N27: =O27-Q27 -> 11393 | O27: 11393
D28: INTEREST ON ARREARS | E28: KSHS. | F28: =IF(F18*4%*1<0,0,F18*4%*1) -> 36 | N28: =O28-Q28 -> 10802 | O28: 10802
F29: 0 | N29: =O29-Q29 -> 8930 | O29: 8930
D30: TOTAL PAYABLE | E30: Kshs. | F30: =SUM(F17:F29) -> 8086 | N30: =O30-Q30 -> 9570 | O30: 9570
N31: =O31-Q31 -> 11390 | O31: 11390
D32: PAID | F32: =meter!T31 -> 0 | N32: =O32-Q32 -> 10750 | O32: 10750
N33: =O33-Q33 -> 11732 | O33: 11732
D34: AMOUNT DUE | F34: =F30-F32 -> 8086 | N34: =O34-Q34 -> 10934 | O34: 10934 | R34: 700
C35: NOTE | N35: =O35-Q35 -> 10270 | O35: 10270
D36: PAY BILL 4139271 ACC NO UM 4E | N36: =O36-Q36 -> 10598 | O36: 10598
N37: =O37-Q37 -> 8770 | O37: 8770
N38: =O38-Q38 -> 8770 | O38: 8770
O39: =SUM(O3:O38) -> 391268 | Q39: =SUM(Q3:Q38) -> 0

Sheet 5E
B1: OLE SAMEDHA PREMIER HOSTELS
B2: ='1A'!B2 -> P.O BOX 9473-00200 NAIROBI | N2: VAR | O2: TAX DUE
B3: WATER BILL | N3: =O3-Q3 -> 10270 | O3: 10270
H4: BILL NO. | I4: ='1A'!H3+30-1 -> 67 | J4: ='1A'!H3+30-1 -> 67 | N4: =O4-Q4 -> 10304 | O4: 10304
N5: =O5-Q5 -> 10988 | O5: 10988
B6: TENANT NAME | D6: =meter!B33 -> ABDIAZIZ ABDI | N6: =O6-Q6 -> 11070 | O6: 11070
N7: =O7-Q7 -> 1197 | O7: 1197
B8: HOUSE NUMBER: | D8: 5E | N8: =O8-Q8 -> 9250 | O8: 9250
N9: =O9-Q9 -> 8770 | O9: 8770
B10: ISSUE DATE | D10: ='1A'!C9 -> 30TH JAN 2026 | N10: =O10-Q10 -> 23190 | O10: 23190
N11: =O11-Q11 -> 10910 | O11: 10910
B12: LAST PAY DATE | D12: ='1A'!C11 -> 5TH FEB 2026 | N12: =O12-Q12 -> 10910 | O12: 10910
N13: =O13-Q13 -> 12190 | O13: 12190
N14: =O14-Q14 -> 11070 | O14: 11070
B15: PREVIOUS READING | D15: CURRENT READING | F15: CONSUMPTION | N15: =O15-Q15 -> 9090 | O15: 9090
B16: =meter!E33 -> 30 | D16: =meter!F33 -> 31 | E16: Units | F16: =D16-B16 -> 1 | N16: =O16-Q16 -> 9420 | O16: 9420
F17: Amount (Kshs.) | N17: =O17-Q17 -> 11154 | O17: 11154
D18: LAST ACCOUNT B/F | E18: Kshs. | F18: =meter!O32 -> 0 | N18: =O18-Q18 -> 10430 | O18: 10430
N19: =O19-Q19 -> 11831 | O19: 11831
D20: MONTH BILL | E20: KSHS. | F20: =meter!I33 -> 150 | N20: =O20-Q20 -> 10590 | O20: 10590
N21: =O21-Q21 -> 22423 | O21: 22423
D22: PUMP/POWER CHARGES | E22: KSHS. | F22: ='1A'!E21 -> 0 | N22: =O22-Q22 -> 9250 | O22: 9250
N23: =O23-Q23 -> 10162 | O23: 10162
D24: MONTH HOUSE RENT | E24: KSHS. | F24: =meter!N33 -> 7000 | N24: =O24-Q24 -> 10270 | O24: 10270
N25: =O25-Q25 -> 11070 | O25: 11070
D26: ='1A'!C25 -> SECURITY | E26: ='1A'!D25 -> Kshs. | F26: ='1A'!E25 -> 0 | N26: =O26-Q26 -> 11550 | O26: 11550
D27: GARBAGE FEE | E27: Kshs. | N27: =O27-Q27 -> 11393 | O27: 11393
D28: ADJUSTMENT-INTEREST ON ARREARS | E28: KSHS. | F28: =IF(F18*4%*1<0,0,F18*4%*1) -> 0 | N28: =O28-Q28 -> 10802 | O28: 10802
N29: =O29-Q29 -> 8930 | O29: 8930
D30: TOTAL PAYABLE | E30: Kshs. | F30: =SUM(F17:F29) -> 7150 | N30: =O30-Q30 -> 9570 | O30: 9570
N31: =O31-Q31 -> 11390 | O31: 11390
D32: PAID | F32: =meter!T33 -> 0 | N32: =O32-Q32 -> 10750 | O32: 10750
N33: =O33-Q33 -> 11732 | O33: 11732
D34: AMOUNT DUE | F34: =F30-F32 -> 7150 | N34: =O34-Q34 -> 10934 | O34: 10934 | R34: 700
C35: NOTE | N35: =O35-Q35 -> 10270 | O35: 10270
D36: PAY BILL 4139271 ACC NO UM 5E | N36: =O36-Q36 -> 10598 | O36: 10598
N37: =O37-Q37 -> 8770 | O37: 8770
N38: =O38-Q38 -> 8770 | O38: 8770
O39: =SUM(O3:O38) -> 391268 | Q39: =SUM(Q3:Q38) -> 0

Sheet 6E
B1: OLE SAMEDHA PREMIER HOSTELS
B2: ='1A'!B2 -> P.O BOX 9473-00200 NAIROBI | N2: VAR | O2: TAX DUE
B3: WATER BILL | N3: =O3-Q3 -> 10270 | O3: 10270
H4: BILL NO. | I4: ='1A'!H3+29-1 -> 66 | J4: ='1A'!H3+29-1 -> 66 | N4: =O4-Q4 -> 10304 | O4: 10304
N5: =O5-Q5 -> 10988 | O5: 10988
B6: TENANT NAME | N6: =O6-Q6 -> 11070 | O6: 11070
N7: =O7-Q7 -> 1197 | O7: 1197
B8: HOUSE NUMBER: | D8: 6E | N8: =O8-Q8 -> 9250 | O8: 9250
N9: =O9-Q9 -> 8770 | O9: 8770
B10: ISSUE DATE | D10: ='1A'!C9 -> 30TH JAN 2026 | N10: =O10-Q10 -> 23190 | O10: 23190
N11: =O11-Q11 -> 10910 | O11: 10910
B12: LAST PAY DATE | D12: ='1A'!C11 -> 5TH FEB 2026 | N12: =O12-Q12 -> 10910 | O12: 10910
N13: =O13-Q13 -> 12190 | O13: 12190
N14: =O14-Q14 -> 11070 | O14: 11070
B15: PREVIOUS READING | D15: CURRENT READING | F15: CONSUMPTION | N15: =O15-Q15 -> 9090 | O15: 9090
B16: =meter!E32 -> 29 | D16: =meter!F32 -> 30 | E16: Units | F16: =D16-B16 -> 1 | N16: =O16-Q16 -> 9420 | O16: 9420
F17: Amount (Kshs.) | N17: =O17-Q17 -> 11154 | O17: 11154
D18: LAST ACCOUNT B/F | E18: Kshs. | F18: =meter!O33 -> 0 | L18: a | N18: =O18-Q18 -> 10430 | O18: 10430
N19: =O19-Q19 -> 11831 | O19: 11831
D20: MONTH BILL | E20: KSHS. | F20: =meter!I32 -> 150 | N20: =O20-Q20 -> 10590 | O20: 10590
N21: =O21-Q21 -> 22423 | O21: 22423
D22: PUMP/POWER CHARGES | E22: KSHS. | F22: ='1A'!E21 -> 0 | N22: =O22-Q22 -> 9250 | O22: 9250
N23: =O23-Q23 -> 10162 | O23: 10162
D24: MONTH HOUSE RENT | E24: KSHS. | F24: =meter!N32 -> 7000 | N24: =O24-Q24 -> 10270 | O24: 10270
N25: =O25-Q25 -> 11070 | O25: 11070
D26: ='1A'!C25 -> SECURITY | E26: ='1A'!D25 -> Kshs. | F26: ='1A'!E25 -> 0 | N26: =O26-Q26 -> 11550 | O26: 11550
D27: GARBAGE FEE | E27: Kshs. | N27: =O27-Q27 -> 11393 | O27: 11393
D28: ADJUSTMENT | E28: KSHS. | F28: =IF(F18*4%*1<0,0,F18*4%*1) -> 0 | N28: =O28-Q28 -> 10802 | O28: 10802
N29: =O29-Q29 -> 8930 | O29: 8930
D30: TOTAL PAYABLE | E30: Kshs. | F30: =SUM(F17:F29) -> 7150 | N30: =O30-Q30 -> 9570 | O30: 9570
N31: =O31-Q31 -> 11390 | O31: 11390
D32: PAID | F32: =meter!T32 -> 0 | N32: =O32-Q32 -> 10750 | O32: 10750
N33: =O33-Q33 -> 11732 | O33: 11732
D34: AMOUNT DUE | F34: =F30-F32 -> 7150 | N34: =O34-Q34 -> 10934 | O34: 10934 | R34: 700
C35: NOTE | N35: =O35-Q35 -> 10270 | O35: 10270
D36: PAY BILL 4139271 ACC NO UM 6E | N36: =O36-Q36 -> 10598 | O36: 10598
N37: =O37-Q37 -> 8770 | O37: 8770
N38: =O38-Q38 -> 8770 | O38: 8770
O39: =SUM(O3:O38) -> 391268 | Q39: =SUM(Q3:Q38) -> 0

Sheet 7E
B1: OLE SAMEDHA PREMIER HOSTELS
B2: ='1A'!B2 -> P.O BOX 9473-00200 NAIROBI | N2: VAR | O2: TAX DUE
B3: WATER BILL | N3: =O3-Q3 -> 10270 | O3: 10270
H4: BILL NO. | I4: ='1A'!H3+31-1 -> 68 | J4: ='1A'!H3+31-1 -> 68 | N4: =O4-Q4 -> 10304 | O4: 10304
N5: =O5-Q5 -> 10988 | O5: 10988
B6: TENANT NAME | D6: =meter!B34 -> YUSUF | N6: =O6-Q6 -> 11070 | O6: 11070
N7: =O7-Q7 -> 1197 | O7: 1197
B8: HOUSE NUMBER: | D8: 7E | N8: =O8-Q8 -> 9250 | O8: 9250
N9: =O9-Q9 -> 8770 | O9: 8770
B10: ISSUE DATE | D10: ='1A'!C9 -> 30TH JAN 2026 | N10: =O10-Q10 -> 23190 | O10: 23190
N11: =O11-Q11 -> 10910 | O11: 10910
B12: LAST PAY DATE | D12: ='1A'!C11 -> 5TH FEB 2026 | N12: =O12-Q12 -> 10910 | O12: 10910
N13: =O13-Q13 -> 12190 | O13: 12190
N14: =O14-Q14 -> 11070 | O14: 11070
B15: PREVIOUS READING | D15: CURRENT READING | F15: CONSUMPTION | N15: =O15-Q15 -> 9090 | O15: 9090
B16: =meter!E34 -> 48 | D16: =meter!F34 -> 49 | E16: Units | F16: =D16-B16 -> 1 | N16: =O16-Q16 -> 9420 | O16: 9420
F17: Amount (Kshs.) | N17: =O17-Q17 -> 11154 | O17: 11154
D18: LAST ACCOUNT B/F | E18: Kshs. | F18: =meter!O34 -> 0 | N18: =O18-Q18 -> 10430 | O18: 10430
N19: =O19-Q19 -> 11831 | O19: 11831
D20: MONTH BILL | E20: KSHS. | F20: =meter!I34 -> 150 | N20: =O20-Q20 -> 10590 | O20: 10590
N21: =O21-Q21 -> 22423 | O21: 22423
D22: PUMP/POWER CHARGES | E22: KSHS. | F22: ='1A'!E21 -> 0 | N22: =O22-Q22 -> 9250 | O22: 9250
N23: =O23-Q23 -> 10162 | O23: 10162
D24: MONTH HOUSE RENT | E24: KSHS. | F24: =meter!N34 -> 10000 | N24: =O24-Q24 -> 10270 | O24: 10270
N25: =O25-Q25 -> 11070 | O25: 11070
D26: ='1A'!C25 -> SECURITY | E26: ='1A'!D25 -> Kshs. | F26: ='1A'!E25 -> 0 | N26: =O26-Q26 -> 11550 | O26: 11550
D27: GARBAGE FEE | E27: Kshs. | N27: =O27-Q27 -> 11393 | O27: 11393
D28: ADJUSTMENT-INTEREST ON ARREARS | E28: KSHS. | F28: =IF(F18*4%*1<0,0,F18*4%*1) -> 0 | N28: =O28-Q28 -> 10802 | O28: 10802
N29: =O29-Q29 -> 8930 | O29: 8930
D30: TOTAL PAYABLE | E30: Kshs. | F30: =SUM(F17:F29) -> 10150 | N30: =O30-Q30 -> 9570 | O30: 9570
N31: =O31-Q31 -> 11390 | O31: 11390
D32: PAID | F32: =meter!T34 -> 0 | N32: =O32-Q32 -> 10750 | O32: 10750
N33: =O33-Q33 -> 11732 | O33: 11732
D34: AMOUNT DUE | F34: =F30-F32 -> 10150 | N34: =O34-Q34 -> 10934 | O34: 10934 | R34: 700
N35: =O35-Q35 -> 10270 | O35: 10270
D36: PAY BILL 4139271 ACC NO UM 7E | N36: =O36-Q36 -> 10598 | O36: 10598
N37: =O37-Q37 -> 8770 | O37: 8770
N38: =O38-Q38 -> 8770 | O38: 8770
O39: =SUM(O3:O38) -> 391268 | Q39: =SUM(Q3:Q38) -> 0

Sheet 1F
A1: G | B1: OLE SAMEDHA PREMIER HOSTELS
B2: ='1A'!B2 -> P.O BOX 9473-00200 NAIROBI | N2: VAR | O2: TAX DUE
B3: WATER BILL | N3: =O3-Q3 -> 10270 | O3: 10270
H4: BILL NO. | I4: ='1A'!H3+32-1 -> 69 | J4: ='1A'!H3+32-1 -> 69 | N4: =O4-Q4 -> 10304 | O4: 10304
N5: =O5-Q5 -> 10988 | O5: 10988
B6: TENANT NAME | D6: =meter!B35 -> TUSMA | N6: =O6-Q6 -> 11070 | O6: 11070
N7: =O7-Q7 -> 1197 | O7: 1197
B8: HOUSE NUMBER: | D8: 1F | N8: =O8-Q8 -> 9250 | O8: 9250
N9: =O9-Q9 -> 8770 | O9: 8770
B10: ISSUE DATE | D10: 45566 | N10: =O10-Q10 -> 23190 | O10: 23190
N11: =O11-Q11 -> 10910 | O11: 10910
B12: LAST PAY DATE | D12: 45570 | N12: =O12-Q12 -> 10910 | O12: 10910
N13: =O13-Q13 -> 12190 | O13: 12190
N14: =O14-Q14 -> 11070 | O14: 11070
B15: PREVIOUS READING | D15: CURRENT READING | F15: CONSUMPTION | N15: =O15-Q15 -> 9090 | O15: 9090
B16: =meter!E35 -> 9 | D16: =meter!F35 -> 10 | E16: Units | F16: =D16-B16 -> 1 | N16: =O16-Q16 -> 9420 | O16: 9420
F17: Amount (Kshs.) | N17: =O17-Q17 -> 11154 | O17: 11154
D18: LAST ACCOUNT B/F | E18: Kshs. | F18: =meter!O35 -> 0 | N18: =O18-Q18 -> 10430 | O18: 10430
N19: =O19-Q19 -> 11831 | O19: 11831
D20: MONTH BILL | E20: KSHS. | F20: =meter!I35 -> 150 | N20: =O20-Q20 -> 10590 | O20: 10590
N21: =O21-Q21 -> 22423 | O21: 22423
D22: PUMP/POWER CHARGES | E22: KSHS. | F22: ='1A'!E21 -> 0 | N22: =O22-Q22 -> 9250 | O22: 9250
N23: =O23-Q23 -> 10162 | O23: 10162
D24: MONTH HOUSE RENT | E24: KSHS. | F24: =meter!N35 -> 8000 | N24: =O24-Q24 -> 10270 | O24: 10270
N25: =O25-Q25 -> 11070 | O25: 11070
D26: ='1A'!C25 -> SECURITY | E26: ='1A'!D25 -> Kshs. | F26: =meter!M35 -> 0 | N26: =O26-Q26 -> 11550 | O26: 11550
D27: GARBAGE FEE | E27: Kshs. | N27: =O27-Q27 -> 11393 | O27: 11393
D28: INTEREST LATE PAYMENT | E28: KSHS. | F28: =IF(F18*4%*1<0,0,F18*4%*1) -> 0 | N28: =O28-Q28 -> 10802 | O28: 10802
N29: =O29-Q29 -> 8930 | O29: 8930
D30: TOTAL PAYABLE | E30: Kshs. | F30: =SUM(F17:F29) -> 8150 | N30: =O30-Q30 -> 9570 | O30: 9570
N31: =O31-Q31 -> 11390 | O31: 11390
D32: PAID | F32: =meter!T35 -> 0 | N32: =O32-Q32 -> 10750 | O32: 10750
N33: =O33-Q33 -> 11732 | O33: 11732
D34: AMOUNT DUE | F34: =F30-F32 -> 8150 | N34: =O34-Q34 -> 10934 | O34: 10934 | R34: 700
C35: NOTE | D35: PAY BILL 4139271 ACC NO UM 1F | N35: =O35-Q35 -> 10270 | O35: 10270
N36: =O36-Q36 -> 10598 | O36: 10598
N37: =O37-Q37 -> 8770 | O37: 8770
N38: =O38-Q38 -> 8770 | O38: 8770

Sheet 2F
B1: OLE SAMEDHA APARTMENTS-Kitengela | D1: OLE SAMEDHA PREMIER HOSTELS
B2: ='1A'!B2 -> P.O BOX 9473-00200 NAIROBI | N2: VAR | O2: TAX DUE
B3: WATER BILL | N3: =O3-Q3 -> 10270 | O3: 10270
H4: BILL NO. | I4: ='1A'!H3+33-1 -> 70 | J4: ='1A'!H3+33-1 -> 70 | N4: =O4-Q4 -> 10304 | O4: 10304
N5: =O5-Q5 -> 10988 | O5: 10988
B6: TENANT NAME | D6: =meter!B36 -> FOZIA YUSSUF | N6: =O6-Q6 -> 11070 | O6: 11070
N7: =O7-Q7 -> 1197 | O7: 1197
B8: HOUSE NUMBER: | D8: 2F | N8: =O8-Q8 -> 9250 | O8: 9250
N9: =O9-Q9 -> 8770 | O9: 8770
B10: ISSUE DATE | D10: ='1A'!C9 -> 30TH JAN 2026 | N10: =O10-Q10 -> 23190 | O10: 23190
N11: =O11-Q11 -> 10910 | O11: 10910
B12: LAST PAY DATE | D12: ='1A'!C11 -> 5TH FEB 2026 | N12: =O12-Q12 -> 10910 | O12: 10910
N13: =O13-Q13 -> 12190 | O13: 12190
N14: =O14-Q14 -> 11070 | O14: 11070
B15: PREVIOUS READING | D15: CURRENT READING | F15: CONSUMPTION | N15: =O15-Q15 -> 9090 | O15: 9090
B16: =meter!E36 -> 45 | D16: =meter!F36 -> 46 | E16: Units | F16: =D16-B16 -> 1 | N16: =O16-Q16 -> 9420 | O16: 9420
F17: Amount (Kshs.) | N17: =O17-Q17 -> 11154 | O17: 11154
D18: LAST ACCOUNT B/F | E18: Kshs. | F18: =meter!O36 -> 0 | N18: =O18-Q18 -> 10430 | O18: 10430
N19: =O19-Q19 -> 11831 | O19: 11831
D20: MONTH BILL | E20: KSHS. | F20: =meter!I36 -> 150 | N20: =O20-Q20 -> 10590 | O20: 10590
N21: =O21-Q21 -> 22423 | O21: 22423
D22: PUMP/POWER CHARGES | E22: KSHS. | F22: ='1A'!E21 -> 0 | N22: =O22-Q22 -> 9250 | O22: 9250
N23: =O23-Q23 -> 10162 | O23: 10162
D24: MONTH HOUSE RENT | E24: KSHS. | F24: =meter!N36 -> 8000 | N24: =O24-Q24 -> 10270 | O24: 10270
N25: =O25-Q25 -> 11070 | O25: 11070
D26: ='1A'!C25 -> SECURITY | E26: ='1A'!D25 -> Kshs. | F26: ='1A'!E25 -> 0 | N26: =O26-Q26 -> 11550 | O26: 11550
D27: GARBAGE FEE | E27: Kshs. | N27: =O27-Q27 -> 11393 | O27: 11393
D28: ADJUSTMENT | E28: KSHS. | F28: =IF(F18*4%*1<0,0,F18*4%*1) -> 0 | N28: =O28-Q28 -> 10802 | O28: 10802
N29: =O29-Q29 -> 8930 | O29: 8930
D30: TOTAL PAYABLE | E30: Kshs. | F30: =SUM(F17:F29) -> 8150 | N30: =O30-Q30 -> 9570 | O30: 9570
N31: =O31-Q31 -> 11390 | O31: 11390
D32: PAID | F32: =meter!T36 -> 0 | N32: =O32-Q32 -> 10750 | O32: 10750
N33: =O33-Q33 -> 11732 | O33: 11732
D34: AMOUNT DUE | F34: =F30-F32 -> 8150 | N34: =O34-Q34 -> 10934 | O34: 10934 | R34: 700
N35: =O35-Q35 -> 10270 | O35: 10270
D36: PAY BILL 4139271 ACC NO UM 2F | N36: =O36-Q36 -> 10598 | O36: 10598
N37: =O37-Q37 -> 8770 | O37: 8770
N38: =O38-Q38 -> 8770 | O38: 8770
O39: =SUM(O3:O38) -> 391268 | Q39: =SUM(Q3:Q38) -> 0

Sheet 3F
B1: OLE SAMEDHA PREMIER HOSTELS
B2: ='1A'!B2 -> P.O BOX 9473-00200 NAIROBI | N2: VAR | O2: TAX DUE
B3: WATER BILL | N3: =O3-Q3 -> 10270 | O3: 10270
H4: BILL NO. | I4: ='1A'!H3+34-1 -> 71 | J4: ='1A'!H3+34-1 -> 71 | N4: =O4-Q4 -> 10304 | O4: 10304
N5: =O5-Q5 -> 10988 | O5: 10988
B6: TENANT NAME | D6: =meter!B37 -> HALIMA | N6: =O6-Q6 -> 11070 | O6: 11070
N7: =O7-Q7 -> 1197 | O7: 1197
B8: HOUSE NUMBER: | D8: 3F | N8: =O8-Q8 -> 9250 | O8: 9250
N9: =O9-Q9 -> 8770 | O9: 8770
B10: ISSUE DATE | D10: ='1A'!C9 -> 30TH JAN 2026 | N10: =O10-Q10 -> 23190 | O10: 23190
N11: =O11-Q11 -> 10910 | O11: 10910
B12: LAST PAY DATE | D12: ='1A'!C11 -> 5TH FEB 2026 | N12: =O12-Q12 -> 10910 | O12: 10910
N13: =O13-Q13 -> 12190 | O13: 12190
N14: =O14-Q14 -> 11070 | O14: 11070
B15: PREVIOUS READING | D15: CURRENT READING | F15: CONSUMPTION | N15: =O15-Q15 -> 9090 | O15: 9090
B16: =meter!E37 -> 28 | D16: =meter!F37 -> 29 | E16: Units | F16: =D16-B16 -> 1 | N16: =O16-Q16 -> 9420 | O16: 9420
F17: Amount (Kshs.) | N17: =O17-Q17 -> 11154 | O17: 11154
D18: LAST ACCOUNT B/F | E18: Kshs. | F18: =meter!O37 -> 0 | N18: =O18-Q18 -> 10430 | O18: 10430
N19: =O19-Q19 -> 11831 | O19: 11831
D20: MONTH BILL | E20: KSHS. | F20: =meter!I37 -> 150 | N20: =O20-Q20 -> 10590 | O20: 10590
N21: =O21-Q21 -> 22423 | O21: 22423
D22: PUMP/POWER CHARGES | E22: KSHS. | F22: ='1A'!E21 -> 0 | N22: =O22-Q22 -> 9250 | O22: 9250
N23: =O23-Q23 -> 10162 | O23: 10162
D24: MONTH HOUSE RENT | E24: KSHS. | F24: =meter!N37 -> 7000 | N24: =O24-Q24 -> 10270 | O24: 10270
N25: =O25-Q25 -> 11070 | O25: 11070
D26: ='1A'!C25 -> SECURITY | E26: ='1A'!D25 -> Kshs. | F26: =meter!M37 -> 0 | N26: =O26-Q26 -> 11550 | O26: 11550
D27: GARBAGE FEE | E27: Kshs. | N27: =O27-Q27 -> 11393 | O27: 11393
D28: INTEREST ON ARREARS | E28: KSHS. | F28: =IF(F18*4%*1<0,0,F18*4%*1) -> 0 | N28: =O28-Q28 -> 10802 | O28: 10802
N29: =O29-Q29 -> 8930 | O29: 8930
D30: TOTAL PAYABLE | E30: Kshs. | F30: =SUM(F17:F29) -> 7150 | N30: =O30-Q30 -> 9570 | O30: 9570
N31: =O31-Q31 -> 11390 | O31: 11390
D32: PAID | F32: =meter!T37 -> 0 | N32: =O32-Q32 -> 10750 | O32: 10750
N33: =O33-Q33 -> 11732 | O33: 11732
D34: AMOUNT DUE | F34: =F30-F32 -> 7150 | N34: =O34-Q34 -> 10934 | O34: 10934 | R34: 700
D35: PAY BILL 4139271 ACC NO UM 3F | N35: =O35-Q35 -> 10270 | O35: 10270
N36: =O36-Q36 -> 10598 | O36: 10598
N37: =O37-Q37 -> 8770 | O37: 8770
N38: =O38-Q38 -> 8770 | O38: 8770
O39: =SUM(O3:O38) -> 391268 | Q39: =SUM(Q3:Q38) -> 0

Sheet 4F
B1: OLE SAMEDHA PREMIER HOSTELS
B2: ='1A'!B2 -> P.O BOX 9473-00200 NAIROBI | N2: VAR | O2: TAX DUE
B3: WATER BILL | N3: =O3-Q3 -> 10270 | O3: 10270
H4: BILL NO. | I4: ='1A'!H3+35-1 -> 72 | J4: ='1A'!H3+35-1 -> 72 | N4: =O4-Q4 -> 10304 | O4: 10304
N5: =O5-Q5 -> 10988 | O5: 10988
B6: TENANT NAME | D6: =meter!B38 -> ASMA | N6: =O6-Q6 -> 11070 | O6: 11070
N7: =O7-Q7 -> 1197 | O7: 1197
B8: HOUSE NUMBER: | D8: 4F | N8: =O8-Q8 -> 9250 | O8: 9250
N9: =O9-Q9 -> 8770 | O9: 8770
B10: ISSUE DATE | D10: ='1A'!C9 -> 30TH JAN 2026 | N10: =O10-Q10 -> 23190 | O10: 23190
N11: =O11-Q11 -> 10910 | O11: 10910
B12: LAST PAY DATE | D12: ='1A'!C11 -> 5TH FEB 2026 | N12: =O12-Q12 -> 10910 | O12: 10910
N13: =O13-Q13 -> 12190 | O13: 12190
N14: =O14-Q14 -> 11070 | O14: 11070
B15: PREVIOUS READING | D15: CURRENT READING | F15: CONSUMPTION | N15: =O15-Q15 -> 9090 | O15: 9090
B16: =meter!E38 -> 36 | D16: =meter!F38 -> 37 | E16: Units | F16: =D16-B16 -> 1 | H16: ESTIMATE | N16: =O16-Q16 -> 9420 | O16: 9420
F17: Amount (Kshs.) | N17: =O17-Q17 -> 11154 | O17: 11154
D18: LAST ACCOUNT B/F | E18: Kshs. | F18: =meter!O38 -> 0 | N18: =O18-Q18 -> 10430 | O18: 10430
N19: =O19-Q19 -> 11831 | O19: 11831
D20: MONTH BILL | E20: KSHS. | F20: =meter!I38 -> 150 | N20: =O20-Q20 -> 10590 | O20: 10590
N21: =O21-Q21 -> 22423 | O21: 22423
D22: PUMP/POWER CHARGES | E22: KSHS. | F22: ='1A'!E21 -> 0 | N22: =O22-Q22 -> 9250 | O22: 9250
N23: =O23-Q23 -> 10162 | O23: 10162
D24: MONTH HOUSE RENT | E24: KSHS. | F24: =meter!N38 -> 7000 | N24: =O24-Q24 -> 10270 | O24: 10270
N25: =O25-Q25 -> 11070 | O25: 11070
D26: ='1A'!C25 -> SECURITY | E26: ='1A'!D25 -> Kshs. | F26: ='1A'!E25 -> 0 | N26: =O26-Q26 -> 11550 | O26: 11550
D27: GARBAGE FEE | E27: Kshs. | F27: 0 | N27: =O27-Q27 -> 11393 | O27: 11393
D28: ADJUSTMENT | E28: KSHS. | F28: =IF(F18*4%*1<0,0,F18*4%*1) -> 0 | N28: =O28-Q28 -> 10802 | O28: 10802
N29: =O29-Q29 -> 8930 | O29: 8930
D30: TOTAL PAYABLE | E30: Kshs. | F30: =SUM(F17:F29) -> 7150 | N30: =O30-Q30 -> 9570 | O30: 9570
N31: =O31-Q31 -> 11390 | O31: 11390
D32: PAID | F32: =meter!T38 -> 0 | N32: =O32-Q32 -> 10750 | O32: 10750
N33: =O33-Q33 -> 11732 | O33: 11732
D34: AMOUNT DUE | F34: =F30-F32 -> 7150 | N34: =O34-Q34 -> 10934 | O34: 10934 | R34: 700
N35: =O35-Q35 -> 10270 | O35: 10270
D36: PAY BILL 4139271 ACC NO UM 4F | N36: =O36-Q36 -> 10598 | O36: 10598
N37: =O37-Q37 -> 8770 | O37: 8770
N38: =O38-Q38 -> 8770 | O38: 8770
O39: =SUM(O3:O38) -> 391268 | Q39: =SUM(Q3:Q38) -> 0

Sheet 36B
B1: OLE SAMEDHA APARTMENTS-Kitengela
B2: ='1A'!B2 -> P.O BOX 9473-00200 NAIROBI
B3: WATER BILL
H4: BILL NO. | I4: ='1A'!H3+36-1 -> 73
B6: TENANT NAME | D6: SAMMY ONDARI
B8: HOUSE NUMBER: | D8: 36B
B10: ISSUE DATE | D10: ='1A'!C9 -> 30TH JAN 2026
B12: LAST PAY DATE | D12: ='1A'!C11 -> 5TH FEB 2026
B15: PREVIOUS READING | D15: CURRENT READING | F15: CONSUMPTION
B16: =meter!#REF! -> #REF! | D16: =meter!#REF! -> #REF! | E16: Units | F16: =D16-B16 -> #REF!
F17: Amount (Kshs.)
D18: LAST ACCOUNT B/F | E18: Kshs. | F18: =meter!O38 -> 0
D20: MONTH BILL | E20: KSHS. | F20: =meter!I38 -> 150
D22: PUMP/POWER CHARGES | E22: KSHS. | F22: ='1A'!E21 -> 0
D24: MONTH HOUSE RENT | E24: KSHS. | F24: =meter!#REF! -> #REF!
D26: ='1A'!C25 -> SECURITY | E26: ='1A'!D25 -> Kshs. | F26: =meter!#REF! -> #REF!
D28: ADJUSTMENT | E28: KSHS. | F28: =IF(F18*2%*3<0,0,F18*2%*3) -> 0
D30: TOTAL PAYABLE | E30: Kshs. | F30: =SUM(F17:F29) -> #REF!
D32: PAID | F32: =meter!T38 -> 0
D34: AMOUNT DUE | F34: =F30-F32 -> #REF!
C35: NOTE
A36: a) | B36: Rent is due on or before 5th of the month. By 7th day, any rent not paid will attract interest at 2% per day.
A37: b) | B37: Any default in Rent payment by 10th of the month the house shall be locked without notice and belongings removed for re-letting.
A39: c) | B39: Amounts not cleared by last pay date will render to water disconnection.
A41: d) | B41: A reconnection fee of Kshs. 1,000 will be charged and paid before supply is reconnected.
A42: e) | B42: ANY MINOR REPAIRS OCCURING AFTER 3 MONTHS OF OCCUPANCY ARE TENANT'S RESPONSIBILITY AS PER TENANCY AGREEMENT.
A43: f) | B43: The water bills are payable through the same account for monthly rent strictly through:
B44: Frebazeth Company Limited
B45: RAFIKI DTM (Deposit Taking Microfinance)
B46: Kitengela Branch
B47: A/C NO. 0082020000386
B48: (Kindly indicate your Name & House number on the deposit slip & inform the Bank teller to capture it.)
B49: A receipt will be issued upon bank confirmation of the transaction.
A50: g) | B50: NO MPESA or cash payments allowed.
B51: E & O E
B52: NB: Kindly give the management atleast two (2) months prior notice incase you intend to terminate the tenancy for ease of logisitics.

Sheet 5F
B1: OLE SAMEDHA PREMIER HOSTELS
B2: ='1A'!B2 -> P.O BOX 9473-00200 NAIROBI | N2: VAR | O2: TAX DUE
B3: WATER BILL | N3: =O3-Q3 -> 10270 | O3: 10270
H4: BILL NO. | I4: ='1A'!H3+34-1 -> 71 | J4: ='1A'!H3+34-1 -> 71 | N4: =O4-Q4 -> 10304 | O4: 10304
N5: =O5-Q5 -> 10988 | O5: 10988
B6: TENANT NAME | D6: =meter!B39 -> ZAHRA AISHA | N6: =O6-Q6 -> 11070 | O6: 11070
N7: =O7-Q7 -> 1197 | O7: 1197
B8: HOUSE NUMBER: | D8: 5F | N8: =O8-Q8 -> 9250 | O8: 9250
N9: =O9-Q9 -> 8770 | O9: 8770
B10: ISSUE DATE | D10: ='1A'!C9 -> 30TH JAN 2026 | N10: =O10-Q10 -> 23190 | O10: 23190
N11: =O11-Q11 -> 10910 | O11: 10910
B12: LAST PAY DATE | D12: ='1A'!C11 -> 5TH FEB 2026 | N12: =O12-Q12 -> 10910 | O12: 10910
N13: =O13-Q13 -> 12190 | O13: 12190
N14: =O14-Q14 -> 11070 | O14: 11070
B15: PREVIOUS READING | D15: CURRENT READING | F15: CONSUMPTION | N15: =O15-Q15 -> 9090 | O15: 9090
B16: =meter!E39 -> 57 | D16: =meter!F39 -> 59 | E16: Units | F16: =D16-B16 -> 2 | N16: =O16-Q16 -> 9420 | O16: 9420
F17: Amount (Kshs.) | N17: =O17-Q17 -> 11154 | O17: 11154
D18: LAST ACCOUNT B/F | E18: Kshs. | F18: =meter!O39 -> 0 | N18: =O18-Q18 -> 10430 | O18: 10430
N19: =O19-Q19 -> 11831 | O19: 11831
D20: MONTH BILL | E20: KSHS. | F20: =meter!I39 -> 300 | N20: =O20-Q20 -> 10590 | O20: 10590
N21: =O21-Q21 -> 22423 | O21: 22423
D22: PUMP/POWER CHARGES | E22: KSHS. | F22: ='1A'!E21 -> 0 | N22: =O22-Q22 -> 9250 | O22: 9250
N23: =O23-Q23 -> 10162 | O23: 10162
D24: MONTH HOUSE RENT | E24: KSHS. | F24: =meter!N39 -> 7000 | N24: =O24-Q24 -> 10270 | O24: 10270
N25: =O25-Q25 -> 11070 | O25: 11070
D26: ='1A'!C25 -> SECURITY | E26: ='1A'!D25 -> Kshs. | F26: =meter!M37 -> 0 | N26: =O26-Q26 -> 11550 | O26: 11550
D27: GARBAGE FEE | E27: Kshs. | F27: 0 | N27: =O27-Q27 -> 11393 | O27: 11393
D28: INTEREST ON ARREARS | E28: KSHS. | F28: =IF(F18*4%*1<0,0,F18*4%*1) -> 0 | N28: =O28-Q28 -> 10802 | O28: 10802
N29: =O29-Q29 -> 8930 | O29: 8930
D30: TOTAL PAYABLE | E30: Kshs. | F30: =SUM(F17:F29) -> 7300 | N30: =O30-Q30 -> 9570 | O30: 9570
N31: =O31-Q31 -> 11390 | O31: 11390
D32: PAID | F32: =meter!T37 -> 0 | N32: =O32-Q32 -> 10750 | O32: 10750
N33: =O33-Q33 -> 11732 | O33: 11732
D34: AMOUNT DUE | F34: =F30-F32 -> 7300 | N34: =O34-Q34 -> 10934 | O34: 10934 | R34: 700
B38: Rent is due on or before 5th of the month. By 7th day, any rent not paid will attract interest at 2% per day.
B39: Any default in Rent payment by 10th of the following month the house shall be locked without notice and belongings removed for re-letting.
B41: PAY BILL 4139271 ACC NO UM 5F
C42: Once you’ve made the payment, please forward the details to 0700 194 262

Sheet 6F
B1: OLE SAMEDHA PREMIER HOSTELS
B2: ='1A'!B2 -> P.O BOX 9473-00200 NAIROBI | N2: VAR | O2: TAX DUE
B3: WATER BILL | N3: =O3-Q3 -> 10270 | O3: 10270
H4: BILL NO. | I4: ='1A'!H3+34-1 -> 71 | J4: ='1A'!H3+34-1 -> 71 | N4: =O4-Q4 -> 10304 | O4: 10304
N5: =O5-Q5 -> 10988 | O5: 10988
B6: TENANT NAME | D6: =meter!B40 -> MUHAMMED NASIR | N6: =O6-Q6 -> 11070 | O6: 11070
N7: =O7-Q7 -> 1197 | O7: 1197
B8: HOUSE NUMBER: | D8: 6F | N8: =O8-Q8 -> 9250 | O8: 9250
N9: =O9-Q9 -> 8770 | O9: 8770
B10: ISSUE DATE | D10: ='1A'!C9 -> 30TH JAN 2026 | N10: =O10-Q10 -> 23190 | O10: 23190
N11: =O11-Q11 -> 10910 | O11: 10910
B12: LAST PAY DATE | D12: ='1A'!C11 -> 5TH FEB 2026 | N12: =O12-Q12 -> 10910 | O12: 10910
N13: =O13-Q13 -> 12190 | O13: 12190
N14: =O14-Q14 -> 11070 | O14: 11070
B15: PREVIOUS READING | D15: CURRENT READING | F15: CONSUMPTION | N15: =O15-Q15 -> 9090 | O15: 9090
B16: =meter!E40 -> 10 | D16: =meter!F40 -> 11 | E16: Units | F16: =D16-B16 -> 1 | N16: =O16-Q16 -> 9420 | O16: 9420
F17: Amount (Kshs.) | N17: =O17-Q17 -> 11154 | O17: 11154
D18: LAST ACCOUNT B/F | E18: Kshs. | F18: =meter!O40 -> 0 | N18: =O18-Q18 -> 10430 | O18: 10430
N19: =O19-Q19 -> 11831 | O19: 11831
D20: MONTH BILL | E20: KSHS. | F20: =meter!I40 -> 150 | N20: =O20-Q20 -> 10590 | O20: 10590
N21: =O21-Q21 -> 22423 | O21: 22423
D22: PUMP/POWER CHARGES | E22: KSHS. | F22: ='1A'!E21 -> 0 | N22: =O22-Q22 -> 9250 | O22: 9250
N23: =O23-Q23 -> 10162 | O23: 10162
D24: MONTH HOUSE RENT | E24: KSHS. | F24: =meter!N40 -> 6500 | N24: =O24-Q24 -> 10270 | O24: 10270
N25: =O25-Q25 -> 11070 | O25: 11070
D26: ='1A'!C25 -> SECURITY | E26: ='1A'!D25 -> Kshs. | F26: =meter!M37 -> 0 | N26: =O26-Q26 -> 11550 | O26: 11550
D27: GARBAGE FEE | E27: Kshs. | F27: 0 | N27: =O27-Q27 -> 11393 | O27: 11393
D28: INTEREST ON ARREARS | E28: KSHS. | F28: =IF(F18*4%*1<0,0,F18*4%*1) -> 0 | N28: =O28-Q28 -> 10802 | O28: 10802
N29: =O29-Q29 -> 8930 | O29: 8930
D30: TOTAL PAYABLE | E30: Kshs. | F30: =SUM(F17:F29) -> 6650 | N30: =O30-Q30 -> 9570 | O30: 9570
N31: =O31-Q31 -> 11390 | O31: 11390
D32: PAID | F32: =meter!T40 -> 0 | N32: =O32-Q32 -> 10750 | O32: 10750
N33: =O33-Q33 -> 11732 | O33: 11732
D34: AMOUNT DUE | F34: =F30-F32 -> 6650 | N34: =O34-Q34 -> 10934 | O34: 10934 | R34: 700
B35: Rent is due on or before 5th of the month. By 7th day, any rent not paid will attract interest at 2% per day. | N35: =O35-Q35 -> 10270 | O35: 10270
A36: a) | B36: Any default in Rent payment by 10th of the following month the house shall be locked without notice and belongings removed for re-letting. | N36: =O36-Q36 -> 10598 | O36: 10598
A37: b) | N37: =O37-Q37 -> 8770 | O37: 8770
B38: PAY BILL 4139271 ACC NO UM 6F
C39: Once you’ve made the payment, please forward the details to 0700 194 262

Sheet 7F
B1: OLE SAMEDHA PREMIER HOSTELS
B2: ='1A'!B2 -> P.O BOX 9473-00200 NAIROBI | N2: VAR | O2: TAX DUE
B3: WATER BILL | N3: =O3-Q3 -> 10270 | O3: 10270
H4: BILL NO. | I4: ='1A'!H3+34-1 -> 71 | J4: ='1A'!H3+34-1 -> 71 | N4: =O4-Q4 -> 10304 | O4: 10304
N5: =O5-Q5 -> 10988 | O5: 10988
B6: TENANT NAME | D6: =meter!B41 -> ZAKARIA | N6: =O6-Q6 -> 11070 | O6: 11070
N7: =O7-Q7 -> 1197 | O7: 1197
B8: HOUSE NUMBER: | D8: 7F | N8: =O8-Q8 -> 9250 | O8: 9250
N9: =O9-Q9 -> 8770 | O9: 8770
B10: ISSUE DATE | D10: ='1A'!C9 -> 30TH JAN 2026 | N10: =O10-Q10 -> 23190 | O10: 23190
N11: =O11-Q11 -> 10910 | O11: 10910
B12: LAST PAY DATE | D12: ='1A'!C11 -> 5TH FEB 2026 | N12: =O12-Q12 -> 10910 | O12: 10910
N13: =O13-Q13 -> 12190 | O13: 12190
N14: =O14-Q14 -> 11070 | O14: 11070
B15: PREVIOUS READING | D15: CURRENT READING | F15: CONSUMPTION | N15: =O15-Q15 -> 9090 | O15: 9090
B16: =meter!E41 -> 48 | D16: =meter!F41 -> 49 | E16: Units | F16: =D16-B16 -> 1 | N16: =O16-Q16 -> 9420 | O16: 9420
F17: Amount (Kshs.) | N17: =O17-Q17 -> 11154 | O17: 11154
D18: LAST ACCOUNT B/F | E18: Kshs. | F18: =meter!O41 -> 1032 | N18: =O18-Q18 -> 10430 | O18: 10430
N19: =O19-Q19 -> 11831 | O19: 11831
D20: MONTH BILL | E20: KSHS. | F20: =meter!I41 -> 150 | N20: =O20-Q20 -> 10590 | O20: 10590
N21: =O21-Q21 -> 22423 | O21: 22423
D22: PUMP/POWER CHARGES | E22: KSHS. | F22: ='1A'!E21 -> 0 | N22: =O22-Q22 -> 9250 | O22: 9250
N23: =O23-Q23 -> 10162 | O23: 10162
D24: MONTH HOUSE RENT | E24: KSHS. | F24: =meter!N41 -> 10000 | N24: =O24-Q24 -> 10270 | O24: 10270
N25: =O25-Q25 -> 11070 | O25: 11070
D26: ='1A'!C25 -> SECURITY | E26: ='1A'!D25 -> Kshs. | F26: =meter!M37 -> 0 | N26: =O26-Q26 -> 11550 | O26: 11550
D27: GARBAGE FEE | E27: Kshs. | F27: 0 | N27: =O27-Q27 -> 11393 | O27: 11393
D28: INTEREST ON ARREARS | E28: KSHS. | F28: =IF(F18*4%*1<0,0,F18*4%*1) -> 41.28 | N28: =O28-Q28 -> 10802 | O28: 10802
N29: =O29-Q29 -> 8930 | O29: 8930
D30: TOTAL PAYABLE | E30: Kshs. | F30: =SUM(F17:F29) -> 11223.28 | N30: =O30-Q30 -> 9570 | O30: 9570
N31: =O31-Q31 -> 11390 | O31: 11390
D32: PAID | F32: =meter!T37 -> 0 | N32: =O32-Q32 -> 10750 | O32: 10750
N33: =O33-Q33 -> 11732 | O33: 11732
D34: AMOUNT DUE | F34: =F30-F32 -> 11223.28 | N34: =O34-Q34 -> 10934 | O34: 10934 | R34: 700
N35: =O35-Q35 -> 10270 | O35: 10270
A37: Rent is due on or before 5th of the month. By 7th day, any rent not paid will attract interest at 2% per day.
A38: Any default in Rent payment by 10th of the following month the house shall be locked without notice and belongings removed for re-letting.
A40: PAY BILL 4139271 ACC NO UM 7F
B41: Once you’ve made the payment, please forward the details to 0700 194 262

Sheet 1G
B1: OLE SAMEDHA PREMIER HOSTELS
B2: ='1A'!B2 -> P.O BOX 9473-00200 NAIROBI | N2: VAR | O2: TAX DUE
B3: WATER BILL | N3: =O3-Q3 -> 10270 | O3: 10270
H4: BILL NO. | I4: ='1A'!H3+34-1 -> 71 | J4: ='1A'!H3+34-1 -> 71 | N4: =O4-Q4 -> 10304 | O4: 10304
N5: =O5-Q5 -> 10988 | O5: 10988
B6: TENANT NAME | D6: =meter!B42 -> 0 | N6: =O6-Q6 -> 11070 | O6: 11070
N7: =O7-Q7 -> 1197 | O7: 1197
B8: HOUSE NUMBER: | D8: 1G | N8: =O8-Q8 -> 9250 | O8: 9250
N9: =O9-Q9 -> 8770 | O9: 8770
B10: ISSUE DATE | D10: 45473 | N10: =O10-Q10 -> 23190 | O10: 23190
N11: =O11-Q11 -> 10910 | O11: 10910
B12: LAST PAY DATE | D12: 45478 | N12: =O12-Q12 -> 10910 | O12: 10910
N13: =O13-Q13 -> 12190 | O13: 12190
N14: =O14-Q14 -> 11070 | O14: 11070
B15: PREVIOUS READING | D15: CURRENT READING | F15: CONSUMPTION | N15: =O15-Q15 -> 9090 | O15: 9090
B16: =meter!E42 -> 40 | D16: =meter!F42 -> 40 | E16: Units | F16: =D16-B16 -> 0 | N16: =O16-Q16 -> 9420 | O16: 9420
F17: Amount (Kshs.) | N17: =O17-Q17 -> 11154 | O17: 11154
D18: LAST ACCOUNT B/F | E18: Kshs. | F18: =meter!O42 -> 0 | N18: =O18-Q18 -> 10430 | O18: 10430
N19: =O19-Q19 -> 11831 | O19: 11831
D20: MONTH BILL | E20: KSHS. | F20: =meter!I42 -> 0 | N20: =O20-Q20 -> 10590 | O20: 10590
N21: =O21-Q21 -> 22423 | O21: 22423
D22: PUMP/POWER CHARGES | E22: KSHS. | F22: ='1A'!E21 -> 0 | N22: =O22-Q22 -> 9250 | O22: 9250
N23: =O23-Q23 -> 10162 | O23: 10162
D24: MONTH HOUSE RENT | E24: KSHS. | F24: =meter!N42 -> 8000 | N24: =O24-Q24 -> 10270 | O24: 10270
N25: =O25-Q25 -> 11070 | O25: 11070
D26: ='1A'!C25 -> SECURITY | E26: ='1A'!D25 -> Kshs. | F26: =meter!M37 -> 0 | N26: =O26-Q26 -> 11550 | O26: 11550
D27: GARBAGE FEE | E27: Kshs. | F27: 0 | N27: =O27-Q27 -> 11393 | O27: 11393
D28: INTEREST ON ARREARS | E28: KSHS. | F28: =IF(F18*4%*1<0,0,F18*4%*1) -> 0 | N28: =O28-Q28 -> 10802 | O28: 10802
N29: =O29-Q29 -> 8930 | O29: 8930
D30: TOTAL PAYABLE | E30: Kshs. | F30: =SUM(F17:F29) -> 8000 | N30: =O30-Q30 -> 9570 | O30: 9570
N31: =O31-Q31 -> 11390 | O31: 11390
D32: PAID | F32: =meter!T37 -> 0 | N32: =O32-Q32 -> 10750 | O32: 10750
N33: =O33-Q33 -> 11732 | O33: 11732
D34: AMOUNT DUE | F34: =F30-F32 -> 8000 | N34: =O34-Q34 -> 10934 | O34: 10934 | R34: 700
C35: NOTE | N35: =O35-Q35 -> 10270 | O35: 10270
A36: a) | B36: Rent is due on or before 5th of the month. By 7th day, any rent not paid will attract interest at 2% per day. | N36: =O36-Q36 -> 10598 | O36: 10598
A37: b) | B37: Any default in Rent payment by 10th of the following month the house shall be locked without notice and belongings removed for re-letting. | N37: =O37-Q37 -> 8770 | O37: 8770
B38: PAY BILL 4139271 ACC NO UM 1G | N38: =O38-Q38 -> 8770 | O38: 8770

Sheet 2G
B1: OLE SAMEDHA PREMIER HOSTELS
B2: ='1A'!B2 -> P.O BOX 9473-00200 NAIROBI | N2: VAR | O2: TAX DUE
B3: WATER BILL | N3: =O3-Q3 -> 10270 | O3: 10270
H4: BILL NO. | I4: ='1A'!H3+34-1 -> 71 | J4: ='1A'!H3+34-1 -> 71 | N4: =O4-Q4 -> 10304 | O4: 10304
N5: =O5-Q5 -> 10988 | O5: 10988
B6: TENANT NAME | D6: =meter!B43 -> ISMAHAN MAIMUNA | N6: =O6-Q6 -> 11070 | O6: 11070
N7: =O7-Q7 -> 1197 | O7: 1197
B8: HOUSE NUMBER: | D8: 2G | N8: =O8-Q8 -> 9250 | O8: 9250
N9: =O9-Q9 -> 8770 | O9: 8770
B10: ISSUE DATE | D10: ='1A'!C9 -> 30TH JAN 2026 | N10: =O10-Q10 -> 23190 | O10: 23190
N11: =O11-Q11 -> 10910 | O11: 10910
B12: LAST PAY DATE | D12: ='1A'!C11 -> 5TH FEB 2026 | N12: =O12-Q12 -> 10910 | O12: 10910
N13: =O13-Q13 -> 12190 | O13: 12190
N14: =O14-Q14 -> 11070 | O14: 11070
B15: PREVIOUS READING | D15: CURRENT READING | F15: CONSUMPTION | N15: =O15-Q15 -> 9090 | O15: 9090
B16: =meter!E37 -> 28 | D16: =meter!F37 -> 29 | E16: Units | F16: =D16-B16 -> 1 | N16: =O16-Q16 -> 9420 | O16: 9420
F17: Amount (Kshs.) | N17: =O17-Q17 -> 11154 | O17: 11154
D18: LAST ACCOUNT B/F | E18: Kshs. | F18: =meter!O43 -> 774 | N18: =O18-Q18 -> 10430 | O18: 10430
N19: =O19-Q19 -> 11831 | O19: 11831
D20: MONTH BILL | E20: KSHS. | F20: =meter!I43 -> 150 | N20: =O20-Q20 -> 10590 | O20: 10590
N21: =O21-Q21 -> 22423 | O21: 22423
D22: PUMP/POWER CHARGES | E22: KSHS. | F22: ='1A'!E21 -> 0 | N22: =O22-Q22 -> 9250 | O22: 9250
N23: =O23-Q23 -> 10162 | O23: 10162
D24: MONTH HOUSE RENT | E24: KSHS. | F24: =meter!N43 -> 8000 | N24: =O24-Q24 -> 10270 | O24: 10270
N25: =O25-Q25 -> 11070 | O25: 11070
D26: ='1A'!C25 -> SECURITY | E26: ='1A'!D25 -> Kshs. | F26: =meter!M37 -> 0 | N26: =O26-Q26 -> 11550 | O26: 11550
D27: GARBAGE FEE | E27: Kshs. | F27: 0 | N27: =O27-Q27 -> 11393 | O27: 11393
D28: INTEREST ON ARREARS | E28: KSHS. | F28: =IF(F18*4%*1<0,0,F18*4%*1) -> 30.96 | N28: =O28-Q28 -> 10802 | O28: 10802
N29: =O29-Q29 -> 8930 | O29: 8930
D30: TOTAL PAYABLE | E30: Kshs. | F30: =SUM(F17:F29) -> 8954.96 | N30: =O30-Q30 -> 9570 | O30: 9570
N31: =O31-Q31 -> 11390 | O31: 11390
D32: PAID | F32: =meter!T37 -> 0 | N32: =O32-Q32 -> 10750 | O32: 10750
N33: =O33-Q33 -> 11732 | O33: 11732
D34: AMOUNT DUE | F34: =F30-F32 -> 8954.96 | N34: =O34-Q34 -> 10934 | O34: 10934 | R34: 700
B35: Rent is due on or before 5th of the month. By 7th day, any rent not paid will attract interest at 2% per day. | G35: Rent is due on or before 5th of the month. By 7th day, any rent not paid will attract interest at 2% per day. | N35: =O35-Q35 -> 10270 | O35: 10270
B36: Any default in Rent payment by 10th of the following month the house shall be locked without notice and belongings removed for re-letting. | G36: Any default in Rent payment by 10th of the following month the house shall be locked without notice and belongings removed for re-letting. | N36: =O36-Q36 -> 10598 | O36: 10598
N37: =O37-Q37 -> 8770 | O37: 8770
B38: PAY BILL 4139271 ACC NO UM 2G | N38: =O38-Q38 -> 8770 | O38: 8770
C39: Once you’ve made the payment, please forward the details to 0700 194 262 | H39: Once you’ve made the payment, please forward the details to 0700 194 262 | O39: =SUM(O3:O38) -> 391268 | Q39: =SUM(Q3:Q38) -> 0

Sheet 3G
B1: OLE SAMEDHA PREMIER HOSTELS
B2: ='1A'!B2 -> P.O BOX 9473-00200 NAIROBI | N2: VAR | O2: TAX DUE
B3: WATER BILL | N3: =O3-Q3 -> 10270 | O3: 10270
H4: BILL NO. | I4: ='1A'!H3+34-1 -> 71 | J4: ='1A'!H3+34-1 -> 71 | N4: =O4-Q4 -> 10304 | O4: 10304
N5: =O5-Q5 -> 10988 | O5: 10988
B6: TENANT NAME | D6: =meter!B44 -> AMER ALAMRY | N6: =O6-Q6 -> 11070 | O6: 11070
N7: =O7-Q7 -> 1197 | O7: 1197
B8: HOUSE NUMBER: | D8: 3G | N8: =O8-Q8 -> 9250 | O8: 9250
N9: =O9-Q9 -> 8770 | O9: 8770
B10: ISSUE DATE | D10: ='1A'!C9 -> 30TH JAN 2026 | N10: =O10-Q10 -> 23190 | O10: 23190
N11: =O11-Q11 -> 10910 | O11: 10910
B12: LAST PAY DATE | D12: ='1A'!C11 -> 5TH FEB 2026 | N12: =O12-Q12 -> 10910 | O12: 10910
N13: =O13-Q13 -> 12190 | O13: 12190
N14: =O14-Q14 -> 11070 | O14: 11070
B15: PREVIOUS READING | D15: CURRENT READING | F15: CONSUMPTION | N15: =O15-Q15 -> 9090 | O15: 9090
B16: =meter!E44 -> 65 | D16: =meter!F44 -> 66 | E16: Units | F16: =D16-B16 -> 1 | N16: =O16-Q16 -> 9420 | O16: 9420
F17: Amount (Kshs.) | N17: =O17-Q17 -> 11154 | O17: 11154
D18: LAST ACCOUNT B/F | E18: Kshs. | F18: =meter!O44 -> 645 | N18: =O18-Q18 -> 10430 | O18: 10430
N19: =O19-Q19 -> 11831 | O19: 11831
D20: MONTH BILL | E20: KSHS. | F20: =meter!I44 -> 150 | N20: =O20-Q20 -> 10590 | O20: 10590
N21: =O21-Q21 -> 22423 | O21: 22423
D22: PUMP/POWER CHARGES | E22: KSHS. | F22: ='1A'!E21 -> 0 | N22: =O22-Q22 -> 9250 | O22: 9250
N23: =O23-Q23 -> 10162 | O23: 10162
D24: MONTH HOUSE RENT | E24: KSHS. | F24: =meter!N44 -> 10000 | N24: =O24-Q24 -> 10270 | O24: 10270
N25: =O25-Q25 -> 11070 | O25: 11070
D26: ='1A'!C25 -> SECURITY | E26: ='1A'!D25 -> Kshs. | F26: =meter!M37 -> 0 | N26: =O26-Q26 -> 11550 | O26: 11550
D27: GARBAGE FEE | E27: Kshs. | F27: 0 | N27: =O27-Q27 -> 11393 | O27: 11393
D28: INTEREST ON ARREARS | E28: KSHS. | F28: =IF(F18*4%*1<0,0,F18*4%*1) -> 25.8 | N28: =O28-Q28 -> 10802 | O28: 10802
N29: =O29-Q29 -> 8930 | O29: 8930
D30: TOTAL PAYABLE | E30: Kshs. | F30: =SUM(F18:F29) -> 10820.8 | N30: =O30-Q30 -> 9570 | O30: 9570
N31: =O31-Q31 -> 11390 | O31: 11390
D32: PAID | F32: =meter!T37 -> 0 | N32: =O32-Q32 -> 10750 | O32: 10750
N33: =O33-Q33 -> 11732 | O33: 11732
D34: AMOUNT DUE | F34: =F30-F32 -> 10820.8 | N34: =O34-Q34 -> 10934 | O34: 10934 | R34: 700
B36: Rent is due on or before 5th of the month. By 7th day, any rent not paid will attract interest at 2% per day.
B37: Any default in Rent payment by 10th of the following month the house shall be locked without notice and belongings removed for re-letting.
B39: PAYBILL 4139271 ACC NO UM 3G
C40: Once you’ve made the payment, please forward the details to 0700 194 262

Sheet 4G
B1: OLE SAMEDHA PREMIER HOSTELS
B2: ='1A'!B2 -> P.O BOX 9473-00200 NAIROBI | N2: VAR | O2: TAX DUE
B3: WATER BILL | N3: =O3-Q3 -> 10270 | O3: 10270
H4: BILL NO. | I4: ='1A'!H3+34-1 -> 71 | J4: ='1A'!H3+34-1 -> 71 | N4: =O4-Q4 -> 10304 | O4: 10304
N5: =O5-Q5 -> 10988 | O5: 10988
B6: TENANT NAME | D6: =meter!B45 -> SABRIA MOHAMMED | N6: =O6-Q6 -> 11070 | O6: 11070
N7: =O7-Q7 -> 1197 | O7: 1197
B8: HOUSE NUMBER: | D8: 4G | N8: =O8-Q8 -> 9250 | O8: 9250
N9: =O9-Q9 -> 8770 | O9: 8770
B10: ISSUE DATE | D10: ='1A'!C9 -> 30TH JAN 2026 | N10: =O10-Q10 -> 23190 | O10: 23190
N11: =O11-Q11 -> 10910 | O11: 10910
B12: LAST PAY DATE | D12: ='1A'!C11 -> 5TH FEB 2026 | N12: =O12-Q12 -> 10910 | O12: 10910
N13: =O13-Q13 -> 12190 | O13: 12190
N14: =O14-Q14 -> 11070 | O14: 11070
B15: PREVIOUS READING | D15: CURRENT READING | F15: CONSUMPTION | N15: =O15-Q15 -> 9090 | O15: 9090
B16: =meter!E45 -> 43 | D16: =meter!F45 -> 43 | E16: Units | F16: =D16-B16 -> 0 | N16: =O16-Q16 -> 9420 | O16: 9420
F17: Amount (Kshs.) | N17: =O17-Q17 -> 11154 | O17: 11154
D18: LAST ACCOUNT B/F | E18: Kshs. | F18: =meter!O45 -> 516 | N18: =O18-Q18 -> 10430 | O18: 10430
N19: =O19-Q19 -> 11831 | O19: 11831
D20: MONTH BILL | E20: KSHS. | F20: =meter!I45 -> 0 | N20: =O20-Q20 -> 10590 | O20: 10590
N21: =O21-Q21 -> 22423 | O21: 22423
D22: PUMP/POWER CHARGES | E22: KSHS. | F22: ='1A'!E21 -> 0 | N22: =O22-Q22 -> 9250 | O22: 9250
N23: =O23-Q23 -> 10162 | O23: 10162
D24: MONTH HOUSE RENT | E24: KSHS. | F24: =meter!N45 -> 8000 | N24: =O24-Q24 -> 10270 | O24: 10270
N25: =O25-Q25 -> 11070 | O25: 11070
D26: ='1A'!C25 -> SECURITY | E26: ='1A'!D25 -> Kshs. | F26: =meter!M37 -> 0 | N26: =O26-Q26 -> 11550 | O26: 11550
D27: GARBAGE FEE | E27: Kshs. | F27: 0 | N27: =O27-Q27 -> 11393 | O27: 11393
D28: INTEREST ON ARREARS | E28: KSHS. | F28: =IF(F18*4%*1<0,0,F18*4%*1) -> 20.64 | N28: =O28-Q28 -> 10802 | O28: 10802
N29: =O29-Q29 -> 8930 | O29: 8930
D30: TOTAL PAYABLE | E30: Kshs. | F30: 0 | N30: =O30-Q30 -> 9570 | O30: 9570
N31: =O31-Q31 -> 11390 | O31: 11390
D32: PAID | F32: =meter!T37 -> 0 | N32: =O32-Q32 -> 10750 | O32: 10750
N33: =O33-Q33 -> 11732 | O33: 11732
D34: AMOUNT DUE | F34: =SUM(F18:F33) -> 8536.64 | N34: =O34-Q34 -> 10934 | O34: 10934 | R34: 700
B37: Rent is due on or before 5th of the month. By 7th day, any rent not paid will attract interest at 2% per day. | G37: Rent is due on or before 5th of the month. By 7th day, any rent not paid will attract interest at 2% per day.
B38: Any default in Rent payment by 10th of the following month the house shall be locked without notice and belongings removed for re-letting. | G38: Any default in Rent payment by 10th of the following month the house shall be locked without notice and belongings removed for re-letting.
B40: PAY BILL 4139271 ACC NO UM 4G
C41: Once you’ve made the payment, please forward the details to 0700 194 262 | H41: Once you’ve made the payment, please forward the details to 0700 194 262

Sheet 5G
B1: OLE SAMEDHA PREMIER HOSTELS
B2: ='1A'!B2 -> P.O BOX 9473-00200 NAIROBI | N2: VAR | O2: TAX DUE
B3: WATER BILL | N3: =O3-Q3 -> 10270 | O3: 10270
H4: BILL NO. | I4: ='1A'!H3+34-1 -> 71 | J4: ='1A'!H3+34-1 -> 71 | N4: =O4-Q4 -> 10304 | O4: 10304
N5: =O5-Q5 -> 10988 | O5: 10988
B6: TENANT NAME | D6: =meter!B46 -> ADEN SAID | N6: =O6-Q6 -> 11070 | O6: 11070
N7: =O7-Q7 -> 1197 | O7: 1197
B8: HOUSE NUMBER: | D8: 5G | N8: =O8-Q8 -> 9250 | O8: 9250
N9: =O9-Q9 -> 8770 | O9: 8770
B10: ISSUE DATE | D10: ='1A'!C9 -> 30TH JAN 2026 | N10: =O10-Q10 -> 23190 | O10: 23190
N11: =O11-Q11 -> 10910 | O11: 10910
B12: LAST PAY DATE | D12: ='1A'!C11 -> 5TH FEB 2026 | N12: =O12-Q12 -> 10910 | O12: 10910
N13: =O13-Q13 -> 12190 | O13: 12190
N14: =O14-Q14 -> 11070 | O14: 11070
B15: PREVIOUS READING | D15: CURRENT READING | F15: CONSUMPTION | N15: =O15-Q15 -> 9090 | O15: 9090
B16: =meter!E46 -> 47 | D16: =meter!F46 -> 47 | E16: Units | F16: =D16-B16 -> 0 | N16: =O16-Q16 -> 9420 | O16: 9420
F17: Amount (Kshs.) | N17: =O17-Q17 -> 11154 | O17: 11154
D18: LAST ACCOUNT B/F | E18: Kshs. | F18: =meter!O46 -> 0 | N18: =O18-Q18 -> 10430 | O18: 10430
N19: =O19-Q19 -> 11831 | O19: 11831
D20: MONTH BILL | E20: KSHS. | F20: =meter!I46 -> 0 | N20: =O20-Q20 -> 10590 | O20: 10590
N21: =O21-Q21 -> 22423 | O21: 22423
D22: PUMP/POWER CHARGES | E22: KSHS. | F22: ='1A'!E21 -> 0 | N22: =O22-Q22 -> 9250 | O22: 9250
N23: =O23-Q23 -> 10162 | O23: 10162
D24: MONTH HOUSE RENT | E24: KSHS. | F24: =meter!N46 -> 8000 | N24: =O24-Q24 -> 10270 | O24: 10270
N25: =O25-Q25 -> 11070 | O25: 11070
D26: ='1A'!C25 -> SECURITY | E26: ='1A'!D25 -> Kshs. | F26: =meter!M37 -> 0 | N26: =O26-Q26 -> 11550 | O26: 11550
D27: GARBAGE FEE | E27: Kshs. | F27: 0 | N27: =O27-Q27 -> 11393 | O27: 11393
D28: INTEREST ON ARREARS | E28: KSHS. | F28: =IF(F18*4%*1<0,0,F18*4%*1) -> 0 | N28: =O28-Q28 -> 10802 | O28: 10802
N29: =O29-Q29 -> 8930 | O29: 8930
D30: TOTAL PAYABLE | E30: Kshs. | F30: =SUM(F18:F29) -> 8000 | N30: =O30-Q30 -> 9570 | O30: 9570
N31: =O31-Q31 -> 11390 | O31: 11390
D32: PAID | F32: =meter!T37 -> 0 | N32: =O32-Q32 -> 10750 | O32: 10750
N33: =O33-Q33 -> 11732 | O33: 11732
D34: AMOUNT DUE | F34: =F30-F32 -> 8000 | N34: =O34-Q34 -> 10934 | O34: 10934 | R34: 700
C35: NOTE | N35: =O35-Q35 -> 10270 | O35: 10270
A36: Rent is due on or before 5th of the month. By 7th day, any rent not paid will attract interest at 2% per day. | F36: Rent is due on or before 5th of the month. By 7th day, any rent not paid will attract interest at 2% per day. | N36: =O36-Q36 -> 10598 | O36: 10598
A37: Any default in Rent payment by 10th of the following month the house shall be locked without notice and belongings removed for re-letting. | F37: Any default in Rent payment by 10th of the following month the house shall be locked without notice and belongings removed for re-letting. | N37: =O37-Q37 -> 8770 | O37: 8770
N38: =O38-Q38 -> 8770 | O38: 8770
A39: Till: 4536508 | B39: PAY BILL 4139271 ACC NO UM 5G | O39: =SUM(O3:O38) -> 391268 | Q39: =SUM(Q3:Q38) -> 0
B40: Once you’ve made the payment, please forward the details to 0700 194 262 | G40: Once you’ve made the payment, please forward the details to 0700 194 262

Sheet 6G
B1: OLE SAMEDHA PREMIER HOSTELS
B2: ='1A'!B2 -> P.O BOX 9473-00200 NAIROBI | N2: VAR | O2: TAX DUE
B3: WATER BILL | N3: =O3-Q3 -> 10270 | O3: 10270
H4: BILL NO. | I4: ='1A'!H3+34-1 -> 71 | J4: ='1A'!H3+34-1 -> 71 | N4: =O4-Q4 -> 10304 | O4: 10304
N5: =O5-Q5 -> 10988 | O5: 10988
B6: TENANT NAME | D6: =meter!B47 -> TALIB AHMED | N6: =O6-Q6 -> 11070 | O6: 11070
N7: =O7-Q7 -> 1197 | O7: 1197
B8: HOUSE NUMBER: | D8: 6G | N8: =O8-Q8 -> 9250 | O8: 9250
N9: =O9-Q9 -> 8770 | O9: 8770
B10: ISSUE DATE | D10: ='1A'!C9 -> 30TH JAN 2026 | N10: =O10-Q10 -> 23190 | O10: 23190
N11: =O11-Q11 -> 10910 | O11: 10910
B12: LAST PAY DATE | D12: ='1A'!C11 -> 5TH FEB 2026 | N12: =O12-Q12 -> 10910 | O12: 10910
N13: =O13-Q13 -> 12190 | O13: 12190
N14: =O14-Q14 -> 11070 | O14: 11070
B15: PREVIOUS READING | D15: CURRENT READING | F15: CONSUMPTION | N15: =O15-Q15 -> 9090 | O15: 9090
B16: =meter!E47 -> 6 | D16: =meter!F47 -> 7 | E16: Units | F16: =D16-B16 -> 1 | N16: =O16-Q16 -> 9420 | O16: 9420
F17: Amount (Kshs.) | N17: =O17-Q17 -> 11154 | O17: 11154
D18: LAST ACCOUNT B/F | E18: Kshs. | F18: =meter!O47 -> 968 | N18: =O18-Q18 -> 10430 | O18: 10430
N19: =O19-Q19 -> 11831 | O19: 11831
D20: MONTH BILL | E20: KSHS. | F20: =meter!I47 -> 150 | N20: =O20-Q20 -> 10590 | O20: 10590
N21: =O21-Q21 -> 22423 | O21: 22423
D22: PUMP/POWER CHARGES | E22: KSHS. | F22: ='1A'!E21 -> 0 | N22: =O22-Q22 -> 9250 | O22: 9250
N23: =O23-Q23 -> 10162 | O23: 10162
D24: MONTH HOUSE RENT | E24: KSHS. | F24: =meter!N47 -> 10000 | N24: =O24-Q24 -> 10270 | O24: 10270
N25: =O25-Q25 -> 11070 | O25: 11070
D26: ='1A'!C25 -> SECURITY | E26: ='1A'!D25 -> Kshs. | F26: =meter!M37 -> 0 | N26: =O26-Q26 -> 11550 | O26: 11550
D27: GARBAGE FEE | E27: Kshs. | F27: 0 | N27: =O27-Q27 -> 11393 | O27: 11393
D28: INTEREST ON ARREARS | E28: KSHS. | F28: =IF(F18*4%*1<0,0,F18*4%*1) -> 38.72 | N28: =O28-Q28 -> 10802 | O28: 10802
N29: =O29-Q29 -> 8930 | O29: 8930
D30: TOTAL PAYABLE | E30: Kshs. | F30: =SUM(F18:F29) -> 11156.72 | N30: =O30-Q30 -> 9570 | O30: 9570
N31: =O31-Q31 -> 11390 | O31: 11390
D32: PAID | F32: =meter!T37 -> 0 | N32: =O32-Q32 -> 10750 | O32: 10750
N33: =O33-Q33 -> 11732 | O33: 11732
D34: AMOUNT DUE | F34: =F30-F32 -> 11156.72 | N34: =O34-Q34 -> 10934 | O34: 10934 | R34: 700
A35: Rent is due on or before 5th of the month. By 7th day, any rent not paid will attract interest at 2% per day. | N35: =O35-Q35 -> 10270 | O35: 10270
A36: Any default in Rent payment by 10th of the following month the house shall be locked without notice and belongings removed for re-letting. | N36: =O36-Q36 -> 10598 | O36: 10598
N37: =O37-Q37 -> 8770 | O37: 8770
B38: PAY BILL 4139271 ACC NO UM 6G | N38: =O38-Q38 -> 8770 | O38: 8770
B39: Once you’ve made the payment, please forward the details to 0700 194 262 | O39: =SUM(O3:O38) -> 391268 | Q39: =SUM(Q3:Q38) -> 0

Sheet 1H
B1: OLE SAMEDHA PREMIER HOSTELS
B2: ='1A'!B2 -> P.O BOX 9473-00200 NAIROBI | N2: VAR | O2: TAX DUE
B3: WATER BILL | N3: =O3-Q3 -> 10270 | O3: 10270
H4: BILL NO. | I4: ='1A'!H3+34-1 -> 71 | J4: ='1A'!H3+34-1 -> 71 | N4: =O4-Q4 -> 10304 | O4: 10304
N5: =O5-Q5 -> 10988 | O5: 10988
B6: TENANT NAME | D6: =meter!B48 -> FILSAN | N6: =O6-Q6 -> 11070 | O6: 11070
N7: =O7-Q7 -> 1197 | O7: 1197
B8: HOUSE NUMBER: | D8: 1H | N8: =O8-Q8 -> 9250 | O8: 9250
N9: =O9-Q9 -> 8770 | O9: 8770
B10: ISSUE DATE | D10: ='1A'!C9 -> 30TH JAN 2026 | N10: =O10-Q10 -> 23190 | O10: 23190
N11: =O11-Q11 -> 10910 | O11: 10910
B12: LAST PAY DATE | D12: ='1A'!C11 -> 5TH FEB 2026 | N12: =O12-Q12 -> 10910 | O12: 10910
N13: =O13-Q13 -> 12190 | O13: 12190
N14: =O14-Q14 -> 11070 | O14: 11070
B15: PREVIOUS READING | D15: CURRENT READING | F15: CONSUMPTION | N15: =O15-Q15 -> 9090 | O15: 9090
B16: =meter!E48 -> 21 | D16: =meter!F48 -> 21 | E16: Units | F16: =D16-B16 -> 0 | N16: =O16-Q16 -> 9420 | O16: 9420
F17: Amount (Kshs.) | N17: =O17-Q17 -> 11154 | O17: 11154
D18: LAST ACCOUNT B/F | E18: Kshs. | F18: =meter!O48 -> 774 | N18: =O18-Q18 -> 10430 | O18: 10430
N19: =O19-Q19 -> 11831 | O19: 11831
D20: MONTH BILL | E20: KSHS. | F20: =meter!I48 -> 0 | N20: =O20-Q20 -> 10590 | O20: 10590
N21: =O21-Q21 -> 22423 | O21: 22423
D22: PUMP/POWER CHARGES | E22: KSHS. | F22: ='1A'!E21 -> 0 | N22: =O22-Q22 -> 9250 | O22: 9250
N23: =O23-Q23 -> 10162 | O23: 10162
D24: MONTH HOUSE RENT | E24: KSHS. | F24: =meter!N48 -> 8000 | N24: =O24-Q24 -> 10270 | O24: 10270
N25: =O25-Q25 -> 11070 | O25: 11070
D26: ='1A'!C25 -> SECURITY | E26: ='1A'!D25 -> Kshs. | F26: =meter!M37 -> 0 | N26: =O26-Q26 -> 11550 | O26: 11550
D27: GARBAGE FEE | E27: Kshs. | F27: 0 | N27: =O27-Q27 -> 11393 | O27: 11393
D28: INTEREST ON ARREARS | E28: KSHS. | F28: =IF(F18*4%*1<0,0,F18*4%*1) -> 30.96 | N28: =O28-Q28 -> 10802 | O28: 10802
N29: =O29-Q29 -> 8930 | O29: 8930
D30: TOTAL PAYABLE | E30: Kshs. | F30: =SUM(F18:F29) -> 8804.96 | N30: =O30-Q30 -> 9570 | O30: 9570
N31: =O31-Q31 -> 11390 | O31: 11390
D32: PAID | F32: =meter!T37 -> 0 | N32: =O32-Q32 -> 10750 | O32: 10750
N33: =O33-Q33 -> 11732 | O33: 11732
D34: AMOUNT DUE | F34: =F30-F32 -> 8804.96 | N34: =O34-Q34 -> 10934 | O34: 10934 | R34: 700
D36: PAY BILL 4139271 ACC NO UM 1H
A38: Rent is due on or before 5th of the month. By 7th day, any rent not paid will attract interest at 2% per day.
A39: Any default in Rent payment by 10th of the following month the house shall be locked without notice and belongings removed for re-letting.
A41: Till: 4536508
B42: Once you’ve made the payment, please forward the details to 0700 194 262

Sheet 2H
B1: OLE SAMEDHA PREMIER HOSTELS
B2: ='1A'!B2 -> P.O BOX 9473-00200 NAIROBI | N2: VAR | O2: TAX DUE
B3: WATER BILL | N3: =O3-Q3 -> 10270 | O3: 10270
H4: BILL NO. | I4: ='1A'!H3+34-1 -> 71 | J4: ='1A'!H3+34-1 -> 71 | N4: =O4-Q4 -> 10304 | O4: 10304
N5: =O5-Q5 -> 10988 | O5: 10988
B6: TENANT NAME | D6: =meter!B49 -> RAHMA FATUMA | N6: =O6-Q6 -> 11070 | O6: 11070
N7: =O7-Q7 -> 1197 | O7: 1197
B8: HOUSE NUMBER: | D8: 2H | N8: =O8-Q8 -> 9250 | O8: 9250
N9: =O9-Q9 -> 8770 | O9: 8770
B10: ISSUE DATE | D10: ='1A'!C9 -> 30TH JAN 2026 | N10: =O10-Q10 -> 23190 | O10: 23190
N11: =O11-Q11 -> 10910 | O11: 10910
B12: LAST PAY DATE | D12: ='1A'!C11 -> 5TH FEB 2026 | N12: =O12-Q12 -> 10910 | O12: 10910
N13: =O13-Q13 -> 12190 | O13: 12190
N14: =O14-Q14 -> 11070 | O14: 11070
B15: PREVIOUS READING | D15: CURRENT READING | F15: CONSUMPTION | N15: =O15-Q15 -> 9090 | O15: 9090
B16: =meter!E49 -> 22 | D16: =meter!F49 -> 23 | E16: Units | F16: =D16-B16 -> 1 | N16: =O16-Q16 -> 9420 | O16: 9420
F17: Amount (Kshs.) | N17: =O17-Q17 -> 11154 | O17: 11154
D18: LAST ACCOUNT B/F | E18: Kshs. | F18: =meter!O49 -> 0 | N18: =O18-Q18 -> 10430 | O18: 10430
N19: =O19-Q19 -> 11831 | O19: 11831
D20: MONTH BILL | E20: KSHS. | F20: =meter!I49 -> 150 | N20: =O20-Q20 -> 10590 | O20: 10590
N21: =O21-Q21 -> 22423 | O21: 22423
D22: PUMP/POWER CHARGES | E22: KSHS. | F22: ='1A'!E21 -> 0 | N22: =O22-Q22 -> 9250 | O22: 9250
N23: =O23-Q23 -> 10162 | O23: 10162
D24: MONTH HOUSE RENT | E24: KSHS. | F24: =meter!N49 -> 8000 | N24: =O24-Q24 -> 10270 | O24: 10270
N25: =O25-Q25 -> 11070 | O25: 11070
D26: ='1A'!C25 -> SECURITY | E26: ='1A'!D25 -> Kshs. | F26: =meter!M37 -> 0 | N26: =O26-Q26 -> 11550 | O26: 11550
D27: GARBAGE FEE | E27: Kshs. | F27: 0 | N27: =O27-Q27 -> 11393 | O27: 11393
D28: INTEREST ON ARREARS | E28: KSHS. | F28: =IF(F18*4%*1<0,0,F18*4%*1) -> 0 | N28: =O28-Q28 -> 10802 | O28: 10802
N29: =O29-Q29 -> 8930 | O29: 8930
D30: TOTAL PAYABLE | E30: Kshs. | F30: =SUM(F17:F29) -> 8150 | N30: =O30-Q30 -> 9570 | O30: 9570
N31: =O31-Q31 -> 11390 | O31: 11390
D32: PAID | F32: =meter!T37 -> 0 | N32: =O32-Q32 -> 10750 | O32: 10750
N33: =O33-Q33 -> 11732 | O33: 11732
D34: AMOUNT DUE | F34: =F30-F32 -> 8150 | N34: =O34-Q34 -> 10934 | O34: 10934 | R34: 700
N35: =O35-Q35 -> 10270 | O35: 10270
D36: PAY BILL 4139271 ACC NO UM 2H | N36: =O36-Q36 -> 10598 | O36: 10598
N37: =O37-Q37 -> 8770 | O37: 8770
A38: Rent is due on or before 5th of the month. By 7th day, any rent not paid will attract interest at 2% per day. | N38: =O38-Q38 -> 8770 | O38: 8770
A39: Any default in Rent payment by 10th of the following month the house shall be locked without notice and belongings removed for re-letting. | O39: =SUM(O3:O38) -> 391268 | Q39: =SUM(Q3:Q38) -> 0
A41: Till: 4536508
B42: Once you’ve made the payment, please forward the details to 0700 194 262

Sheet 3H
B1: OLE SAMEDHA PREMIER HOSTELS
B2: ='1A'!B2 -> P.O BOX 9473-00200 NAIROBI | N2: VAR | O2: TAX DUE
B3: WATER BILL | N3: =O3-Q3 -> 10270 | O3: 10270
H4: BILL NO. | I4: ='1A'!H3+34-1 -> 71 | J4: ='1A'!H3+34-1 -> 71 | N4: =O4-Q4 -> 10304 | O4: 10304
N5: =O5-Q5 -> 10988 | O5: 10988
B6: TENANT NAME | D6: =meter!B50 -> FOZIA MARYAN | N6: =O6-Q6 -> 11070 | O6: 11070
N7: =O7-Q7 -> 1197 | O7: 1197
B8: HOUSE NUMBER: | D8: 3H | N8: =O8-Q8 -> 9250 | O8: 9250
N9: =O9-Q9 -> 8770 | O9: 8770
B10: ISSUE DATE | D10: ='1A'!C9 -> 30TH JAN 2026 | N10: =O10-Q10 -> 23190 | O10: 23190
N11: =O11-Q11 -> 10910 | O11: 10910
B12: LAST PAY DATE | D12: ='1A'!C11 -> 5TH FEB 2026 | N12: =O12-Q12 -> 10910 | O12: 10910
N13: =O13-Q13 -> 12190 | O13: 12190
N14: =O14-Q14 -> 11070 | O14: 11070
B15: PREVIOUS READING | D15: CURRENT READING | F15: CONSUMPTION | N15: =O15-Q15 -> 9090 | O15: 9090
B16: =meter!E50 -> 51 | D16: =meter!F50 -> 52 | E16: Units | F16: =D16-B16 -> 1 | N16: =O16-Q16 -> 9420 | O16: 9420
F17: Amount (Kshs.) | N17: =O17-Q17 -> 11154 | O17: 11154
D18: LAST ACCOUNT B/F | E18: Kshs. | F18: =meter!O50 -> 0 | N18: =O18-Q18 -> 10430 | O18: 10430
N19: =O19-Q19 -> 11831 | O19: 11831
D20: MONTH BILL | E20: KSHS. | F20: =meter!I50 -> 150 | N20: =O20-Q20 -> 10590 | O20: 10590
N21: =O21-Q21 -> 22423 | O21: 22423
D22: PUMP/POWER CHARGES | E22: KSHS. | F22: ='1A'!E21 -> 0 | N22: =O22-Q22 -> 9250 | O22: 9250
N23: =O23-Q23 -> 10162 | O23: 10162
D24: MONTH HOUSE RENT | E24: KSHS. | F24: =meter!N50 -> 7500 | N24: =O24-Q24 -> 10270 | O24: 10270
N25: =O25-Q25 -> 11070 | O25: 11070
D26: ='1A'!C25 -> SECURITY | E26: ='1A'!D25 -> Kshs. | F26: =meter!M37 -> 0 | N26: =O26-Q26 -> 11550 | O26: 11550
D27: GARBAGE FEE | E27: Kshs. | F27: 0 | N27: =O27-Q27 -> 11393 | O27: 11393
D28: INTEREST ON ARREARS | E28: KSHS. | F28: =IF(F18*4%*1<0,0,F18*4%*1) -> 0 | N28: =O28-Q28 -> 10802 | O28: 10802
N29: =O29-Q29 -> 8930 | O29: 8930
D30: TOTAL PAYABLE | E30: Kshs. | F30: =SUM(F18:F29) -> 7650 | N30: =O30-Q30 -> 9570 | O30: 9570
N31: =O31-Q31 -> 11390 | O31: 11390
D32: PAID | F32: =meter!T37 -> 0 | N32: =O32-Q32 -> 10750 | O32: 10750
N33: =O33-Q33 -> 11732 | O33: 11732
D34: AMOUNT DUE | F34: =F30-F32 -> 7650 | N34: =O34-Q34 -> 10934 | O34: 10934 | R34: 700
A35: Rent is due on or before 5th of the month. By 7th day, any rent not paid will attract interest at 2% per day.
A36: Any default in Rent payment by 10th of the following month the house shall be locked without notice and belongings removed for re-letting. | D36: PAY BILL 4139271 ACC NO UM 3H
A38: Till: 4536508
B39: Once you’ve made the payment, please forward the details to 0700 194 262

Sheet 4H
B1: OLE SAMEDHA PREMIER HOSTELS
B2: ='1A'!B2 -> P.O BOX 9473-00200 NAIROBI | N2: VAR | O2: TAX DUE
B3: WATER BILL | N3: =O3-Q3 -> 10270 | O3: 10270
H4: BILL NO. | I4: ='1A'!H3+34-1 -> 71 | J4: ='1A'!H3+34-1 -> 71 | N4: =O4-Q4 -> 10304 | O4: 10304
N5: =O5-Q5 -> 10988 | O5: 10988
B6: TENANT NAME | D6: =meter!B51 -> ZEITUN | N6: =O6-Q6 -> 11070 | O6: 11070
N7: =O7-Q7 -> 1197 | O7: 1197
B8: HOUSE NUMBER: | D8: 4H | N8: =O8-Q8 -> 9250 | O8: 9250
N9: =O9-Q9 -> 8770 | O9: 8770
B10: ISSUE DATE | D10: ='1A'!C9 -> 30TH JAN 2026 | N10: =O10-Q10 -> 23190 | O10: 23190
N11: =O11-Q11 -> 10910 | O11: 10910
B12: LAST PAY DATE | D12: ='1A'!C11 -> 5TH FEB 2026 | N12: =O12-Q12 -> 10910 | O12: 10910
N13: =O13-Q13 -> 12190 | O13: 12190
N14: =O14-Q14 -> 11070 | O14: 11070
B15: PREVIOUS READING | D15: CURRENT READING | F15: CONSUMPTION | N15: =O15-Q15 -> 9090 | O15: 9090
B16: =meter!E51 -> 19 | D16: =meter!F51 -> 19 | E16: Units | F16: =D16-B16 -> 0 | N16: =O16-Q16 -> 9420 | O16: 9420
F17: Amount (Kshs.) | N17: =O17-Q17 -> 11154 | O17: 11154
D18: LAST ACCOUNT B/F | E18: Kshs. | F18: =meter!O51 -> 0 | N18: =O18-Q18 -> 10430 | O18: 10430
N19: =O19-Q19 -> 11831 | O19: 11831
D20: MONTH BILL | E20: KSHS. | F20: =meter!I51 -> 0 | N20: =O20-Q20 -> 10590 | O20: 10590
N21: =O21-Q21 -> 22423 | O21: 22423
D22: PUMP/POWER CHARGES | E22: KSHS. | F22: ='1A'!E21 -> 0 | N22: =O22-Q22 -> 9250 | O22: 9250
N23: =O23-Q23 -> 10162 | O23: 10162
D24: MONTH HOUSE RENT | E24: KSHS. | F24: =meter!N51 -> 8000 | N24: =O24-Q24 -> 10270 | O24: 10270
N25: =O25-Q25 -> 11070 | O25: 11070
D26: ='1A'!C25 -> SECURITY | E26: ='1A'!D25 -> Kshs. | F26: =meter!M37 -> 0 | N26: =O26-Q26 -> 11550 | O26: 11550
D27: GARBAGE FEE | E27: Kshs. | F27: 0 | N27: =O27-Q27 -> 11393 | O27: 11393
D28: INTEREST ON ARREARS | E28: KSHS. | F28: =IF(F18*4%*1<0,0,F18*4%*1) -> 0 | N28: =O28-Q28 -> 10802 | O28: 10802
N29: =O29-Q29 -> 8930 | O29: 8930
D30: TOTAL PAYABLE | E30: Kshs. | F30: =SUM(F18:F29) -> 8000 | N30: =O30-Q30 -> 9570 | O30: 9570
N31: =O31-Q31 -> 11390 | O31: 11390
D32: PAID | F32: =meter!T37 -> 0 | N32: =O32-Q32 -> 10750 | O32: 10750
N33: =O33-Q33 -> 11732 | O33: 11732
D34: AMOUNT DUE | F34: =F30-F32 -> 8000 | N34: =O34-Q34 -> 10934 | O34: 10934 | R34: 700
A35: Rent is due on or before 5th of the month. By 7th day, any rent not paid will attract interest at 2% per day.
A36: Any default in Rent payment by 10th of the following month the house shall be locked without notice and belongings removed for re-letting.
B38: PAY BILL 4139271 ACC NO UM 4H
B39: Once you’ve made the payment, please forward the details to 0700 194 262

Sheet 5H
B1: OLE SAMEDHA PREMIER HOSTELS
B2: ='1A'!B2 -> P.O BOX 9473-00200 NAIROBI | N2: VAR | O2: TAX DUE
B3: WATER BILL | N3: =O3-Q3 -> 10270 | O3: 10270
H4: BILL NO. | I4: ='1A'!H3+34-1 -> 71 | J4: ='1A'!H3+34-1 -> 71 | N4: =O4-Q4 -> 10304 | O4: 10304
N5: =O5-Q5 -> 10988 | O5: 10988
B6: TENANT NAME | D6: =meter!B52 -> ALBASHIR | N6: =O6-Q6 -> 11070 | O6: 11070
N7: =O7-Q7 -> 1197 | O7: 1197
B8: HOUSE NUMBER: | D8: 5H | N8: =O8-Q8 -> 9250 | O8: 9250
N9: =O9-Q9 -> 8770 | O9: 8770
B10: ISSUE DATE | D10: ='1A'!C9 -> 30TH JAN 2026 | N10: =O10-Q10 -> 23190 | O10: 23190
N11: =O11-Q11 -> 10910 | O11: 10910
B12: LAST PAY DATE | D12: ='1A'!C11 -> 5TH FEB 2026 | N12: =O12-Q12 -> 10910 | O12: 10910
N13: =O13-Q13 -> 12190 | O13: 12190
N14: =O14-Q14 -> 11070 | O14: 11070
B15: PREVIOUS READING | D15: CURRENT READING | F15: CONSUMPTION | N15: =O15-Q15 -> 9090 | O15: 9090
B16: =meter!E52 -> 34 | D16: =meter!F52 -> 36 | E16: Units | F16: =D16-B16 -> 2 | N16: =O16-Q16 -> 9420 | O16: 9420
F17: Amount (Kshs.) | N17: =O17-Q17 -> 11154 | O17: 11154
D18: LAST ACCOUNT B/F | E18: Kshs. | F18: =meter!O52 -> 1064 | N18: =O18-Q18 -> 10430 | O18: 10430
N19: =O19-Q19 -> 11831 | O19: 11831
D20: MONTH BILL | E20: KSHS. | F20: =meter!I52 -> 300 | N20: =O20-Q20 -> 10590 | O20: 10590
N21: =O21-Q21 -> 22423 | O21: 22423
D22: PUMP/POWER CHARGES | E22: KSHS. | F22: ='1A'!E21 -> 0 | N22: =O22-Q22 -> 9250 | O22: 9250
N23: =O23-Q23 -> 10162 | O23: 10162
D24: MONTH HOUSE RENT | E24: KSHS. | F24: =meter!N52 -> 8000 | N24: =O24-Q24 -> 10270 | O24: 10270
N25: =O25-Q25 -> 11070 | O25: 11070
D26: ='1A'!C25 -> SECURITY | E26: ='1A'!D25 -> Kshs. | F26: =meter!M37 -> 0 | N26: =O26-Q26 -> 11550 | O26: 11550
D27: GARBAGE FEE | E27: Kshs. | F27: 0 | N27: =O27-Q27 -> 11393 | O27: 11393
D28: INTEREST ON ARREARS | E28: KSHS. | F28: =IF(F18*4%*1<0,0,F18*4%*1) -> 42.56 | N28: =O28-Q28 -> 10802 | O28: 10802
N29: =O29-Q29 -> 8930 | O29: 8930
D30: TOTAL PAYABLE | E30: Kshs. | F30: =SUM(F17:F29) -> 9406.56 | N30: =O30-Q30 -> 9570 | O30: 9570
N31: =O31-Q31 -> 11390 | O31: 11390
D32: PAID | F32: =meter!T37 -> 0 | N32: =O32-Q32 -> 10750 | O32: 10750
N33: =O33-Q33 -> 11732 | O33: 11732
D34: AMOUNT DUE | F34: =F30-F32 -> 9406.56 | N34: =O34-Q34 -> 10934 | O34: 10934 | R34: 700
A35: Rent is due on or before 5th of the month. By 7th day, any rent not paid will attract interest at 2% per day. | N35: =O35-Q35 -> 10270 | O35: 10270
A36: Any default in Rent payment by 10th of the following month the house shall be locked without notice and belongings removed for re-letting. | N36: =O36-Q36 -> 10598 | O36: 10598
N37: =O37-Q37 -> 8770 | O37: 8770
A38: PAY BILL 4139271 ACC NO UM 5H | N38: =O38-Q38 -> 8770 | O38: 8770
B39: Once you’ve made the payment, please forward the details to 0700 194 262 | O39: =SUM(O3:O38) -> 391268 | Q39: =SUM(Q3:Q38) -> 0

Sheet 6H
B1: OLE SAMEDHA PREMIER HOSTELS
B2: ='1A'!B2 -> P.O BOX 9473-00200 NAIROBI
B3: WATER BILL
H4: BILL NO. | I4: ='1A'!H3+37-1 -> 74
B6: TENANT NAME | D6: =meter!B53 -> OSAMA ABDULAHI
B8: HOUSE NUMBER: | D8: 6H
B10: ISSUE DATE | D10: ='1A'!C9 -> 30TH JAN 2026
B12: LAST PAY DATE | D12: ='1A'!C11 -> 5TH FEB 2026
B15: PREVIOUS READING | D15: CURRENT READING | F15: CONSUMPTION
B16: =meter!E53 -> 15 | D16: =meter!F53 -> 16 | E16: Units | F16: =D16-B16 -> 1
F17: Amount (Kshs.)
D18: LAST ACCOUNT B/F | E18: Kshs. | F18: =meter!O53 -> 725
D20: MONTH BILL | E20: KSHS. | F20: =meter!I53 -> 150
D22: PUMP/POWER CHARGES | E22: KSHS. | F22: ='1A'!E21 -> 0
D24: MONTH HOUSE RENT | E24: KSHS. | F24: =meter!N53 -> 7500
D26: ='1A'!C25 -> SECURITY | E26: ='1A'!D25 -> Kshs. | F26: =meter!M39 -> 0
D27: GARBAGE FEE | E27: Kshs.
D28: INTEREST LATE PAYMENT | E28: KSHS. | F28: =IF(F18*4%*1<0,0,F18*4%*1) -> 29
D30: TOTAL PAYABLE | E30: Kshs. | F30: =SUM(F17:F29) -> 8404
D32: PAID | F32: =meter!T38 -> 0
D34: AMOUNT DUE | F34: =F30-F32 -> 8404
B37: NOTE
A38: Rent is due on or before 5th of the month. By 7th day, any rent not paid will attract interest at 2% per day. | D38: PAY BILL 4139271 ACC NO UM 6H
A39: Any default in Rent payment by 10th of the following month the house shall be locked without notice and belongings removed for re-letting.
A41: Till: 4536508
B42: Once you’ve made the payment, please forward the details to 0700 194 262

Sheet meter
B3: NAMES | C3: HOUSE | D3: PERIOD | E3: PREVIOUS | F3: CURRENT | G3: READING | H3: RATE | I3: cost @200/= | J3: Fixed Charge | K3: Total H2O Bill | L3: GARBAGE FEE | M3: SECURITY | N3: RENT | O3: BAL B/F | P3: VAR | Q3: TAX DUE | R3: INTEREST & PENALTY | S3: TOTAL | T3: PAID | U3: BAL C/F | V3: EARLY DISCOUNT 3% | W3: REMARKS
A4: 1 | B4: ABDI NALMA | C4: 1A | D4: 46054 | E4: 23 | F4: 24 | G4: =SUM(F4-E4) -> 1 | H4: 150 | I4: =G4*H4 -> 150 | K4: =I4+J4 -> 150 | L4: 0 | N4: 7000 | P4: =Q4-S4 -> 3120 | Q4: 10270 | R4: ='1A'!E27 -> 0 | S4: =K4+L4+M4+N4+O4+R4 -> 7150 | T4: 0 | U4: =S4-T4 -> 7150 | X4: 1
A5: =A4+1 -> 2 | B5: NEW TENANT | C5: 2A | D5: 46054 | E5: 34 | F5: 37 | G5: =F5-E5 -> 3 | H5: 150 | I5: =G5*H5 -> 450 | K5: =I5+J5 -> 450 | L5: 0 | N5: 7000 | P5: =Q5-S5 -> 2854 | Q5: 10304 | R5: ='2A'!F28 -> 0 | S5: =K5+L5+M5+N5+O5+R5 -> 7450 | T5: 0 | U5: =S5-T5 -> 7450 | X5: 2
A6: =A5+1 -> 3 | B6: RAMADHAN | C6: 3A | D6: =SUM(D5) -> 46054 | E6: 14 | F6: 15 | G6: =F6-E6 -> 1 | H6: 150 | I6: =G6*H6 -> 150 | K6: =I6+J6 -> 150 | L6: 0 | N6: 7000 | P6: =Q6-S6 -> 3838 | Q6: 10988 | R6: ='3A'!E28 -> 0 | S6: =K6+L6+M6+N6+O6+R6 -> 7150 | T6: 0 | U6: =S6-T6 -> 7150 | X6: 3
A7: =A6+1 -> 4 | B7: NASRA | C7: 4A | D7: =SUM(D5) -> 46054 | E7: 10 | F7: 12 | G7: =F7-E7 -> 2 | H7: 150 | I7: =G7*H7 -> 300 | K7: =I7+J7 -> 300 | L7: 0 | N7: 7000 | O7: 451 | P7: =Q7-S7 -> 3237.82 | Q7: 11070 | R7: ='4A'!E28 -> 81.18 | S7: =K7+L7+M7+N7+O7+R7 -> 7832.18 | T7: 0 | U7: =S7-T7 -> 7832.18 | X7: 4
A8: =A7+1 -> 5 | B8: NADYA JAMAL & AMINA ABDUL | C8: 5A | D8: =SUM(D5) -> 46054 | E8: 18 | F8: 21 | G8: =SUM(F8-E8) -> 3 | H8: 150 | I8: =G8*H8 -> 450 | K8: =I8+J8 -> 450 | L8: 0 | N8: 7000 | O8: 451 | P8: =Q8-S8 -> -6785.18 | Q8: 1197 | R8: ='5A'!E28 -> 81.18 | S8: =K8+L8+M8+N8+O8+R8 -> 7982.18 | T8: 0 | U8: =S8-T8 -> 7982.18 | X8: 5
A9: =A8+1 -> 6 | C9: 6A | D9: =SUM(D6) -> 46054 | E9: 11 | F9: 11 | G9: =F9-E9 -> 0 | H9: 150 | I9: =G9*H9 -> 0 | K9: =I9+J9 -> 0 | L9: 0 | N9: 6000 | O9: 580 | P9: =Q9-S9 -> 2670 | Q9: 9250 | R9: ='6A'!E28 -> 0 | S9: =K9+L9+M9+N9+O9+R9 -> 6580 | T9: 0 | U9: =S9-T9 -> 6580 | X9: 6
A10: =A9+1 -> 7 | B10: MOHAMED | C10: 1B | D10: =SUM(D7) -> 46054 | E10: 9 | F10: 10 | G10: =F10-E10 -> 1 | H10: 150 | I10: =G10*H10 -> 150 | K10: =I10+J10 -> 150 | L10: 0 | N10: 7000 | P10: =Q10-S10 -> 1620 | Q10: 8770 | R10: ='1B'!E28 -> 0 | S10: =K10+L10+M10+N10+O10+R10 -> 7150 | T10: 0 | U10: =S10-T10 -> 7150 | X10: 7
A11: =A10+1 -> 8 | C11: 2B | D11: =SUM(D8) -> 46054 | E11: 13 | F11: 15 | G11: =F11-E11 -> 2 | H11: 150 | I11: =G11*H11 -> 300 | K11: =I11+J11 -> 300 | L11: 0 | N11: 7000 | P11: =Q11-S11 -> 15890 | Q11: 23190 | R11: ='2B'!E28 -> 0 | S11: =K11+L11+M11+N11+O11+R11 -> 7300 | T11: 0 | U11: =S11-T11 -> 7300 | X11: 8
A12: =A11+1 -> 9 | B12: NEW | C12: 3B | D12: =SUM(D9) -> 46054 | E12: 10 | F12: 15 | G12: =F12-E12 -> 5 | H12: 150 | I12: =G12*H12 -> 750 | K12: =I12+J12 -> 750 | L12: 0 | N12: 7000 | P12: =Q12-S12 -> 3160 | Q12: 10910 | R12: ='3B'!E28 -> 0 | S12: =K12+L12+M12+N12+O12+R12 -> 7750 | T12: 0 | U12: =S12-T12 -> 7750 | X12: 9
A13: =A12+1 -> 10 | C13: 4B | D13: =SUM(D10) -> 46054 | E13: 16 | F13: 17 | G13: =F13-E13 -> 1 | H13: 150 | I13: =G13*H13 -> 150 | K13: =I13+J13 -> 150 | L13: 0 | N13: 7000 | P13: =Q13-S13 -> 3760 | Q13: 10910 | R13: ='4B'!E28 -> 0 | S13: =K13+L13+M13+N13+O13+R13 -> 7150 | T13: 0 | U13: =S13-T13 -> 7150 | X13: 10 | Y13: 0
A14: =A13+1 -> 11 | C14: 5B | D14: =SUM(D11) -> 46054 | E14: 1 | F14: 1 | G14: =F14-E14 -> 0 | H14: 150 | I14: =G14*H14 -> 0 | K14: =I14+J14 -> 0 | L14: 0 | N14: 7000 | O14: 451 | P14: =Q14-S14 -> 4720.96 | Q14: 12190 | R14: ='5B'!E28 -> 18.04 | S14: =K14+L14+M14+N14+O14+R14 -> 7469.04 | T14: 0 | U14: =S14-T14 -> 7469.04 | X14: 11
A15: =A14+1 -> 12 | B15: MUNIRA | C15: 6B | D15: =SUM(D12) -> 46054 | E15: 23 | F15: 27 | G15: =F15-E15 -> 4 | H15: 150 | I15: =G15*H15 -> 600 | K15: =I15+J15 -> 600 | L15: 0 | N15: 8000 | P15: =Q15-S15 -> 2470 | Q15: 11070 | R15: ='6B'!F28 -> 0 | S15: =K15+L15+M15+N15+O15+R15 -> 8600 | T15: 0 | U15: =S15-T15 -> 8600 | X15: 12 | Y15: 0 | Z15: =O15-Y15 -> 0
A16: =A15+1 -> 13 | B16: RIDHWAN | C16: 1C | D16: =SUM(D13) -> 46054 | E16: 13 | F16: 13 | G16: =F16-E16 -> 0 | H16: 150 | I16: =G16*H16 -> 0 | K16: =I16+J16 -> 0 | L16: 0 | N16: 8000 | P16: =Q16-S16 -> 1090 | Q16: 9090 | R16: ='1C'!F28 -> 0 | S16: =K16+L16+M16+N16+O16+R16 -> 8000 | T16: 0 | U16: =S16-T16 -> 8000 | X16: 13 | Y16: 0 | Z16: =O16-Y16 -> 0
A17: =A16+1 -> 14 | C17: 2C | D17: =SUM(D14) -> 46054 | E17: 45 | F17: 45 | G17: =F17-E17 -> 0 | H17: 150 | I17: =G17*H17 -> 0 | K17: =I17+J17 -> 0 | L17: 0 | N17: 8000 | O17: 516 | P17: =Q17-S17 -> 883.36 | Q17: 9420 | R17: ='2C'!F28 -> 20.64 | S17: =K17+L17+M17+N17+O17+R17 -> 8536.64 | T17: 0 | U17: =S17-T17 -> 8536.64 | X17: 14 | Y17: 0 | Z17: =O17-Y17 -> 516
A18: =A17+1 -> 15 | B18: AHMED | C18: 3C | D18: =SUM(D15) -> 46054 | E18: 52 | F18: 52 | G18: =F18-E18 -> 0 | H18: 150 | I18: =G18*H18 -> 0 | K18: =I18+J18 -> 0 | L18: 0 | N18: 10000 | P18: =Q18-S18 -> 1154 | Q18: 11154 | R18: ='3C'!F28 -> 0 | S18: =K18+L18+M18+N18+O18+R18 -> 10000 | T18: 0 | U18: =S18-T18 -> 10000 | X18: 15 | Y18: 0
A19: =A18+1 -> 16 | B19: ABASS | C19: 4C | D19: =SUM(D16) -> 46054 | E19: 11 | F19: 12 | G19: =F19-E19 -> 1 | H19: 150 | I19: =G19*H19 -> 150 | K19: =I19+J19 -> 150 | L19: 0 | N19: 8000 | O19: 516 | P19: =Q19-S19 -> 1743.36 | Q19: 10430 | R19: ='4C'!F28 -> 20.64 | S19: =K19+L19+M19+N19+O19+R19 -> 8686.64 | T19: 0 | U19: =S19-T19 -> 8686.64 | X19: 16 | Z19: =O19-Y19 -> 516
A20: =A19+1 -> 17 | C20: 5C | D20: =SUM(D17) -> 46054 | E20: 12 | F20: 12 | G20: =F20-E20 -> 0 | H20: 150 | I20: =G20*H20 -> 0 | K20: =I20+J20 -> 0 | L20: 0 | N20: 8000 | P20: =Q20-S20 -> 3831 | Q20: 11831 | R20: ='5C'!F28 -> 0 | S20: =K20+L20+M20+N20+O20+R20 -> 8000 | T20: 0 | U20: =S20-T20 -> 8000 | X20: 17 | Z20: =O20-Y20 -> 0
A21: =A20+1 -> 18 | B21: KHADIJA | C21: 6C | D21: =SUM(D18) -> 46054 | E21: 17 | F21: 20 | G21: =F21-E21 -> 3 | H21: 150 | I21: =G21*H21 -> 450 | K21: =I21+J21 -> 450 | L21: 0 | N21: 10000 | P21: =Q21-S21 -> 140 | Q21: 10590 | R21: ='6C'!F28 -> 0 | S21: =K21+L21+M21+N21+O21+R21 -> 10450 | T21: 0 | U21: =S21-T21 -> 10450 | X21: 18 | Z21: =O21-Y21 -> 0
A22: =A21+1 -> 19 | B22: AIRHA | C22: 1D | D22: =SUM(D19) -> 46054 | E22: 12 | F22: 15 | G22: =F22-E22 -> 3 | H22: 150 | I22: =G22*H22 -> 450 | K22: =I22+J22 -> 450 | L22: 0 | N22: 8000 | P22: =Q22-S22 -> 13973 | Q22: 22423 | R22: ='1D'!F28 -> 0 | S22: =K22+L22+M22+N22+O22+R22 -> 8450 | T22: 0 | U22: =S22-T22 -> 8450 | X22: 19 | Z22: =O22-Y22 -> 0
A23: =A22+1 -> 20 | B23: MOHAMMED | C23: 2D | D23: =SUM(D20) -> 46054 | E23: 21 | F23: 28 | G23: =F23-E23 -> 7 | H23: 150 | I23: =G23*H23 -> 1050 | K23: =I23+J23 -> 1050 | L23: 0 | N23: 8000 | P23: =Q23-S23 -> 200 | Q23: 9250 | R23: ='2D'!F28 -> 0 | S23: =K23+L23+M23+N23+O23+R23 -> 9050 | T23: 0 | U23: =S23-T23 -> 9050 | X23: 20 | Y23: 0 | Z23: =O23-Y23 -> 0
A24: =A23+1 -> 21 | B24: RIYAQ MOHAMMED | C24: 3D | D24: =SUM(D21) -> 46054 | E24: 23 | F24: 25 | G24: =F24-E24 -> 2 | H24: 150 | I24: =G24*H24 -> 300 | K24: =I24+J24 -> 300 | L24: 0 | N24: 8000 | P24: =Q24-S24 -> 1862 | Q24: 10162 | R24: ='3D'!F28 -> 0 | S24: =K24+L24+M24+N24+O24+R24 -> 8300 | T24: 0 | U24: =S24-T24 -> 8300 | X24: 21
A25: =A24+1 -> 22 | B25: RID WAH ABDULLAH | C25: 4D | D25: =SUM(D22) -> 46054 | E25: 14 | F25: 16 | G25: =F25-E25 -> 2 | H25: 150 | I25: =G25*H25 -> 300 | K25: =I25+J25 -> 300 | L25: 0 | N25: 8000 | O25: 774 | P25: =Q25-S25 -> 1165.04 | Q25: 10270 | R25: ='4D'!F28 -> 30.96 | S25: =K25+L25+M25+N25+O25+R25 -> 9104.96 | T25: 0 | U25: =S25-T25 -> 9104.96 | X25: 22 | Z25: =O25-Y25 -> 774
A26: =A25+1 -> 23 | B26: NASRA | C26: 5D | D26: =SUM(D23) -> 46054 | E26: 25 | F26: 28 | G26: =F26-E26 -> 3 | H26: 150 | I26: =G26*H26 -> 450 | K26: =I26+J26 -> 450 | L26: 0 | N26: 8000 | P26: =Q26-S26 -> 2620 | Q26: 11070 | R26: ='5D'!F28 -> 0 | S26: =K26+L26+M26+N26+O26+R26 -> 8450 | T26: 0 | U26: =S26-T26 -> 8450 | X26: 23 | Y26: 0
A27: =A26+1 -> 24 | C27: 6D | D27: =SUM(D24) -> 46054 | E27: 28 | F27: 29 | G27: =F27-E27 -> 1 | H27: 150 | I27: =G27*H27 -> 150 | K27: =I27+J27 -> 150 | L27: 0 | N27: 7500 | O27: 484 | P27: =Q27-S27 -> 3396.64 | Q27: 11550 | R27: ='6D'!F28 -> 19.36 | S27: =K27+L27+M27+N27+O27+R27 -> 8153.36 | T27: 0 | U27: =S27-T27 -> 8153.36 | X27: 24 | Y27: 0 | Z27: =O27-Y27 -> 484
A28: =A27+1 -> 25 | B28: SALIM ABDULL | C28: 1E | D28: =SUM(D25) -> 46054 | E28: 35 | F28: 35 | G28: =F28-E28 -> 0 | H28: 150 | I28: =G28*H28 -> 0 | K28: =I28+J28 -> 0 | L28: 0 | N28: 8000 | P28: =Q28-S28 -> 3393 | Q28: 11393 | R28: ='1E'!F28 -> 0 | S28: =K28+L28+M28+N28+O28+R28 -> 8000 | T28: 0 | U28: =S28-T28 -> 8000 | X28: 25
A29: =A28+1 -> 26 | B29: QATRA | C29: 2E | D29: =SUM(D26) -> 46054 | E29: 28 | F29: 32 | G29: =F29-E29 -> 4 | H29: 150 | I29: =G29*H29 -> 600 | K29: =I29+J29 -> 600 | L29: 0 | N29: 8000 | P29: =Q29-S29 -> 2202 | Q29: 10802 | R29: ='3E'!F28 -> 0 | S29: =K29+L29+M29+N29+O29+R29 -> 8600 | T29: 0 | U29: =S29-T29 -> 8600 | X29: 26
A30: =A29+1 -> 27 | B30: BAHATI | C30: 3E | D30: =SUM(D27) -> 46054 | E30: 20 | F30: 21 | G30: =F30-E30 -> 1 | H30: 150 | I30: =G30*H30 -> 150 | K30: =I30+J30 -> 150 | L30: 0 | N30: 7000 | P30: =Q30-S30 -> 1780 | Q30: 8930 | R30: ='2E'!F28 -> 0 | S30: =K30+L30+M30+N30+O30+R30 -> 7150 | T30: 0 | U30: =S30-T30 -> 7150 | V30: =S30*3% -> 214.5 | W30: ECBKL 28/2/2018 | X30: 27B | Y30: 0 | Z30: =O30-Y30 -> 0
A31: =A30+1 -> 28 | B31: ABDUL | C31: 4E | D31: =SUM(D28) -> 46054 | E31: 29 | F31: 30 | G31: =F31-E31 -> 1 | H31: 150 | I31: =G31*H31 -> 150 | K31: =I31+J31 -> 150 | L31: 0 | N31: 7000 | O31: 900 | P31: =Q31-S31 -> 1484 | Q31: 9570 | R31: ='4E'!F28 -> 36 | S31: =K31+L31+M31+N31+O31+R31 -> 8086 | T31: 0 | U31: =S31-T31 -> 8086 | X31: 28B | Y31: 0
A32: =A31+1 -> 29 | B32: ASIYA | C32: 5E | D32: =SUM(D29) -> 46054 | E32: 29 | F32: 30 | G32: =F32-E32 -> 1 | H32: 150 | I32: =G32*H32 -> 150 | K32: =I32+J32 -> 150 | L32: 0 | N32: 7000 | P32: =Q32-S32 -> 4240 | Q32: 11390 | R32: ='6E'!F28 -> 0 | S32: =K32+L32+M32+N32+O32+R32 -> 7150 | T32: 0 | U32: =S32-T32 -> 7150 | X32: 29 | Y32: 0
A33: =A32+1 -> 30 | B33: ABDIAZIZ ABDI | C33: 6E | D33: =SUM(D30) -> 46054 | E33: 30 | F33: 31 | G33: =F33-E33 -> 1 | H33: 150 | I33: =G33*H33 -> 150 | K33: =I33+J33 -> 150 | L33: 0 | N33: 7000 | P33: =Q33-S33 -> 3600 | Q33: 10750 | R33: 0 | S33: =K33+L33+M33+N33+O33+R33 -> 7150 | T33: 0 | U33: =S33-T33 -> 7150 | X33: 30 | Y33: 0 | Z33: =O33-Y33 -> 0
A34: =A33+1 -> 31 | B34: YUSUF | C34: 7E | D34: =SUM(D31) -> 46054 | E34: 48 | F34: 49 | G34: =F34-E34 -> 1 | H34: 150 | I34: =G34*H34 -> 150 | K34: =I34+J34 -> 150 | L34: 0 | N34: 10000 | P34: =Q34-S34 -> 1582 | Q34: 11732 | R34: ='7E'!F28 -> 0 | S34: =K34+L34+M34+N34+O34+R34 -> 10150 | T34: 0 | U34: =S34-T34 -> 10150 | X34: 31
A35: =A34+1 -> 32 | B35: TUSMA | C35: 1F | D35: =SUM(D32) -> 46054 | E35: 9 | F35: 10 | G35: =F35-E35 -> 1 | H35: 150 | I35: =G35*H35 -> 150 | K35: =I35+J35 -> 150 | L35: 0 | N35: 8000 | P35: =Q35-S35 -> 2784 | Q35: 10934 | R35: ='1F'!F28 -> 0 | S35: =K35+L35+M35+N35+O35+R35 -> 8150 | T35: 0 | U35: =S35-T35 -> 8150 | X35: 32 | Y35: 0
A36: =A35+1 -> 33 | B36: FOZIA YUSSUF | C36: 2F | D36: =SUM(D33) -> 46054 | E36: 45 | F36: 46 | G36: =F36-E36 -> 1 | H36: 150 | I36: =G36*H36 -> 150 | K36: =I36+J36 -> 150 | L36: 0 | N36: 8000 | P36: =Q36-S36 -> 2120 | Q36: 10270 | R36: ='2F'!F28 -> 0 | S36: =K36+L36+M36+N36+O36+R36 -> 8150 | T36: 0 | U36: =S36-T36 -> 8150 | X36: 33 | Y36: 0 | Z36: =O36-Y36 -> 0
A37: =A36+1 -> 34 | B37: HALIMA | C37: 3F | D37: =SUM(D34) -> 46054 | E37: 28 | F37: 29 | G37: =F37-E37 -> 1 | H37: 150 | I37: =G37*H37 -> 150 | K37: =I37+J37 -> 150 | L37: 0 | N37: 7000 | P37: =Q37-S37 -> 3448 | Q37: 10598 | R37: ='3F'!F28 -> 0 | S37: =K37+L37+M37+N37+O37+R37 -> 7150 | T37: 0 | U37: =S37-T37 -> 7150 | X37: 34 | Y37: 0
A38: =A37+1 -> 35 | B38: ASMA | C38: 4F | D38: =SUM(D35) -> 46054 | E38: 36 | F38: 37 | G38: =F38-E38 -> 1 | H38: 150 | I38: =G38*H38 -> 150 | K38: =I38+J38 -> 150 | L38: 0 | N38: 7000 | P38: =Q38-S38 -> 1620 | Q38: 8770 | R38: ='4F'!F28 -> 0 | S38: =K38+L38+M38+N38+O38+R38 -> 7150 | T38: 0 | U38: =S38-T38 -> 7150 | X38: 35 | Y38: 0 | Z38: =O38-Y38 -> 0
A39: =A38+1 -> 36 | B39: ZAHRA AISHA | C39: 5F | D39: =SUM(D36) -> 46054 | E39: 57 | F39: 59 | G39: =SUM(F39-E39) -> 2 | H39: 150 | I39: =G39*H39 -> 300 | K39: =I39+J39 -> 300 | L39: 0 | N39: 7000 | P39: =Q39-S39 -> 1441 | Q39: 8770 | R39: ='6H'!F28 -> 29 | S39: =K39+L39+M39+N39+O39+R39 -> 7329 | T39: 0 | U39: =S39-T39 -> 7329 | X39: 37B | Y39: 0 | Z39: =O39-Y39 -> 0
A40: =A39+1 -> 37 | B40: MUHAMMED NASIR | C40: 6F | D40: =SUM(D37) -> 46054 | E40: 10 | F40: 11 | G40: =SUM(F40-E40) -> 1 | H40: 150 | I40: =G40*H40 -> 150 | K40: =I40+J40 -> 150 | L40: 0 | N40: 6500
A41: =A40+1 -> 38 | B41: ZAKARIA | C41: 7F | D41: =SUM(D38) -> 46054 | E41: 48 | F41: 49 | G41: =SUM(F41-E41) -> 1 | H41: 150 | I41: =G41*H41 -> 150 | K41: =I41+J41 -> 150 | L41: 0 | N41: 10000 | O41: 1032
A42: =A41+1 -> 39 | C42: 1G | D42: =SUM(D39) -> 46054 | E42: 40 | F42: 40 | G42: =SUM(F42-E42) -> 0 | H42: 150 | I42: =G42*H42 -> 0 | K42: =I42+J42 -> 0 | L42: 0 | N42: 8000
A43: =A42+1 -> 40 | B43: ISMAHAN MAIMUNA | C43: 2G | D43: =SUM(D40) -> 46054 | E43: 39 | F43: 40 | G43: =SUM(F43-E43) -> 1 | H43: 150 | I43: =G43*H43 -> 150 | K43: =I43+J43 -> 150 | L43: 0 | N43: 8000 | O43: 774
A44: =A43+1 -> 41 | B44: AMER ALAMRY | C44: 3G | D44: =SUM(D41) -> 46054 | E44: 65 | F44: 66 | G44: =SUM(F44-E44) -> 1 | H44: 150 | I44: =G44*H44 -> 150 | K44: =I44+J44 -> 150 | L44: 0 | N44: 10000 | O44: 645
A45: =A44+1 -> 42 | B45: SABRIA MOHAMMED | C45: 4G | D45: =SUM(D42) -> 46054 | E45: 43 | F45: 43 | G45: =SUM(F45-E45) -> 0 | H45: 150 | I45: =G45*H45 -> 0 | K45: =I45+J45 -> 0 | L45: 0 | N45: 8000 | O45: 516
A46: =A45+1 -> 43 | B46: ADEN SAID | C46: 5G | D46: =SUM(D43) -> 46054 | E46: 47 | F46: 47 | G46: =SUM(F46-E46) -> 0 | H46: 150 | I46: =G46*H46 -> 0 | K46: =I46+J46 -> 0 | L46: 0 | N46: 8000
A47: =A46+1 -> 44 | B47: TALIB AHMED | C47: 6G | D47: =SUM(D44) -> 46054 | E47: 6 | F47: 7 | G47: =SUM(F47-E47) -> 1 | H47: 150 | I47: =G47*H47 -> 150 | K47: =I47+J47 -> 150 | L47: 0 | N47: 10000 | O47: 968
A48: =A47+1 -> 45 | B48: FILSAN | C48: 1H | D48: =SUM(D45) -> 46054 | E48: 21 | F48: 21 | G48: =SUM(F48-E48) -> 0 | H48: 150 | I48: =G48*H48 -> 0 | K48: =I48+J48 -> 0 | L48: 0 | N48: 8000 | O48: 774
A49: =A48+1 -> 46 | B49: RAHMA FATUMA | C49: 2H | D49: =SUM(D46) -> 46054 | E49: 22 | F49: 23 | G49: =SUM(F49-E49) -> 1 | H49: 150 | I49: =G49*H49 -> 150 | K49: =I49+J49 -> 150 | L49: 0 | N49: 8000
A50: =A49+1 -> 47 | B50: FOZIA MARYAN | C50: 3H | D50: =SUM(D47) -> 46054 | E50: 51 | F50: 52 | G50: =SUM(F50-E50) -> 1 | H50: 150 | I50: =G50*H50 -> 150 | K50: =I50+J50 -> 150 | L50: 0 | N50: 7500
A51: =A50+1 -> 48 | B51: ZEITUN | C51: 4H | D51: =SUM(D48) -> 46054 | E51: 19 | F51: 19 | G51: =SUM(F51-E51) -> 0 | H51: 150 | I51: =G51*H51 -> 0 | K51: =I51+J51 -> 0 | L51: 0 | N51: 8000
A52: =A51+1 -> 49 | B52: ALBASHIR | C52: 5H | D52: =SUM(D49) -> 46054 | E52: 34 | F52: 36 | G52: =SUM(F52-E52) -> 2 | H52: 150 | I52: =G52*H52 -> 300 | K52: =I52+J52 -> 300 | L52: 0 | N52: 8000 | O52: 1064
A53: =A52+1 -> 50 | B53: OSAMA ABDULAHI | C53: 6H | D53: =SUM(D50) -> 46054 | E53: 15 | F53: 16 | G53: =SUM(F53-E53) -> 1 | H53: 150 | I53: =G53*H53 -> 150 | L53: 0 | N53: 7500 | O53: 725
C54: TOTAL | G54: =SUM(G4:G39) -> 60 | I54: =SUM(I4:I53) -> 10500 | J54: =SUM(J4:J38) -> 0 | K54: =SUM(K4:K38) -> 8700 | L54: =SUM(L4:L39) -> 0 | N54: =SUM(N4:N53) -> 390000 | Q54: =SUM(Q4:Q39) -> 391268 | R54: =SUM(R4:R39) -> 337 | S54: =SUM(S4:S53) -> 288960 | T54: =SUM(T4:T53) -> 0
I57: =IF(I55-G59>0,I58,I58) -> 0
O59: =SUM(O58-O54) -> 0
I60: =I58+I59 -> 0
H63: =G63*H39 -> 0

Sheet Sheet3

Sheet Sheet4

Sheet Sheet5

Sheet Sheet1
L16: 101456
L17: 21
L18: 1364
L19: 81411 | M19: salary
L21: =L16-L19 -> 20045
L22: =L19-55000 -> 26411

Sheet Sheet2
I1: MAY | J1: JUNE | K1: JUL
I2: 8300 | J2: 21000 | K2: 9962
I3: 9608 | J3: 9962 | K3: 10623
I4: 9608 | J4: 11039 | K4: 8510
I5: 7525 | J5: 10117 | K5: 10100
I6: 11000 | J6: 10778
I7: 8985 | J7: 10750
I8: 7857 | J8: 8510
I9: 6000 | J9: 11230
I10: 9005 | J10: 8500
I11: 10665 | J11: 10590
I12: 9335 | J12: 10400
I13: 8040 | J13: 10000
I14: 8000 | J14: 10840
I15: 10560 | J15: 10200 | K15: 11200
I16: 11000 | J16: 10225 | K16: 11360
I17: 9421 | J17: 9000 | K17: 9787
I18: 10000 | J18: 9945 | K18: 9130
I19: 10700 | J19: 10000 | K19: 10250
I20: 10055 | J20: 5000 | K20: 10740
I21: 10200 | J21: 8900 | K21: 10910
I22: 1977 | J22: 9962 | K22: 9000
I23: 10155 | J23: 10583 | K23: 10353
I24: 10000 | J24: 11200 | K24: 10910
I25: 8000 | J25: 9930 | K25: 8930
I26: 9925 | J26: 8662 | K26: 1200
... I32: 10000 | J32: 10860 | K32: 6000
I33: 5520 | K33: 8500
I34: 9805 | K34: 10430
I35: 20000 | K35: 10000
E36: 119472 | I36: 7000 | K36: 10000
E37: 64399 | I37: 5000 | K37: 11000
E38: =SUM(E36:E37) -> 183871 | I38: 20000 | K38: 8950
I39: 13000 | K39: 11230
I40: 10910 | K40: 400
K41: 7800
K42: 1000
K43: 8000
K44: 6294
I45: =SUM(I2:I44) -> 366751 | J45: =SUM(J2:J44) -> 307193 | K45: =SUM(K2:K44) -> 301808
